Workbook

Sheet Summary
B1: Ceilings Unlimited
B2: 2 Devonport Road
B3: Tauranga
B5: 45853
B7: Summary
B8: Clarifications:
B9: * CBC to provide - Mezz double height scaffold and stairs. All other access allowed.
B10: * Pricing is based on all materials being lifted/removed via crane or hiab to respective Levels to an access point/loadin platform then through facade. Removal/reinstatement of facade as well as Crane/Hiab, Access point/loadin platform to be provided by main contractor along with any associated Traffic Management costs that may be required. | D10: Pre load Floors where possible by end of January 2026
B11: * This trade pricing is based on the acceptance as a package and if individual trades were selected we would need to be contacted to discuss before acceptance.
B12: * We have included Provisional Sum for PS1 Steel Stud Partition Design (Excluded Design of Timber Partitions) a s well as Monitoring and PS4 Sign Off. | D12: PS1 Ceiling Design to be updated between CBC and Comfortech
B14: * No allowance for detailed drawings/shop drawings, resource and consent fees etc. By Others if Required. | D14: PS1 Ceiling Design and Seel Stud Partition Design to Serve as Shop Drawing
B15: * No allownce for samples of products.
B16: * Allowed for works within normal works hours Monday to Friday 7.30am - 5pm.
B17: * Rubbish disposal and system to be provided by main contractor on each Level.
B18: * No allowance for Passive Fire to all service penetrations to wall and ceiling penetrations. To be carried out by associated service contractor of specific Passive Fire Contractor.
B19: * No allowance to Fire Rate any steel work outside of what is incapsulated with walls beneath it. Understand balance of Steel work will be Intumescent Painted by others.
B20: * Interface to intumescent paint not allowed if we have to connect to Intumescent painted Steel. This needs to be clarified by fire engineer and if required treated as a variation.
B21: * No allowance for any timber framing (including timber framed bulkheads), strapping and nogging. By Others.
B22: * We have allowed for a bulkhead in Steel Stud to take perimeter pelmet to ceilings. No allowance for any other bulkheads as we understand these are timber.
B24: * Level 4 Stopping allowed.
B25: * No allowance for any Korok or Gib to associated head detail, by others.
B26: * We have allowed Concealed Grid and Steel Stud from SRP/Studco
B27: * No allowance for any windows or doors including internal glazing/partitioning.
... B52: * Pricing validity strictly as per cover letter. No allowance for cost escalations.
B56: ='Suspended Ceilings_25_8'!B9 -> Suspended Ceiling (1500 x 600) | D56: ='Suspended Ceilings_25_8'!M371 -> 628565
B58: Timber Partitions & Strapping/Nogging | D58: Nil, By Others (CBC)
B60: ='Steel Stud Partitions_25_8'!B9 -> Steel Stud Partitions | D60: ='Steel Stud Partitions_25_8'!M129 -> 111772
B62: Head Track and Gib Packing to Timber Walls (Timber Partitions by Others) | D62: Nil, By Others (CBC)
B64: ='Gib Linings_25_8'!B9 -> Gib Wall and Ceiling Linings | D64: ='Gib Linings_25_8'!M599 -> 469562
B66: =Stopping_25_8!B9 -> Gib Stopping | D66: =Stopping_25_8!M216 -> 203482
B68: Featurecraft Interior Lining | D68: Nil at this Stage as Discussed with Kenny
B70: Aluminium and Timber Skirting | D70: ='Skirting with Columns'!M112 -> 40195
B72: ='PROV SUM PS1 & PS4 _25_8'!B9 -> PROVISIONAL SUM: PS1 Design & PS4 Certificate for Interior Steel Stud Partition | D72: ='PROV SUM PS1 & PS4 _25_8'!M42 -> 12000
B74: PROVISIONAL SUM: Ceiling Seismic Components | D74: As per Provided PS1
B77: Total of all items priced | E77: =SUM(D56:D74) -> 1465576 | H77: 1465591 | J77: =H77-E77 -> 15
B78: * No allowance for GST
D81: =B56 -> Suspended Ceiling (1500 x 600) | E81: =B58 -> Timber Partitions & Strapping/Nogging | F81: =B60 -> Steel Stud Partitions | G81: =B62 -> Head Track and Gib Packing to Timber Walls (Timber Partitions by Others) | H81: =B64 -> Gib Wall and Ceiling Linings | I81: =B66 -> Gib Stopping | J81: =B68 -> Featurecraft Interior Lining | K81: =B70 -> Aluminium and Timber Skirting | L81: =B72 -> PROVISIONAL SUM: PS1 Design & PS4 Certificate for Interior Steel Stud Partition | M81: =B74 -> PROVISIONAL SUM: Ceiling Seismic Components | N81: TTL
B83: ='Suspended Ceilings_25_8'!B357 -> P&G - Admin / Supervision | D83: ='Suspended Ceilings_25_8'!M357 -> 31544.767 | E83: By CBC | F83: ='Steel Stud Partitions_25_8'!M115 -> 5540.8524 | G83: By CBC | H83: ='Gib Linings_25_8'!M585 -> 23360.861 | I83: =Stopping_25_8!M202 -> 9894.2994 | J83: TBA | K83: ='Skirting with Columns'!M98 -> 2004.0345 | L83: ='PROV SUM PS1 & PS4 _25_8'!M27 -> 594.84 | N83: =SUM(D83:M83) -> 72939.654 | P83: 7 months for bulk except 4/5/6 tenanant ceilings
B85: ='Suspended Ceilings_25_8'!B359 -> P&G - Site Establishment | D85: ='Suspended Ceilings_25_8'!M359 -> 15772.383 | F85: ='Steel Stud Partitions_25_8'!M117 -> 2770.4262 | H85: ='Gib Linings_25_8'!M587 -> 11680.43 | I85: =Stopping_25_8!M204 -> 4947.1497 | K85: ='Skirting with Columns'!M100 -> 1002.0173 | L85: ='PROV SUM PS1 & PS4 _25_8'!M29 -> 0 | N85: =SUM(D85:M85) -> 36172.407 | P85: =SUM(N83:N85) -> 109112.06
B87: ='Suspended Ceilings_25_8'!B361 -> P&G - Access Equip | D87: ='Suspended Ceilings_25_8'!M361 -> 2628.7306 | F87: ='Steel Stud Partitions_25_8'!M119 -> 461.7377 | H87: ='Gib Linings_25_8'!M589 -> 1946.7384 | I87: =Stopping_25_8!M206 -> 824.52495 | K87: ='Skirting with Columns'!M102 -> 167.00288 | L87: ='PROV SUM PS1 & PS4 _25_8'!M31 -> 0 | N87: =SUM(D87:M87) -> 6028.7345
B89: ='Suspended Ceilings_25_8'!B363 -> P&G | D89: ='Suspended Ceilings_25_8'!M363 -> 0 | F89: ='Steel Stud Partitions_25_8'!M121 -> 0 | H89: ='Gib Linings_25_8'!M591 -> 0 | I89: =Stopping_25_8!M208 -> 0 | K89: ='Skirting with Columns'!M104 -> 0 | L89: ='PROV SUM PS1 & PS4 _25_8'!M33 -> 0 | N89: =SUM(D89:M89) -> 0
B91: ='Suspended Ceilings_25_8'!B365 -> P&G Parking | D91: ='Suspended Ceilings_25_8'!M365 -> 6312.2513 | F91: ='Steel Stud Partitions_25_8'!M123 -> 2371.5225 | H91: ='Gib Linings_25_8'!M593 -> 8443.1025 | I91: =Stopping_25_8!M210 -> 7837.6725 | K91: ='Skirting with Columns'!M106 -> 643.725 | L91: ='PROV SUM PS1 & PS4 _25_8'!M35 -> 0 | N91: =SUM(D91:M91) -> 25608.274
B93: ='Suspended Ceilings_25_8'!B369 -> Margin | D93: ='Suspended Ceilings_25_8'!M369 -> 46560.34 | F93: ='Steel Stud Partitions_25_8'!M127 -> 8279.3663 | H93: ='Gib Linings_25_8'!M597 -> 34782.305 | I93: =Stopping_25_8!M214 -> 15072.691 | K93: ='Skirting with Columns'!M110 -> 2977.3884 | L93: ='PROV SUM PS1 & PS4 _25_8'!M39 -> 840.7072 | N93: =SUM(D93:M93) -> 108512.8

Sheet Suspended Ceilings_25_8
B1: =Summary!B1 -> Ceilings Unlimited
B2: =Summary!B2 -> 2 Devonport Road
B3: =Summary!B3 -> Tauranga
B6: 45853
B9: Suspended Ceiling (1500 x 600)
Q10: =SUM(C17,C35,C76,C143,C183,C225,C269,C311) -> 988
H11: 50 | Q11: =SUM(C18,C36,C77,C144,C184,C226,C270,C312) -> 1376
A12: Item | B12: Description | C12: Qty | D12: Unit | E12: Constant | F12: Constant X Unit = Total HRS | G12: $ Lab per Unit | H12: Total Labour | I12: Materials per Unit | J12: Total Materials | K12: Total Labour & Materials | L12: Total Labour & Materials Per Unit | M12: Total | N12: % Complete | O12: Claim
B15: Basement:
B16: Concealed Grid:
B17: (CS01) Concealed Grid @ 600 crs | C17: 96 | D17: m2 | E17: 0.32 | F17: =C17*E17 -> 30.72 | G17: =$H$11*E17 -> 16 | H17: =F17*$H$11 -> 1536 | I17: 15.51 | J17: =C17*I17 -> 1488.96 | K17: =SUM(H17,J17) -> 3024.96 | L17: =K17/C17 -> 31.51 | M17: =C17*L17 -> 3024.96 | N17: 0 | O17: =M17*N17 -> 0
B18: Perimeter to Above | C18: 166 | D18: m
B20: (CS12) Fire Rated Ceiling | C20: Nil, By Others
B22: (WA24) Fire Rated Ceiling | C22: Korok, By Others
B24: (CS52) | C24: Soffit, By Others
B26: Bulkheads:
B27: (CS12) Fire Rated Bulkhead (1500) | C27: 6 | D27: m | F27: =C27*E27 -> 0 | G27: =$H$11*E27 -> 0 | H27: =F27*$H$11 -> 0 | J27: =C27*I27 -> 0 | K27: =SUM(H27,J27) -> 0 | L27: =K27/C27 -> 0 | M27: =C27*L27 -> 0 | N27: 0 | O27: =M27*N27 -> 0
B29: (WA24) | C29: Korok, By Others
P30: =SUM(M13:M26) -> 3024.96 | Q30: =P30*SUM($L$357:$L$363) -> 287.3712
P31: =P30/$M$354 -> 0.0057536517 | Q31: =P31*$M$365 -> 36.318495 | R31: =SUM(P30,Q30,Q31) -> 3348.6497 | S31: =R31*1.08 -> 3616.5417
B33: Ground:
B34: Concealed Grid:
B35: (CS01) Concealed Grid @ 600 crs | C35: 267 | D35: m2 | E35: 0.32 | F35: =C35*E35 -> 85.44 | G35: =$H$11*E35 -> 16 | H35: =F35*$H$11 -> 4272 | I35: 15.51 | J35: =C35*I35 -> 4141.17 | K35: =SUM(H35,J35) -> 8413.17 | L35: =K35/C35 -> 31.51 | M35: =C35*L35 -> 8413.17 | N35: 0 | O35: =M35*N35 -> 0
B36: Perimeter to Above | C36: 302 | D36: m
B38: (CS10) | C38: Timber Structure, By Others
B40: (CS11) | C40: Korok, By Others
B42: (CL50) | C42: Timber Structure, By Others
B44: Bulkheads:
B46: Type 2 Bulkhead @ 0.9m | C46: 16 | D46: m | E46: 0.35 | F46: =C46*E46 -> 5.6 | G46: =$H$11*E46 -> 17.5 | H46: =F46*$H$11 -> 280 | I46: 39.2 | J46: =C46*I46 -> 627.2 | K46: =SUM(H46,J46) -> 907.2 | L46: =K46/C46 -> 56.7 | M46: =C46*L46 -> 907.2 | N46: 0 | O46: =M46*N46 -> 0
B47: Bracket to Grid | C47: =C46/1.2 -> 13.333333 | D47: no | E47: 0.09 | F47: =C47*E47 -> 1.2 | G47: =$H$11*E47 -> 4.5 | H47: =F47*$H$11 -> 60 | I47: 5.28 | J47: =C47*I47 -> 70.4 | K47: =SUM(H47,J47) -> 130.4 | L47: =K47/C47 -> 9.78 | M47: =C47*L47 -> 130.4 | N47: 0 | O47: =M47*N47 -> 0
B48: Bracket to Soffit | C48: =C46/2.4 -> 6.6666667 | D48: no | E48: 0 | F48: =C48*E48 -> 0 | G48: =$H$11*E48 -> 0 | H48: =F48*$H$11 -> 0 | I48: 5.28 | J48: =C48*I48 -> 35.2 | K48: =SUM(H48,J48) -> 35.2 | L48: =K48/C48 -> 5.28 | M48: =C48*L48 -> 35.2 | N48: 0 | O48: =M48*N48 -> 0
B49: Longitudinal | C49: 7 | D49: no | E49: 0.25 | F49: =C49*E49 -> 1.75 | G49: =$H$11*E49 -> 12.5 | H49: =F49*$H$11 -> 87.5 | I49: 17.05 | J49: =C49*I49 -> 119.35 | K49: =SUM(H49,J49) -> 206.85 | L49: =K49/C49 -> 29.55 | M49: =C49*L49 -> 206.85 | N49: 0 | O49: =M49*N49 -> 0
B50: Lateral | C50: 7 | D50: no | E50: 0.12 | F50: =C50*E50 -> 0.84 | G50: =$H$11*E50 -> 6 | H50: =F50*$H$11 -> 42 | I50: 8.06 | J50: =C50*I50 -> 56.42 | K50: =SUM(H50,J50) -> 98.42 | L50: =K50/C50 -> 14.06 | M50: =C50*L50 -> 98.42 | N50: 0 | O50: =M50*N50 -> 0
B52: Type 2 Bulkhead @ 1.2m | C52: 26 | D52: m | E52: 0.25 | F52: =C52*E52 -> 6.5 | G52: =$H$11*E52 -> 12.5 | H52: =F52*$H$11 -> 325 | I52: 24.31 | J52: =C52*I52 -> 632.06 | K52: =SUM(H52,J52) -> 957.06 | L52: =K52/C52 -> 36.81 | M52: =C52*L52 -> 957.06 | N52: 0 | O52: =M52*N52 -> 0
B53: Bracket to Grid | C53: =C52/1.2 -> 21.666667 | D53: no | E53: 0.09 | F53: =C53*E53 -> 1.95 | G53: =$H$11*E53 -> 4.5 | H53: =F53*$H$11 -> 97.5 | I53: 5.28 | J53: =C53*I53 -> 114.4 | K53: =SUM(H53,J53) -> 211.9 | L53: =K53/C53 -> 9.78 | M53: =C53*L53 -> 211.9 | N53: 0 | O53: =M53*N53 -> 0
B54: Bracket to Soffit | C54: =C52/2.4 -> 10.833333 | D54: no | E54: 0 | F54: =C54*E54 -> 0 | G54: =$H$11*E54 -> 0 | H54: =F54*$H$11 -> 0 | I54: 5.28 | J54: =C54*I54 -> 57.2 | K54: =SUM(H54,J54) -> 57.2 | L54: =K54/C54 -> 5.28 | M54: =C54*L54 -> 57.2 | N54: 0 | O54: =M54*N54 -> 0
B55: Longitudinal | C55: 7 | D55: no | E55: 0.25 | F55: =C55*E55 -> 1.75 | G55: =$H$11*E55 -> 12.5 | H55: =F55*$H$11 -> 87.5 | I55: 17.05 | J55: =C55*I55 -> 119.35 | K55: =SUM(H55,J55) -> 206.85 | L55: =K55/C55 -> 29.55 | M55: =C55*L55 -> 206.85 | N55: 0 | O55: =M55*N55 -> 0
B56: Lateral | C56: 7 | D56: no | E56: 0.12 | F56: =C56*E56 -> 0.84 | G56: =$H$11*E56 -> 6 | H56: =F56*$H$11 -> 42 | I56: 8.06 | J56: =C56*I56 -> 56.42 | K56: =SUM(H56,J56) -> 98.42 | L56: =K56/C56 -> 14.06 | M56: =C56*L56 -> 98.42 | N56: 0 | O56: =M56*N56 -> 0
B58: Type 2 Bulkhead @ 1.4m | C58: 17 | D58: m | E58: 0.35 | F58: =C58*E58 -> 5.95 | G58: =$H$11*E58 -> 17.5 | H58: =F58*$H$11 -> 297.5 | I58: 41.58 | J58: =C58*I58 -> 706.86 | K58: =SUM(H58,J58) -> 1004.36 | L58: =K58/C58 -> 59.08 | M58: =C58*L58 -> 1004.36 | N58: 0 | O58: =M58*N58 -> 0
B59: Bracket to Grid | C59: =C58/1.2 -> 14.166667 | D59: no | E59: 0.09 | F59: =C59*E59 -> 1.275 | G59: =$H$11*E59 -> 4.5 | H59: =F59*$H$11 -> 63.75 | I59: 5.28 | J59: =C59*I59 -> 74.8 | K59: =SUM(H59,J59) -> 138.55 | L59: =K59/C59 -> 9.78 | M59: =C59*L59 -> 138.55 | N59: 0 | O59: =M59*N59 -> 0
B60: Bracket to Soffit | C60: =C58/2.4 -> 7.0833333 | D60: no | E60: 0 | F60: =C60*E60 -> 0 | G60: =$H$11*E60 -> 0 | H60: =F60*$H$11 -> 0 | I60: 5.28 | J60: =C60*I60 -> 37.4 | K60: =SUM(H60,J60) -> 37.4 | L60: =K60/C60 -> 5.28 | M60: =C60*L60 -> 37.4 | N60: 0 | O60: =M60*N60 -> 0
B61: Longitudinal | C61: 7 | D61: no | E61: 0.25 | F61: =C61*E61 -> 1.75 | G61: =$H$11*E61 -> 12.5 | H61: =F61*$H$11 -> 87.5 | I61: 17.05 | J61: =C61*I61 -> 119.35 | K61: =SUM(H61,J61) -> 206.85 | L61: =K61/C61 -> 29.55 | M61: =C61*L61 -> 206.85 | N61: 0 | O61: =M61*N61 -> 0
B62: Lateral | C62: 7 | D62: no | E62: 0.12 | F62: =C62*E62 -> 0.84 | G62: =$H$11*E62 -> 6 | H62: =F62*$H$11 -> 42 | I62: 8.06 | J62: =C62*I62 -> 56.42 | K62: =SUM(H62,J62) -> 98.42 | L62: =K62/C62 -> 14.06 | M62: =C62*L62 -> 98.42 | N62: 0 | O62: =M62*N62 -> 0
B64: Type 2 Bulkhead @ 1.9m | C64: 3 | D64: m | E64: 0.41 | F64: =C64*E64 -> 1.23 | G64: =$H$11*E64 -> 20.5 | H64: =F64*$H$11 -> 61.5 | I64: 42.99 | J64: =C64*I64 -> 128.97 | K64: =SUM(H64,J64) -> 190.47 | L64: =K64/C64 -> 63.49 | M64: =C64*L64 -> 190.47 | N64: 0 | O64: =M64*N64 -> 0
B65: Bracket to Grid | C65: 2 | D65: no | E65: 0.09 | F65: =C65*E65 -> 0.18 | G65: =$H$11*E65 -> 4.5 | H65: =F65*$H$11 -> 9 | I65: 5.28 | J65: =C65*I65 -> 10.56 | K65: =SUM(H65,J65) -> 19.56 | L65: =K65/C65 -> 9.78 | M65: =C65*L65 -> 19.56 | N65: 0 | O65: =M65*N65 -> 0
B66: Bracket to Soffit | C66: 2 | D66: no | E66: 0 | F66: =C66*E66 -> 0 | G66: =$H$11*E66 -> 0 | H66: =F66*$H$11 -> 0 | I66: 5.28 | J66: =C66*I66 -> 10.56 | K66: =SUM(H66,J66) -> 10.56 | L66: =K66/C66 -> 5.28 | M66: =C66*L66 -> 10.56 | N66: 0 | O66: =M66*N66 -> 0
B67: Longitudinal | C67: 2 | D67: no | E67: 0.25 | F67: =C67*E67 -> 0.5 | G67: =$H$11*E67 -> 12.5 | H67: =F67*$H$11 -> 25 | I67: 224.29 | J67: =C67*I67 -> 448.58 | K67: =SUM(H67,J67) -> 473.58 | L67: =K67/C67 -> 236.79 | M67: =C67*L67 -> 473.58 | N67: 0 | O67: =M67*N67 -> 0
B68: Lateral | C68: 2 | D68: no | E68: 0.12 | F68: =C68*E68 -> 0.24 | G68: =$H$11*E68 -> 6 | H68: =F68*$H$11 -> 12 | I68: 15.29 | J68: =C68*I68 -> 30.58 | K68: =SUM(H68,J68) -> 42.58 | L68: =K68/C68 -> 21.29 | M68: =C68*L68 -> 42.58 | N68: 0 | O68: =M68*N68 -> 0
B70: Perimeter Custom Made Pelmet: | C70: Nil | P70: =SUM(M35:M69) -> 13545 | Q70: =P70*SUM($L$357:$L$363) -> 1286.775
P71: =P70/$M$354 -> 0.025763386 | Q71: =P71*$M$365 -> 162.62496 | R71: =SUM(P70,Q70,Q71) -> 14994.4 | S71: =R71*1.08 -> 16193.952
B74: Level 1:
B75: Concealed Grid:
B76: (CS01) Concealed Grid @ 600 crs | C76: 296 | D76: m2 | E76: 0.32 | F76: =C76*E76 -> 94.72 | G76: =$H$11*E76 -> 16 | H76: =F76*$H$11 -> 4736 | I76: 15.51 | J76: =C76*I76 -> 4590.96 | K76: =SUM(H76,J76) -> 9326.96 | L76: =K76/C76 -> 31.51 | M76: =C76*L76 -> 9326.96 | N76: 0 | O76: =M76*N76 -> 0
B77: Perimeter to Above | C77: 249 | D77: m
B78: Bridging for Services | C78: 1 | D78: item | E78: 0 | F78: =C78*E78 -> 0 | G78: =$H$11*E78 -> 0 | H78: =F78*$H$11 -> 0 | I78: 500 | J78: =C78*I78 -> 500 | K78: =SUM(H78,J78) -> 500 | L78: =K78/C78 -> 500 | M78: =C78*L78 -> 500 | N78: 0 | O78: =M78*N78 -> 0
B80: (CS12) Fire Rated Ceiling | C80: 2 | D80: m2 | F80: =C80*E80 -> 0 | G80: =$H$11*E80 -> 0 | H80: =F80*$H$11 -> 0 | J80: =C80*I80 -> 0 | K80: =SUM(H80,J80) -> 0 | L80: =K80/C80 -> 0 | M80: =C80*L80 -> 0 | N80: 0 | O80: =M80*N80 -> 0
B82: (CL50) | C82: Timber Structure, By Others
B84: Back Bracing Seismic Components | C84: Refer Provisional Sum
B86: Two Grid & Tile:
B87: (CS02) Armstrong 1500 x 600 x 24mm faced Grid - White | C87: 722 | D87: m2 | E87: 0.21 | F87: =C87*E87 -> 151.62 | G87: =$H$11*E87 -> 10.5 | H87: =F87*$H$11 -> 7581 | I87: 11.51 | J87: =C87*I87 -> 8310.22 | K87: =SUM(H87,J87) -> 15891.22 | L87: =K87/C87 -> 22.01 | M87: =C87*L87 -> 15891.22 | N87: 0 | O87: =M87*N87 -> 0
B88: Perimeter to Above | C88: 181 | D88: m | E88: 0.1 | F88: =C88*E88 -> 18.1 | G88: =$H$11*E88 -> 5 | H88: =F88*$H$11 -> 905 | I88: 2.53 | J88: =C88*I88 -> 457.93 | K88: =SUM(H88,J88) -> 1362.93 | L88: =K88/C88 -> 7.53 | M88: =C88*L88 -> 1362.93 | N88: 0 | O88: =M88*N88 -> 0
B89: EV to Round Columns | C89: 13 | D89: no | E89: 0.75 | F89: =C89*E89 -> 9.75 | G89: =$H$11*E89 -> 37.5 | H89: =F89*$H$11 -> 487.5 | I89: 25 | J89: =C89*I89 -> 325 | K89: =SUM(H89,J89) -> 812.5 | L89: =K89/C89 -> 62.5 | M89: =C89*L89 -> 812.5 | N89: 0 | O89: =M89*N89 -> 0
B90: (CS02) 1500 x 600 x 22mm Eurocoustic Tonga A22, Square Edge Tiles | C90: 722 | D90: m2 | E90: 0.1 | F90: =C90*E90 -> 72.2 | G90: =$H$11*E90 -> 5 | H90: =F90*$H$11 -> 3610 | I90: 36.36 | J90: =C90*I90 -> 26251.92 | K90: =SUM(H90,J90) -> 29861.92 | L90: =K90/C90 -> 41.36 | M90: =C90*L90 -> 29861.92 | N90: 0 | O90: =M90*N90 -> 0 | U90: =SUM(L87,L90) -> 63.37
B91: 1500 Nogs - Lighting | C91: 186 | D91: no | E91: 0 | F91: =C91*E91 -> 0 | G91: =$H$11*E91 -> 0 | H91: =F91*$H$11 -> 0 | I91: 5.79 | J91: =C91*I91 -> 1076.94 | K91: =SUM(H91,J91) -> 1076.94 | L91: =K91/C91 -> 5.79 | M91: =C91*L91 -> 1076.94 | N91: 0 | O91: =M91*N91 -> 0
B93: Bridging for Services | C93: 1 | D93: item | E93: 0 | F93: =C93*E93 -> 0 | G93: =$H$11*E93 -> 0 | H93: =F93*$H$11 -> 0 | I93: 500 | J93: =C93*I93 -> 500 | K93: =SUM(H93,J93) -> 500 | L93: =K93/C93 -> 500 | M93: =C93*L93 -> 500 | N93: 0 | O93: =M93*N93 -> 0
B95: Seismic In Ceiling Bulkhead & Control Joint:
B97: Control Joint | C97: 18 | D97: m
B98: MT | C98: 0
B99: CT | C99: 18 | D99: m | E99: 0.09 | F99: =C99*E99 -> 1.62 | G99: =$H$11*E99 -> 4.5 | H99: =F99*$H$11 -> 81 | I99: 2.82 | J99: =C99*I99 -> 50.76 | K99: =SUM(H99,J99) -> 131.76 | L99: =K99/C99 -> 7.32 | M99: =C99*L99 -> 131.76
B101: Type 3 Bulkhead @ 1.0m | C101: 62 | D101: m | E101: 0.25 | F101: =C101*E101 -> 15.5 | G101: =$H$11*E101 -> 12.5 | H101: =F101*$H$11 -> 775 | I101: 27.16 | J101: =C101*I101 -> 1683.92 | K101: =SUM(H101,J101) -> 2458.92 | L101: =K101/C101 -> 39.66 | M101: =C101*L101 -> 2458.92 | N101: 0.95 | O101: =M101*N101 -> 2335.974
B102: Bracket to Grid | C102: =C101/1.5 -> 41.333333 | D102: no | E102: 0.09 | F102: =C102*E102 -> 3.72 | G102: =$H$11*E102 -> 4.5 | H102: =F102*$H$11 -> 186 | I102: 5.28 | J102: =C102*I102 -> 218.24 | K102: =SUM(H102,J102) -> 404.24 | L102: =K102/C102 -> 9.78 | M102: =C102*L102 -> 404.24 | N102: 0.95 | O102: =M102*N102 -> 384.028 | U102: =SUM(C101,C107,C114,C126,C163,C173,C205,C215,C249,C259,C291,C301,C338) -> 1108
B103: Bracket to Soffit | C103: =C101/1.8 -> 34.444444 | D103: no | E103: 0 | F103: =C103*E103 -> 0 | G103: =$H$11*E103 -> 0 | H103: =F103*$H$11 -> 0 | I103: 5.28 | J103: =C103*I103 -> 181.86667 | K103: =SUM(H103,J103) -> 181.86667 | L103: =K103/C103 -> 5.28 | M103: =C103*L103 -> 181.86667 | N103: 0.95 | O103: =M103*N103 -> 172.77333
B104: Longitudinal | C104: 35 | D104: no | E104: 0.25 | F104: =C104*E104 -> 8.75 | G104: =$H$11*E104 -> 12.5 | H104: =F104*$H$11 -> 437.5 | I104: 17.05 | J104: =C104*I104 -> 596.75 | K104: =SUM(H104,J104) -> 1034.25 | L104: =K104/C104 -> 29.55 | M104: =C104*L104 -> 1034.25 | N104: 0.95 | O104: =M104*N104 -> 982.5375
B105: Lateral | C105: 35 | D105: no | E105: 0.12 | F105: =C105*E105 -> 4.2 | G105: =$H$11*E105 -> 6 | H105: =F105*$H$11 -> 210 | I105: 8.06 | J105: =C105*I105 -> 282.1 | K105: =SUM(H105,J105) -> 492.1 | L105: =K105/C105 -> 14.06 | M105: =C105*L105 -> 492.1 | N105: 0.95 | O105: =M105*N105 -> 467.495 | Q105: =SUM(O101:O105) -> 4342.8078
B107: Type 2 Bulkhead @ 1.2 | C107: 32 | D107: m | E107: 0.25 | F107: =C107*E107 -> 8 | G107: =$H$11*E107 -> 12.5 | H107: =F107*$H$11 -> 400 | I107: 26.56 | J107: =C107*I107 -> 849.92 | K107: =SUM(H107,J107) -> 1249.92 | L107: =K107/C107 -> 39.06 | M107: =C107*L107 -> 1249.92 | N107: 0 | O107: =M107*N107 -> 0
B108: Bracket to Grid | C108: =C107/1.2 -> 26.666667 | D108: no | E108: 0.09 | F108: =C108*E108 -> 2.4 | G108: =$H$11*E108 -> 4.5 | H108: =F108*$H$11 -> 120 | I108: 5.28 | J108: =C108*I108 -> 140.8 | K108: =SUM(H108,J108) -> 260.8 | L108: =K108/C108 -> 9.78 | M108: =C108*L108 -> 260.8 | N108: 0 | O108: =M108*N108 -> 0
B109: Bracket to Soffit | C109: =C107/2.4 -> 13.333333 | D109: no | E109: 0 | F109: =C109*E109 -> 0 | G109: =$H$11*E109 -> 0 | H109: =F109*$H$11 -> 0 | I109: 5.28 | J109: =C109*I109 -> 70.4 | K109: =SUM(H109,J109) -> 70.4 | L109: =K109/C109 -> 5.28 | M109: =C109*L109 -> 70.4 | N109: 0 | O109: =M109*N109 -> 0
B110: Longitudinal | C110: 14 | D110: no | E110: 0.25 | F110: =C110*E110 -> 3.5 | G110: =$H$11*E110 -> 12.5 | H110: =F110*$H$11 -> 175 | I110: 17.05 | J110: =C110*I110 -> 238.7 | K110: =SUM(H110,J110) -> 413.7 | L110: =K110/C110 -> 29.55 | M110: =C110*L110 -> 413.7 | N110: 0 | O110: =M110*N110 -> 0
B111: Lateral | C111: 14 | D111: no | E111: 0.12 | F111: =C111*E111 -> 1.68 | G111: =$H$11*E111 -> 6 | H111: =F111*$H$11 -> 84 | I111: 8.06 | J111: =C111*I111 -> 112.84 | K111: =SUM(H111,J111) -> 196.84 | L111: =K111/C111 -> 14.06 | M111: =C111*L111 -> 196.84 | N111: 0 | O111: =M111*N111 -> 0
B112: EV to take linings | C112: 18 | D112: m | E112: 0.1 | F112: =C112*E112 -> 1.8 | G112: =$H$11*E112 -> 5 | H112: =F112*$H$11 -> 90 | I112: 14.88 | J112: =C112*I112 -> 267.84 | K112: =SUM(H112,J112) -> 357.84 | L112: =K112/C112 -> 19.88 | M112: =C112*L112 -> 357.84
B114: Type 2 Bulkhead - High Level @ 1.2m | C114: 16 | D114: m | E114: 0.45 | F114: =C114*E114 -> 7.2 | G114: =$H$11*E114 -> 22.5 | H114: =F114*$H$11 -> 360 | I114: 26.56 | J114: =C114*I114 -> 424.96 | K114: =SUM(H114,J114) -> 784.96 | L114: =K114/C114 -> 49.06 | M114: =C114*L114 -> 784.96 | N114: 0 | O114: =M114*N114 -> 0
B115: Bracket to Grid | C115: =C114/1.2 -> 13.333333 | D115: no | E115: 0.09 | F115: =C115*E115 -> 1.2 | G115: =$H$11*E115 -> 4.5 | H115: =F115*$H$11 -> 60 | I115: 5.28 | J115: =C115*I115 -> 70.4 | K115: =SUM(H115,J115) -> 130.4 | L115: =K115/C115 -> 9.78 | M115: =C115*L115 -> 130.4 | N115: 0 | O115: =M115*N115 -> 0
B116: Bracket to Soffit | C116: =C114/2.4 -> 6.6666667 | D116: no | E116: 0 | F116: =C116*E116 -> 0 | G116: =$H$11*E116 -> 0 | H116: =F116*$H$11 -> 0 | I116: 5.28 | J116: =C116*I116 -> 35.2 | K116: =SUM(H116,J116) -> 35.2 | L116: =K116/C116 -> 5.28 | M116: =C116*L116 -> 35.2 | N116: 0 | O116: =M116*N116 -> 0
B117: Longitudinal | C117: 35 | D117: no | E117: 0.25 | F117: =C117*E117 -> 8.75 | G117: =$H$11*E117 -> 12.5 | H117: =F117*$H$11 -> 437.5 | I117: 17.05 | J117: =C117*I117 -> 596.75 | K117: =SUM(H117,J117) -> 1034.25 | L117: =K117/C117 -> 29.55 | M117: =C117*L117 -> 1034.25 | N117: 0 | O117: =M117*N117 -> 0
B118: Lateral | C118: 35 | D118: no | E118: 0.12 | F118: =C118*E118 -> 4.2 | G118: =$H$11*E118 -> 6 | H118: =F118*$H$11 -> 210 | I118: 8.06 | J118: =C118*I118 -> 282.1 | K118: =SUM(H118,J118) -> 492.1 | L118: =K118/C118 -> 14.06 | M118: =C118*L118 -> 492.1 | N118: 0 | O118: =M118*N118 -> 0
B120: Bulkheads:
B121: (CS12) Fire Rated Bulkhead | C121: Nil, By Others
B123: Bulkhead (1200) | C123: Timber Structure, By Others
B125: Perimeter Custom Made Pelmet: | X125: 0.3
B126: (CS04) Recessed Bulkhead | C126: 93 | D126: m | E126: =$X$125 -> 0.3 | F126: =C126*E126 -> 27.9 | G126: =$H$11*E126 -> 15 | H126: =F126*$H$11 -> 1395 | I126: 122.5 | J126: =C126*I126 -> 11392.5 | K126: =SUM(H126,J126) -> 12787.5 | L126: =K126/C126 -> 137.5 | M126: =C126*L126 -> 12787.5 | N126: 0 | O126: =M126*N126 -> 0
B127: Supporting Structure to Above | C127: 93 | D127: m | E127: 0.32 | F127: =C127*E127 -> 29.76 | G127: =$H$11*E127 -> 16 | H127: =F127*$H$11 -> 1488 | I127: 40 | J127: =C127*I127 -> 3720 | K127: =SUM(H127,J127) -> 5208 | L127: =K127/C127 -> 56 | M127: =C127*L127 -> 5208 | N127: 0 | O127: =M127*N127 -> 0
B128: Bracket to Soffit | C128: =C126/1.8 -> 51.666667 | D128: no | E128: 0 | F128: =C128*E128 -> 0 | G128: =$H$11*E128 -> 0 | H128: =F128*$H$11 -> 0 | I128: 5.28 | J128: =C128*I128 -> 272.8 | K128: =SUM(H128,J128) -> 272.8 | L128: =K128/C128 -> 5.28 | M128: =C128*L128 -> 272.8 | N128: 0 | O128: =M128*N128 -> 0
B129: Lateral Brace to Above | C129: 52 | D129: no | E129: 0.25 | F129: =C129*E129 -> 13 | G129: =$H$11*E129 -> 12.5 | H129: =F129*$H$11 -> 650 | I129: 17.05 | J129: =C129*I129 -> 886.6 | K129: =SUM(H129,J129) -> 1536.6 | L129: =K129/C129 -> 29.55 | M129: =C129*L129 -> 1536.6 | N129: 0 | O129: =M129*N129 -> 0
B130: Longitudinal Brace | C130: 52 | D130: no | E130: 0.12 | F130: =C130*E130 -> 6.24 | G130: =$H$11*E130 -> 6 | H130: =F130*$H$11 -> 312 | I130: 8.06 | J130: =C130*I130 -> 419.12 | K130: =SUM(H130,J130) -> 731.12 | L130: =K130/C130 -> 14.06 | M130: =C130*L130 -> 731.12 | N130: 0 | O130: =M130*N130 -> 0 | Q130: =SUM(M127:M130) -> 7748.52
B133: Custom Reveal Ceiling to Façade (Outside of Grid A 5 - 7) | C133: 17 | D133: m | E133: =$X$125 -> 0.3 | F133: =C133*E133 -> 5.1 | G133: =$H$11*E133 -> 15 | H133: =F133*$H$11 -> 255 | I133: 122.5 | J133: =C133*I133 -> 2082.5 | K133: =SUM(H133,J133) -> 2337.5 | L133: =K133/C133 -> 137.5 | M133: =C133*L133 -> 2337.5 | N133: 0 | O133: =M133*N133 -> 0 | Q133: =SUM(M76:M137) -> 93275.327 | R133: =Q105/Q133 -> 0.04655902
B134: Supporting Structure to Above | C134: 17 | D134: m | E134: 0.45 | F134: =C134*E134 -> 7.65 | G134: =$H$11*E134 -> 22.5 | H134: =F134*$H$11 -> 382.5 | I134: 41 | J134: =C134*I134 -> 697 | K134: =SUM(H134,J134) -> 1079.5 | L134: =K134/C134 -> 63.5 | M134: =C134*L134 -> 1079.5 | N134: 0 | O134: =M134*N134 -> 0
B135: Bracket to Soffit | C135: 8 | D135: no | E135: 0 | F135: =C135*E135 -> 0 | G135: =$H$11*E135 -> 0 | H135: =F135*$H$11 -> 0 | I135: 5.28 | J135: =C135*I135 -> 42.24 | K135: =SUM(H135,J135) -> 42.24 | L135: =K135/C135 -> 5.28 | M135: =C135*L135 -> 42.24 | N135: 0 | O135: =M135*N135 -> 0
B136: Lateral Brace to Above | C136: 5 | D136: no | E136: 0.25 | F136: =C136*E136 -> 1.25 | G136: =$H$11*E136 -> 12.5 | H136: =F136*$H$11 -> 62.5 | I136: 17.05 | J136: =C136*I136 -> 85.25 | K136: =SUM(H136,J136) -> 147.75 | L136: =K136/C136 -> 29.55 | M136: =C136*L136 -> 147.75 | N136: 0 | O136: =M136*N136 -> 0
B137: Longitudinal Brace | C137: 5 | D137: no | E137: 0.12 | F137: =C137*E137 -> 0.6 | G137: =$H$11*E137 -> 6 | H137: =F137*$H$11 -> 30 | I137: 8.06 | J137: =C137*I137 -> 40.3 | K137: =SUM(H137,J137) -> 70.3 | L137: =K137/C137 -> 14.06 | M137: =C137*L137 -> 70.3 | N137: 0 | O137: =M137*N137 -> 0
P138: =SUM(M76:M137)+R383 -> 94559.895 | Q138: =P138*SUM($L$357:$L$363) -> 8983.19
...

Sheet Workings_Ceilings
AB4: ***POST APRIL*** | AM4: ***POST APRIL***
N5: Armstrong | Y5: Armstrong | AJ5: Armstrong
B6: Job Name
B7: total sqm | C7: 5337 | D7: m2 | F7: Standard grid | H7: 5% Freight | N7: Job Name | Y7: Job Name | AJ7: Job Name
B8: Cost Plus Margin | F8: Nett cost | G8: Comfortech | H8: 10% waste | N8: total sqm | O8: 5337 | P8: m2 | R8: Standard grid | T8: 5% Freight | Y8: total sqm | Z8: 5337 | AA8: m2 | AC8: Standard grid | AE8: 5% Freight | AJ8: total sqm | AK8: 5337 | AL8: m2 | AN8: Standard grid | AP8: 5% Freight
B9: admin | F9: Wall angle | G9: 2.12 | H9: =G9*1.15 -> 2.438 | N9: Cost Plus Margin | R9: Nett cost | T9: 10% waste | Y9: Cost Plus Margin | AC9: Nett cost | AE9: 10% waste | AJ9: Cost Plus Margin | AN9: Nett cost | AP9: 10% waste
B10: hourly rate | C10: 55 | F10: Mains | G10: 2.89 | H10: =G10*1.15 -> 3.3235 | N10: admin | R10: Wall angle | S10: 2.12 | T10: =S10*1.15 -> 2.438 | Y10: admin | AC10: Wall angle | AD10: 2.2 | AE10: =AD10*1.15 -> 2.53 | AJ10: admin | AN10: Wall angle | AO10: 2.2 | AP10: =AO10*1.15 -> 2.53
B11: wall trim | C11: 1467 | D11: m | F11: 1200 Nogs | G11: 2.62 | H11: =G11*1.15 -> 3.013 | N11: hourly rate | O11: 55 | R11: Mains | S11: 2.89 | T11: =S11*1.15 -> 3.3235 | Y11: hourly rate | Z11: 55 | AC11: Mains | AD11: 3.01 | AE11: =AD11*1.15 -> 3.4615 | AJ11: hourly rate | AK11: 55 | AN11: Mains | AO11: 3 | AP11: =AO11*1.15 -> 3.45
B12: tile type | C12: Tonga Eurocoustic | N12: wall trim | O12: 1224 | P12: m | R12: 1500 Nogs | S12: 3.53 | T12: =S12*1.15 -> 4.0595 | Y12: wall trim | Z12: 1224 | AA12: m | AC12: 1500 Nogs | AD12: 3.67 | AE12: =AD12*1.15 -> 4.2205 | AJ12: wall trim | AK12: 1224 | AL12: m | AN12: 1500 Nogs | AO12: 3.36 | AP12: =AO12*1.15 -> 3.864
B13: tile price | C13: =K17 -> 22.636897 | D13: per tile | F13: **WHITE GRID | I13: $19.63 per tile | N13: tile type | O13: Eurocoustic Tonga white | Y13: tile type | Z13: Eurocoustic Tonga white | AJ13: tile type | AK13: Eurocoustic Tonga white
B14: Module | C14: 1200 x 600 | I14: tiles plus 15% | K14: 1191 | N14: tile price | O14: =W20 -> 31.689713 | P14: per tile | R14: Berc Clips | S14: 1.97 | T14: =S14*1.15 -> 2.2655 | Y14: tile price | Z14: =AH20 -> 34.360877 | AA14: per tile | AC14: Berc Clips | AD14: 1.97 | AE14: =AD14*1.15 -> 2.2655 | AJ14: tile price | AK14: =AS20 -> 32.693929 | AL14: per tile | AN14: Berc Clips | AO14: 1.97 | AP14: =AO14*1.15 -> 2.2655
I15: 8525 | N15: Module | O15: 1500 x 600 | Y15: Module | Z15: 1500 x 600 | AJ15: Module | AK15: 1500 x 600
I16: 711 boxes @ $236 | K16: 167796 | U16: $26.02 per tile | AF16: $28.28 per tile | AQ16: $28.28 per tile plus 5% Freight $29.69
B17: Total Cost | C17: =C7*C36 -> 316331.26 | K17: =K16/C32 -> 22.636897 | U17: tiles plus 15% | AF17: tiles plus 15% | AQ17: tiles plus 10% wastage
B18: Total Revenue | C18: =C17*(1+C8) -> 316331.26 | D18: Price | N18: Total Cost | O18: =O8*O38 -> 336794.89 | U18: 7191 | Y18: Total Cost | Z18: =Z8*Z38 -> 354819.54 | AF18: 7191 | AJ18: Total Cost | AK18: =AK8*AK38 -> 341466.01 | AQ18: 6523 | AR18: 653 boxes
B19: Profit | C19: =C18-C17 -> 0 | N19: Total Revenue | O19: =O18*(1+O9) -> 336794.89 | P19: Price | U19: 720 boxes @ $261 | W19: 187920 | Y19: Total Revenue | Z19: =Z18*(1+Z9) -> 354819.54 | AA19: Price | AF19: 720 boxes @ $283 | AH19: 203760 | AJ19: Total Revenue | AK19: =AK18*(1+AK9) -> 341466.01 | AL19: Price | AQ19: 653 boxes @ $296.90 | AS19: 193875
N20: Profit | O20: =O19-O18 -> 0 | W20: =W19/O34 -> 31.689713 | Y20: Profit | Z20: =Z19-Z18 -> 0 | AH20: =AH19/Z34 -> 34.360877 | AJ20: Profit | AK20: =AK19-AK18 -> 0 | AS20: =AS19/AK34 -> 32.693929
B21: Standard grid
B22: USG | E22: Waste 10% on product include in cost | N22: Standard grid | Y22: Standard grid | AJ22: Standard grid
B23: Adminstration | E23: COST | F23: =SUM(C9) -> 0 | G23: HOURS | H23: COST | I23: =C10 -> 55 | N23: Peakform | Q23: Waste 10% on product include in cost | Y23: Peakform | AB23: Waste 10% on product include in cost | AJ23: Peakform | AM23: Waste 10% on product include in cost
B24: MT45 3600 | C24: =C11 -> 1467 | D24: m | E24: =H9 -> 2.438 | F24: =C24*E24 -> 3576.546 | G24: =C24/10 -> 146.7 | H24: =G24*$I$23 -> 8068.5 | N24: Adminstration | Q24: COST | R24: =SUM(O10) -> 0 | S24: HOURS | T24: COST | U24: =O11 -> 55 | Y24: Adminstration | AB24: COST | AC24: =SUM(Z10) -> 0 | AD24: HOURS | AE24: COST | AF24: =Z11 -> 55 | AJ24: Adminstration | AM24: COST | AN24: =SUM(AK10) -> 0 | AO24: HOURS | AP24: COST | AQ24: =AK11 -> 55
B25: DX3600 | C25: =C7*90% -> 4803.3 | D25: m | E25: =H10 -> 3.3235 | F25: =C25*E25 -> 15963.768 | G25: =C25/23 -> 208.83913 | H25: =G25*$I$23 -> 11486.152 | N25: BPT1932H | O25: =O12 -> 1224 | P25: m | Q25: =T10 -> 2.438 | R25: =O25*Q25 -> 2984.112 | S25: =O25/10 -> 122.4 | T25: =S25*$U$24 -> 6732 | Y25: BPT1932H | Z25: =Z12 -> 1224 | AA25: m | AB25: =AE10 -> 2.53 | AC25: =Z25*AB25 -> 3096.72 | AD25: =Z25/10 -> 122.4 | AE25: =AD25*$U$24 -> 6732 | AJ25: BPT1932H | AK25: =AK12 -> 1224 | AL25: m | AM25: =AP10 -> 2.53 | AN25: =AK25*AM25 -> 3096.72 | AO25: =AK25/10 -> 122.4 | AP25: =AO25*$U$24 -> 6732
B26: DX1200 | C26: =C7*180% -> 9606.6 | D26: m | E26: =H11 -> 3.013 | F26: =C26*E26 -> 28944.686 | G26: =C26/23 -> 417.67826 | H26: =G26*$I$23 -> 22972.304 | N26: BP734042P | O26: =(O8/1.5)*1.07 -> 3807.06 | P26: m | Q26: =T11 -> 3.3235 | R26: =O26*Q26 -> 12652.764 | S26: =O26/23 -> 165.52435 | T26: =S26*$U$24 -> 9103.8391 | Y26: BP734042P | Z26: =(Z8/1.5)*1.07 -> 3807.06 | AA26: m | AB26: =AE11 -> 3.4615 | AC26: =Z26*AB26 -> 13178.138 | AD26: =Z26/23 -> 165.52435 | AE26: =AD26*$U$24 -> 9103.8391 | AJ26: BP734042P | AK26: =(AK8/1.5)*1.07 -> 3807.06 | AL26: m | AM26: =AP11 -> 3.45 | AN26: =AK26*AM26 -> 13134.357 | AO26: =AK26/23 -> 165.52435 | AP26: =AO26*$U$24 -> 9103.8391
B27: Wire | C27: =ROUND(C7/200, 0) -> 27 | D27: ea | E27: 100 | F27: =C27*E27 -> 2700 | N27: BP313052P | O27: =O8*180% -> 9606.6 | P27: m | Q27: =T12 -> 4.0595 | R27: =O27*Q27 -> 38997.993 | S27: =O27/23 -> 417.67826 | T27: =S27*$U$24 -> 22972.304 | Y27: BP313052P | Z27: =Z8*180% -> 9606.6 | AA27: m | AB27: =AE12 -> 4.2205 | AC27: =Z27*AB27 -> 40544.655 | AD27: =Z27/23 -> 417.67826 | AE27: =AD27*$U$24 -> 22972.304 | AJ27: BP313052P | AK27: =AK8*180% -> 9606.6 | AL27: m | AM27: =AP12 -> 3.864 | AN27: =AK27*AM27 -> 37119.902 | AO27: =AK27/23 -> 417.67826 | AP27: =AO27*$U$24 -> 22972.304
B28: Fixings | C28: =C7*66% -> 3522.42 | D28: ea | E28: 3 | F28: =C28*E28 -> 10567.26 | G28: =C28/13 -> 270.95538 | H28: =G28*$I$23 -> 14902.546 | N28: ACM7 Clips | O28: =SUM(O12/2)/0.9 -> 680 | P28: ea | Q28: =T14 -> 2.2655 | R28: =O28*Q28 -> 1540.54 | S28: =O28/30 -> 22.666667 | T28: =S28*$U$24 -> 1246.6667 | Y28: ACM7 Clips | Z28: =SUM(Z12/2)/0.9 -> 680 | AA28: ea | AB28: =AE14 -> 2.2655 | AC28: =Z28*AB28 -> 1540.54 | AD28: =Z28/30 -> 22.666667 | AE28: =AD28*$U$24 -> 1246.6667 | AJ28: ACM7 Clips | AK28: =SUM(AK12/2)/0.9 -> 680 | AL28: ea | AM28: =AP14 -> 2.2655 | AN28: =AK28*AM28 -> 1540.54 | AO28: =AK28/30 -> 22.666667 | AP28: =AO28*$U$24 -> 1246.6667
B29: Grid Only | C29: =F29+H29 -> 119181.76 | F29: =SUM(F23:F28) -> 61752.259 | H29: =SUM(H24:H28) -> 57429.503 | N29: Wire | O29: =ROUND(O8/200, 0) -> 27 | P29: ea | Q29: 115 | R29: =O29*Q29 -> 3105 | U29: =T29*$I$21 -> 0 | Y29: Wire | Z29: =ROUND(Z8/200, 0) -> 27 | AA29: ea | AB29: 115 | AC29: =Z29*AB29 -> 3105 | AF29: =AE29*$I$21 -> 0 | AJ29: Wire | AK29: =ROUND(AK8/200, 0) -> 27 | AL29: ea | AM29: 115 | AN29: =AK29*AM29 -> 3105 | AQ29: =AP29*$I$21 -> 0
C30: =C29/C7 -> 22.331228 | D30: M2 | E30: mat | F30: =F29/C7 -> 11.570594 | G30: lab | H30: =H29/C7 -> 10.760634 | I30: =H30/I23 -> 0.19564789 | N30: Fixings | O30: =O8*66% -> 3522.42 | P30: ea | Q30: 1.5 | R30: =O30*Q30 -> 5283.63 | S30: =O30/13 -> 270.95538 | T30: =S30*$U$24 -> 14902.546 | Y30: Fixings | Z30: =Z8*66% -> 3522.42 | AA30: ea | AB30: 1.5 | AC30: =Z30*AB30 -> 5283.63 | AD30: =Z30/13 -> 270.95538 | AE30: =AD30*$U$24 -> 14902.546 | AJ30: Fixings | AK30: =AK8*66% -> 3522.42 | AL30: ea | AM30: 1.5 | AN30: =AK30*AM30 -> 5283.63 | AO30: =AK30/13 -> 270.95538 | AP30: =AO30*$U$24 -> 14902.546
N31: Grid Only | O31: =R31+T31 -> 119521.39 | R31: =SUM(R24:R30) -> 64564.039 | T31: =SUM(T25:T30) -> 54957.356 | Y31: Grid Only | Z31: =AC31+AE31 -> 121706.04 | AC31: =SUM(AC24:AC30) -> 66748.683 | AE31: =SUM(AE25:AE30) -> 54957.356 | AJ31: Grid Only | AK31: =AN31+AP31 -> 118237.51 | AN31: =SUM(AN24:AN30) -> 63280.149 | AP31: =SUM(AP25:AP30) -> 54957.356
B32: Ceiling Tiles | C32: =C7/0.72 -> 7412.5 | D32: ea | E32: =C13 -> 22.636897 | F32: =C32*E32 -> 167796 | G32: =C7/10 -> 533.7 | H32: =G32*$I$23 -> 29353.5 | O32: =O31/O8 -> 22.394865 | P32: M2 | Q32: mat | R32: =R31/O8 -> 12.09744 | S32: lab | T32: =T31/O8 -> 10.297425 | U32: =T32/U24 -> 0.18722591 | Z32: =Z31/Z8 -> 22.804205 | AA32: M2 | AB32: mat | AC32: =AC31/Z8 -> 12.50678 | AD32: lab | AE32: =AE31/Z8 -> 10.297425 | AF32: =AE32/AF24 -> 0.18722591 | AK32: =AK31/AK8 -> 22.154301 | AL32: M2 | AM32: mat | AN32: =AN31/AK8 -> 11.856876 | AO32: lab | AP32: =AP31/AK8 -> 10.297425 | AQ32: =AP32/AQ24 -> 0.18722591
B33: Tiles Only | C33: =F32+H32 -> 197149.5
C34: =C33/C7 -> 36.940135 | D34: M2 | E34: mat | F34: =F32/C7 -> 31.440135 | G34: lab | H34: =H32/C7 -> 5.5 | I34: m2 | J34: =H34/I23 -> 0.1 | N34: Ceiling Tiles | O34: =O8/0.9 -> 5930 | P34: ea | Q34: =O14 -> 31.689713 | R34: =O34*Q34 -> 187920 | S34: =O8/10 -> 533.7 | T34: =S34*$U$24 -> 29353.5 | Y34: Ceiling Tiles | Z34: =Z8/0.9 -> 5930 | AA34: ea | AB34: =Z14 -> 34.360877 | AC34: =Z34*AB34 -> 203760 | AD34: =Z8/10 -> 533.7 | AE34: =AD34*$U$24 -> 29353.5 | AJ34: Ceiling Tiles | AK34: =AK8/0.9 -> 5930 | AL34: ea | AM34: =AK14 -> 32.693929 | AN34: =AK34*AM34 -> 193875 | AO34: =AK8/10 -> 533.7 | AP34: =AO34*$U$24 -> 29353.5
G35: =SUM(G24:G32) -> 1577.8728 | H35: tot hours | N35: Tiles Only | O35: =R34+T34 -> 217273.5 | Y35: Tiles Only | Z35: =AC34+AE34 -> 233113.5 | AJ35: Tiles Only | AK35: =AN34+AP34 -> 223228.5
B36: Cost | C36: =C30+C34 -> 59.271363 | D36: M2 | O36: =O35/O8 -> 40.710793 | P36: M2 | Q36: mat | R36: =R34/O8 -> 35.210793 | S36: lab | T36: =T34/O8 -> 5.5 | U36: m2 | V36: =T36/U24 -> 0.1 | Z36: =Z35/Z8 -> 43.678752 | AA36: M2 | AB36: mat | AC36: =AC34/Z8 -> 38.178752 | AD36: lab | AE36: =AE34/Z8 -> 5.5 | AF36: m2 | AG36: =AE36/AF24 -> 0.1 | AK36: =AK35/AK8 -> 41.826588 | AL36: M2 | AM36: mat | AN36: =AN34/AK8 -> 36.326588 | AO36: lab | AP36: =AP34/AK8 -> 5.5 | AQ36: m2 | AR36: =AP36/AQ24 -> 0.1
E37: mat | S37: =SUM(S25:S34) -> 1532.9247 | T37: tot hours | AD37: =SUM(AD25:AD34) -> 1532.9247 | AE37: tot hours | AO37: =SUM(AO25:AO34) -> 1532.9247 | AP37: tot hours
E38: =F32+F29 -> 229548.26 | H38: Actual cost of ceiling | N38: Cost | O38: =O32+O36 -> 63.105658 | P38: M2 | Y38: Cost | Z38: =Z32+Z36 -> 66.482957 | AA38: M2 | AJ38: Cost | AK38: =AK32+AK36 -> 63.980889 | AL38: M2
E39: =F34+F30 -> 43.010729 | F39: m2 | H39: =E39 -> 43.010729 | I39: m2 | Q39: mat | AB39: mat | AM39: mat
E40: lab | Q40: =R34+R31 -> 252484.04 | T40: Actual cost of ceiling | AB40: =AC34+AC31 -> 270508.68 | AE40: Actual cost of ceiling | AM40: =AN34+AN31 -> 257155.15 | AP40: Actual cost of ceiling
E41: =H32+H29 -> 86783.003 | H41: Contract rate | O41: =Q41/Q46 -> 0.74966706 | Q41: =R36+R32 -> 47.308233 | R41: m2 | T41: =Q41 -> 47.308233 | U41: m2 | Z41: =AB41/AB46 -> 0.76238384 | AB41: =AC36+AC32 -> 50.685532 | AC41: m2 | AE41: =AB41 -> 50.685532 | AF41: m2 | AK41: =AM41/AM46 -> 0.75309151 | AM41: =AN36+AN32 -> 48.183464 | AN41: m2 | AP41: =AM41 -> 48.183464 | AQ41: m2
E42: =E41/C7 -> 16.260634 | F42: m2 | H42: =E42 -> 16.260634 | Q42: lab | AB42: lab | AM42: lab
D43: Actual cost | Q43: =T34+T31 -> 84310.856 | T43: Contract rate | AB43: =AE34+AE31 -> 84310.856 | AE43: Contract rate | AM43: =AP34+AP31 -> 84310.856 | AP43: Contract rate
E44: =E39+E42 -> 59.271363 | O44: =Q44/Q46 -> 0.25033294 | Q44: =T36+T32 -> 15.797425 | R44: m2 | T44: 6.5 | Z44: =AB44/AB46 -> 0.23761616 | AB44: =AE36+AE32 -> 15.797425 | AC44: m2 | AE44: 6.5 | AK44: =AM44/AM46 -> 0.24690849 | AM44: =AP36+AP32 -> 15.797425 | AN44: m2 | AP44: 6.5
D45: Contract cost | H45: =H39+H42 -> 59.271363 | P45: Actual cost | AA45: Actual cost | AL45: Actual cost
H46: =E45-H45 -> -59.271363 | I46: difference | Q46: =Q41+Q44 -> 63.105658 | AB46: =AB41+AB44 -> 66.482957 | AM46: =AM41+AM44 -> 63.980889
D47: 0.05 | E47: =E44*D47 -> 2.9635681 | H47: =H46*C7 -> -316331.26 | I47: gain from contract rate | P47: Contract cost | T47: =T41+T44 -> 53.808233 | AA47: Contract cost | AE47: =AE41+AE44 -> 57.185532 | AL47: Contract cost | AP47: =AP41+AP44 -> 54.683464
D48: 0.04 | E48: =E44*D48 -> 2.3708545 | T48: =Q47-T47 -> -53.808233 | U48: difference | AE48: =AB47-AE47 -> -57.185532 | AF48: difference | AP48: =AM47-AP47 -> -54.683464 | AQ48: difference
E49: =SUM(E44:E48) -> 64.605785 | P49: P&G | Q49: =Q46*0.04 -> 2.5242263 | T49: =T48*O8 -> -287174.54 | U49: gain from contract rate | AA49: P&G | AB49: =AB46*0.04 -> 2.6593183 | AE49: =AE48*Z8 -> -305199.18 | AF49: gain from contract rate | AL49: P&G | AM49: =AM46*0.04 -> 2.5592356 | AP49: =AP48*AK8 -> -291845.65 | AQ49: gain from contract rate
D50: 0.1 | E50: =E49*D50 -> 6.4605785 | P50: Loading | Q50: =Q46*0.02 -> 1.2621132 | AA50: Loading | AB50: =AB46*0.02 -> 1.3296591 | AL50: Loading | AM50: =AM46*0.02 -> 1.2796178
E51: =SUM(E49:E50) -> 71.066364 | P51: Margin | Q51: =Q46*0.1 -> 6.3105658 | AA51: Margin | AB51: =AB46*0.1 -> 6.6482957 | AL51: Margin | AM51: =AM46*0.1 -> 6.3980889
Q52: =SUM(Q46:Q51) -> 73.202563 | AB52: =SUM(AB46:AB51) -> 77.12023 | AM52: =SUM(AM46:AM51) -> 74.217831
G58: Wires
B59: Suspended system | F59: Dis between TCR | G59: Across TCR wire | O59: Suspended system | S59: Dis between TCR | T59: Across TCR wire
B60: 28mm furring channel @ | C60: 0.6 | E60: TCR spacing | F60: 1.2 | G60: 1.2 | O60: 28mm furring channel @ | P60: 0.6 | R60: TCR spacing | S60: 1.2 | T60: 1.2
B61: 40 x 40 | C61: 1376 | O61: 40 x 40 | P61: 1085
B62: M2 | C62: 988 | E62: Total furring LM | F62: Total Perim LM | G62: M2 of ceiling | O62: M2 | P62: 735 | R62: Total furring LM | S62: Total Perim LM | T62: M2 of ceiling
B63: Material | E63: =SUM(G63/C60) -> 1646.6667 | F63: =C61 -> 1376 | G63: =C62 -> 988 | O63: Material | R63: =SUM(T63/P60) -> 1225 | S63: =P61 -> 1085 | T63: =P62 -> 735
C64: $/m | I64: 1st March 5% | P64: $/m | V64: 1st March 5%
D65: Area | E65: M/No | F65: Total | G65: Waste | I65: 1 | Q65: Area | R65: M/No | S65: Total | T65: Waste | V65: 1
B66: 28mm furring channel | C66: 1.86 | D66: Change on spacings | E66: =G63/C60 -> 1646.6667 | F66: =SUM(C66*E66) -> 3062.8 | H66: 2.38 | I66: =H66*$I$65 -> 2.38 | O66: 28mm furring channel | P66: 2.18 | Q66: Change on spacings | R66: =T63/P60 -> 1225 | S66: =SUM(P66*R66) -> 2670.5 | U66: 2.38 | V66: =U66*$I$65 -> 2.38
B67: Joiner KL 138 | C67: 4.45 | D67: =C60*3.6 -> 2.16 | E67: =(G63/D67) -> 457.40741 | F67: =SUM(C67*E67) -> 2035.463 | H67: 1.1 | I67: =H67*$I$65 -> 1.1 | O67: Joiner KL 138 | P67: =V67 -> 1.1 | Q67: =P60*3.6 -> 2.16 | R67: =(T63/Q67) -> 340.27778 | S67: =SUM(P67*R67) -> 374.30556 | U67: 1.1 | V67: =U67*$I$65 -> 1.1
B68: Locking clip KL 139 | C68: 0.42 | D68: =C60*F60 -> 0.72 | E68: =(G63/D68) -> 1372.2222 | F68: =SUM(C68*E68) -> 576.33333 | H68: 0.4 | I68: =H68*$I$65 -> 0.4 | O68: Locking clip KL 139 | P68: =V68 -> 0.4 | Q68: =P60*S60 -> 0.72 | R68: =(T63/Q68) -> 1020.8333 | S68: =SUM(P68*R68) -> 408.33333 | U68: 0.4 | V68: =U68*$I$65 -> 0.4
B69: TCR | C69: 3.97 | D69: =F60 -> 1.2 | E69: =(G63/D69) -> 823.33333 | F69: =SUM(C69*E69) -> 3268.6333 | H69: 3.3 | I69: =H69*$I$65 -> 3.3 | O69: TCR | P69: 2.27 | Q69: =S60 -> 1.2 | R69: =(T63/Q69) -> 612.5 | S69: =SUM(P69*R69) -> 1390.375 | U69: 3.3 | V69: =U69*$I$65 -> 3.3
B70: Hanging wire | C70: 90 | E70: =ROUNDUP(G63/200,0) -> 5 | F70: =SUM(C70*E70) -> 450 | O70: Hanging wire | P70: 90 | R70: =ROUNDUP(T63/200,0) -> 4 | S70: =SUM(P70*R70) -> 360
B71: Fixings (to substrate) | C71: =L71 -> 3.7 | E71: =(G63/F60/G60) -> 686.11111 | F71: =C71*E71 -> 2538.6111 | H71: 0.7 | I71: =H71*$I$65 -> 0.7 | J71: Plus Fixings | K71: 3 | L71: =SUM(I71,K71) -> 3.7 | O71: Fixings (to substrate) | P71: =Y71 -> 3.7 | R71: =(T63/S60/T60) -> 510.41667 | S71: =P71*R71 -> 1888.5417 | U71: 0.7 | V71: =U71*$I$65 -> 0.7 | W71: Plus Fixings | X71: 3 | Y71: =SUM(V71,X71) -> 3.7
B72: Quack Perimeter | C72: =L89 -> 6.735 | E72: =C61 -> 1376 | F72: =C72*E72 -> 9267.36 | H72: 3.97 | I72: =H72*$I$65 -> 3.97 | O72: 141 Channel/40 x 40 x 1.15 Angle | P72: 3.44 | R72: =P61 -> 1085 | S72: =P72*R72 -> 3732.4 | U72: 3.97 | V72: =U72*$I$65 -> 3.97
F73: =SUM(F66:F72) -> 21199.201 | S73: =SUM(S66:S72) -> 10824.456
B74: Material cost per m2 | C74: =F73/G63 -> 21.456681 | O74: Material cost per m2 | P74: =S73/T63 -> 14.72715
B75: Fixings (screws) | C75: 0.015 | O75: Fixings (screws) | P75: 0.015
B76: Unload | C76: 0.03 | O76: Unload | P76: 0.03
C77: =SUM(C74:C76) -> 21.501681 | P77: =SUM(P74:P76) -> 14.77215
B78: waste 5% | C78: =C77*5% -> 1.075084 | O78: waste 5% | P78: =P77*5% -> 0.73860752
B79: Material cost per m2 | C79: =SUM(C77:C78) -> 22.576765 | O79: Material cost per m2 | P79: =SUM(P77:P78) -> 15.510758
K80: Comfortech List | L80: Comfortech Spec | M80: SRP List | N80: SRP Spec
E81: lab rate | J81: TCR | K81: 5.25 | L81: 3.97 | R81: lab rate
E82: 50 | J82: Furring | K82: 3.17 | L82: 1.86 | R82: 50
B83: Labour per m as per rates | D83: m/hr | J83: Perimeter Quak | K83: 12.74 | L83: 11.82 | O83: Labour per m as per rates | Q83: m/hr
B84: Furring channel | C84: =E82/D84 -> 2 | D84: 25 | E84: =C84*E63 -> 3293.3333 | J84: Quack FC joiner | K84: 4.45 | L84: 4.63 | O84: Furring channel | P84: =R82/Q84 -> 2 | Q84: 25 | R84: =P84*R63 -> 2450
B85: TCR | C85: =E82/D85 -> 5 | D85: 10 | E85: =E69*C85 -> 4116.6667 | J85: Locking Key | K85: 0.58 | L85: 0.42 | O85: TCR | P85: =R82/Q85 -> 5 | Q85: 10 | R85: =R69*P85 -> 3062.5
B86: Fixings | C86: =E82/D86 -> 1.6666667 | D86: 30 | E86: =SUM(C86*E71) -> 1143.5185 | J86: Perimeter Std | L86: 1.65 | O86: Fixings | P86: =R82/Q86 -> 1.6666667 | Q86: 30 | R86: =SUM(P86*R71) -> 850.69444
B87: 40 x 40 | C87: =E82/D87 -> 5 | D87: 10 | E87: =C61*C87 -> 6880 | O87: 40 x 40 | P87: =R82/Q87 -> 5 | Q87: 10 | R87: =P61*P87 -> 5425
E88: =SUM(E84:E87) -> 15433.519 | L88: =SUM(L83,L86) -> 13.47 | R88: =SUM(R84:R87) -> 11788.194
B89: Labour cost per m2 | C89: =E88/G63 -> 15.62097 | L89: =L88/2 -> 6.735 | O89: Labour cost per m2 | P89: =R88/T63 -> 16.03836
C90: =SUM(C79+C89) -> 38.197735 | D90: m2 | E90: Total cost per m2 | H90: 31.51 | I90: =C90-H90 -> 6.6877351 | J90: =C61*I90 -> 9202.3235 | P90: =SUM(P79+P89) -> 31.549118 | Q90: m2 | R90: Total cost per m2
B91: Total cost of ceiling job is | E91: =C90*G63 -> 37739.362 | O91: Total cost of ceiling job is | R91: =P90*T63 -> 23188.602
B93: Cost per m2 | O93: Cost per m2
B94: Material | C94: =C79 -> 22.576765 | D94: m2 | O94: Material | P94: =P79 -> 15.510758 | Q94: m2
B95: Labour | C95: =C89 -> 15.62097 | D95: m2 | E95: =C95*G63 -> 15433.519 | F95: =E95/E82 -> 308.67037 | G95: hrs | O95: Labour | P95: =P89 -> 16.03836 | Q95: m2 | R95: =P95*T63 -> 11788.194 | S95: =R95/R82 -> 235.76389 | T95: hrs
C96: =C95/E82 -> 0.3124194 | P96: =P95/R82 -> 0.3207672
C105: Hatch | D105: Freight | E105: Labour frame out and Install Hatch | F105: Stopping Material | G105: Stopping Labour | M105: =SUM(#REF!) -> #REF! | O105: =#REF! -> #REF!
B106: 300 x 300 - Set Bead | C106: 75 | D106: 5 | E106: 1.5 | F106: 2.5 | G106: 1 | I106: =E106+G106 -> 2.5 | J106: =I106*#REF! -> #REF! | K106: =SUM(C106:D106,F106) -> 82.5 | L106: =SUM(J106:K106) -> #REF! | M106: =L106*$M$105 -> #REF! | N106: =SUM(L106:M106) -> #REF! | O106: =N106*$O$105 -> #REF! | P106: =SUM(N106:O106) -> #REF!
B107: 450 x 450 - Set Bead | C107: 82 | D107: 5 | E107: 1.5 | F107: 3.75 | G107: 1 | I107: =E107+G107 -> 2.5 | J107: =I107*#REF! -> #REF! | K107: =SUM(C107:D107,F107) -> 90.75 | L107: =SUM(J107:K107) -> #REF! | M107: =L107*$M$105 -> #REF! | N107: =SUM(L107:M107) -> #REF! | O107: =N107*$O$105 -> #REF! | P107: =SUM(N107:O107) -> #REF!
B108: 530 x 530 - Set Bead | C108: 89 | D108: 5 | E108: 1.5 | F108: 4.25 | G108: 1 | I108: =E108+G108 -> 2.5 | J108: =I108*#REF! -> #REF! | K108: =SUM(C108:D108,F108) -> 98.25 | L108: =SUM(J108:K108) -> #REF! | M108: =L108*$M$105 -> #REF! | N108: =SUM(L108:M108) -> #REF! | O108: =N108*$O$105 -> #REF! | P108: =SUM(N108:O108) -> #REF!
C111: Hatch | D111: Freight | E111: Labour frame out and Install Hatch | F111: Stopping Material | G111: Stopping Labour | M111: =M105 -> #REF! | O111: =O105 -> #REF!
B112: 300 x 300 - Set Bead
B113: 450 x 450 - Set Bead | C113: 750 | D113: 5 | E113: 1.5 | F113: 3.75 | G113: 1.5 | I113: =E113+G113 -> 3 | J113: =I113*#REF! -> #REF! | K113: =SUM(C113:D113,F113) -> 758.75 | L113: =SUM(J113:K113) -> #REF! | M113: =L113*$M$105 -> #REF! | N113: =SUM(L113:M113) -> #REF! | O113: =N113*$O$105 -> #REF! | P113: =SUM(N113:O113) -> #REF!
B114: 530 x 530 - Set Bead | C114: 940 | D114: 15 | E114: 2.5 | F114: 4.25 | G114: 1.5 | I114: =E114+G114 -> 4 | J114: =I114*#REF! -> #REF! | K114: =SUM(C114:D114,F114) -> 959.25 | L114: =SUM(J114:K114) -> #REF! | M114: =L114*$M$105 -> #REF! | N114: =SUM(L114:M114) -> #REF! | O114: =N114*$O$105 -> #REF! | P114: =SUM(N114:O114) -> #REF!
C122: 92mm steel studs @ | D122: 0.6 | E122: Stud spacing | O122: 92mm steel studs @ | P122: 1.8 | Q122: Stud spacing | Y122: 92mm steel studs @ | Z122: 1.8 | AA122: Stud spacing | AD122: TYPE 3 | AI122: 92mm steel studs @ | AJ122: 2.4 | AK122: Stud spacing | AN122: TYPE 2
C124: Material | E124: Length of wall | F124: Height of wall | G124: Total stud LM | H124: Total track LM | I124: M2 of wall | O124: Material | Q124: Length of wall | R124: Height of wall | S124: Total stud LM | T124: Total track LM | U124: M2 of wall | Y124: Material | AA124: Length of wall | AB124: Height of wall | AC124: Total stud LM | AD124: Total track LM | AE124: M2 of wall | AI124: Material | AK124: Length of wall | AL124: Height of wall | AM124: Total stud LM | AN124: Total track LM | AO124: M2 of wall
D125: $/m | E125: 106 | F125: 1 | G125: =SUM(E152*F125) -> 177.66667 | H125: =E125*2 -> 212 | I125: =E125*F125 -> 106 | P125: $/m | Q125: 106 | R125: 1 | S125: =SUM(Q152*R125) -> 59.888889 | T125: =Q125*2 -> 212 | U125: =Q125*R125 -> 106 | Z125: $/m | AA125: 116 | AB125: 1 | AC125: =SUM(AA152*AB125) -> 65.444444 | AD125: =AA125*2 -> 232 | AE125: =AA125*AB125 -> 116 | AJ125: $/m | AK125: 3 | AL125: 1.9 | AM125: =SUM(AK152*AL125)*2 -> 8.55 | AN125: =AK125*2 -> 6 | AO125: =AK125*AL125 -> 5.7
B126: Stud | C126: 64 .75 bmt | D126: 4.09 | N126: Stud | O126: 92 .75 bmt | P126: 4.09 | X126: Stud | Y126: 92 .75 bmt | Z126: 5.06 | AC126: Bracket | AH126: Stud | AI126: 92 .75 bmt | AJ126: 5.06 | AM126: Bracket
Z127: =AE127 -> 5 | AB127: =AA152 -> 65.444444 | AC127: 5 | AD127: =AB127*AC127 -> 327.22222 | AE127: =AD127/AC125 -> 5 | AJ127: =AO127 -> 1.3157895 | AL127: =AK152 -> 2.25 | AM127: 5 | AN127: =AL127*AM127 -> 11.25 | AO127: =AN127/AM125 -> 1.3157895
...

Sheet Sheet1
E7: ***POST APRIL***
B8: Armstrong
B10: Job Name
B11: total sqm | C11: 4001 | D11: m2 | F11: Standard grid | H11: 5% Freight
B12: Cost Plus Margin | F12: Nett cost | H12: 10% waste
B13: admin | F13: Wall angle | G13: 2.2 | H13: =G13*1.15 -> 2.53
B14: hourly rate | C14: 50 | F14: Mains | G14: 3 | H14: =G14*1.15 -> 3.45
B15: wall trim | C15: 1698 | D15: m | F15: 1500 Nogs | G15: 3.36 | H15: =G15*1.15 -> 3.864
B16: tile type | C16: Eurocoustic Tonga white
B17: tile price | C17: =K23 -> 32.725044 | D17: per tile | F17: Berc Clips | G17: 1.97 | H17: =G17*1.15 -> 2.2655
B18: Module | C18: 1500 x 600
I19: $28.28 per tile plus 5% Freight $29.69
I20: tiles plus 10% wastage
B21: Total Cost | C21: =C11*C41 -> 257933.41 | I21: 4891 | J21: 490 boxes
B22: Total Revenue | C22: =C21*(1+C12) -> 257933.41 | D22: Price | I22: 490 boxes @ $296.90 | K22: 145481
B23: Profit | C23: =C22-C21 -> 0 | K23: =K22/C37 -> 32.725044
B25: Standard grid
B26: Peakform | E26: Waste 10% on product include in cost
B27: Adminstration | E27: COST | F27: =SUM(C13) -> 0 | G27: HOURS | H27: COST | I27: 50
B28: BPT1932H | C28: =C15 -> 1698 | D28: m | E28: =H13 -> 2.53 | F28: =C28*E28 -> 4295.94 | G28: =C28/10 -> 169.8 | H28: =G28*$I$27 -> 8490 | I28: =H28/I27 -> 169.8 | J28: =I28/C15 -> 0.1 | K28: =F28/C28 -> 2.53
B29: BP734042P | C29: =(C11/1.5)*1.07 -> 2854.0467 | D29: m | E29: =H14 -> 3.45 | F29: =C29*E29 -> 9846.461 | G29: =C29/23 -> 124.08899 | H29: =G29*$I$27 -> 6204.4493
B30: BP313052P | C30: =C11*180% -> 7201.8 | D30: m | E30: =H15 -> 3.864 | F30: =C30*E30 -> 27827.755 | G30: =C30/23 -> 313.12174 | H30: =G30*$I$27 -> 15656.087
B31: ACM7 Clips | C31: =SUM(C15/2)/0.9 -> 943.33333 | D31: ea | E31: =H17 -> 2.2655 | F31: =C31*E31 -> 2137.1217 | G31: =C31/30 -> 31.444444 | H31: =G31*$I$27 -> 1572.2222
B32: Wire | C32: =ROUND(C11/200, 0) -> 20 | D32: ea | E32: 115 | F32: =C32*E32 -> 2300 | I32: =H32*$I$21 -> 0
B33: Fixings | C33: =C11*66% -> 2640.66 | D33: ea | E33: 1.5 | F33: =C33*E33 -> 3960.99 | G33: =C33/13 -> 203.12769 | H33: =G33*$I$27 -> 10156.385
B34: Grid Only | C34: =F34+H34 -> 92447.411 | F34: =SUM(F27:F33) -> 50368.268 | H34: =SUM(H28:H33) -> 42079.143
C35: =C34/C11 -> 23.106076 | D35: M2 | E35: mat | F35: =F34/C11 -> 12.58892 | G35: lab | H35: =H34/C11 -> 10.517156 | I35: =H35/I27 -> 0.21034313 | J35: =I35-J28 -> 0.11034313
B37: Ceiling Tiles | C37: =C11/0.9 -> 4445.5556 | D37: ea | E37: =C17 -> 32.725044 | F37: =C37*E37 -> 145481 | G37: =C11/10 -> 400.1 | H37: =G37*$I$27 -> 20005
B38: Tiles Only | C38: =F37+H37 -> 165486
C39: =C38/C11 -> 41.36116 | D39: M2 | E39: mat | F39: =F37/C11 -> 36.36116 | G39: lab | H39: =H37/C11 -> 5 | I39: m2 | J39: =H39/I27 -> 0.1
G40: =SUM(G28:G37) -> 1241.6829 | H40: tot hours
B41: Cost | C41: =C35+C39 -> 64.467236 | D41: M2
E42: mat
E43: =F37+F34 -> 195849.27 | H43: Actual cost of ceiling
C44: =E44/E49 -> 0.75930166 | E44: =F39+F35 -> 48.950079 | F44: m2 | H44: =E44 -> 48.950079 | I44: m2
E45: lab
E46: =H37+H34 -> 62084.143 | H46: Contract rate
C47: =E47/E49 -> 0.24069834 | E47: =H39+H35 -> 15.517156 | F47: m2 | H47: 6.5
D48: Actual cost
E49: =E44+E47 -> 64.467236
D50: Contract cost | H50: =H44+H47 -> 55.450079
H51: =E50-H50 -> -55.450079 | I51: difference
D52: P&G | E52: =E49*0.04 -> 2.5786894 | H52: =H51*C11 -> -221855.77 | I52: gain from contract rate
D53: Loading | E53: =E49*0.02 -> 1.2893447
D54: Margin | E54: =E49*0.1 -> 6.4467236
E55: =SUM(E49:E54) -> 74.781994
E63: ***POST APRIL***
B64: Armstrong
B66: Job Name
B67: total sqm | C67: 665 | D67: m2 | F67: Standard grid | H67: 5% Freight
B68: Cost Plus Margin | F68: Nett cost | H68: 10% waste
B69: admin | F69: Wall angle | G69: 2.2 | H69: =G69*1.15 -> 2.53
B70: hourly rate | C70: 50 | F70: Mains | G70: 3 | H70: =G70*1.15 -> 3.45
B71: wall trim | C71: 338 | D71: m | F71: 1500 Nogs | G71: 3.36 | H71: =G71*1.15 -> 3.864
B72: tile type | C72: Eurocoustic Tonga white
B73: tile price | C73: =K80 -> 32.73 | D73: per tile | F73: Berc Clips | G73: 1.97 | H73: =G73*1.15 -> 2.2655
B74: Module | C74: 1500 x 600
I75: $28.28 per tile plus 5% Freight $29.69
I76: tiles plus 10% wastage
B77: Total Cost | C77: =C67*C97 -> 45508.842 | I77: 4891 | J77: 490 boxes
B78: Total Revenue | C78: =C77*(1+C68) -> 45508.842 | D78: Price | I78: 490 boxes @ $296.90 | K78: 145481
B79: Profit | C79: =C78-C77 -> 0 | K79: =K78/C93 -> 196.89158
K80: 32.73
B81: Standard grid
B82: Peakform | E82: Waste 10% on product include in cost
B83: Adminstration | E83: COST | F83: =SUM(C69) -> 0 | G83: HOURS | H83: COST | I83: 60
B84: BPT1932H | C84: =C71 -> 338 | D84: m | E84: =H69 -> 2.53 | F84: =C84*E84 -> 855.14 | G84: =C84/10 -> 33.8 | H84: =G84*$I$83 -> 2028 | I84: =H84/I83 -> 33.8 | J84: =I84/C71 -> 0.1 | K84: =F84/C84 -> 2.53
B85: BP734042P | C85: =(C67/1.5)*1.07 -> 474.36667 | D85: m | E85: =H70 -> 3.45 | F85: =C85*E85 -> 1636.565 | G85: =C85/23 -> 20.624638 | H85: =G85*$I$83 -> 1237.4783
B86: BP313052P | C86: =C67*180% -> 1197 | D86: m | E86: =H71 -> 3.864 | F86: =C86*E86 -> 4625.208 | G86: =C86/23 -> 52.043478 | H86: =G86*$I$83 -> 3122.6087
B87: ACM7 Clips | C87: =SUM(C71/2)/0.9 -> 187.77778 | D87: ea | E87: =H73 -> 2.2655 | F87: =C87*E87 -> 425.41056 | G87: =C87/30 -> 6.2592593 | H87: =G87*$I$83 -> 375.55556
B88: Wire | C88: =ROUND(C67/200, 0) -> 3 | D88: ea | E88: 115 | F88: =C88*E88 -> 345 | I88: =H88*$I$21 -> 0
B89: Fixings | C89: =C67*66% -> 438.9 | D89: ea | E89: 1.5 | F89: =C89*E89 -> 658.35 | G89: =C89/13 -> 33.761538 | H89: =G89*$I$83 -> 2025.6923
B90: Grid Only | C90: =F90+H90 -> 17335.008 | F90: =SUM(F83:F89) -> 8545.6736 | H90: =SUM(H84:H89) -> 8789.3348
C91: =C90/C67 -> 26.067682 | D91: M2 | E91: mat | F91: =F90/C67 -> 12.850637 | G91: lab | H91: =H90/C67 -> 13.217045 | I91: =H91/I83 -> 0.22028408 | J91: =I91-J84 -> 0.12028408
B93: Ceiling Tiles | C93: =C67/0.9 -> 738.88889 | D93: ea | E93: =C73 -> 32.73 | F93: =C93*E93 -> 24183.833 | G93: =C67/10 -> 66.5 | H93: =G93*$I$83 -> 3990
B94: Tiles Only | C94: =F93+H93 -> 28173.833
C95: =C94/C67 -> 42.366667 | D95: M2 | E95: mat | F95: =F93/C67 -> 36.366667 | G95: lab | H95: =H93/C67 -> 6 | I95: m2 | J95: =H95/I83 -> 0.1
G96: =SUM(G84:G93) -> 212.98891 | H96: tot hours
B97: Cost | C97: =C91+C95 -> 68.434348 | D97: M2
E98: mat
E99: =F93+F90 -> 32729.507 | H99: Actual cost of ceiling
C100: =E100/E105 -> 0.71919007 | E100: =F95+F91 -> 49.217304 | F100: m2 | H100: =E100 -> 49.217304 | I100: m2
E101: lab
E102: =H93+H90 -> 12779.335 | H102: Contract rate
C103: =E103/E105 -> 0.28080993 | E103: =H95+H91 -> 19.217045 | F103: m2 | H103: 6.5
D104: Actual cost
E105: =E100+E103 -> 68.434348
D106: Contract cost | H106: =H100+H103 -> 55.717304
H107: =E106-H106 -> -55.717304 | I107: difference
D108: P&G | E108: =E105*0.04 -> 2.7373739 | H108: =H107*C67 -> -37052.007 | I108: gain from contract rate
D109: Loading | E109: =E105*0.02 -> 1.368687
D110: Margin | E110: =E105*0.1 -> 6.8434348
E111: =SUM(E105:E110) -> 79.383844

Sheet Steel Stud Partitions_25_8
B1: =Summary!B1 -> Ceilings Unlimited
B2: =Summary!B2 -> 2 Devonport Road
B3: =Summary!B3 -> Tauranga
B6: 45853
B9: Steel Stud Partitions
H11: 50
A12: Item | B12: Description | C12: Qty | D12: Unit | E12: Constant | F12: Constant X Unit = Total HRS | G12: $ Lab per Unit | H12: Total Labour | I12: Materials per Unit | J12: Total Materials | K12: Total Labour & Materials | L12: Total Labour & Materials Per Unit | M12: Total | N12: % Complete | O12: Claim | U12: =SUM(C16,C22,C29,C35,C42,C47,C55,C60,C68,C73,C81,C86,C94,C99,C107) -> 1912
B15: Basement:
B16: (WA52) 92mm x 0.55 Whisper Wall Stud (3.4m) | C16: 98 | D16: m2 | E16: =$Y$20 -> 0.4 | F16: =C16*E16 -> 39.2 | G16: =$H$11*E16 -> 20 | H16: =F16*$H$11 -> 1960 | I16: 15.19 | J16: =C16*I16 -> 1488.62 | K16: =SUM(H16,J16) -> 3448.62 | L16: =K16/C16 -> 35.19 | M16: =C16*L16 -> 3448.62 | N16: 0 | O16: =M16*N16 -> 0 | T16: 29/lm
B17: EV Stud to Corners/Wall Ends | C17: 133 | D17: m | E17: 0.07 | F17: =C17*E17 -> 9.31 | G17: =$H$11*E17 -> 3.5 | H17: =F17*$H$11 -> 465.5 | I17: 7 | J17: =C17*I17 -> 931 | K17: =SUM(H17,J17) -> 1396.5 | L17: =K17/C17 -> 10.5 | M17: =C17*L17 -> 1396.5 | N17: 0 | O17: =M17*N17 -> 0
B18: Infill to Comflor take head track | C18: 29 | D18: m | E18: 0.25 | F18: =C18*E18 -> 7.25 | G18: =$H$11*E18 -> 12.5 | H18: =F18*$H$11 -> 362.5 | I18: 15 | J18: =C18*I18 -> 435 | K18: =SUM(H18,J18) -> 797.5 | L18: =K18/C18 -> 27.5 | M18: =C18*L18 -> 797.5 | N18: 0 | O18: =M18*N18 -> 0 | V18: =SUM(F17,F16) -> 48.51
B19: Gib Packing to Head | C19: 29 | D19: m | E19: 0.15 | F19: =C19*E19 -> 4.35 | G19: =$H$11*E19 -> 7.5 | H19: =F19*$H$11 -> 217.5 | I19: 6 | J19: =C19*I19 -> 174 | K19: =SUM(H19,J19) -> 391.5 | L19: =K19/C19 -> 13.5 | M19: =C19*L19 -> 391.5 | N19: 0 | O19: =M19*N19 -> 0 | V19: =V18/C16 -> 0.495
P20: =SUM(M16:M19) -> 6034.12 | Q20: =P20*SUM($L$115:$L$119) -> 573.2414 | Y20: 0.4
B21: Ground: | P21: =P20/$M$112 -> 0.065341427 | Q21: =P21*$M$123 -> 154.95866 | R21: =SUM(P20,Q20,Q21) -> 6762.3201 | S21: =R21*1.08 -> 7303.3057
B22: (WA06) 64mm x 0.55 Steel Stud (4.2m) | C22: 95 | D22: m2 | E22: =$Y$20 -> 0.4 | F22: =C22*E22 -> 38 | G22: =$H$11*E22 -> 20 | H22: =F22*$H$11 -> 1900 | I22: 10.77 | J22: =C22*I22 -> 1023.15 | K22: =SUM(H22,J22) -> 2923.15 | L22: =K22/C22 -> 30.77 | M22: =C22*L22 -> 2923.15 | N22: 0 | O22: =M22*N22 -> 0 | T22: 23/lm | V22: =SUM(F22:F23) -> 41.55
B23: EV Stud to Corners/Wall Ends | C23: 71 | D23: m | E23: 0.05 | F23: =C23*E23 -> 3.55 | G23: =$H$11*E23 -> 2.5 | H23: =F23*$H$11 -> 177.5 | I23: 2.7 | J23: =C23*I23 -> 191.7 | K23: =SUM(H23,J23) -> 369.2 | L23: =K23/C23 -> 5.2 | M23: =C23*L23 -> 369.2 | N23: 0 | O23: =M23*N23 -> 0 | V23: =V22/C22 -> 0.43736842
B24: Infill to Comflor take head track | C24: 23 | D24: m | E24: 0.25 | F24: =C24*E24 -> 5.75 | G24: =$H$11*E24 -> 12.5 | H24: =F24*$H$11 -> 287.5 | I24: 15 | J24: =C24*I24 -> 345 | K24: =SUM(H24,J24) -> 632.5 | L24: =K24/C24 -> 27.5 | M24: =C24*L24 -> 632.5 | N24: 0 | O24: =M24*N24 -> 0
B25: Gib Packing to Head | C25: 23 | D25: m | E25: 0.15 | F25: =C25*E25 -> 3.45 | G25: =$H$11*E25 -> 7.5 | H25: =F25*$H$11 -> 172.5 | I25: 6 | J25: =C25*I25 -> 138 | K25: =SUM(H25,J25) -> 310.5 | L25: =K25/C25 -> 13.5 | M25: =C25*L25 -> 310.5 | N25: 0 | O25: =M25*N25 -> 0
P26: =SUM(M22:M25) -> 4235.35 | Q26: =P26*SUM($L$115:$L$119) -> 402.35825
P27: =P26/$M$112 -> 0.04586316 | Q27: =P27*$M$123 -> 108.76552 | R27: =SUM(P26,Q26,Q27) -> 4746.4738 | S27: =R27*1.08 -> 5126.1917
B28: Level 1:
B29: (WA06) 64mm x 0.55 Steel Stud (4.2m) | C29: 185 | D29: m2 | E29: =$Y$20 -> 0.4 | F29: =C29*E29 -> 74 | G29: =$H$11*E29 -> 20 | H29: =F29*$H$11 -> 3700 | I29: 10.77 | J29: =C29*I29 -> 1992.45 | K29: =SUM(H29,J29) -> 5692.45 | L29: =K29/C29 -> 30.77 | M29: =C29*L29 -> 5692.45 | N29: 0 | O29: =M29*N29 -> 0 | T29: 44/lm | V29: =SUM(F29:F30) -> 84.1
B30: EV Stud to Corners/Wall Ends | C30: 202 | D30: m | E30: 0.05 | F30: =C30*E30 -> 10.1 | G30: =$H$11*E30 -> 2.5 | H30: =F30*$H$11 -> 505 | I30: 2.7 | J30: =C30*I30 -> 545.4 | K30: =SUM(H30,J30) -> 1050.4 | L30: =K30/C30 -> 5.2 | M30: =C30*L30 -> 1050.4 | N30: 0 | O30: =M30*N30 -> 0 | V30: =V29/C29 -> 0.45459459
B31: Infill to Comflor take head track | C31: 44 | D31: m | E31: 0.25 | F31: =C31*E31 -> 11 | G31: =$H$11*E31 -> 12.5 | H31: =F31*$H$11 -> 550 | I31: 15 | J31: =C31*I31 -> 660 | K31: =SUM(H31,J31) -> 1210 | L31: =K31/C31 -> 27.5 | M31: =C31*L31 -> 1210 | N31: 0 | O31: =M31*N31 -> 0
B32: Gib Packing to Head | C32: 44 | D32: m | E32: 0.15 | F32: =C32*E32 -> 6.6 | G32: =$H$11*E32 -> 7.5 | H32: =F32*$H$11 -> 330 | I32: 6 | J32: =C32*I32 -> 264 | K32: =SUM(H32,J32) -> 594 | L32: =K32/C32 -> 13.5 | M32: =C32*L32 -> 594 | N32: 0 | O32: =M32*N32 -> 0
B35: (WA52) 92mm x 0.55 Whisper Wall Stud (4.2m) | C35: 64 | D35: m2 | E35: =$Y$20 -> 0.4 | F35: =C35*E35 -> 25.6 | G35: =$H$11*E35 -> 20 | H35: =F35*$H$11 -> 1280 | I35: 14.55 | J35: =C35*I35 -> 931.2 | K35: =SUM(H35,J35) -> 2211.2 | L35: =K35/C35 -> 34.55 | M35: =C35*L35 -> 2211.2 | N35: 0 | O35: =M35*N35 -> 0 | T35: 15/lm | V35: =SUM(F35:F36) -> 30.01
B36: EV Stud to Corners/Wall Ends | C36: 63 | D36: m | E36: 0.07 | F36: =C36*E36 -> 4.41 | G36: =$H$11*E36 -> 3.5 | H36: =F36*$H$11 -> 220.5 | I36: 7 | J36: =C36*I36 -> 441 | K36: =SUM(H36,J36) -> 661.5 | L36: =K36/C36 -> 10.5 | M36: =C36*L36 -> 661.5 | N36: 0 | O36: =M36*N36 -> 0 | V36: =V35/C35 -> 0.46890625
B37: Infill to Comflor take head track | C37: 15 | D37: m | E37: 0.25 | F37: =C37*E37 -> 3.75 | G37: =$H$11*E37 -> 12.5 | H37: =F37*$H$11 -> 187.5 | I37: 15 | J37: =C37*I37 -> 225 | K37: =SUM(H37,J37) -> 412.5 | L37: =K37/C37 -> 27.5 | M37: =C37*L37 -> 412.5 | N37: 0 | O37: =M37*N37 -> 0
B38: Gib Packing to Head | C38: 15 | D38: m | E38: 0.15 | F38: =C38*E38 -> 2.25 | G38: =$H$11*E38 -> 7.5 | H38: =F38*$H$11 -> 112.5 | I38: 6 | J38: =C38*I38 -> 90 | K38: =SUM(H38,J38) -> 202.5 | L38: =K38/C38 -> 13.5 | M38: =C38*L38 -> 202.5 | N38: 0 | O38: =M38*N38 -> 0
P39: =SUM(M29:M38) -> 12034.55 | Q39: =P39*SUM($L$115:$L$119) -> 1143.2822
P40: =P39/$M$112 -> 0.13031804 | Q40: =P40*$M$123 -> 309.05215 | R40: =SUM(P39,Q39,Q40) -> 13486.884 | S40: =R40*1.08 -> 14565.835
B41: Level 2:
B42: (WA06) 64mm x 0.55 Steel Stud (4.2m) | C42: 232 | D42: m2 | E42: =$Y$20 -> 0.4 | F42: =C42*E42 -> 92.8 | G42: =$H$11*E42 -> 20 | H42: =F42*$H$11 -> 4640 | I42: 10.77 | J42: =C42*I42 -> 2498.64 | K42: =SUM(H42,J42) -> 7138.64 | L42: =K42/C42 -> 30.77 | M42: =C42*L42 -> 7138.64 | N42: 0 | O42: =M42*N42 -> 0 | T42: 55/lm | V42: =SUM(F42:F43) -> 104.75
B43: EV Stud to Corners/Wall Ends | C43: 239 | D43: m | E43: 0.05 | F43: =C43*E43 -> 11.95 | G43: =$H$11*E43 -> 2.5 | H43: =F43*$H$11 -> 597.5 | I43: 2.7 | J43: =C43*I43 -> 645.3 | K43: =SUM(H43,J43) -> 1242.8 | L43: =K43/C43 -> 5.2 | M43: =C43*L43 -> 1242.8 | N43: 0 | O43: =M43*N43 -> 0 | V43: =V42/C42 -> 0.45150862
B44: Infill to Comflor take head track | C44: 55 | D44: m | E44: 0.25 | F44: =C44*E44 -> 13.75 | G44: =$H$11*E44 -> 12.5 | H44: =F44*$H$11 -> 687.5 | I44: 15 | J44: =C44*I44 -> 825 | K44: =SUM(H44,J44) -> 1512.5 | L44: =K44/C44 -> 27.5 | M44: =C44*L44 -> 1512.5 | N44: 0 | O44: =M44*N44 -> 0
B45: Gib Packing to Head | C45: 55 | D45: m | E45: 0.15 | F45: =C45*E45 -> 8.25 | G45: =$H$11*E45 -> 7.5 | H45: =F45*$H$11 -> 412.5 | I45: 6 | J45: =C45*I45 -> 330 | K45: =SUM(H45,J45) -> 742.5 | L45: =K45/C45 -> 13.5 | M45: =C45*L45 -> 742.5 | N45: 0 | O45: =M45*N45 -> 0
B47: (WA52) 92mm x 0.55 Whisper Wall Stud (4.2m) | C47: 51 | D47: m2 | E47: =$Y$20 -> 0.4 | F47: =C47*E47 -> 20.4 | G47: =$H$11*E47 -> 20 | H47: =F47*$H$11 -> 1020 | I47: 14.67 | J47: =C47*I47 -> 748.17 | K47: =SUM(H47,J47) -> 1768.17 | L47: =K47/C47 -> 34.67 | M47: =C47*L47 -> 1768.17 | N47: 0.75 | O47: =M47*N47 -> 1326.1275 | T47: 12/lm | V47: =SUM(F47:F48) -> 25.37
B48: EV Stud to Corners/Wall Ends | C48: 71 | D48: m | E48: 0.07 | F48: =C48*E48 -> 4.97 | G48: =$H$11*E48 -> 3.5 | H48: =F48*$H$11 -> 248.5 | I48: 7 | J48: =C48*I48 -> 497 | K48: =SUM(H48,J48) -> 745.5 | L48: =K48/C48 -> 10.5 | M48: =C48*L48 -> 745.5 | N48: 0.75 | O48: =M48*N48 -> 559.125 | V48: =V47/C47 -> 0.49745098
B49: Infill to Comflor take head track | C49: 12 | D49: m | E49: 0.25 | F49: =C49*E49 -> 3 | G49: =$H$11*E49 -> 12.5 | H49: =F49*$H$11 -> 150 | I49: 15 | J49: =C49*I49 -> 180 | K49: =SUM(H49,J49) -> 330 | L49: =K49/C49 -> 27.5 | M49: =C49*L49 -> 330 | N49: 0 | O49: =M49*N49 -> 0
B50: Gib Packing to Head | C50: 12 | D50: m | E50: 0.15 | F50: =C50*E50 -> 1.8 | G50: =$H$11*E50 -> 7.5 | H50: =F50*$H$11 -> 90 | I50: 6 | J50: =C50*I50 -> 72 | K50: =SUM(H50,J50) -> 162 | L50: =K50/C50 -> 13.5 | M50: =C50*L50 -> 162 | N50: 0 | O50: =M50*N50 -> 0 | P50: =SUM(O42:O50) -> 1885.2525 | Q50: =P50/P51 -> 0.13819362
P51: =SUM(M42:M50) -> 13642.11 | Q51: =P51*SUM($L$115:$L$119) -> 1296.0005
P52: =P51/$M$112 -> 0.14772575 | Q52: =P52*$M$123 -> 350.33495 | R52: =SUM(P51,Q51,Q52) -> 15288.445 | S52: =R52*1.08 -> 16511.521
B54: Level 3:
B55: (WA06) 64mm x 0.55 Steel Stud (4.2m) | C55: 232 | D55: m2 | E55: =$Y$20 -> 0.4 | F55: =C55*E55 -> 92.8 | G55: =$H$11*E55 -> 20 | H55: =F55*$H$11 -> 4640 | I55: 10.77 | J55: =C55*I55 -> 2498.64 | K55: =SUM(H55,J55) -> 7138.64 | L55: =K55/C55 -> 30.77 | M55: =C55*L55 -> 7138.64 | N55: 0 | O55: =M55*N55 -> 0 | T55: 55/lm | V55: =SUM(F55:F56) -> 104.75
B56: EV Stud to Corners/Wall Ends | C56: 239 | D56: m | E56: 0.05 | F56: =C56*E56 -> 11.95 | G56: =$H$11*E56 -> 2.5 | H56: =F56*$H$11 -> 597.5 | I56: 2.7 | J56: =C56*I56 -> 645.3 | K56: =SUM(H56,J56) -> 1242.8 | L56: =K56/C56 -> 5.2 | M56: =C56*L56 -> 1242.8 | N56: 0 | O56: =M56*N56 -> 0 | V56: =V55/C55 -> 0.45150862
B57: Infill to Comflor take head track | C57: 55 | D57: m | E57: 0.25 | F57: =C57*E57 -> 13.75 | G57: =$H$11*E57 -> 12.5 | H57: =F57*$H$11 -> 687.5 | I57: 15 | J57: =C57*I57 -> 825 | K57: =SUM(H57,J57) -> 1512.5 | L57: =K57/C57 -> 27.5 | M57: =C57*L57 -> 1512.5 | N57: 0 | O57: =M57*N57 -> 0
B58: Gib Packing to Head | C58: 55 | D58: m | E58: 0.15 | F58: =C58*E58 -> 8.25 | G58: =$H$11*E58 -> 7.5 | H58: =F58*$H$11 -> 412.5 | I58: 6 | J58: =C58*I58 -> 330 | K58: =SUM(H58,J58) -> 742.5 | L58: =K58/C58 -> 13.5 | M58: =C58*L58 -> 742.5 | N58: 0 | O58: =M58*N58 -> 0
B60: (WA52) 92mm x 0.55 Whisper Wall Stud (4.2m) | C60: 51 | D60: m2 | E60: =$Y$20 -> 0.4 | F60: =C60*E60 -> 20.4 | G60: =$H$11*E60 -> 20 | H60: =F60*$H$11 -> 1020 | I60: 14.67 | J60: =C60*I60 -> 748.17 | K60: =SUM(H60,J60) -> 1768.17 | L60: =K60/C60 -> 34.67 | M60: =C60*L60 -> 1768.17 | N60: 0.75 | O60: =M60*N60 -> 1326.1275 | T60: 12/lm | V60: =SUM(F60:F61) -> 25.37
B61: EV Stud to Corners/Wall Ends | C61: 71 | D61: m | E61: 0.07 | F61: =C61*E61 -> 4.97 | G61: =$H$11*E61 -> 3.5 | H61: =F61*$H$11 -> 248.5 | I61: 7 | J61: =C61*I61 -> 497 | K61: =SUM(H61,J61) -> 745.5 | L61: =K61/C61 -> 10.5 | M61: =C61*L61 -> 745.5 | N61: 0.75 | O61: =M61*N61 -> 559.125 | V61: =V60/C60 -> 0.49745098
B62: Infill to Comflor take head track | C62: 12 | D62: m | E62: 0.25 | F62: =C62*E62 -> 3 | G62: =$H$11*E62 -> 12.5 | H62: =F62*$H$11 -> 150 | I62: 15 | J62: =C62*I62 -> 180 | K62: =SUM(H62,J62) -> 330 | L62: =K62/C62 -> 27.5 | M62: =C62*L62 -> 330 | N62: 0 | O62: =M62*N62 -> 0
B63: Gib Packing to Head | C63: 12 | D63: m | E63: 0.15 | F63: =C63*E63 -> 1.8 | G63: =$H$11*E63 -> 7.5 | H63: =F63*$H$11 -> 90 | I63: 6 | J63: =C63*I63 -> 72 | K63: =SUM(H63,J63) -> 162 | L63: =K63/C63 -> 13.5 | M63: =C63*L63 -> 162 | N63: 0 | O63: =M63*N63 -> 0 | P63: =SUM(O55:O63) -> 1885.2525 | Q63: =P63/P64 -> 0.13819362
P64: =SUM(M55:M63) -> 13642.11 | Q64: =P64*SUM($L$115:$L$119) -> 1296.0005
P65: =P64/$M$112 -> 0.14772575 | Q65: =P65*$M$123 -> 350.33495 | R65: =SUM(P64,Q64,Q65) -> 15288.445 | S65: =R65*1.08 -> 16511.521
B67: Level 4:
B68: (WA06) 64mm x 0.55 Steel Stud (4.2m) | C68: 232 | D68: m2 | E68: =$Y$20 -> 0.4 | F68: =C68*E68 -> 92.8 | G68: =$H$11*E68 -> 20 | H68: =F68*$H$11 -> 4640 | I68: 10.77 | J68: =C68*I68 -> 2498.64 | K68: =SUM(H68,J68) -> 7138.64 | L68: =K68/C68 -> 30.77 | M68: =C68*L68 -> 7138.64 | N68: 0 | O68: =M68*N68 -> 0 | T68: 55/lm | V68: =SUM(F68:F69) -> 104.75
B69: EV Stud to Corners/Wall Ends | C69: 239 | D69: m | E69: 0.05 | F69: =C69*E69 -> 11.95 | G69: =$H$11*E69 -> 2.5 | H69: =F69*$H$11 -> 597.5 | I69: 2.7 | J69: =C69*I69 -> 645.3 | K69: =SUM(H69,J69) -> 1242.8 | L69: =K69/C69 -> 5.2 | M69: =C69*L69 -> 1242.8 | N69: 0 | O69: =M69*N69 -> 0 | V69: =V68/C68 -> 0.45150862
B70: Infill to Comflor take head track | C70: 55 | D70: m | E70: 0.25 | F70: =C70*E70 -> 13.75 | G70: =$H$11*E70 -> 12.5 | H70: =F70*$H$11 -> 687.5 | I70: 15 | J70: =C70*I70 -> 825 | K70: =SUM(H70,J70) -> 1512.5 | L70: =K70/C70 -> 27.5 | M70: =C70*L70 -> 1512.5 | N70: 0 | O70: =M70*N70 -> 0
B71: Gib Packing to Head | C71: 55 | D71: m | E71: 0.15 | F71: =C71*E71 -> 8.25 | G71: =$H$11*E71 -> 7.5 | H71: =F71*$H$11 -> 412.5 | I71: 6 | J71: =C71*I71 -> 330 | K71: =SUM(H71,J71) -> 742.5 | L71: =K71/C71 -> 13.5 | M71: =C71*L71 -> 742.5 | N71: 0 | O71: =M71*N71 -> 0
B73: (WA52) 92mm x 0.55 Whisper Wall Stud (4.2m) | C73: 51 | D73: m2 | E73: =$Y$20 -> 0.4 | F73: =C73*E73 -> 20.4 | G73: =$H$11*E73 -> 20 | H73: =F73*$H$11 -> 1020 | I73: 14.67 | J73: =C73*I73 -> 748.17 | K73: =SUM(H73,J73) -> 1768.17 | L73: =K73/C73 -> 34.67 | M73: =C73*L73 -> 1768.17 | N73: 0 | O73: =M73*N73 -> 0 | T73: 12/lm | V73: =SUM(F73:F74) -> 25.37
B74: EV Stud to Corners/Wall Ends | C74: 71 | D74: m | E74: 0.07 | F74: =C74*E74 -> 4.97 | G74: =$H$11*E74 -> 3.5 | H74: =F74*$H$11 -> 248.5 | I74: 7 | J74: =C74*I74 -> 497 | K74: =SUM(H74,J74) -> 745.5 | L74: =K74/C74 -> 10.5 | M74: =C74*L74 -> 745.5 | N74: 0 | O74: =M74*N74 -> 0 | V74: =V73/C73 -> 0.49745098
B75: Infill to Comflor take head track | C75: 12 | D75: m | E75: 0.25 | F75: =C75*E75 -> 3 | G75: =$H$11*E75 -> 12.5 | H75: =F75*$H$11 -> 150 | I75: 15 | J75: =C75*I75 -> 180 | K75: =SUM(H75,J75) -> 330 | L75: =K75/C75 -> 27.5 | M75: =C75*L75 -> 330 | N75: 0 | O75: =M75*N75 -> 0
B76: Gib Packing to Head | C76: 12 | D76: m | E76: 0.15 | F76: =C76*E76 -> 1.8 | G76: =$H$11*E76 -> 7.5 | H76: =F76*$H$11 -> 90 | I76: 6 | J76: =C76*I76 -> 72 | K76: =SUM(H76,J76) -> 162 | L76: =K76/C76 -> 13.5 | M76: =C76*L76 -> 162 | N76: 0 | O76: =M76*N76 -> 0
P77: =SUM(M68:M76) -> 13642.11 | Q77: =P77*SUM($L$115:$L$119) -> 1296.0005
P78: =P77/$M$112 -> 0.14772575 | Q78: =P78*$M$123 -> 350.33495 | R78: =SUM(P77,Q77,Q78) -> 15288.445 | S78: =R78*1.08 -> 16511.521
B80: Level 5:
B81: (WA06) 64mm x 0.55 Steel Stud (4.2m) | C81: 232 | D81: m2 | E81: =$Y$20 -> 0.4 | F81: =C81*E81 -> 92.8 | G81: =$H$11*E81 -> 20 | H81: =F81*$H$11 -> 4640 | I81: 10.77 | J81: =C81*I81 -> 2498.64 | K81: =SUM(H81,J81) -> 7138.64 | L81: =K81/C81 -> 30.77 | M81: =C81*L81 -> 7138.64 | N81: 0 | O81: =M81*N81 -> 0 | T81: 55/lm | V81: =SUM(F81:F82) -> 104.75
B82: EV Stud to Corners/Wall Ends | C82: 239 | D82: m | E82: 0.05 | F82: =C82*E82 -> 11.95 | G82: =$H$11*E82 -> 2.5 | H82: =F82*$H$11 -> 597.5 | I82: 2.7 | J82: =C82*I82 -> 645.3 | K82: =SUM(H82,J82) -> 1242.8 | L82: =K82/C82 -> 5.2 | M82: =C82*L82 -> 1242.8 | N82: 0 | O82: =M82*N82 -> 0 | V82: =V81/C81 -> 0.45150862
B83: Infill to Comflor take head track | C83: 55 | D83: m | E83: 0.25 | F83: =C83*E83 -> 13.75 | G83: =$H$11*E83 -> 12.5 | H83: =F83*$H$11 -> 687.5 | I83: 15 | J83: =C83*I83 -> 825 | K83: =SUM(H83,J83) -> 1512.5 | L83: =K83/C83 -> 27.5 | M83: =C83*L83 -> 1512.5 | N83: 0 | O83: =M83*N83 -> 0
B84: Gib Packing to Head | C84: 55 | D84: m | E84: 0.15 | F84: =C84*E84 -> 8.25 | G84: =$H$11*E84 -> 7.5 | H84: =F84*$H$11 -> 412.5 | I84: 6 | J84: =C84*I84 -> 330 | K84: =SUM(H84,J84) -> 742.5 | L84: =K84/C84 -> 13.5 | M84: =C84*L84 -> 742.5 | N84: 0 | O84: =M84*N84 -> 0
B86: (WA52) 92mm x 0.55 Whisper Wall Stud (4.2m) | C86: 52 | D86: m2 | E86: =$Y$20 -> 0.4 | F86: =C86*E86 -> 20.8 | G86: =$H$11*E86 -> 20 | H86: =F86*$H$11 -> 1040 | I86: 14.67 | J86: =C86*I86 -> 762.84 | K86: =SUM(H86,J86) -> 1802.84 | L86: =K86/C86 -> 34.67 | M86: =C86*L86 -> 1802.84 | N86: 0 | O86: =M86*N86 -> 0 | T86: 12/lm | V86: =SUM(F86:F87) -> 25.77
B87: EV Stud to Corners/Wall Ends | C87: 71 | D87: m | E87: 0.07 | F87: =C87*E87 -> 4.97 | G87: =$H$11*E87 -> 3.5 | H87: =F87*$H$11 -> 248.5 | I87: 7 | J87: =C87*I87 -> 497 | K87: =SUM(H87,J87) -> 745.5 | L87: =K87/C87 -> 10.5 | M87: =C87*L87 -> 745.5 | N87: 0 | O87: =M87*N87 -> 0 | V87: =V86/C86 -> 0.49557692
B88: Infill to Comflor take head track | C88: 12 | D88: m | E88: 0.25 | F88: =C88*E88 -> 3 | G88: =$H$11*E88 -> 12.5 | H88: =F88*$H$11 -> 150 | I88: 15 | J88: =C88*I88 -> 180 | K88: =SUM(H88,J88) -> 330 | L88: =K88/C88 -> 27.5 | M88: =C88*L88 -> 330 | N88: 0 | O88: =M88*N88 -> 0
B89: Gib Packing to Head | C89: 12 | D89: m | E89: 0.15 | F89: =C89*E89 -> 1.8 | G89: =$H$11*E89 -> 7.5 | H89: =F89*$H$11 -> 90 | I89: 6 | J89: =C89*I89 -> 72 | K89: =SUM(H89,J89) -> 162 | L89: =K89/C89 -> 13.5 | M89: =C89*L89 -> 162 | N89: 0 | O89: =M89*N89 -> 0
P90: =SUM(M81:M89) -> 13676.78 | Q90: =P90*SUM($L$115:$L$119) -> 1299.2941
P91: =P90/$M$112 -> 0.14810118 | Q91: =P91*$M$123 -> 351.22529 | R91: =SUM(P90,Q90,Q91) -> 15327.299 | S91: =R91*1.08 -> 16553.483
B93: Level 6:
B94: (WA06) 64mm x 0.55 Steel Stud (4.2m) | C94: 217 | D94: m2 | E94: =$Y$20 -> 0.4 | F94: =C94*E94 -> 86.8 | G94: =$H$11*E94 -> 20 | H94: =F94*$H$11 -> 4340 | I94: 10.77 | J94: =C94*I94 -> 2337.09 | K94: =SUM(H94,J94) -> 6677.09 | L94: =K94/C94 -> 30.77 | M94: =C94*L94 -> 6677.09 | N94: 0 | O94: =M94*N94 -> 0 | T94: 52/lm | V94: =SUM(F94:F95) -> 97.5
B95: EV Stud to Corners/Wall Ends | C95: 214 | D95: m | E95: 0.05 | F95: =C95*E95 -> 10.7 | G95: =$H$11*E95 -> 2.5 | H95: =F95*$H$11 -> 535 | I95: 2.7 | J95: =C95*I95 -> 577.8 | K95: =SUM(H95,J95) -> 1112.8 | L95: =K95/C95 -> 5.2 | M95: =C95*L95 -> 1112.8 | N95: 0 | O95: =M95*N95 -> 0 | V95: =V94/C94 -> 0.44930876
B96: Infill to Comflor take head track | C96: 52 | D96: m | E96: 0.25 | F96: =C96*E96 -> 13 | G96: =$H$11*E96 -> 12.5 | H96: =F96*$H$11 -> 650 | I96: 15 | J96: =C96*I96 -> 780 | K96: =SUM(H96,J96) -> 1430 | L96: =K96/C96 -> 27.5 | M96: =C96*L96 -> 1430 | N96: 0 | O96: =M96*N96 -> 0
B97: Gib Packing to Head | C97: 52 | D97: m | E97: 0.15 | F97: =C97*E97 -> 7.8 | G97: =$H$11*E97 -> 7.5 | H97: =F97*$H$11 -> 390 | I97: 6 | J97: =C97*I97 -> 312 | K97: =SUM(H97,J97) -> 702 | L97: =K97/C97 -> 13.5 | M97: =C97*L97 -> 702 | N97: 0 | O97: =M97*N97 -> 0
B99: (WA52) 92mm x 0.55 Whisper Wall Stud (4.2m) | C99: 51 | D99: m2 | E99: =$Y$20 -> 0.4 | F99: =C99*E99 -> 20.4 | G99: =$H$11*E99 -> 20 | H99: =F99*$H$11 -> 1020 | I99: 14.67 | J99: =C99*I99 -> 748.17 | K99: =SUM(H99,J99) -> 1768.17 | L99: =K99/C99 -> 34.67 | M99: =C99*L99 -> 1768.17 | N99: 0 | O99: =M99*N99 -> 0 | T99: 12/lm | V99: =SUM(F99:F100) -> 24.81
B100: EV Stud to Corners/Wall Ends | C100: 63 | D100: m | E100: 0.07 | F100: =C100*E100 -> 4.41 | G100: =$H$11*E100 -> 3.5 | H100: =F100*$H$11 -> 220.5 | I100: 7 | J100: =C100*I100 -> 441 | K100: =SUM(H100,J100) -> 661.5 | L100: =K100/C100 -> 10.5 | M100: =C100*L100 -> 661.5 | N100: 0 | O100: =M100*N100 -> 0 | V100: =V99/C99 -> 0.48647059
B101: Infill to Comflor take head track | C101: 12 | D101: m | E101: 0.25 | F101: =C101*E101 -> 3 | G101: =$H$11*E101 -> 12.5 | H101: =F101*$H$11 -> 150 | I101: 15 | J101: =C101*I101 -> 180 | K101: =SUM(H101,J101) -> 330 | L101: =K101/C101 -> 27.5 | M101: =C101*L101 -> 330 | N101: 0 | O101: =M101*N101 -> 0
B102: Gib Packing to Head | C102: 12 | D102: m | E102: 0.15 | F102: =C102*E102 -> 1.8 | G102: =$H$11*E102 -> 7.5 | H102: =F102*$H$11 -> 90 | I102: 6 | J102: =C102*I102 -> 72 | K102: =SUM(H102,J102) -> 162 | L102: =K102/C102 -> 13.5 | M102: =C102*L102 -> 162 | N102: 0 | O102: =M102*N102 -> 0
P103: =SUM(M94:M102) -> 12843.56 | Q103: =P103*SUM($L$115:$L$119) -> 1220.1382
P104: =P103/$M$112 -> 0.13907853 | Q104: =P104*$M$123 -> 329.82786 | R104: =SUM(P103,Q103,Q104) -> 14393.526 | S104: =R104*1.08 -> 15545.008
B106: Plant Room:
B107: (WA06) 64mm x 0.55 Steel Stud (3.3m) | C107: 69 | D107: m2 | E107: =$Y$20 -> 0.4 | F107: =C107*E107 -> 27.6 | G107: =$H$11*E107 -> 20 | H107: =F107*$H$11 -> 1380 | I107: 14.52 | J107: =C107*I107 -> 1001.88 | K107: =SUM(H107,J107) -> 2381.88 | L107: =K107/C107 -> 34.52 | M107: =C107*L107 -> 2381.88 | N107: 0 | O107: =M107*N107 -> 0 | V107: =SUM(F107:F108) -> 29.45
B108: EV Stud to Corners/Wall Ends | C108: 37 | D108: m | E108: 0.05 | F108: =C108*E108 -> 1.85 | G108: =$H$11*E108 -> 2.5 | H108: =F108*$H$11 -> 92.5 | I108: 3.31 | J108: =C108*I108 -> 122.47 | K108: =SUM(H108,J108) -> 214.97 | L108: =K108/C108 -> 5.81 | M108: =C108*L108 -> 214.97 | N108: 0 | O108: =M108*N108 -> 0 | V108: =V107/C107 -> 0.42681159
P109: =SUM(M106:M108) -> 2596.85 | Q109: =P109*SUM($L$115:$L$119) -> 246.70075
P110: =P109/$M$112 -> 0.028120403 | Q110: =P110*$M$123 -> 66.688167 | R110: =SUM(P109,Q109,Q110) -> 2910.2389 | S110: =R110*1.08 -> 3143.058 | W110: =SUM(C101,C88,C75,C62,C49,C37,C18) -> 104
F111: =SUM(F13:F110) -> 1054.01 | H111: =SUM(H13:H110) -> 52700.5 | J111: =SUM(J13:J110) -> 39647.04 | R111: =SUM(R16:R110) -> 103492.08 | S111: =SUM(S16:S110) -> 111771.45
B112: Total of above | M112: =SUM(M13:M110) -> 92347.54 | O112: =SUM(O13:O110) -> 3770.505 | X112: =SUM(C96,C83,C70,C57,C44,C31,C24) -> 339
B113: Miscellaneous
B115: P&G - Admin / Supervision | D115: Sum | L115: 0.06 | M115: =M112*L115 -> 5540.8524 | O115: =($O$112/$M$112)*M115 -> 226.2303 | X115: =SUM(C94,C81,C68,C55,C42,C29,C22) -> 1425
B117: P&G - Site Establishment | D117: Sum | L117: 0.03 | M117: =M112*L117 -> 2770.4262 | O117: =($O$112/$M$112)*M117 -> 113.11515 | V117: =SUM(M101,M96,M88,M83,M75,M70,M62,M57,M49,M44,M37,M31,M24,M18) -> 12182.5
B119: P&G - Access Equip | D119: Sum | L119: 0.005 | M119: =M112*L119 -> 461.7377 | O119: =($O$112/$M$112)*M119 -> 18.852525
B121: P&G | D121: Sum
B123: P&G Parking | D123: Sum | L123: =M123/M112 -> 0.025680408 | M123: =I134 -> 2371.5225 | O123: =($O$112/$M$112)*M123 -> 96.828107
B125: Sub total | M125: =SUM(M112:M124) -> 103492.08 | O125: =SUM(O112:O124) -> 4225.5311
...

Sheet Workings_Partitions
D8: 92mm QS steel studs @ | E8: 0.6 | F8: Stud spacing | G8: With DH | M8: WA52 | Q8: 92mm QS steel studs @ | R8: 0.6 | S8: Stud spacing | T8: With DH | Z8: WA52
D10: Material | F10: Length of wall | G10: Height of wall | H10: Total stud LM | I10: Total track LM | J10: M2 of wall | Q10: Material | S10: Length of wall | T10: Height of wall | U10: Total stud LM | V10: Total track LM | W10: M2 of wall
E11: $/m | F11: 29 | G11: 3.4 | H11: =SUM(F20*G11) -> 167.73333 | I11: =F11*1 -> 29 | J11: =F11*G11 -> 98.6 | R11: $/m | S11: 12 | T11: 4.2 | U11: =SUM(S20*T11) -> 88.2 | V11: =S11*1 -> 12 | W11: =S11*T11 -> 50.4
C12: Stud | D12: 92 QS .55 bmt | E12: 7.4 | P12: Stud | Q12: 92 QS .55 bmt | R12: 5.9
D13: Nog | E13: =H14/H11 -> 3.7794515 | F13: 10.93 | G13: m | H13: =SUM(F13*F11) -> 316.97 | Q13: Nog | R13: =U14/U11 -> 0.80136054 | S13: 5.89 | T13: m | U13: =SUM(S13*S11) -> 70.68
F14: Number of nogs | G14: 2 | H14: =G14*H13 -> 633.94 | S14: Number of nogs | T14: 1 | U14: =T14*U13 -> 70.68
D16: Unload | E16: 0.09 | Q16: Unload | R16: 0.09
D17: Fixings | Q17: Fixings
D18: say 4 each stud | Q18: say 4 each stud
D19: L of wl ÷ spacings = ttl studs | F19: =SUM(F11/E8) -> 48.333333 | Q19: L of wl ÷ spacings = ttl studs | S19: =SUM(S11/R8) -> 20
D20: add 1 for end of wall | F20: =F19+1 -> 49.333333 | G20: total studs in wall | Q20: add 1 for end of wall | S20: =S19+1 -> 21 | T20: total studs in wall
D21: Studs x 4 screws per stud = ttl screws | F21: =SUM(F20*4) -> 197.33333 | G21: total screws | H21: 0.015 | Q21: Studs x 4 screws per stud = ttl screws | S21: =SUM(S20*4) -> 84 | T21: total screws | U21: 0.015
D22: Screws @ $15.00/1000 = .015 | E22: =SUM(F21*H21)/H11 -> 0.017647059 | F22: Cost of fixings per LM | Q22: Screws @ $15.00/1000 = .015 | R22: =SUM(S21*U21)/U11 -> 0.014285714 | S22: Cost of fixings per LM
E24: =SUM(E12:E23) -> 11.287099 | R24: =SUM(R12:R23) -> 6.8056463
D25: waste 5% | E25: =E24*5% -> 0.56435493 | Q25: waste 5% | R25: =R24*5% -> 0.34028231
E26: =SUM(E24:E25) -> 11.851453 | R26: =SUM(R24:R25) -> 7.1459286
C27: Stud | D27: Labour per m as per rates | F27: Lab rate | P27: Stud | Q27: Labour per m as per rates | S27: Lab rate
D28: m/hr | F28: 55 | Q28: m/hr | S28: 55
D29: 20 | E29: =F28/D29 -> 2.75 | Q29: 15 | R29: =S28/Q29 -> 3.6666667
E32: =SUM(E26:E29) -> 14.601453 | I32: Labour cost per m | L32: per m2 | R32: =SUM(R26:R29) -> 10.812595 | V32: Labour cost per m | Y32: per m2
D33: Plant | I33: =E35-I35 -> 3.5745727 | K33: =H11*I33 -> 599.57499 | L33: =K33/J11 -> 6.0808823 | Q33: Plant | V33: =R35-V35 -> 4.3017964 | X33: =U11*V33 -> 379.41845 | Y33: =X33/W11 -> 7.5281437
D34: 0.05 | E34: =E32*5% -> 0.73007267 | I34: Material cost per m | Q34: 0.05 | R34: =R32*5% -> 0.54062976 | V34: Material cost per m
E35: =SUM(E32:E34) -> 15.331526 | F35: per m | I35: =SUM(E12+E13+E22)*1.05 -> 11.756953 | K35: =H11*I35 -> 1972.033 | L35: =K35/J11 -> 20.000335 | R35: =SUM(R32:R34) -> 11.353225 | S35: per m | V35: =SUM(R12+R13+R22)*1.05 -> 7.0514286 | X35: =U11*V35 -> 621.936 | Y35: =X35/W11 -> 12.34
D36: Total cost of stud job is | F36: =E35*H11 -> 2571.608 | Q36: Total cost of stud job is | S36: =R35*U11 -> 1001.3544
F37: To get the medium of the two | S37: To get the medium of the two
C38: Track | D38: 92 .75 bmt x 1 , DH x 1 | E38: =I39 -> 3.815 | F38: Top | G38: Bot | I38: Avge | P38: Track | Q38: 92 .75 bmt x 1 , DH x 1 | R38: =V39 -> 4.435 | S38: Top | T38: Bot | V38: Avge
D39: DPC | E39: 0.31 | F39: 4.78 | G39: 2.85 | H39: =SUM(F39:G39) -> 7.63 | I39: =H39/2 -> 3.815 | Q39: DPC | R39: 0.31 | S39: 4.78 | T39: 4.09 | U39: =SUM(S39:T39) -> 8.87 | V39: =U39/2 -> 4.435
D40: Unload | E40: 0.09 | Q40: Unload | R40: 0.09
D42: Fixings for track | Q42: Fixings for track
D43: Spaced @ 0.6 1.7 @ 2.50 each | F43: =F11/E8 -> 48.333333 | Q43: Spaced @ 0.6 1.7 @ 2.50 each | S43: =S11/R8 -> 20
D44: add extra for ends | F44: =F43+2 -> 50.333333 | G44: total fixings | H44: 2.5 | Q44: add extra for ends | S44: =S43+2 -> 22 | T44: total fixings | U44: 2.5
E45: =SUM(F44*H44)/I11 -> 4.3390805 | F45: Cost of fixings per LM | R45: =SUM(S44*U44)/V11 -> 4.5833333 | S45: Cost of fixings per LM
E47: =SUM(E38:E45) -> 8.5540805 | R47: =SUM(R38:R45) -> 9.4183333
D48: waste 5% | E48: =E47*5% -> 0.42770402 | Q48: waste 5% | R48: =R47*5% -> 0.47091667
E49: =SUM(E47:E48) -> 8.9817845 | R49: =SUM(R47:R48) -> 9.88925
C50: Track | D50: Labour per m as per rates | F50: Lab rate | P50: Track | Q50: Labour per m as per rates | S50: Lab rate
D51: m/hr | F51: 55 | Q51: m/hr | S51: 55
D52: 4 | E52: =F51/D52 -> 13.75 | Q52: 4 | R52: =S51/Q52 -> 13.75
E53: =SUM(E49:E52) -> 22.731784 | I53: Labour cost per m | L53: per m2 | R53: =SUM(R49:R52) -> 23.63925 | V53: Labour cost per m | Y53: per m2
D54: Plant | I54: =E56-I56 -> 14.981089 | K54: =I11*I54 -> 434.45159 | L54: =K54/J11 -> 4.4062027 | Q54: Plant | V54: =R56-V56 -> 15.026463 | X54: =V11*V54 -> 180.31755 | Y54: =X54/W11 -> 3.5777292
D55: 0.05 | E55: =E53*5% -> 1.1365892 | I55: Material cost per m | Q55: 0.05 | R55: =R53*5% -> 1.1819625 | V55: Material cost per m
E56: =SUM(E53:E55) -> 23.868374 | F56: per m | I56: =SUM(E38,E39,E45)*1.05 -> 8.8872845 | K56: =I56*I11 -> 257.73125 | L56: =K56/J11 -> 2.6139072 | R56: =SUM(R53:R55) -> 24.821213 | S56: per m | V56: =SUM(R38,R39,R45)*1.05 -> 9.79475 | X56: =V56*V11 -> 117.537 | Y56: =X56/W11 -> 2.3320833
D57: Total cost of track is | F57: =SUM(E56*I11) -> 692.18284 | Q57: Total cost of track is | S57: =SUM(R56*V11) -> 297.85455
D58: Total cost of Job is | F58: =SUM(F36+F57) -> 3263.7908 | G58: per m | Q58: Total cost of Job is | S58: =SUM(S36+S57) -> 1299.209 | T58: per m
F59: =SUM(F58/J11) -> 33.101327 | G59: m2 | S59: =SUM(S58/W11) -> 25.777956 | T59: m2
F60: =F58/F11 -> 112.54451 | G60: m | L60: Labour/m2 | M60: =SUM(L54,L33) -> 10.487085 | N60: =M60/F51 -> 0.19067427 | S60: =S58/S11 -> 108.26742 | T60: m | Y60: Labour/m2 | Z60: =SUM(Y54,Y33) -> 11.105873 | AA60: =Z60/S51 -> 0.20192496
D61: Materials | F61: =J58 -> 0 | G61: m2 | L61: Material/m2 | M61: =SUM(L35,L56) -> 22.614242 | Q61: Materials | S61: =W58 -> 0 | T61: m2 | Y61: Material/m2 | Z61: =SUM(Y35,Y56) -> 14.672083
D62: Labour | F62: =F59-F61 -> 33.101327 | G62: m2 | Q62: Labour | S62: =S59-S61 -> 25.777956 | T62: m2
B72: 64mm steel studs @ | C72: 0.6 | D72: Stud spacing | K72: WA06 | Q72: 64mm steel studs @ | R72: 0.6 | S72: Stud spacing | Z72: WA06
B74: Material | D74: Length of wall | E74: Height of wall | F74: Total stud LM | G74: Total track LM | H74: M2 of wall | Q74: Material | S74: Length of wall | T74: Height of wall | U74: Total stud LM | V74: Total track LM | W74: M2 of wall
C75: $/m | D75: 21 | E75: 4.2 | F75: =SUM(D85*E75) -> 151.2 | G75: =D75*2 -> 42 | H75: =D75*E75 -> 88.2 | R75: $/m | S75: 21 | T75: 4.2 | U75: =SUM(S85*T75) -> 151.2 | V75: =S75*2 -> 42 | W75: =S75*T75 -> 88.2
A76: Stud | B76: 64 .55 bmt | C76: 2.46 | D76: 55 | P76: Stud | Q76: 64 .55 bmt | R76: 2.46 | S76: 55
B77: Nog | C77: =F78/F75 -> 1.8055556 | D77: 6.5 | E77: m | F77: =SUM(D77*D75) -> 136.5 | Q77: Nog | R77: =U78/U75 -> 1.8055556 | S77: 6.5 | T77: m | U77: =SUM(S77*S75) -> 136.5
D78: Number of nogs | E78: 2 | F78: =E78*F77 -> 273 | S78: Number of nogs | T78: 2 | U78: =T78*U77 -> 273
B80: Unload | C80: 0.09 | Q80: Unload | R80: 0.09
B82: Fixings | Q82: Fixings
B83: say 4 each stud | Q83: say 4 each stud
B84: L of wl ÷ spacings = ttl studs | D84: =SUM(D75/C72) -> 35 | Q84: L of wl ÷ spacings = ttl studs | S84: =SUM(S75/R72) -> 35
B85: add 1 for end of wall | D85: =D84+1 -> 36 | E85: total studs in wall | Q85: add 1 for end of wall | S85: =S84+1 -> 36 | T85: total studs in wall
B86: Studs x 4 screws per stud = ttl screws | D86: =SUM(D85*4) -> 144 | E86: total screws | F86: 0.015 | Q86: Studs x 4 screws per stud = ttl screws | S86: =SUM(S85*4) -> 144 | T86: total screws | U86: 0.015
B87: Screws @ $20.00/1000 = .015 | C87: =SUM(D86*F86)/F75 -> 0.014285714 | D87: Cost of fixings per LM | Q87: Screws @ $20.00/1000 = .015 | R87: =SUM(S86*U86)/U75 -> 0.014285714 | S87: Cost of fixings per LM
C89: =SUM(C76:C88) -> 4.3698413 | R89: =SUM(R76:R88) -> 4.3698413
B90: waste 5% | C90: =SUM(C89*0.05) -> 0.21849206 | Q90: waste 5% | R90: =SUM(R89*0.05) -> 0.21849206
C91: =SUM(C89:C90) -> 4.5883333 | R91: =SUM(R89:R90) -> 4.5883333
A92: Stud | B92: Labour per m as per rates | D92: Lab rate | P92: Stud | Q92: Labour per m as per rates | S92: Lab rate
B93: m/hr | D93: 55 | Q93: m/hr | S93: 55
B94: 20 | C94: =D93/B94 -> 2.75 | Q94: 20 | R94: =S93/Q94 -> 2.75
C95: =SUM(C91:C94) -> 7.3383333 | R95: =SUM(R91:R94) -> 7.3383333
B97: Plant | H97: Labour cost per m | K97: per m2 | Q97: Plant | W97: Labour cost per m | Z97: per m2
B98: 0.05 | C98: =C95*B98 -> 0.36691667 | H98: =C100-H100 -> 3.2114167 | J98: =F75*H98 -> 485.5662 | K98: =J98/H75 -> 5.5052857 | Q98: 0.05 | R98: =R95*Q98 -> 0.36691667 | W98: =R100-W100 -> 3.2114167 | Y98: =U75*W98 -> 485.5662 | Z98: =Y98/W75 -> 5.5052857
H99: Material cost per m | W99: Material cost per m
C100: =SUM(C95:C98) -> 7.70525 | D100: per m | H100: =SUM(C76,C77,C87)*1.05 -> 4.4938333 | J100: =F75*H100 -> 679.4676 | K100: =J100/H75 -> 7.7037143 | R100: =SUM(R95:R98) -> 7.70525 | S100: per m | W100: =SUM(R76,R77,R87)*1.05 -> 4.4938333 | Y100: =U75*W100 -> 679.4676 | Z100: =Y100/W75 -> 7.7037143
B101: Total cost of stud job is | D101: =C100*F75 -> 1165.0338 | Q101: Total cost of stud job is | S101: =R100*U75 -> 1165.0338
A103: Track | B103: 64 .75 bmt | C103: 2.46 | P103: Track | Q103: 64 .75 bmt | R103: 3.73
B104: DPC | C104: 0.31 | Q104: DPC | R104: 0.31
B105: Unload | C105: 0.09 | Q105: Unload | R105: 0.09
B107: Fixings for track | Q107: Fixings for track
B108: Spaced @ 0.6 1.7 @ 2.50 each | D108: =D75/0.6 -> 35 | Q108: Spaced @ 0.6 1.7 @ 2.50 each | S108: =S75/0.6 -> 35
B109: add extra for ends | D109: =D108 -> 35 | E109: total fixings | F109: 2.5 | Q109: add extra for ends | S109: =S108 -> 35 | T109: total fixings | U109: 2.5
C110: =SUM(D109*F109)/G75 -> 2.0833333 | D110: Cost of fixings per LM | R110: =SUM(S109*U109)/V75 -> 2.0833333 | S110: Cost of fixings per LM
C112: =SUM(C103:C110) -> 4.9433333 | R112: =SUM(R103:R110) -> 6.2133333
B113: waste 5% | C113: =SUM(C112*0.05) -> 0.24716667 | Q113: waste 5% | R113: =SUM(R112*0.05) -> 0.31066667
C114: =SUM(C112:C113) -> 5.1905 | R114: =SUM(R112:R113) -> 6.524
A115: Track | B115: Labour per m as per rates | D115: Lab rate | P115: Track | Q115: Labour per m as per rates | S115: Lab rate
B116: m/hr | D116: 55 | H116: Labour cost per m | K116: per m2 | Q116: m/hr | S116: 55 | W116: Labour cost per m | Z116: per m2
B117: 4 | C117: =D116/B117 -> 13.75 | H117: =C121-H119 -> 14.791525 | J117: =G75*H117 -> 621.24405 | K117: =J117/H75 -> 7.0435833 | Q117: 4 | R117: =S116/Q117 -> 13.75 | W117: =R121-W119 -> 14.8582 | Y117: =V75*W117 -> 624.0444 | Z117: =Y117/W75 -> 7.0753333
C118: =SUM(C114:C117) -> 18.9405 | H118: Material cost per m | R118: =SUM(R114:R117) -> 20.274 | W118: Material cost per m
B119: Plant | H119: =SUM(C103,C104,C110)*1.05 -> 5.096 | J119: =H119*G75 -> 214.032 | K119: =J119/H75 -> 2.4266667 | Q119: Plant | W119: =SUM(R103,R104,R110)*1.05 -> 6.4295 | Y119: =W119*V75 -> 270.039 | Z119: =Y119/W75 -> 3.0616667
B120: 0.05 | C120: =C118*B120 -> 0.947025 | Q120: 0.05 | R120: =R118*Q120 -> 1.0137
C121: =SUM(C118:C120) -> 19.887525 | D121: per m | R121: =SUM(R118:R120) -> 21.2877 | S121: per m
B122: Total cost of track is | D122: =SUM(C121*G75) -> 835.27605 | L122: Labour/m2 | M122: =SUM(K98,K117) -> 12.548869 | N122: =M122/D116 -> 0.22816126 | Q122: Total cost of track is | S122: =SUM(R121*V75) -> 894.0834 | AA122: Labour/m2 | AB122: =SUM(Z98,Z117) -> 12.580619 | AC122: =AB122/S116 -> 0.22873853
B123: Total cost of Job is | D123: =SUM(D101+D122) -> 2000.3099 | E123: per m | G123: hrs allowed | L123: Material/m2 | M123: =SUM(K100,K119) -> 10.130381 | Q123: Total cost of Job is | S123: =SUM(S101+S122) -> 2059.1172 | T123: per m | V123: hrs allowed | AA123: Material/m2 | AB123: =SUM(Z100,Z119) -> 10.765381
D124: =SUM(D123/H75) -> 22.67925 | E124: m2 | F124: studs | G124: =SUM(F75/15) -> 10.08 | S124: =SUM(S123/W75) -> 23.346 | T124: m2 | U124: studs | V124: =SUM(U75/15) -> 10.08
D125: =D123/D75 -> 95.25285 | E125: m | F125: track | G125: =G75/4 -> 10.5 | H125: Total cost | S125: =S123/S75 -> 98.0532 | T125: m | U125: track | V125: =V75/4 -> 10.5 | W125: Total cost
B126: Materials | D126: =H121 -> 0 | E126: m2 | G126: =SUM(G124:G125) -> 20.58 | H126: =G126*50 -> 1029 | Q126: Materials | S126: =W121 -> 0 | T126: m2 | V126: =SUM(V124:V125) -> 20.58 | W126: =V126*50 -> 1029
B127: Labour | D127: =D124-D126 -> 22.67925 | E127: m2 | F127: Total m2 a day | G127: =SUM(H75/G126)*9 -> 38.571429 | Q127: Labour | S127: =S124-S126 -> 23.346 | T127: m2 | U127: Total m2 a day | V127: =SUM(W75/V126)*9 -> 38.571429

Sheet Gib Linings_25_8
B1: =Summary!#REF! -> #REF!
B2: =Summary!#REF! -> #REF!
B3: =Summary!#REF! -> #REF!
B6: 45853
B9: Gib Wall and Ceiling Linings
H11: 40
A12: Item | B12: Description | C12: Qty | D12: Unit | E12: Constant | F12: Constant X Unit = Total HRS | G12: $ Lab per Unit | H12: Total Labour | I12: Materials per Unit | J12: Total Materials | K12: Total Labour & Materials | L12: Total Labour & Materials Per Unit | M12: Total | N12: % Complete | O12: Claim
B15: Basement: | T15: =SUM(C17,C18,C20) -> 107
B16: Ceiling Linings:
B17: (CS01) 13mm Gib Standard | C17: 65 | D17: m2 | E17: 0.2 | F17: =C17*E17 -> 13 | G17: =$H$11*E17 -> 8 | H17: =F17*$H$11 -> 520 | I17: 13.51 | J17: =C17*I17 -> 878.15 | K17: =SUM(H17,J17) -> 1398.15 | L17: =K17/C17 -> 21.51 | M17: =C17*L17 -> 1398.15 | N17: 0 | O17: =M17*N17 -> 0
B18: (CS01) 13mm Gib Aqualine | C18: 31 | D18: m2 | E18: 0.2 | F18: =C18*E18 -> 6.2 | G18: =$H$11*E18 -> 8 | H18: =F18*$H$11 -> 248 | I18: 23.99 | J18: =C18*I18 -> 743.69 | K18: =SUM(H18,J18) -> 991.69 | L18: =K18/C18 -> 31.99 | M18: =C18*L18 -> 991.69 | N18: 0 | O18: =M18*N18 -> 0
B20: (WA24) 13mm Gib Standard | C20: 11 | D20: m2 | E20: 0.2 | F20: =C20*E20 -> 2.2 | G20: =$H$11*E20 -> 8 | H20: =F20*$H$11 -> 88 | I20: 13.51 | J20: =C20*I20 -> 148.61 | K20: =SUM(H20,J20) -> 236.61 | L20: =K20/C20 -> 21.51 | M20: =C20*L20 -> 236.61 | N20: 0 | O20: =M20*N20 -> 0 | T20: =SUM(C17:C20) -> 107
B22: Bulkhead Linings:
B23: (CS12) | C23: Nil | T23: =SUM(C23) -> 0
M24: =-T15 -> -107
P25: =SUM(M17:M24) -> 2519.45 | Q25: =P25*SUM($L$585:$L$589) -> 239.34775
P26: =P25/$M$582 -> 0.0064709516 | Q26: =P26*$M$593 -> 54.634908 | R26: =SUM(P25,Q25,Q26) -> 2813.4327 | S26: =R26*1.08 -> 3038.5073
B28: Ground: | T28: =SUM(C30,C31,C33,C33,C36,C36,C39,C42,C44,C46,C48) -> 378
B29: Ceiling Linings:
B30: (CS01) 13mm Gib Standard | C30: 244 | D30: m2 | E30: 0.2 | F30: =C30*E30 -> 48.8 | G30: =$H$11*E30 -> 8 | H30: =F30*$H$11 -> 1952 | I30: 13.51 | J30: =C30*I30 -> 3296.44 | K30: =SUM(H30,J30) -> 5248.44 | L30: =K30/C30 -> 21.51 | M30: =C30*L30 -> 5248.44 | N30: 0 | O30: =M30*N30 -> 0
B31: (CS01) 13mm Gib Aqualine | C31: 23 | D31: m2 | E31: 0.2 | F31: =C31*E31 -> 4.6 | G31: =$H$11*E31 -> 8 | H31: =F31*$H$11 -> 184 | I31: 23.99 | J31: =C31*I31 -> 551.77 | K31: =SUM(H31,J31) -> 735.77 | L31: =K31/C31 -> 31.99 | M31: =C31*L31 -> 735.77 | N31: 0 | O31: =M31*N31 -> 0
B33: (CS10) 16mm Gib Fyreline + 10mm Gib Fyreline | C33: 24 | D33: m2 | E33: 0.6 | F33: =C33*E33 -> 14.4 | G33: =$H$11*E33 -> 24 | H33: =F33*$H$11 -> 576 | I33: 38 | J33: =C33*I33 -> 912 | K33: =SUM(H33,J33) -> 1488 | L33: =K33/C33 -> 62 | M33: =C33*L33 -> 1488 | N33: 0 | O33: =M33*N33 -> 0
B34: Caulking to Above | C34: 21 | D34: m | E34: 0.05 | F34: =C34*E34 -> 1.05 | G34: =$H$11*E34 -> 2 | H34: =F34*$H$11 -> 42 | I34: 2.5 | J34: =C34*I34 -> 52.5 | K34: =SUM(H34,J34) -> 94.5 | L34: =K34/C34 -> 4.5 | M34: =C34*L34 -> 94.5 | N34: 0 | O34: =M34*N34 -> 0
B36: (CS11) 2/13mm Gib Fyreline | C36: 10 | D36: m2 | E36: 0.4 | F36: =C36*E36 -> 4 | G36: =$H$11*E36 -> 16 | H36: =F36*$H$11 -> 160 | I36: 32 | J36: =C36*I36 -> 320 | K36: =SUM(H36,J36) -> 480 | L36: =K36/C36 -> 48 | M36: =C36*L36 -> 480 | N36: 0 | O36: =M36*N36 -> 0
B37: Caulking to Above | C37: 22 | D37: m | E37: 0.05 | F37: =C37*E37 -> 1.1 | G37: =$H$11*E37 -> 2 | H37: =F37*$H$11 -> 44 | I37: 2.5 | J37: =C37*I37 -> 55 | K37: =SUM(H37,J37) -> 99 | L37: =K37/C37 -> 4.5 | M37: =C37*L37 -> 99 | N37: 0 | O37: =M37*N37 -> 0
B39: (CL50) 13mm Gib Standard (Raking to Stair) | C39: 17 | D39: m2 | E39: 0.35 | F39: =C39*E39 -> 5.95 | G39: =$H$11*E39 -> 14 | H39: =F39*$H$11 -> 238 | I39: 13.51 | J39: =C39*I39 -> 229.67 | K39: =SUM(H39,J39) -> 467.67 | L39: =K39/C39 -> 27.51 | M39: =C39*L39 -> 467.67 | N39: 0 | O39: =M39*N39 -> 0 | T39: =SUM(C30,C31,C33,C36,C39) -> 318
B41: Bulkhead Linings:
B42: Bulkhead - 13mm Gib Standard (900) | C42: 15 | D42: m2 | E42: 0.3 | F42: =C42*E42 -> 4.5 | G42: =$H$11*E42 -> 12 | H42: =F42*$H$11 -> 180 | I42: 13.51 | J42: =C42*I42 -> 202.65 | K42: =SUM(H42,J42) -> 382.65 | L42: =K42/C42 -> 25.51 | M42: =C42*L42 -> 382.65 | N42: 0 | O42: =M42*N42 -> 0
B44: Bulkhead - 13mm Gib Standard (1100) | C44: 1 | D44: m2 | E44: 0.3 | F44: =C44*E44 -> 0.3 | G44: =$H$11*E44 -> 12 | H44: =F44*$H$11 -> 12 | I44: 13.51 | J44: =C44*I44 -> 13.51 | K44: =SUM(H44,J44) -> 25.51 | L44: =K44/C44 -> 25.51 | M44: =C44*L44 -> 25.51 | N44: 0 | O44: =M44*N44 -> 0
B46: Bulkhead - 13mmm Gib Standard (1200) | C46: 5 | D46: m2 | E46: 0.3 | F46: =C46*E46 -> 1.5 | G46: =$H$11*E46 -> 12 | H46: =F46*$H$11 -> 60 | I46: 13.51 | J46: =C46*I46 -> 67.55 | K46: =SUM(H46,J46) -> 127.55 | L46: =K46/C46 -> 25.51 | M46: =C46*L46 -> 127.55 | N46: 0 | O46: =M46*N46 -> 0
B48: Bulkhead - 13mm Gib Stanard (1900) | C48: 5 | D48: m2 | E48: 0.3 | F48: =C48*E48 -> 1.5 | G48: =$H$11*E48 -> 12 | H48: =F48*$H$11 -> 60 | I48: 13.51 | J48: =C48*I48 -> 67.55 | K48: =SUM(H48,J48) -> 127.55 | L48: =K48/C48 -> 25.51 | M48: =C48*L48 -> 127.55 | N48: 0 | O48: =M48*N48 -> 0 | T48: =SUM(C42:C48) -> 26
M49: =-T28 -> -378
P50: =SUM(M30:M49) -> 8898.64 | Q50: =P50*SUM($L$585:$L$589) -> 845.3708
P51: =P50/$M$582 -> 0.022855254 | Q51: =P51*$M$593 -> 192.96925 | R51: =SUM(P50,Q50,Q51) -> 9936.98 | S51: =R51*1.08 -> 10731.938
B53: Level 1: | T53: =SUM(C55,C57,C59,C61,C67) -> 356
B54: Ceiling Linings:
B55: (CS01) 13mm Gib Standard | C55: 279 | D55: m2 | E55: 0.2 | F55: =C55*E55 -> 55.8 | G55: =$H$11*E55 -> 8 | H55: =F55*$H$11 -> 2232 | I55: 13.51 | J55: =C55*I55 -> 3769.29 | K55: =SUM(H55,J55) -> 6001.29 | L55: =K55/C55 -> 21.51 | M55: =C55*L55 -> 6001.29 | N55: 0 | O55: =M55*N55 -> 0
B56: EV High Level | C56: 149 | D56: m2 | E56: 0.15 | F56: =C56*E56 -> 22.35 | G56: =$H$11*E56 -> 6 | H56: =F56*$H$11 -> 894 | I56: 0 | J56: =C56*I56 -> 0 | K56: =SUM(H56,J56) -> 894 | L56: =K56/C56 -> 6 | M56: =C56*L56 -> 894 | N56: 0 | O56: =M56*N56 -> 0
B57: (CS01) 13mm Gib Aqualine | C57: 17 | D57: m2 | E57: 0.2 | F57: =C57*E57 -> 3.4 | G57: =$H$11*E57 -> 8 | H57: =F57*$H$11 -> 136 | I57: 23.99 | J57: =C57*I57 -> 407.83 | K57: =SUM(H57,J57) -> 543.83 | L57: =K57/C57 -> 31.99 | M57: =C57*L57 -> 543.83 | N57: 0 | O57: =M57*N57 -> 0
B59: (CL50) 13mm Gib Standard (Raking to Stair) | C59: 34 | D59: m2 | E59: 0.35 | F59: =C59*E59 -> 11.9 | G59: =$H$11*E59 -> 14 | H59: =F59*$H$11 -> 476 | I59: 13.51 | J59: =C59*I59 -> 459.34 | K59: =SUM(H59,J59) -> 935.34 | L59: =K59/C59 -> 27.51 | M59: =C59*L59 -> 935.34 | N59: 0 | O59: =M59*N59 -> 0
B61: 13mm Gib Fyreline Top and Bottom Stair 1 Bottom of Riser | C61: 12 | D61: m2 | E61: 0.4 | F61: =C61*E61 -> 4.8 | G61: =$H$11*E61 -> 16 | H61: =F61*$H$11 -> 192 | I61: 16 | J61: =C61*I61 -> 192 | K61: =SUM(H61,J61) -> 384 | L61: =K61/C61 -> 32 | M61: =C61*L61 -> 384 | N61: 0 | O61: =M61*N61 -> 0
B62: Caulking to Above | C62: 18 | D62: m | E62: 0.1 | F62: =C62*E62 -> 1.8 | G62: =$H$11*E62 -> 4 | H62: =F62*$H$11 -> 72 | I62: 2.5 | J62: =C62*I62 -> 45 | K62: =SUM(H62,J62) -> 117 | L62: =K62/C62 -> 6.5 | M62: =C62*L62 -> 117 | N62: 0 | O62: =M62*N62 -> 0 | T62: =SUM(C55,C57,C59,C61) -> 342
B64: Bulkhead Linings:
B65: (CS12) | C65: Nil
B67: Bulkhead - 13mmm Gib Standard (1200) | C67: 14 | D67: m2 | E67: 0.3 | F67: =C67*E67 -> 4.2 | G67: =$H$11*E67 -> 12 | H67: =F67*$H$11 -> 168 | I67: 13.51 | J67: =C67*I67 -> 189.14 | K67: =SUM(H67,J67) -> 357.14 | L67: =K67/C67 -> 25.51 | M67: =C67*L67 -> 357.14 | N67: 0 | O67: =M67*N67 -> 0 | T67: =C67 -> 14
M68: =-T53 -> -356
P69: =SUM(M55:M68) -> 8876.6 | Q69: =P69*SUM($L$585:$L$589) -> 843.277
P70: =P69/$M$582 -> 0.022798646 | Q70: =P70*$M$593 -> 192.49131 | R70: =SUM(P69,Q69,Q70) -> 9912.3683 | S70: =R70*1.08 -> 10705.358
B72: Level 2: | T72: =SUM(C74,C75,C77,C80) -> 126
B73: Ceiling Linings:
B74: (CS01) 13mm Gib Standard | C74: 75 | D74: m2 | E74: 0.2 | F74: =C74*E74 -> 15 | G74: =$H$11*E74 -> 8 | H74: =F74*$H$11 -> 600 | I74: 13.51 | J74: =C74*I74 -> 1013.25 | K74: =SUM(H74,J74) -> 1613.25 | L74: =K74/C74 -> 21.51 | M74: =C74*L74 -> 1613.25 | N74: 0 | O74: =M74*N74 -> 0
B75: (CS01) 13mm Gib Aqualine | C75: 15 | D75: m2 | E75: 0.2 | F75: =C75*E75 -> 3 | G75: =$H$11*E75 -> 8 | H75: =F75*$H$11 -> 120 | I75: 23.99 | J75: =C75*I75 -> 359.85 | K75: =SUM(H75,J75) -> 479.85 | L75: =K75/C75 -> 31.99 | M75: =C75*L75 -> 479.85 | N75: 0 | O75: =M75*N75 -> 0
B77: (CL50) 13mm Gib Standard (Raking to Stair) | C77: 30 | D77: m2 | E77: 0.35 | F77: =C77*E77 -> 10.5 | G77: =$H$11*E77 -> 14 | H77: =F77*$H$11 -> 420 | I77: 13.51 | J77: =C77*I77 -> 405.3 | K77: =SUM(H77,J77) -> 825.3 | L77: =K77/C77 -> 27.51 | M77: =C77*L77 -> 825.3 | N77: 0 | O77: =M77*N77 -> 0 | T77: =SUM(C77,C75,C74) -> 120
B79: Bulkhead Linings:
B80: Bulkhead - 13mmm Gib Standard (1200) | C80: 6 | D80: m2 | E80: 0.3 | F80: =C80*E80 -> 1.8 | G80: =$H$11*E80 -> 12 | H80: =F80*$H$11 -> 72 | I80: 13.51 | J80: =C80*I80 -> 81.06 | K80: =SUM(H80,J80) -> 153.06 | L80: =K80/C80 -> 25.51 | M80: =C80*L80 -> 153.06 | N80: 0 | O80: =M80*N80 -> 0
M81: =-T72 -> -126
P82: =SUM(M74:M81) -> 2945.46 | Q82: =P82*SUM($L$585:$L$589) -> 279.8187
P83: =P82/$M$582 -> 0.0075651151 | Q83: =P83*$M$593 -> 63.873042 | R83: =SUM(P82,Q82,Q83) -> 3289.1517 | S83: =R83*1.08 -> 3552.2839
B85: Level 3: | T85: =SUM(C87,C88,C90,C93) -> 94
B86: Ceiling Linings:
B87: (CS01) 13mm Gib Standard | C87: 43 | D87: m2 | E87: 0.2 | F87: =C87*E87 -> 8.6 | G87: =$H$11*E87 -> 8 | H87: =F87*$H$11 -> 344 | I87: 13.51 | J87: =C87*I87 -> 580.93 | K87: =SUM(H87,J87) -> 924.93 | L87: =K87/C87 -> 21.51 | M87: =C87*L87 -> 924.93 | N87: 0 | O87: =M87*N87 -> 0
B88: (CS01) 13mm Gib Aqualine | C88: 15 | D88: m2 | E88: 0.2 | F88: =C88*E88 -> 3 | G88: =$H$11*E88 -> 8 | H88: =F88*$H$11 -> 120 | I88: 23.99 | J88: =C88*I88 -> 359.85 | K88: =SUM(H88,J88) -> 479.85 | L88: =K88/C88 -> 31.99 | M88: =C88*L88 -> 479.85 | N88: 0 | O88: =M88*N88 -> 0
B90: (CL50) 13mm Gib Standard (Raking to Stair) | C90: 30 | D90: m2 | E90: 0.35 | F90: =C90*E90 -> 10.5 | G90: =$H$11*E90 -> 14 | H90: =F90*$H$11 -> 420 | I90: 13.51 | J90: =C90*I90 -> 405.3 | K90: =SUM(H90,J90) -> 825.3 | L90: =K90/C90 -> 27.51 | M90: =C90*L90 -> 825.3 | N90: 0 | O90: =M90*N90 -> 0 | T90: =SUM(C87:C90) -> 88
B92: Bulkhead Linings:
B93: Bulkhead - 13mmm Gib Standard (1200) | C93: 6 | D93: m2 | E93: 0.3 | F93: =C93*E93 -> 1.8 | G93: =$H$11*E93 -> 12 | H93: =F93*$H$11 -> 72 | I93: 13.51 | J93: =C93*I93 -> 81.06 | K93: =SUM(H93,J93) -> 153.06 | L93: =K93/C93 -> 25.51 | M93: =C93*L93 -> 153.06 | N93: 0 | O93: =M93*N93 -> 0
M94: =-T85 -> -94
P95: =SUM(M87:M94) -> 2289.14 | Q95: =P95*SUM($L$585:$L$589) -> 217.4683
P96: =P95/$M$582 -> 0.0058794238 | Q96: =P96*$M$593 -> 49.640577 | R96: =SUM(P95,Q95,Q96) -> 2556.2489 | S96: =R96*1.08 -> 2760.7488
B98: Level 4: | T98: =SUM(C100,C101,C103,C106) -> 86
B99: Ceiling Linings:
B100: (CS01) 13mm Gib Standard | C100: 35 | D100: m2 | E100: 0.2 | F100: =C100*E100 -> 7 | G100: =$H$11*E100 -> 8 | H100: =F100*$H$11 -> 280 | I100: 13.51 | J100: =C100*I100 -> 472.85 | K100: =SUM(H100,J100) -> 752.85 | L100: =K100/C100 -> 21.51 | M100: =C100*L100 -> 752.85 | N100: 0 | O100: =M100*N100 -> 0
B101: (CS01) 13mm Gib Aqualine | C101: 15 | D101: m2 | E101: 0.2 | F101: =C101*E101 -> 3 | G101: =$H$11*E101 -> 8 | H101: =F101*$H$11 -> 120 | I101: 23.99 | J101: =C101*I101 -> 359.85 | K101: =SUM(H101,J101) -> 479.85 | L101: =K101/C101 -> 31.99 | M101: =C101*L101 -> 479.85 | N101: 0 | O101: =M101*N101 -> 0
B103: (CL50) 13mm Gib Standard (Raking to Stair) | C103: 30 | D103: m2 | E103: 0.35 | F103: =C103*E103 -> 10.5 | G103: =$H$11*E103 -> 14 | H103: =F103*$H$11 -> 420 | I103: 13.51 | J103: =C103*I103 -> 405.3 | K103: =SUM(H103,J103) -> 825.3 | L103: =K103/C103 -> 27.51 | M103: =C103*L103 -> 825.3 | N103: 0 | O103: =M103*N103 -> 0 | T103: =SUM(C100:C103) -> 80
B105: Bulkhead Linings:
B106: Bulkhead - 13mmm Gib Standard (1200) | C106: 6 | D106: m2 | E106: 0.3 | F106: =C106*E106 -> 1.8 | G106: =$H$11*E106 -> 12 | H106: =F106*$H$11 -> 72 | I106: 13.51 | J106: =C106*I106 -> 81.06 | K106: =SUM(H106,J106) -> 153.06 | L106: =K106/C106 -> 25.51 | M106: =C106*L106 -> 153.06 | N106: 0 | O106: =M106*N106 -> 0
M107: =-T98 -> -86
P108: =SUM(M100:M107) -> 2125.06 | Q108: =P108*SUM($L$585:$L$589) -> 201.8807
P109: =P108/$M$582 -> 0.0054580009 | Q109: =P109*$M$593 -> 46.082461 | R109: =SUM(P108,Q108,Q109) -> 2373.0232 | S109: =R109*1.08 -> 2562.865
B111: Level 5: | T111: =SUM(C113,C114,C116,C119) -> 95
B112: Ceiling Linings:
B113: (CS01) 13mm Gib Standard | C113: 44 | D113: m2 | E113: 0.2 | F113: =C113*E113 -> 8.8 | G113: =$H$11*E113 -> 8 | H113: =F113*$H$11 -> 352 | I113: 13.51 | J113: =C113*I113 -> 594.44 | K113: =SUM(H113,J113) -> 946.44 | L113: =K113/C113 -> 21.51 | M113: =C113*L113 -> 946.44 | N113: 0 | O113: =M113*N113 -> 0
B114: (CS01) 13mm Gib Aqualine | C114: 15 | D114: m2 | E114: 0.2 | F114: =C114*E114 -> 3 | G114: =$H$11*E114 -> 8 | H114: =F114*$H$11 -> 120 | I114: 23.99 | J114: =C114*I114 -> 359.85 | K114: =SUM(H114,J114) -> 479.85 | L114: =K114/C114 -> 31.99 | M114: =C114*L114 -> 479.85 | N114: 0 | O114: =M114*N114 -> 0
B116: (CL50) 13mm Gib Standard (Raking to Stair) | C116: 30 | D116: m2 | E116: 0.35 | F116: =C116*E116 -> 10.5 | G116: =$H$11*E116 -> 14 | H116: =F116*$H$11 -> 420 | I116: 13.51 | J116: =C116*I116 -> 405.3 | K116: =SUM(H116,J116) -> 825.3 | L116: =K116/C116 -> 27.51 | M116: =C116*L116 -> 825.3 | N116: 0 | O116: =M116*N116 -> 0 | T116: =SUM(C113:C116) -> 89
B118: Bulkhead Linings:
B119: Bulkhead - 13mmm Gib Standard (1200) | C119: 6 | D119: m2 | E119: 0.3 | F119: =C119*E119 -> 1.8 | G119: =$H$11*E119 -> 12 | H119: =F119*$H$11 -> 72 | I119: 13.51 | J119: =C119*I119 -> 81.06 | K119: =SUM(H119,J119) -> 153.06 | L119: =K119/C119 -> 25.51 | M119: =C119*L119 -> 153.06 | N119: 0 | O119: =M119*N119 -> 0
M120: =-T111 -> -95
P121: =SUM(M113:M120) -> 2309.65 | Q121: =P121*SUM($L$585:$L$589) -> 219.41675
P122: =P121/$M$582 -> 0.0059321016 | Q122: =P122*$M$593 -> 50.085342 | R122: =SUM(P121,Q121,Q122) -> 2579.1521 | S122: =R122*1.08 -> 2785.4843
B123: Level 6: | T123: =SUM(C125,C126,C128,C130,C133) -> 331
B124: Ceiling Linings:
B125: (CS01) 13mm Gib Standard | C125: 56 | D125: m2 | E125: 0.2 | F125: =C125*E125 -> 11.2 | G125: =$H$11*E125 -> 8 | H125: =F125*$H$11 -> 448 | I125: 13.51 | J125: =C125*I125 -> 756.56 | K125: =SUM(H125,J125) -> 1204.56 | L125: =K125/C125 -> 21.51 | M125: =C125*L125 -> 1204.56 | N125: 0 | O125: =M125*N125 -> 0
B126: (CS01) 13mm Gib Aqualine | C126: 16 | D126: m2 | E126: 0.2 | F126: =C126*E126 -> 3.2 | G126: =$H$11*E126 -> 8 | H126: =F126*$H$11 -> 128 | I126: 23.99 | J126: =C126*I126 -> 383.84 | K126: =SUM(H126,J126) -> 511.84 | L126: =K126/C126 -> 31.99 | M126: =C126*L126 -> 511.84 | N126: 0 | O126: =M126*N126 -> 0
B128: (CL50) 13mm Gib Standard (Raking to Stair) | C128: 12 | D128: m2 | E128: 0.35 | F128: =C128*E128 -> 4.2 | G128: =$H$11*E128 -> 14 | H128: =F128*$H$11 -> 168 | I128: 13.51 | J128: =C128*I128 -> 162.12 | K128: =SUM(H128,J128) -> 330.12 | L128: =K128/C128 -> 27.51 | M128: =C128*L128 -> 330.12 | N128: 0 | O128: =M128*N128 -> 0 | T128: =SUM(C125:C128) -> 84
B130: 13mm Gib Noiseline underside of Roof Grid 1.5 - 3 | C130: 244 | D130: m2 | E130: 0.3 | F130: =C130*E130 -> 73.2 | G130: =$H$11*E130 -> 12 | H130: =F130*$H$11 -> 2928 | I130: 16 | J130: =C130*I130 -> 3904 | K130: =SUM(H130,J130) -> 6832 | L130: =K130/C130 -> 28 | M130: =C130*L130 -> 6832 | N130: 0 | O130: =M130*N130 -> 0
B132: Bulkhead Linings:
B133: Bulkhead - 13mmm Gib Standard (1200) | C133: 3 | D133: m2 | E133: 0.3 | F133: =C133*E133 -> 0.9 | G133: =$H$11*E133 -> 12 | H133: =F133*$H$11 -> 36 | I133: 13.51 | J133: =C133*I133 -> 40.53 | K133: =SUM(H133,J133) -> 76.53 | L133: =K133/C133 -> 25.51 | M133: =C133*L133 -> 76.53 | N133: 0 | O133: =M133*N133 -> 0
M134: =-T123 -> -331
P135: =SUM(M125:M134) -> 8624.05 | Q135: =P135*SUM($L$585:$L$589) -> 819.28475
P136: =P135/$M$582 -> 0.022149997 | Q136: =P136*$M$593 -> 187.0147 | R136: =SUM(P135,Q135,Q136) -> 9630.3494 | S136: =R136*1.08 -> 10400.777
B138: Plant Room: | T138: =SUM(C140) -> 73
...

Sheet Stopping_25_8
B1: =Summary!#REF! -> #REF!
B2: =Summary!#REF! -> #REF!
B3: =Summary!#REF! -> #REF!
B6: 45853
B9: Gib Stopping
H11: 36
A12: Item | B12: Description | C12: Qty | D12: Unit | E12: Constant | F12: Constant X Unit = Total HRS | G12: $ Lab per Unit | H12: Total Labour | I12: Materials per Unit | J12: Total Materials | K12: Total Labour & Materials | L12: Total Labour & Materials Per Unit | M12: Total | N12: % Complete | O12: Claim
B15: Basement:
B16: Stopping Ceiling Linings:
B17: Level 4 | C17: 107 | D17: m2 | E17: 0.2 | F17: =C17*E17 -> 21.4 | G17: =$H$11*E17 -> 7.2 | H17: =F17*$H$11 -> 770.4 | I17: 0.85 | J17: =C17*I17 -> 90.95 | K17: =SUM(H17,J17) -> 861.35 | L17: =K17/C17 -> 8.05 | M17: =C17*L17 -> 861.35 | N17: 0 | O17: =M17*N17 -> 0
B18: Square Stopping | C18: 166 | D18: m | E18: 0.2 | F18: =C18*E18 -> 33.2 | G18: =$H$11*E18 -> 7.2 | H18: =F18*$H$11 -> 1195.2 | I18: 1.1 | J18: =C18*I18 -> 182.6 | K18: =SUM(H18,J18) -> 1377.8 | L18: =K18/C18 -> 8.3 | M18: =C18*L18 -> 1377.8 | N18: 0 | O18: =M18*N18 -> 0
P19: =SUM(M16:M18) -> 2239.15 | Q19: =P19*SUM($L$202:$L$206) -> 212.71925
B20: Stopping Bulkhead Linings: | C20: Nil | P20: =P19/$M$199 -> 0.013578425 | Q20: =P20*$M$210 -> 106.42325 | R20: =SUM(P19,Q19,Q20) -> 2558.2925 | S20: =R20*1.08 -> 2762.9559
B24: Ground: | C24: `
B25: Stopping Ceiling Linings:
B26: Level 4 | C26: 318 | D26: m2 | E26: 0.2 | F26: =C26*E26 -> 63.6 | G26: =$H$11*E26 -> 7.2 | H26: =F26*$H$11 -> 2289.6 | I26: 0.85 | J26: =C26*I26 -> 270.3 | K26: =SUM(H26,J26) -> 2559.9 | L26: =K26/C26 -> 8.05 | M26: =C26*L26 -> 2559.9 | N26: 0 | O26: =M26*N26 -> 0
B27: Square Stopping | C27: 302 | D27: m | E27: 0.2 | F27: =C27*E27 -> 60.4 | G27: =$H$11*E27 -> 7.2 | H27: =F27*$H$11 -> 2174.4 | I27: 1.1 | J27: =C27*I27 -> 332.2 | K27: =SUM(H27,J27) -> 2506.6 | L27: =K27/C27 -> 8.3 | M27: =C27*L27 -> 2506.6 | N27: 0 | O27: =M27*N27 -> 0
B28: EV Negative to US of Stairs | C28: 23 | D28: m | E28: 0.3 | F28: =C28*E28 -> 6.9 | G28: =$H$11*E28 -> 10.8 | H28: =F28*$H$11 -> 248.4 | I28: 7 | J28: =C28*I28 -> 161 | K28: =SUM(H28,J28) -> 409.4 | L28: =K28/C28 -> 17.8 | M28: =C28*L28 -> 409.4 | N28: 0 | O28: =M28*N28 -> 0
P29: =SUM(M26:M28) -> 5475.9 | Q29: =P29*SUM($L$202:$L$206) -> 520.2105
B30: Stopping Bulkhead Linings: | P30: =P29/$M$199 -> 0.033206394 | Q30: =P30*$M$210 -> 260.26084 | R30: =SUM(P29,Q29,Q30) -> 6256.3713 | S30: =R30*1.08 -> 6756.881
B31: Level 4 | C31: 26 | D31: m2 | E31: 0.2 | F31: =C31*E31 -> 5.2 | G31: =$H$11*E31 -> 7.2 | H31: =F31*$H$11 -> 187.2 | I31: 0.85 | J31: =C31*I31 -> 22.1 | K31: =SUM(H31,J31) -> 209.3 | L31: =K31/C31 -> 8.05 | M31: =C31*L31 -> 209.3 | N31: 0 | O31: =M31*N31 -> 0
B32: External Corner | C32: 39 | D32: m | E32: 0.19 | F32: =C32*E32 -> 7.41 | G32: =$H$11*E32 -> 6.84 | H32: =F32*$H$11 -> 266.76 | I32: 2.02 | J32: =C32*I32 -> 78.78 | K32: =SUM(H32,J32) -> 345.54 | L32: =K32/C32 -> 8.86 | M32: =C32*L32 -> 345.54 | N32: 0 | O32: =M32*N32 -> 0
P33: =SUM(M30:M32) -> 554.84 | Q33: =P33*SUM($L$202:$L$206) -> 52.7098
P34: =P33/$M$199 -> 0.0033646041 | Q34: =P34*$M$210 -> 26.370665 | R34: =SUM(P33,Q33,Q34) -> 633.92046 | S34: =R34*1.08 -> 684.6341
B36: Level 1:
B37: Stopping Ceiling Linings:
B38: Level 4 | C38: 342 | D38: m2 | E38: 0.2 | F38: =C38*E38 -> 68.4 | G38: =$H$11*E38 -> 7.2 | H38: =F38*$H$11 -> 2462.4 | I38: 0.85 | J38: =C38*I38 -> 290.7 | K38: =SUM(H38,J38) -> 2753.1 | L38: =K38/C38 -> 8.05 | M38: =C38*L38 -> 2753.1 | N38: 0 | O38: =M38*N38 -> 0
B39: Square Stopping | C39: 260 | D39: m | E39: 0.2 | F39: =C39*E39 -> 52 | G39: =$H$11*E39 -> 7.2 | H39: =F39*$H$11 -> 1872 | I39: 1.1 | J39: =C39*I39 -> 286 | K39: =SUM(H39,J39) -> 2158 | L39: =K39/C39 -> 8.3 | M39: =C39*L39 -> 2158 | N39: 0 | O39: =M39*N39 -> 0
B40: EV Negative to US of Stairs | C40: 51 | D40: m | E40: 0.3 | F40: =C40*E40 -> 15.3 | G40: =$H$11*E40 -> 10.8 | H40: =F40*$H$11 -> 550.8 | I40: 7 | J40: =C40*I40 -> 357 | K40: =SUM(H40,J40) -> 907.8 | L40: =K40/C40 -> 17.8 | M40: =C40*L40 -> 907.8 | N40: 0 | O40: =M40*N40 -> 0
P41: =SUM(M38:M40) -> 5818.9 | Q41: =P41*SUM($L$202:$L$206) -> 552.7955
B42: Stopping Bulkhead Linings: | P42: =P41/$M$199 -> 0.035286379 | Q42: =P42*$M$210 -> 276.56308 | R42: =SUM(P41,Q41,Q42) -> 6648.2586 | S42: =R42*1.08 -> 7180.1193
B43: Level 4 | C43: 14 | D43: m2 | E43: 0.2 | F43: =C43*E43 -> 2.8 | G43: =$H$11*E43 -> 7.2 | H43: =F43*$H$11 -> 100.8 | I43: 0.85 | J43: =C43*I43 -> 11.9 | K43: =SUM(H43,J43) -> 112.7 | L43: =K43/C43 -> 8.05 | M43: =C43*L43 -> 112.7 | N43: 0 | O43: =M43*N43 -> 0
B44: External Corner | C44: 11 | D44: m | E44: 0.19 | F44: =C44*E44 -> 2.09 | G44: =$H$11*E44 -> 6.84 | H44: =F44*$H$11 -> 75.24 | I44: 2.02 | J44: =C44*I44 -> 22.22 | K44: =SUM(H44,J44) -> 97.46 | L44: =K44/C44 -> 8.86 | M44: =C44*L44 -> 97.46 | N44: 0 | O44: =M44*N44 -> 0
P45: =SUM(M42:M44) -> 210.16 | Q45: =P45*SUM($L$202:$L$206) -> 19.9652
P46: =P45/$M$199 -> 0.0012744308 | Q46: =P46*$M$210 -> 9.9885713 | R46: =SUM(P45,Q45,Q46) -> 240.11377 | S46: =R46*1.08 -> 259.32287
B48: Level 2:
B49: Stopping Ceiling Linings:
B50: Level 4 | C50: 120 | D50: m2 | E50: 0.2 | F50: =C50*E50 -> 24 | G50: =$H$11*E50 -> 7.2 | H50: =F50*$H$11 -> 864 | I50: 0.85 | J50: =C50*I50 -> 102 | K50: =SUM(H50,J50) -> 966 | L50: =K50/C50 -> 8.05 | M50: =C50*L50 -> 966 | N50: 0 | O50: =M50*N50 -> 0
B51: Square Stopping | C51: 156 | D51: m | E51: 0.2 | F51: =C51*E51 -> 31.2 | G51: =$H$11*E51 -> 7.2 | H51: =F51*$H$11 -> 1123.2 | I51: 1.1 | J51: =C51*I51 -> 171.6 | K51: =SUM(H51,J51) -> 1294.8 | L51: =K51/C51 -> 8.3 | M51: =C51*L51 -> 1294.8 | N51: 0 | O51: =M51*N51 -> 0
B52: EV Negative to US of Stairs | C52: 43 | D52: m | E52: 0.3 | F52: =C52*E52 -> 12.9 | G52: =$H$11*E52 -> 10.8 | H52: =F52*$H$11 -> 464.4 | I52: 7 | J52: =C52*I52 -> 301 | K52: =SUM(H52,J52) -> 765.4 | L52: =K52/C52 -> 17.8 | M52: =C52*L52 -> 765.4 | N52: 0 | O52: =M52*N52 -> 0
P53: =SUM(M50:M52) -> 3026.2 | Q53: =P53*SUM($L$202:$L$206) -> 287.489
B54: Stopping Bulkhead Linings: | P54: =P53/$M$199 -> 0.018351173 | Q54: =P54*$M$210 -> 143.83048 | R54: =SUM(P53,Q53,Q54) -> 3457.5195 | S54: =R54*1.08 -> 3734.121
B55: Level 4 | C55: 6 | D55: m2 | E55: 0.2 | F55: =C55*E55 -> 1.2 | G55: =$H$11*E55 -> 7.2 | H55: =F55*$H$11 -> 43.2 | I55: 0.85 | J55: =C55*I55 -> 5.1 | K55: =SUM(H55,J55) -> 48.3 | L55: =K55/C55 -> 8.05 | M55: =C55*L55 -> 48.3 | N55: 0 | O55: =M55*N55 -> 0
B56: External Corner | C56: 5 | D56: m | E56: 0.19 | F56: =C56*E56 -> 0.95 | G56: =$H$11*E56 -> 6.84 | H56: =F56*$H$11 -> 34.2 | I56: 2.02 | J56: =C56*I56 -> 10.1 | K56: =SUM(H56,J56) -> 44.3 | L56: =K56/C56 -> 8.86 | M56: =C56*L56 -> 44.3 | N56: 0 | O56: =M56*N56 -> 0
P57: =SUM(M54:M56) -> 92.6 | Q57: =P57*SUM($L$202:$L$206) -> 8.797
P58: =P57/$M$199 -> 0.00056153546 | Q58: =P58*$M$210 -> 4.4011311 | R58: =SUM(P57,Q57,Q58) -> 105.79813 | S58: =R58*1.08 -> 114.26198
B60: Level 3:
B61: Stopping Ceiling Linings:
B62: Level 4 | C62: 88 | D62: m2 | E62: 0.2 | F62: =C62*E62 -> 17.6 | G62: =$H$11*E62 -> 7.2 | H62: =F62*$H$11 -> 633.6 | I62: 0.85 | J62: =C62*I62 -> 74.8 | K62: =SUM(H62,J62) -> 708.4 | L62: =K62/C62 -> 8.05 | M62: =C62*L62 -> 708.4 | N62: 0 | O62: =M62*N62 -> 0
B63: Square Stopping | C63: 127 | D63: m | E63: 0.2 | F63: =C63*E63 -> 25.4 | G63: =$H$11*E63 -> 7.2 | H63: =F63*$H$11 -> 914.4 | I63: 1.1 | J63: =C63*I63 -> 139.7 | K63: =SUM(H63,J63) -> 1054.1 | L63: =K63/C63 -> 8.3 | M63: =C63*L63 -> 1054.1 | N63: 0 | O63: =M63*N63 -> 0
B64: EV Negative to US of Stairs | C64: 43 | D64: m | E64: 0.3 | F64: =C64*E64 -> 12.9 | G64: =$H$11*E64 -> 10.8 | H64: =F64*$H$11 -> 464.4 | I64: 7 | J64: =C64*I64 -> 301 | K64: =SUM(H64,J64) -> 765.4 | L64: =K64/C64 -> 17.8 | M64: =C64*L64 -> 765.4 | N64: 0 | O64: =M64*N64 -> 0
P65: =SUM(M62:M64) -> 2527.9 | Q65: =P65*SUM($L$202:$L$206) -> 240.1505
B66: Stopping Bulkhead Linings: | P66: =P65/$M$199 -> 0.015329433 | Q66: =P66*$M$210 -> 120.14708 | R66: =SUM(P65,Q65,Q66) -> 2888.1976 | S66: =R66*1.08 -> 3119.2534
B67: Level 4 | C67: 6 | D67: m2 | E67: 0.2 | F67: =C67*E67 -> 1.2 | G67: =$H$11*E67 -> 7.2 | H67: =F67*$H$11 -> 43.2 | I67: 0.85 | J67: =C67*I67 -> 5.1 | K67: =SUM(H67,J67) -> 48.3 | L67: =K67/C67 -> 8.05 | M67: =C67*L67 -> 48.3 | N67: 0 | O67: =M67*N67 -> 0
B68: External Corner | C68: 5 | D68: m | E68: 0.19 | F68: =C68*E68 -> 0.95 | G68: =$H$11*E68 -> 6.84 | H68: =F68*$H$11 -> 34.2 | I68: 2.02 | J68: =C68*I68 -> 10.1 | K68: =SUM(H68,J68) -> 44.3 | L68: =K68/C68 -> 8.86 | M68: =C68*L68 -> 44.3 | N68: 0 | O68: =M68*N68 -> 0
P69: =SUM(M66:M68) -> 92.6 | Q69: =P69*SUM($L$202:$L$206) -> 8.797
P70: =P69/$M$199 -> 0.00056153546 | Q70: =P70*$M$210 -> 4.4011311 | R70: =SUM(P69,Q69,Q70) -> 105.79813 | S70: =R70*1.08 -> 114.26198
B72: Level 4:
B73: Stopping Ceiling Linings:
B74: Level 4 | C74: 80 | D74: m2 | E74: 0.2 | F74: =C74*E74 -> 16 | G74: =$H$11*E74 -> 7.2 | H74: =F74*$H$11 -> 576 | I74: 0.85 | J74: =C74*I74 -> 68 | K74: =SUM(H74,J74) -> 644 | L74: =K74/C74 -> 8.05 | M74: =C74*L74 -> 644 | N74: 0 | O74: =M74*N74 -> 0
B75: Square Stopping | C75: 113 | D75: m | E75: 0.2 | F75: =C75*E75 -> 22.6 | G75: =$H$11*E75 -> 7.2 | H75: =F75*$H$11 -> 813.6 | I75: 1.1 | J75: =C75*I75 -> 124.3 | K75: =SUM(H75,J75) -> 937.9 | L75: =K75/C75 -> 8.3 | M75: =C75*L75 -> 937.9 | N75: 0 | O75: =M75*N75 -> 0
B76: EV Negative to US of Stairs | C76: 43 | D76: m | E76: 0.3 | F76: =C76*E76 -> 12.9 | G76: =$H$11*E76 -> 10.8 | H76: =F76*$H$11 -> 464.4 | I76: 7 | J76: =C76*I76 -> 301 | K76: =SUM(H76,J76) -> 765.4 | L76: =K76/C76 -> 17.8 | M76: =C76*L76 -> 765.4 | N76: 0 | O76: =M76*N76 -> 0
P77: =SUM(M74:M76) -> 2347.3 | Q77: =P77*SUM($L$202:$L$206) -> 222.9935
B78: Stopping Bulkhead Linings: | P78: =P77/$M$199 -> 0.014234257 | Q78: =P78*$M$210 -> 111.56344 | R78: =SUM(P77,Q77,Q78) -> 2681.8569 | S78: =R78*1.08 -> 2896.4055
B79: Level 4 | C79: 6 | D79: m2 | E79: 0.2 | F79: =C79*E79 -> 1.2 | G79: =$H$11*E79 -> 7.2 | H79: =F79*$H$11 -> 43.2 | I79: 0.85 | J79: =C79*I79 -> 5.1 | K79: =SUM(H79,J79) -> 48.3 | L79: =K79/C79 -> 8.05 | M79: =C79*L79 -> 48.3 | N79: 0 | O79: =M79*N79 -> 0
B80: External Corner | C80: 5 | D80: m | E80: 0.19 | F80: =C80*E80 -> 0.95 | G80: =$H$11*E80 -> 6.84 | H80: =F80*$H$11 -> 34.2 | I80: 2.02 | J80: =C80*I80 -> 10.1 | K80: =SUM(H80,J80) -> 44.3 | L80: =K80/C80 -> 8.86 | M80: =C80*L80 -> 44.3 | N80: 0 | O80: =M80*N80 -> 0
P81: =SUM(M78:M80) -> 92.6 | Q81: =P81*SUM($L$202:$L$206) -> 8.797
P82: =P81/$M$199 -> 0.00056153546 | Q82: =P82*$M$210 -> 4.4011311 | R82: =SUM(P81,Q81,Q82) -> 105.79813 | S82: =R82*1.08 -> 114.26198
B84: Level 5:
B85: Stopping Ceiling Linings:
B86: Level 4 | C86: 89 | D86: m2 | E86: 0.2 | F86: =C86*E86 -> 17.8 | G86: =$H$11*E86 -> 7.2 | H86: =F86*$H$11 -> 640.8 | I86: 0.85 | J86: =C86*I86 -> 75.65 | K86: =SUM(H86,J86) -> 716.45 | L86: =K86/C86 -> 8.05 | M86: =C86*L86 -> 716.45 | N86: 0 | O86: =M86*N86 -> 0
B87: Square Stopping | C87: 127 | D87: m | E87: 0.2 | F87: =C87*E87 -> 25.4 | G87: =$H$11*E87 -> 7.2 | H87: =F87*$H$11 -> 914.4 | I87: 1.1 | J87: =C87*I87 -> 139.7 | K87: =SUM(H87,J87) -> 1054.1 | L87: =K87/C87 -> 8.3 | M87: =C87*L87 -> 1054.1 | N87: 0 | O87: =M87*N87 -> 0
B88: EV Negative to US of Stairs | C88: 43 | D88: m | E88: 0.3 | F88: =C88*E88 -> 12.9 | G88: =$H$11*E88 -> 10.8 | H88: =F88*$H$11 -> 464.4 | I88: 7 | J88: =C88*I88 -> 301 | K88: =SUM(H88,J88) -> 765.4 | L88: =K88/C88 -> 17.8 | M88: =C88*L88 -> 765.4 | N88: 0 | O88: =M88*N88 -> 0
P89: =SUM(M86:M88) -> 2535.95 | Q89: =P89*SUM($L$202:$L$206) -> 240.91525
B90: Stopping Bulkhead Linings: | P90: =P89/$M$199 -> 0.015378249 | Q90: =P90*$M$210 -> 120.52968 | R90: =SUM(P89,Q89,Q90) -> 2897.3949 | S90: =R90*1.08 -> 3129.1865
B91: Level 4 | C91: 6 | D91: m2 | E91: 0.2 | F91: =C91*E91 -> 1.2 | G91: =$H$11*E91 -> 7.2 | H91: =F91*$H$11 -> 43.2 | I91: 0.85 | J91: =C91*I91 -> 5.1 | K91: =SUM(H91,J91) -> 48.3 | L91: =K91/C91 -> 8.05 | M91: =C91*L91 -> 48.3 | N91: 0 | O91: =M91*N91 -> 0
B92: External Corner | C92: 5 | D92: m | E92: 0.19 | F92: =C92*E92 -> 0.95 | G92: =$H$11*E92 -> 6.84 | H92: =F92*$H$11 -> 34.2 | I92: 2.02 | J92: =C92*I92 -> 10.1 | K92: =SUM(H92,J92) -> 44.3 | L92: =K92/C92 -> 8.86 | M92: =C92*L92 -> 44.3 | N92: 0 | O92: =M92*N92 -> 0
P93: =SUM(M90:M92) -> 92.6 | Q93: =P93*SUM($L$202:$L$206) -> 8.797
P94: =P93/$M$199 -> 0.00056153546 | Q94: =P94*$M$210 -> 4.4011311 | R94: =SUM(P93,Q93,Q94) -> 105.79813 | S94: =R94*1.08 -> 114.26198
B96: Level 6:
B97: Stopping Ceiling Linings:
B98: Level 4 | C98: 84 | D98: m2 | E98: 0.2 | F98: =C98*E98 -> 16.8 | G98: =$H$11*E98 -> 7.2 | H98: =F98*$H$11 -> 604.8 | I98: 0.85 | J98: =C98*I98 -> 71.4 | K98: =SUM(H98,J98) -> 676.2 | L98: =K98/C98 -> 8.05 | M98: =C98*L98 -> 676.2 | N98: 0 | O98: =M98*N98 -> 0
B99: Square Stopping | C99: 136 | D99: m | E99: 0.2 | F99: =C99*E99 -> 27.2 | G99: =$H$11*E99 -> 7.2 | H99: =F99*$H$11 -> 979.2 | I99: 1.1 | J99: =C99*I99 -> 149.6 | K99: =SUM(H99,J99) -> 1128.8 | L99: =K99/C99 -> 8.3 | M99: =C99*L99 -> 1128.8 | N99: 0 | O99: =M99*N99 -> 0
B100: EV Negative to US of Stairs | C100: 20 | D100: m | E100: 0.3 | F100: =C100*E100 -> 6 | G100: =$H$11*E100 -> 10.8 | H100: =F100*$H$11 -> 216 | I100: 7 | J100: =C100*I100 -> 140 | K100: =SUM(H100,J100) -> 356 | L100: =K100/C100 -> 17.8 | M100: =C100*L100 -> 356 | N100: 0 | O100: =M100*N100 -> 0
P101: =SUM(M98:M100) -> 2161 | Q101: =P101*SUM($L$202:$L$206) -> 205.295
B102: Stopping Bulkhead Linings: | P102: =P101/$M$199 -> 0.013104516 | Q102: =P102*$M$210 -> 102.7089 | R102: =SUM(P101,Q101,Q102) -> 2469.0039 | S102: =R102*1.08 -> 2666.5242
B103: Level 4 | C103: 3 | D103: m2 | E103: 0.2 | F103: =C103*E103 -> 0.6 | G103: =$H$11*E103 -> 7.2 | H103: =F103*$H$11 -> 21.6 | I103: 0.85 | J103: =C103*I103 -> 2.55 | K103: =SUM(H103,J103) -> 24.15 | L103: =K103/C103 -> 8.05 | M103: =C103*L103 -> 24.15 | N103: 0 | O103: =M103*N103 -> 0
B104: External Corner | C104: 2 | D104: m | E104: 0.19 | F104: =C104*E104 -> 0.38 | G104: =$H$11*E104 -> 6.84 | H104: =F104*$H$11 -> 13.68 | I104: 2.02 | J104: =C104*I104 -> 4.04 | K104: =SUM(H104,J104) -> 17.72 | L104: =K104/C104 -> 8.86 | M104: =C104*L104 -> 17.72 | N104: 0 | O104: =M104*N104 -> 0
P105: =SUM(M102:M104) -> 41.87 | Q105: =P105*SUM($L$202:$L$206) -> 3.97765
P106: =P105/$M$199 -> 0.00025390378 | Q106: =P106*$M$210 -> 1.9900147 | R106: =SUM(P105,Q105,Q106) -> 47.837665 | S106: =R106*1.08 -> 51.664678
B108: Plant Room:
B109: Stopping Ceiling Linings:
B110: Level 4 | C110: 73 | D110: m2 | E110: 0.2 | F110: =C110*E110 -> 14.6 | G110: =$H$11*E110 -> 7.2 | H110: =F110*$H$11 -> 525.6 | I110: 0.85 | J110: =C110*I110 -> 62.05 | K110: =SUM(H110,J110) -> 587.65 | L110: =K110/C110 -> 8.05 | M110: =C110*L110 -> 587.65 | N110: 0 | O110: =M110*N110 -> 0
B111: Square Stopping | C111: 77 | D111: m | E111: 0.2 | F111: =C111*E111 -> 15.4 | G111: =$H$11*E111 -> 7.2 | H111: =F111*$H$11 -> 554.4 | I111: 1.45 | J111: =C111*I111 -> 111.65 | K111: =SUM(H111,J111) -> 666.05 | L111: =K111/C111 -> 8.65 | M111: =C111*L111 -> 666.05 | N111: 0 | O111: =M111*N111 -> 0
P112: =SUM(M107:M111) -> 1253.7 | Q112: =P112*SUM($L$202:$L$206) -> 119.1015
P113: =P112/$M$199 -> 0.0076025595 | Q113: =P113*$M$210 -> 59.586372 | R113: =SUM(P112,Q112,Q113) -> 1432.3879 | S113: =R113*1.08 -> 1546.9789
B115: Basement:
B116: Stopping Wall Linings:
B117: Level 4 | C117: ='Gib Linings_25_8'!T158 -> 1061 | D117: m2 | E117: 0.2 | F117: =C117*E117 -> 212.2 | G117: =$H$11*E117 -> 7.2 | H117: =F117*$H$11 -> 7639.2 | I117: 0.85 | J117: =C117*I117 -> 901.85 | K117: =SUM(H117,J117) -> 8541.05 | L117: =K117/C117 -> 8.05 | M117: =C117*L117 -> 8541.05 | N117: 0 | O117: =M117*N117 -> 0
B118: External Corners | C118: 92 | D118: m | E118: 0.19 | F118: =C118*E118 -> 17.48 | G118: =$H$11*E118 -> 6.84 | H118: =F118*$H$11 -> 629.28 | I118: 2.02 | J118: =C118*I118 -> 185.84 | K118: =SUM(H118,J118) -> 815.12 | L118: =K118/C118 -> 8.86 | M118: =C118*L118 -> 815.12 | N118: 0 | O118: =M118*N118 -> 0
...

Sheet Skirting with Columns
B1: =Summary!#REF! -> #REF!
B2: =Summary!#REF! -> #REF!
B3: =Summary!#REF! -> #REF!
B6: 45853
B9: Skirting
H11: 52
A12: Item | B12: Description | C12: Qty | D12: Unit | E12: Constant | F12: Constant X Unit = Total HRS | G12: $ Lab per Unit | H12: Total Labour | I12: Materials per Unit | J12: Total Materials | K12: Total Labour & Materials | L12: Total Labour & Materials Per Unit | M12: Total | N12: % Complete | O12: Claim
B15: Basement:
B17: SK1 Type - 90 x 10 Timber Flat | C17: 135 | D17: m | E17: 0.2 | F17: =C17*E17 -> 27 | G17: =$H$11*E17 -> 10.4 | H17: =F17*$H$11 -> 1404 | I17: 7.06 | J17: =C17*I17 -> 953.1 | K17: =SUM(H17,J17) -> 2357.1 | L17: =K17/C17 -> 17.46 | M17: =C17*L17 -> 2357.1 | N17: 0 | O17: =M17*N17 -> 0
B18: SK2 Type | C18: Nil, Tile by Others
P19: =SUM(M14:M18) -> 2357.1 | Q19: =P19*SUM($L$98:$L$102) -> 223.9245
P20: =P19/$M$95 -> 0.070570641 | Q20: =P20*$M$106 -> 45.428086 | R20: =SUM(P19,Q19,Q20) -> 2626.4526 | S20: =R20*1.08 -> 2836.5688 | Y20: 0.5
B21: Ground: | U21: Tape/Pins | V21: Glue | X21: 0.05 | Y21: Loadin
B22: SK1 Type - 90 x 10 Timber Flat | C22: 97 | D22: m | E22: 0.2 | F22: =C22*E22 -> 19.4 | G22: =$H$11*E22 -> 10.4 | H22: =F22*$H$11 -> 1008.8 | I22: =Z22 -> 7.0625 | J22: =C22*I22 -> 685.0625 | K22: =SUM(H22,J22) -> 1693.8625 | L22: =K22/C22 -> 17.4625 | M22: =C22*L22 -> 1693.8625 | N22: 0 | O22: =M22*N22 -> 0 | T22: 5 | U22: 0.5 | V22: 0.75 | W22: =SUM(T22:V22) -> 6.25 | X22: =W22*1.05 -> 6.5625 | Y22: =$Y$20 -> 0.5 | Z22: =SUM(X22:Y22) -> 7.0625 | AA22: =C22*Y22 -> 48.5
B23: SK2 Type | C23: Nil, Tile by Others
B24: SK3 Type - 100mm Flat | C24: 27 | D24: m | E24: 0.25 | F24: =C24*E24 -> 6.75 | G24: =$H$11*E24 -> 13 | H24: =F24*$H$11 -> 351 | I24: =Z24 -> 19.8095 | J24: =C24*I24 -> 534.8565 | K24: =SUM(H24,J24) -> 885.8565 | L24: =K24/C24 -> 32.8095 | M24: =C24*L24 -> 885.8565 | N24: 0 | O24: =M24*N24 -> 0 | T24: 14.17 | U24: 2.72 | V24: 1.5 | W24: =SUM(T24:V24) -> 18.39 | X24: =W24*1.05 -> 19.3095 | Y24: =$Y$20 -> 0.5 | Z24: =SUM(X24:Y24) -> 19.8095 | AA24: =C24*Y24 -> 13.5
B25: SK4 Type - 100mm Flat | C25: 15 | D25: m | E25: 0.25 | F25: =C25*E25 -> 3.75 | G25: =$H$11*E25 -> 13 | H25: =F25*$H$11 -> 195 | I25: =Z25 -> 19.8095 | J25: =C25*I25 -> 297.1425 | K25: =SUM(H25,J25) -> 492.1425 | L25: =K25/C25 -> 32.8095 | M25: =C25*L25 -> 492.1425 | N25: 0 | O25: =M25*N25 -> 0 | T25: 14.17 | U25: 2.72 | V25: 1.5 | W25: =SUM(T25:V25) -> 18.39 | X25: =W25*1.05 -> 19.3095 | Y25: =$Y$20 -> 0.5 | Z25: =SUM(X25:Y25) -> 19.8095 | AA25: =C25*Y25 -> 7.5
B26: SK5 Type - 25mm Flat | C26: 21 | D26: m | E26: 0.25 | F26: =C26*E26 -> 5.25 | G26: =$H$11*E26 -> 13 | H26: =F26*$H$11 -> 273 | I26: =Z26 -> 14.4335 | J26: =C26*I26 -> 303.1035 | K26: =SUM(H26,J26) -> 576.1035 | L26: =K26/C26 -> 27.4335 | M26: =C26*L26 -> 576.1035 | N26: 0 | O26: =M26*N26 -> 0 | T26: 9.8 | U26: 2.72 | V26: 0.75 | W26: =SUM(T26:V26) -> 13.27 | X26: =W26*1.05 -> 13.9335 | Y26: =$Y$20 -> 0.5 | Z26: =SUM(X26:Y26) -> 14.4335 | AA26: =C26*Y26 -> 10.5 | AB26: =SUM(AA22:AA26) -> 80
B28: SK4 - Plastered Column | C28: 3 | D28: no | E28: 0.5 | F28: =C28*E28 -> 1.5 | G28: =$H$11*E28 -> 26 | H28: =F28*$H$11 -> 78 | I28: 58 | J28: =C28*I28 -> 174 | K28: =SUM(H28,J28) -> 252 | L28: =K28/C28 -> 84 | M28: =C28*L28 -> 252 | N28: 0 | O28: =M28*N28 -> 0
B29: SK5 - Other Columns | C29: 13 | D29: no | E29: 0.5 | F29: =C29*E29 -> 6.5 | G29: =$H$11*E29 -> 26 | H29: =F29*$H$11 -> 338 | I29: 48 | J29: =C29*I29 -> 624 | K29: =SUM(H29,J29) -> 962 | L29: =K29/C29 -> 74 | M29: =C29*L29 -> 962 | N29: 0 | O29: =M29*N29 -> 0
P30: =SUM(M22:M29) -> 4861.965 | Q30: =P30*SUM($L$98:$L$102) -> 461.88668
B31: Level 1: | P31: =P30/$M$95 -> 0.14556531 | Q31: =P31*$M$106 -> 93.704028 | R31: =SUM(P30,Q30,Q31) -> 5417.5557 | S31: =R31*1.08 -> 5850.9602
B32: SK1 Type - 90 x 10 Timber Flat | C32: 28 | D32: m | E32: 0.2 | F32: =C32*E32 -> 5.6 | G32: =$H$11*E32 -> 10.4 | H32: =F32*$H$11 -> 291.2 | I32: 7.06 | J32: =C32*I32 -> 197.68 | K32: =SUM(H32,J32) -> 488.88 | L32: =K32/C32 -> 17.46 | M32: =C32*L32 -> 488.88 | N32: 0 | O32: =M32*N32 -> 0
B33: SK2 Type | C33: Nil, Tile by Others
B34: SK3 Type - 100mm Flat | C34: 9 | D34: m | E34: 0.25 | F34: =C34*E34 -> 2.25 | G34: =$H$11*E34 -> 13 | H34: =F34*$H$11 -> 117 | I34: 19.81 | J34: =C34*I34 -> 178.29 | K34: =SUM(H34,J34) -> 295.29 | L34: =K34/C34 -> 32.81 | M34: =C34*L34 -> 295.29 | N34: 0 | O34: =M34*N34 -> 0
B35: SK4 Type - 100mm Flat | C35: Nil
B36: SK5 Type - 25mm Flat | C36: 83 | D36: m | E36: 0.25 | F36: =C36*E36 -> 20.75 | G36: =$H$11*E36 -> 13 | H36: =F36*$H$11 -> 1079 | I36: 14.43 | J36: =C36*I36 -> 1197.69 | K36: =SUM(H36,J36) -> 2276.69 | L36: =K36/C36 -> 27.43 | M36: =C36*L36 -> 2276.69 | N36: 0 | O36: =M36*N36 -> 0
B38: SK5 - Other Columns | C38: 20 | D38: no | E38: 0.5 | F38: =C38*E38 -> 10 | G38: =$H$11*E38 -> 26 | H38: =F38*$H$11 -> 520 | I38: 58 | J38: =C38*I38 -> 1160 | K38: =SUM(H38,J38) -> 1680 | L38: =K38/C38 -> 84 | M38: =C38*L38 -> 1680 | N38: 0 | O38: =M38*N38 -> 0
P39: =SUM(M32:M38) -> 4740.86 | Q39: =P39*SUM($L$98:$L$102) -> 450.3817
P40: =P39/$M$95 -> 0.14193947 | Q40: =P40*$M$106 -> 91.369987 | R40: =SUM(P39,Q39,Q40) -> 5282.6117 | S40: =R40*1.08 -> 5705.2206
B41: Level 2:
B42: SK1 Type - 90 x 10 Timber Flat | C42: 28 | D42: m | E42: 0.2 | F42: =C42*E42 -> 5.6 | G42: =$H$11*E42 -> 10.4 | H42: =F42*$H$11 -> 291.2 | I42: 7.06 | J42: =C42*I42 -> 197.68 | K42: =SUM(H42,J42) -> 488.88 | L42: =K42/C42 -> 17.46 | M42: =C42*L42 -> 488.88 | N42: 0 | O42: =M42*N42 -> 0
B43: SK2 Type | C43: Nil, Tile by Others
B44: SK3 Type - 100mm Flat | C44: 9 | D44: m | E44: 0.25 | F44: =C44*E44 -> 2.25 | G44: =$H$11*E44 -> 13 | H44: =F44*$H$11 -> 117 | I44: 19.81 | J44: =C44*I44 -> 178.29 | K44: =SUM(H44,J44) -> 295.29 | L44: =K44/C44 -> 32.81 | M44: =C44*L44 -> 295.29 | N44: 0 | O44: =M44*N44 -> 0
B45: SK4 Type - 100mm Flat | C45: Nil
B46: SK5 Type - 25mm Flat | C46: 83 | D46: m | E46: 0.25 | F46: =C46*E46 -> 20.75 | G46: =$H$11*E46 -> 13 | H46: =F46*$H$11 -> 1079 | I46: 14.43 | J46: =C46*I46 -> 1197.69 | K46: =SUM(H46,J46) -> 2276.69 | L46: =K46/C46 -> 27.43 | M46: =C46*L46 -> 2276.69 | N46: 0 | O46: =M46*N46 -> 0
B48: SK5 - Other Columns | C48: 20 | D48: no | E48: 0.5 | F48: =C48*E48 -> 10 | G48: =$H$11*E48 -> 26 | H48: =F48*$H$11 -> 520 | I48: 58 | J48: =C48*I48 -> 1160 | K48: =SUM(H48,J48) -> 1680 | L48: =K48/C48 -> 84 | M48: =C48*L48 -> 1680 | N48: 0 | O48: =M48*N48 -> 0
P49: =SUM(M42:M48) -> 4740.86 | Q49: =P49*SUM($L$98:$L$102) -> 450.3817
P50: =P49/$M$95 -> 0.14193947 | Q50: =P50*$M$106 -> 91.369987 | R50: =SUM(P49,Q49,Q50) -> 5282.6117 | S50: =R50*1.08 -> 5705.2206
B51: Level 3:
B52: SK1 Type - 90 x 10 Timber Flat | C52: 28 | D52: m | E52: 0.2 | F52: =C52*E52 -> 5.6 | G52: =$H$11*E52 -> 10.4 | H52: =F52*$H$11 -> 291.2 | I52: 7.06 | J52: =C52*I52 -> 197.68 | K52: =SUM(H52,J52) -> 488.88 | L52: =K52/C52 -> 17.46 | M52: =C52*L52 -> 488.88 | N52: 0 | O52: =M52*N52 -> 0
B53: SK2 Type | C53: Nil, Tile by Others
B54: SK3 Type - 100mm Flat | C54: 9 | D54: m | E54: 0.25 | F54: =C54*E54 -> 2.25 | G54: =$H$11*E54 -> 13 | H54: =F54*$H$11 -> 117 | I54: 19.81 | J54: =C54*I54 -> 178.29 | K54: =SUM(H54,J54) -> 295.29 | L54: =K54/C54 -> 32.81 | M54: =C54*L54 -> 295.29 | N54: 0 | O54: =M54*N54 -> 0
B55: SK4 Type - 100mm Flat | C55: Nil
B56: SK5 Type - 25mm Flat | C56: 83 | D56: m | E56: 0.25 | F56: =C56*E56 -> 20.75 | G56: =$H$11*E56 -> 13 | H56: =F56*$H$11 -> 1079 | I56: 14.43 | J56: =C56*I56 -> 1197.69 | K56: =SUM(H56,J56) -> 2276.69 | L56: =K56/C56 -> 27.43 | M56: =C56*L56 -> 2276.69 | N56: 0 | O56: =M56*N56 -> 0
B58: SK5 - Other Columns | C58: 20 | D58: no | E58: 0.5 | F58: =C58*E58 -> 10 | G58: =$H$11*E58 -> 26 | H58: =F58*$H$11 -> 520 | I58: 58 | J58: =C58*I58 -> 1160 | K58: =SUM(H58,J58) -> 1680 | L58: =K58/C58 -> 84 | M58: =C58*L58 -> 1680 | N58: 0 | O58: =M58*N58 -> 0
P59: =SUM(M52:M58) -> 4740.86 | Q59: =P59*SUM($L$98:$L$102) -> 450.3817
P60: =P59/$M$95 -> 0.14193947 | Q60: =P60*$M$106 -> 91.369987 | R60: =SUM(P59,Q59,Q60) -> 5282.6117 | S60: =R60*1.08 -> 5705.2206
B61: Level 4:
B62: SK1 Type - 90 x 10 Timber Flat | C62: 29 | D62: m | E62: 0.2 | F62: =C62*E62 -> 5.8 | G62: =$H$11*E62 -> 10.4 | H62: =F62*$H$11 -> 301.6 | I62: 7.06 | J62: =C62*I62 -> 204.74 | K62: =SUM(H62,J62) -> 506.34 | L62: =K62/C62 -> 17.46 | M62: =C62*L62 -> 506.34 | N62: 0 | O62: =M62*N62 -> 0
B63: SK2 Type | C63: Nil, Tile by Others
B64: SK3 Type - 100mm Flat | C64: 40 | D64: m | E64: 0.25 | F64: =C64*E64 -> 10 | G64: =$H$11*E64 -> 13 | H64: =F64*$H$11 -> 520 | I64: 19.81 | J64: =C64*I64 -> 792.4 | K64: =SUM(H64,J64) -> 1312.4 | L64: =K64/C64 -> 32.81 | M64: =C64*L64 -> 1312.4 | N64: 0 | O64: =M64*N64 -> 0
B65: SK4 Type - 100mm Flat | C65: Nil
B66: SK5 Type - 25mm Flat | C66: 52 | D66: m | E66: 0.25 | F66: =C66*E66 -> 13 | G66: =$H$11*E66 -> 13 | H66: =F66*$H$11 -> 676 | I66: 14.43 | J66: =C66*I66 -> 750.36 | K66: =SUM(H66,J66) -> 1426.36 | L66: =K66/C66 -> 27.43 | M66: =C66*L66 -> 1426.36 | N66: 0 | O66: =M66*N66 -> 0
B68: SK5 - Other Columns | C68: 18 | D68: no | E68: 0.5 | F68: =C68*E68 -> 9 | G68: =$H$11*E68 -> 26 | H68: =F68*$H$11 -> 468 | I68: 58 | J68: =C68*I68 -> 1044 | K68: =SUM(H68,J68) -> 1512 | L68: =K68/C68 -> 84 | M68: =C68*L68 -> 1512 | N68: 0 | O68: =M68*N68 -> 0
P69: =SUM(M62:M68) -> 4757.1 | Q69: =P69*SUM($L$98:$L$102) -> 451.9245
P70: =P69/$M$95 -> 0.14242569 | Q70: =P70*$M$106 -> 91.682978 | R70: =SUM(P69,Q69,Q70) -> 5300.7075 | S70: =R70*1.08 -> 5724.7641
B71: Level 5:
B72: SK1 Type - 90 x 10 Timber Flat | C72: 29 | D72: m | E72: 0.2 | F72: =C72*E72 -> 5.8 | G72: =$H$11*E72 -> 10.4 | H72: =F72*$H$11 -> 301.6 | I72: 7.06 | J72: =C72*I72 -> 204.74 | K72: =SUM(H72,J72) -> 506.34 | L72: =K72/C72 -> 17.46 | M72: =C72*L72 -> 506.34 | N72: 0 | O72: =M72*N72 -> 0
B73: SK2 Type | C73: Nil, Tile by Others
B74: SK3 Type - 100mm Flat | C74: 40 | D74: m | E74: 0.25 | F74: =C74*E74 -> 10 | G74: =$H$11*E74 -> 13 | H74: =F74*$H$11 -> 520 | I74: 19.81 | J74: =C74*I74 -> 792.4 | K74: =SUM(H74,J74) -> 1312.4 | L74: =K74/C74 -> 32.81 | M74: =C74*L74 -> 1312.4 | N74: 0 | O74: =M74*N74 -> 0
B75: SK4 Type - 100mm Flat | C75: Nil
B76: SK5 Type - 25mm Flat | C76: 52 | D76: m | E76: 0.25 | F76: =C76*E76 -> 13 | G76: =$H$11*E76 -> 13 | H76: =F76*$H$11 -> 676 | I76: 14.43 | J76: =C76*I76 -> 750.36 | K76: =SUM(H76,J76) -> 1426.36 | L76: =K76/C76 -> 27.43 | M76: =C76*L76 -> 1426.36 | N76: 0 | O76: =M76*N76 -> 0
B78: SK5 - Other Columns | C78: 20 | D78: no | E78: 0.5 | F78: 1.5 | G78: 27.5 | H78: 82.5 | I78: 58 | J78: 180 | K78: 262.5 | L78: 87.5 | M78: 262.5 | N78: 0 | O78: 0
P79: =SUM(M72:M78) -> 3507.6 | Q79: =P79*SUM($L$98:$L$102) -> 333.222
P80: =P79/$M$95 -> 0.10501616 | Q80: =P80*$M$106 -> 67.601525 | R80: =SUM(P79,Q79,Q80) -> 3908.4235 | S80: =R80*1.08 -> 4221.0974
B81: Level 6:
B82: SK1 Type - 90 x 10 Timber Flat | C82: 29 | D82: m | E82: 0.2 | F82: =C82*E82 -> 5.8 | G82: =$H$11*E82 -> 10.4 | H82: =F82*$H$11 -> 301.6 | I82: 7.06 | J82: =C82*I82 -> 204.74 | K82: =SUM(H82,J82) -> 506.34 | L82: =K82/C82 -> 17.46 | M82: =C82*L82 -> 506.34 | N82: 0 | O82: =M82*N82 -> 0
B83: SK2 Type | C83: Nil, Tile by Others
B84: SK3 Type - 100mm Flat | C84: 39 | D84: m | E84: 0.25 | F84: =C84*E84 -> 9.75 | G84: =$H$11*E84 -> 13 | H84: =F84*$H$11 -> 507 | I84: 19.81 | J84: =C84*I84 -> 772.59 | K84: =SUM(H84,J84) -> 1279.59 | L84: =K84/C84 -> 32.81 | M84: =C84*L84 -> 1279.59 | N84: 0 | O84: =M84*N84 -> 0
B85: SK4 Type - 100mm Flat | C85: Nil
B86: SK5 Type - 25mm Flat | C86: 60 | D86: m | E86: 0.25 | F86: =C86*E86 -> 15 | G86: =$H$11*E86 -> 13 | H86: =F86*$H$11 -> 780 | I86: 14.43 | J86: =C86*I86 -> 865.8 | K86: =SUM(H86,J86) -> 1645.8 | L86: =K86/C86 -> 27.43 | M86: =C86*L86 -> 1645.8 | N86: 0 | O86: =M86*N86 -> 0
B88: SK5 - Other Columns | C88: 18 | D88: no | E88: 0.5 | F88: 1.5 | G88: 27.5 | H88: 82.5 | I88: 58 | J88: 180 | K88: 262.5 | L88: 87.5 | M88: 262.5 | N88: 0 | O88: 0
P89: =SUM(M82:M88) -> 3694.23 | Q89: =P89*SUM($L$98:$L$102) -> 350.95185
P90: =P89/$M$95 -> 0.11060378 | Q90: =P90*$M$106 -> 71.198421 | R90: =SUM(P89,Q89,Q90) -> 4116.3803 | S90: =R90*1.08 -> 4445.6907 | T90: =SUM(C88,C78,C68,C58,C48,C38,C29) -> 129
B91: Plant Room: | C91: Nil
F94: =SUM(F13:F93) -> 286.1 | H94: =SUM(H13:H93) -> 14886.2 | J94: =SUM(J13:J93) -> 18514.375 | R94: =SUM(R13:R93) -> 37217.355 | S94: =SUM(S13:S93) -> 40194.743
B95: Total of above | M95: =SUM(M13:M93) -> 33400.575 | O95: =SUM(O13:O93) -> 0
B96: Miscellaneous
B98: P&G - Admin / Supervision | D98: Sum | L98: 0.06 | M98: =M95*L98 -> 2004.0345 | O98: =($O$95/$M$95)*M98 -> 0
B100: P&G - Site Establishment | D100: Sum | L100: 0.03 | M100: =M95*L100 -> 1002.0173 | O100: =($O$95/$M$95)*M100 -> 0
B102: P&G - Access Equip | D102: Sum | L102: 0.005 | M102: =M95*L102 -> 167.00288 | O102: =($O$95/$M$95)*M102 -> 0
B104: P&G | D104: Sum
B106: P&G Parking | D106: Sum | L106: =M106/M95 -> 0.019272872 | M106: =I117 -> 643.725 | O106: =($O$95/$M$95)*M106 -> 0
B108: Sub total | M108: =SUM(M95:M107) -> 37217.355 | O108: =SUM(O95:O107) -> 0
B110: Margin | L110: 0.08 | M110: =M108*L110 -> 2977.3884 | O110: =O108/M108*M110 -> 0
B112: TOTAL OF SKIRTING | M112: =ROUNDUP(SUM(M108:M111),0) -> 40195 | N112: =O112/M112 -> 0 | O112: =SUM(O108:O111) -> 0
G114: Parking
H115: Man
G116: =F94/8 -> 35.7625 | H116: 1
G117: =G116/H116 -> 35.7625 | H117: 18 | I117: =G117*H117 -> 643.725
B123: Rate build for travel by car | I123: Rate build for travel by car
B124: Travel there and back based on 4 | I124: Travel there and back based on 1
B125: hrs travel per person | C125: Rate /Km | D125: Total | E125: Number of people | I125: hrs travel per person | J125: Rate /Km | K125: Total | L125: Number of people
B126: 1 | C126: 55 | D126: =B126*C126 -> 55 | E126: =D126*F126 -> 110 | F126: 2 | I126: 4 | J126: 55 | K126: =I126*J126 -> 220 | L126: =K126*M126 -> 440 | M126: 2
B127: km | E127: There and back | I127: km | L127: There and back
B128: 0.7 | E128: =B128*C128 -> 0 | I128: 0.7 | J128: 310 | L128: =I128*J128 -> 217
B129: Amount of trips needed | E129: =SUM(E126:E128) -> 110 | I129: Amount of trips needed | L129: =SUM(L126:L128) -> 657
B130: 2 | E130: =B130*E129 -> 220 | I130: 1 | L130: =I130*L129 -> 657
B131: Accom/per day | C131: days | E131: Times amount of people | I131: Accom/per day | J131: days | L131: Times amount of people
...

Sheet PROV SUM PS1 & PS4 _25_8
B1: =Summary!#REF! -> #REF!
B2: =Summary!#REF! -> #REF!
B3: =Summary!#REF! -> #REF!
B6: =Summary!#REF! -> #REF!
B9: PROVISIONAL SUM: PS1 Design & PS4 Certificate for Interior Steel Stud Partition
H11: 52
A12: Item | B12: Description | C12: Qty | D12: Unit | E12: Constant | F12: Constant X Unit = Total HRS | G12: $ Lab per Unit | H12: Total Labour | I12: Materials per Unit | J12: Total Materials | K12: Total Labour & Materials | L12: Total Labour & Materials Per Unit | M12: Total | N12: Total | O12: Claim
Q13: 1.06 | R13: 1.08
B15: Suspended Ceiling Design | C15: By CBC | Q15: =M15*$Q$13 -> 0 | R15: =Q15*$R$13 -> 0 | S15: 13250
B16: Steel Stud Partition Design | C16: 1 | D16: item | F16: =C16*E16 -> 0 | G16: =$H$11*E16 -> 0 | H16: =F16*$H$11 -> 0 | I16: 2904 | J16: =C16*I16 -> 2904 | K16: =SUM(H16,J16) -> 2904 | L16: =K16/C16 -> 2904 | M16: =C16*L16 -> 2904 | N16: 3500 | Q16: =M16*$Q$13 -> 3078.24 | R16: =Q16*$R$13 -> 3324.4992 | S16: 3500 | U16: 2950
B17: Construction Monitoring for PS4 to Above | C17: 8 | D17: no | F17: =C17*E17 -> 0 | G17: =$H$11*E17 -> 0 | H17: =F17*$H$11 -> 0 | I17: 675 | J17: =C17*I17 -> 5400 | K17: =SUM(H17,J17) -> 5400 | L17: =K17/C17 -> 675 | M17: =C17*L17 -> 5400 | N17: 6250 | Q17: =M17*$Q$13 -> 5724 | R17: =Q17*$R$13 -> 6181.92 | S17: 6250 | U17: 5400
B19: PS1 Design Certificate | C19: 1 | D19: item | F19: =C19*E19 -> 0 | G19: =$H$11*E19 -> 0 | H19: =F19*$H$11 -> 0 | I19: 920 | J19: =C19*I19 -> 920 | K19: =SUM(H19,J19) -> 920 | L19: =K19/C19 -> 920 | M19: =C19*L19 -> 920 | N19: 1200 | Q19: =M19*$Q$13 -> 975.2 | R19: =Q19*$R$13 -> 1053.216 | S19: 1200 | U19: 750
B20: PS4 Design Certificate | C20: 1 | D20: item | F20: =C20*E20 -> 0 | G20: =$H$11*E20 -> 0 | H20: =F20*$H$11 -> 0 | I20: 690 | J20: =C20*I20 -> 690 | K20: =SUM(H20,J20) -> 690 | L20: =K20/C20 -> 690 | M20: =C20*L20 -> 690 | N20: 800 | Q20: =M20*$Q$13 -> 731.4 | R20: =Q20*$R$13 -> 789.912 | S20: 800 | U20: 690
R22: =SUM(R15:R20) -> 11349.547 | S22: =SUM(S15:S20) -> 25000 | U22: =SUM(U16:U20) -> 9790
F23: =SUM(F13:F22) -> 0 | H23: =SUM(H13:H22) -> 0 | J23: =SUM(J13:J22) -> 9914
B24: Total of above | M24: =SUM(M13:M22) -> 9914 | N24: =SUM(N13:N22) -> 11750
B25: Miscellaneous
B27: P&G - Admin / Supervision | D27: Sum | L27: 0.06 | M27: =M24*L27 -> 594.84
B29: P&G - Site Establishment | D29: Sum | L29: 0 | M29: =M24*L29 -> 0
B31: P&G - Access Equip | D31: Sum | L31: 0 | M31: =M24*L31 -> 0
B33: P&G - Parking | D33: Sum
B35: P&G Contingency | D35: Sum | L35: 0.05
B37: Sub total | M37: =SUM(M24:M36) -> 10508.84
B39: Margin | L39: 0.08 | M39: =M37*L39 -> 840.7072
M41: =ROUNDUP(SUM(M37:M40),0) -> 11350
M42: 12000
F43: =F23/6.5 -> 0 | G43: 1.25 | H43: =F43*G43 -> 0 | I43: =H43*H11 -> 0
I44: =F43*140 -> 0
B46: Rate build for travel by car | I46: Rate build for travel by car
B47: Travel there and back based on 4 | I47: Travel there and back based on 1
B48: hrs travel per person | C48: Rate /Km | D48: Total | E48: Number of people | I48: hrs travel per person | J48: Rate /Km | K48: Total | L48: Number of people
B49: 1 | C49: 55 | D49: =B49*C49 -> 55 | E49: =D49*F49 -> 110 | F49: 2 | I49: 4 | J49: 55 | K49: =I49*J49 -> 220 | L49: =K49*M49 -> 440 | M49: 2
B50: km | E50: There and back | I50: km | L50: There and back
B51: 0.7 | E51: =B51*C51 -> 0 | I51: 0.7 | J51: 310 | L51: =I51*J51 -> 217
B52: Amount of trips needed | E52: =SUM(E49:E51) -> 110 | I52: Amount of trips needed | L52: =SUM(L49:L51) -> 657
B53: 2 | E53: =B53*E52 -> 220 | I53: 1 | L53: =I53*L52 -> 657
B54: Accom/per day | C54: days | E54: Times amount of people | I54: Accom/per day | J54: days | L54: Times amount of people
D55: =B55*C55 -> 0 | E55: =D55*F49 -> 0 | I55: 125 | J55: 4 | K55: =I55*J55 -> 500 | L55: =K55*M49 -> 1000
E56: =SUM(E53:E55) -> 220 | L56: =SUM(L53:L55) -> 1657
