Workbook

Sheet Summary
B1: Ceilings Unlimited
B2: Craigs Investment Partners - Fitout
B3: Tauranga
B5: 46043
B6: Summary
B7: Clarifications:
B8: * No allowance for access equipment over 3000 or any scaffold/access to stair wells, atrium voids or lift shafts including edge protection. To be supplied by Main Contractor
B9: * We note most material sizes will not fit within the lift indicated for use. Pricing is based on all materials being lifted/removed via crane or hiab to respective Levels to an access point/loadin platform then through facade. Removal/reinstatement of facade as well as Crane/Hiab of materials up and down, Access point/loadin platform to be provided by main contractor along with any associated Traffic Management costs that may be required.
B10: * This trade pricing is based on the acceptance as a package and if individual trades were selected we would need to be contacted to discuss before acceptance.
B11: * Pricing has been split across levels but based on all works proceeding. Removal of items may come at cost premium affecting cost to other levels.
B12: * Based on Retentions on a sliding scale basis.
B13: * No allowance for detailed drawings/shop drawings, Prototypes, Samples and Resource and Consent fees etc. By Others.
B14: * Pricing is based on Brevity PS1 Designs. We have not allowed for any construction monitoring or PS4 sign off, if required to carried out by othes.
B15: * Allowed for works within normal works hours Monday to Friday 7.30am - 5pm.
B16: * Pricing based on sliding scale retention basis.
B17: * Rubbish disposal to be provided by main contractor/others on each level or works
... B114: * Detailed Programming to be to be discussed prior to acceptance.
B115: * Pricing validity as per cover letter. We have not allowed for any escalation of costs after this point and will be claimed as a variation accordingly if required (We have taken into consideration known price increases on Potters Aluminum and Gib Linings in the first half of 2026). | J115: Level 4 | K115: Level 5 | L115: Level 6
B117: Suspended Ceilings | C117: ='Suspended Ceilings'!M141 -> 241937 | I117: =B117 -> Suspended Ceilings | J117: ='Suspended Ceilings'!Q143 -> 12484.965 | K117: ='Suspended Ceilings'!Q145 -> 2860.8406 | L117: ='Suspended Ceilings'!Q147 -> 226590.94 | O117: =P117-C117 -> -0.25866122 | P117: =SUM(J117:L117) -> 241936.74
B119: Partitions | C119: ='Partitions SPEC Rates'!M179 -> 147472 | I119: =B119 -> Partitions | J119: ='Partitions SPEC Rates'!Q181 -> 49494.234 | K119: ='Partitions SPEC Rates'!Q183 -> 41336.657 | L119: ='Partitions SPEC Rates'!Q185 -> 56640.165 | O119: =P119-C119 -> -0.94303941 | P119: =SUM(J119:L119) -> 147471.06
B121: Insulation | C121: =Insulation!M113 -> 41680 | I121: =B121 -> Insulation | J121: =Insulation!Q115 -> 12987.284 | K121: =Insulation!Q117 -> 9111.1218 | L121: =Insulation!Q119 -> 19581.414 | O121: =P121-C121 -> -0.18003321 | P121: =SUM(J121:L121) -> 41679.82
B123: Gib Wall and Ceiling Linings | C123: ='Gib Linings'!M211 -> 186146 | I123: =B123 -> Gib Wall and Ceiling Linings | J123: ='Gib Linings'!Q213 -> 48509.091 | K123: ='Gib Linings'!Q215 -> 44677.051 | L123: ='Gib Linings'!Q217 -> 92958.928 | O123: =P123-C123 -> -0.929105 | P123: =SUM(J123:L123) -> 186145.07
B125: Stopping to Gib Wall and Ceilings | C125: =Stopping!M90 -> 66579 | I125: =B125 -> Stopping to Gib Wall and Ceilings | J125: =Stopping!Q92 -> 18949.133 | K125: =Stopping!Q94 -> 15992.349 | L125: =Stopping!Q96 -> 31637.33 | O125: =P125-C125 -> -0.187854 | P125: =SUM(J125:L125) -> 66578.812
B127: Potters Rigitone Matrix Ceiling Lining | C127: ='Potters Rigitone Matrix'!M61 -> 48735 | I127: =B127 -> Potters Rigitone Matrix Ceiling Lining | J127: 0 | K127: 0 | L127: ='Potters Rigitone Matrix'!M61 -> 48735 | O127: =P127-C127 -> 0 | P127: =SUM(J127:L127) -> 48735
B129: Ambitec (PF-01 and PF-02 to Wall and Bulkheads Only) | C129: =Ambitec!M83 -> 135513 | I129: =B129 -> Ambitec (PF-01 and PF-02 to Wall and Bulkheads Only) | J129: =Ambitec!S85 -> 38178.604 | K129: =Ambitec!S87 -> 29195.403 | L129: =Ambitec!S89 -> 68138.135 | O129: =P129-C129 -> -0.8583075 | P129: =SUM(J129:L129) -> 135512.14
B131: Featurecraft (TB-01 and TB-02) | C131: =Featurecraft!M86 -> 687105 | I131: =B131 -> Featurecraft (TB-01 and TB-02) | J131: =Featurecraft!Q88 -> 276610.12 | K131: =Featurecraft!Q90 -> 201242.99 | L131: =Featurecraft!Q92 -> 209251.88 | O131: =P131-C131 -> -0.0048782172 | P131: =SUM(J131:L131) -> 687105
B133: Potters Aluminium, Doors, Glazing and Skirting | C133: ='Potters Aluminium and Glazing'!M426 -> 326715 | I133: =B133 -> Potters Aluminium, Doors, Glazing and Skirting | J133: ='Potters Aluminium and Glazing'!Q428 -> 95019.673 | K133: ='Potters Aluminium and Glazing'!Q430 -> 80525.42 | L133: ='Potters Aluminium and Glazing'!Q432 -> 151169.61 | O133: =P133-C133 -> -0.2990088 | P133: =SUM(J133:L133) -> 326714.7
B135: Wall Covering: Asona Quicklock (FP-01) | C135: ='Asona Quicklock'!M118 -> 138546 | I135: =B135 -> Wall Covering: Asona Quicklock (FP-01) | J135: ='Asona Quicklock'!Q120 -> 31037.57 | K135: ='Asona Quicklock'!Q122 -> 40717.699 | L135: ='Asona Quicklock'!Q124 -> 66790.113 | O135: =P135-C135 -> -0.61848 | P135: =SUM(J135:L135) -> 138545.38
B139: Total of all items priced | F139: =SUM(C117:C135) -> 2020428 | J139: =SUM(J116:J135) -> 583270.68 | K139: =SUM(K116:K135) -> 465659.53 | L139: =SUM(L116:L135) -> 971493.51 | O139: =P139-C139 -> 2020423.7 | P139: =SUM(J139:L139) -> 2020423.7
B140: * No allowance for GST
C146: =B117 -> Suspended Ceilings | F146: =B119 -> Partitions | G146: =B121 -> Insulation | H146: =B123 -> Gib Wall and Ceiling Linings | I146: =B125 -> Stopping to Gib Wall and Ceilings | J146: =B127 -> Potters Rigitone Matrix Ceiling Lining | K146: =B129 -> Ambitec (PF-01 and PF-02 to Wall and Bulkheads Only) | L146: =B131 -> Featurecraft (TB-01 and TB-02) | M146: =B133 -> Potters Aluminium, Doors, Glazing and Skirting | N146: =B135 -> Wall Covering: Asona Quicklock (FP-01)
B148: P&G - Admin / Supervision | C148: ='Suspended Ceilings'!M127 -> 4515.5375 | F148: =Partitions!M169 -> 2939.5963 | G148: =Insulation!M99 -> 773.86729 | H148: ='Gib Linings'!M197 -> 3463.3787 | I148: =Stopping!M76 -> 1212.502 | J148: ='Potters Rigitone Matrix'!M47 -> 901.82985 | K148: =Ambitec!M69 -> 2593.9368 | L148: =Featurecraft!M72 -> 13094.444 | M148: ='Potters Aluminium and Glazing'!M412 -> 6142.5314 | N148: ='Asona Quicklock'!M104 -> 2656.472 | O148: =SUM(C148:N148) -> 38294.096
B149: P&G - Site Establishment | C149: ='Suspended Ceilings'!M129 -> 2202.7012 | F149: =Partitions!M171 -> 1433.9494 | G149: =Insulation!M101 -> 377.49624 | H149: ='Gib Linings'!M199 -> 1689.453 | I149: =Stopping!M78 -> 591.4644 | J149: ='Potters Rigitone Matrix'!M49 -> 439.917 | K149: =Ambitec!M71 -> 1265.335 | L149: =Featurecraft!M74 -> 6387.5337 | M149: ='Potters Aluminium and Glazing'!M414 -> 2996.3568 | N149: ='Asona Quicklock'!M106 -> 1295.84 | O149: =SUM(C149:N149) -> 18680.047
B150: P&G - Access Equip | C150: ='Suspended Ceilings'!M131 -> 550.6753 | F150: =Partitions!M173 -> 358.48735 | G150: =Insulation!M103 -> 94.37406 | H150: ='Gib Linings'!M201 -> 422.36325 | I150: =Stopping!M80 -> 147.8661 | J150: ='Potters Rigitone Matrix'!M51 -> 109.97925 | K150: =Ambitec!M73 -> 316.33375 | L150: =Featurecraft!M76 -> 1596.8834 | M150: ='Potters Aluminium and Glazing'!M416 -> 749.08919 | N150: ='Asona Quicklock'!M108 -> 323.96 | O150: =SUM(C150:N150) -> 4670.0117
B151: P&G - Parking | C151: ='Suspended Ceilings'!M133 -> 2876.91 | F151: =Partitions!M175 -> 2904.0347 | G151: =Insulation!M105 -> 699.705 | H151: ='Gib Linings'!M203 -> 2760.525 | I151: =Stopping!M82 -> 2310.12 | J151: ='Potters Rigitone Matrix'!M53 -> 970.3125 | K151: =Ambitec!M75 -> 220.5 | L151: =Featurecraft!M78 -> 4037.3325 | M151: ='Potters Aluminium and Glazing'!M418 -> 1633.2049 | N151: ='Asona Quicklock'!M110 -> 0 | O151: =SUM(C151:N151) -> 18412.645
B152: P&G | C152: ='Suspended Ceilings'!M135 -> 0 | F152: =Partitions!M177 -> 0 | G152: =Insulation!M107 -> 0 | H152: ='Gib Linings'!M205 -> 0 | I152: =Stopping!M84 -> 0 | J152: ='Potters Rigitone Matrix'!M55 -> 0 | K152: =Ambitec!M77 -> 0 | L152: =Featurecraft!M80 -> 0 | M152: ='Potters Aluminium and Glazing'!M420 -> 0 | N152: ='Asona Quicklock'!M112 -> 0 | O152: =SUM(C152:N152) -> 0
B153: Margin | C153: ='Suspended Ceilings'!M139 -> 11520.797 | F153: =Partitions!M181 -> 7551.5504 | G153: =Insulation!M111 -> 1984.7533 | H153: ='Gib Linings'!M209 -> 8864.051 | I153: =Stopping!M88 -> 3170.4196 | J153: ='Potters Rigitone Matrix'!M59 -> 2320.6869 | K153: =Ambitec!M81 -> 4582.5362 | L153: =Featurecraft!M84 -> 23235.435 | M153: ='Potters Aluminium and Glazing'!M424 -> 15557.843 | N153: ='Asona Quicklock'!M116 -> 4685.1095 | O153: =SUM(C153:N153) -> 83473.182
B154: Total | C154: =SUM(C148:C153) -> 21666.621 | F154: =SUM(F148:F153) -> 15187.618 | G154: =SUM(G148:G153) -> 3930.1959 | H154: =SUM(H148:H153) -> 17199.771 | I154: =SUM(I148:I153) -> 7432.3721 | J154: =SUM(J148:J153) -> 4742.7255 | K154: =SUM(K148:K153) -> 8978.6417 | L154: =SUM(L148:L153) -> 48351.628 | M154: =SUM(M148:M153) -> 27079.025 | N154: =SUM(N148:N153) -> 8961.3815
P155: Hours/Week | S155: Day
B156: Labour Hours to Above | S156: 5
B157: Level 4 | C157: ='Suspended Ceilings'!K143 -> 123.13 | F157: ='Partitions SPEC Rates'!K181 -> 421.68775 | G157: =Insulation!K115 -> 96.09 | H157: ='Gib Linings'!K213 -> 317.76 | I157: =Stopping!K92 -> 293.57 | L157: =Featurecraft!K88 -> 676.35 | M157: =SUM('Potters Aluminium and Glazing'!K428:K429) -> 276.29932 | O157: =SUM(C157:N157) -> 2204.8871 | P157: 42.5 | Q157: =O157/P157 -> 51.879696 | R157: =Q157/$T$157 -> 12.969924 | S157: =R157*$S$156 -> 64.84962 | T157: 4 | U157: Men
B158: Level 5 | C158: ='Suspended Ceilings'!K145 -> 31 | F158: ='Partitions SPEC Rates'!K183 -> 355.7075 | G158: =Insulation!K117 -> 67.5 | H158: ='Gib Linings'!K215 -> 288.51 | I158: =Stopping!K94 -> 222.04 | L158: =Featurecraft!K90 -> 473.94 | M158: =SUM('Potters Aluminium and Glazing'!K430:K431) -> 235.79432 | O158: =SUM(C158:N158) -> 1674.4918 | P158: 42.5 | Q158: =O158/P158 -> 39.399807 | R158: =Q158/$T$158 -> 7.8799615 | S158: =R158*$S$156 -> 39.399807 | T158: 5 | U158: Men
B159: Level 6 | C159: ='Suspended Ceilings'!K147 -> 1124.4967 | F159: ='Partitions SPEC Rates'!K185 -> 494.56 | G159: =Insulation!K119 -> 147.39 | H159: ='Gib Linings'!K217 -> 620.63 | I159: =Stopping!K96 -> 511.11 | J159: ='Potters Rigitone Matrix'!K67 -> 431.25 | K159: =Ambitec!K89 -> 98 | L159: =Featurecraft!K92 -> 644.08 | M159: =SUM('Potters Aluminium and Glazing'!K432:K433) -> 382.12955 | O159: =SUM(C159:N159) -> 4453.6462 | P159: 42.5 | Q159: =O159/P159 -> 104.79168 | R159: =Q159/$T$159 -> 14.970239 | S159: =R159*$S$156 -> 74.851197 | T159: 7 | U159: Men
C160: =SUM(C157:C159) -> 1278.6267 | F160: =SUM(F157:F159) -> 1271.9552 | G160: =SUM(G157:G159) -> 310.98 | H160: =SUM(H157:H159) -> 1226.9 | I160: =SUM(I157:I159) -> 1026.72 | J160: =SUM(J157:J159) -> 431.25 | K160: =SUM(K157:K159) -> 98 | L160: =SUM(L157:L159) -> 1794.37 | M160: =SUM(M157:M159) -> 894.22318 | N160: =SUM(N157:N159) -> 0 | O160: =SUM(C160:N160) -> 8333.0251
B164: Job Duration | C164: 4.5 | F164: Onsite Supervise | G164: 45 | H164: 65 | I164: =G164*H164 -> 2925 | J164: =$C$164*I164 -> 13162.5 | L164: 75 davy
F165: PM | G165: 45 | H165: 75 | I165: =G165*H165 -> 3375 | J165: =$C$164*I165 -> 15187.5 | L165: 65 Jayden
F166: Parking PM | J166: 1250
F167: QS | G167: 22.5 | H167: 75 | I167: =G167*H167 -> 1687.5 | J167: =$C$164*I167 -> 7593.75
J168: =SUM(J164:J167) -> 37193.75
I172: Level 4 | J172: 46204 | K172: 46316
I174: Level 5 | J174: 46204 | K174: 46316
C175: Metro | F175: SENT
C176: Bayglaze | F176: SENT | I176: Level 6 | J176: 46227 | K176: 46339
C177: Ambitec | F177: SENT
C178: Featurecraft | F178: SENT
C179: Total Doors | F179: SENT
C180: Asona | F180: SENT
C186: Alaska | F186: 9th January
C188: Impact | F188: 13th Janaury
C190: CBC | F190: 9th January
C192: W&H | F192: Friday 19th
B197: Ceiling Access Hatches - Plasterboard (Supply & Install) | C197: 530 x 530 Set Bead Ceiling Hatches | F197: ='Suspended Ceilings'!L54 -> 262 | G197: =F197*'Suspended Ceilings'!N142 -> 12.067937 | H197: =SUM(F197:G197) -> 274.06794 | I197: =H197*'Suspended Ceilings'!P142 -> 13.703397 | J197: =SUM(H197:I197) -> 287.77133
B198: Ceiling Access Hatches - Decorative or Perforated (Supply & Install) | C198: 500 x 500 Hard Edge Hatch to Above | F198: ='Suspended Ceilings'!L106 -> 365 | G198: =F198*'Suspended Ceilings'!N142 -> 16.812202 | H198: =SUM(F198:G198) -> 381.8122 | I198: =H198*'Suspended Ceilings'!P142 -> 19.09061 | J198: =SUM(H198:I198) -> 400.90281
B199: Suspended Ceiling & Tiles (Supply & Install)
B201: Plasterboard Ceiling (Supply & Install) | C201: 13mm Standard Includes Stopping Level 4 | F201: ='Gib Linings'!L17 -> 24 | G201: =F201*'Gib Linings'!N212 -> 1.1841541 | H201: =SUM(F201:G201) -> 25.184154 | I201: =H201*'Gib Linings'!P212 -> 1.2592077 | J201: =SUM(H201:I201) -> 26.443362
F202: =Stopping!L17 -> 9.35 | G202: =F202*Stopping!N91 -> 0.67373888 | H202: =SUM(F202:G202) -> 10.023739 | I202: =H202*Stopping!P91 -> 0.50118694 | J202: =SUM(H202:I202) -> 10.524926 | K202: =SUM(J201:J202) -> 36.968288
F203: ='Suspended Ceilings'!L51 -> 37.06 | G203: =F203*'Suspended Ceilings'!N142 -> 1.7070143 | H203: =SUM(F203:G203) -> 38.767014 | I203: =H203*'Suspended Ceilings'!P142 -> 1.9383507 | J203: =SUM(H203:I203) -> 40.705365 | K203: =SUM(J201:J203) -> 77.673653
B205: Plasterboard Ceiling (Supply & Install) | C205: 13mm Noiseline Includes Stopping Level 4 | F205: ='Gib Linings'!L43 -> 28.57 | G205: =F205*'Gib Linings'!N212 -> 1.4096368 | H205: =SUM(F205:G205) -> 29.979637 | I205: =H205*'Gib Linings'!P212 -> 1.4989818 | J205: =SUM(H205:I205) -> 31.478619
F206: =Stopping!L17 -> 9.35 | G206: =F206*Stopping!N91 -> 0.67373888 | H206: =SUM(F206:G206) -> 10.023739 | I206: =H206*Stopping!P91 -> 0.50118694 | J206: =SUM(H206:I206) -> 10.524926 | K206: =SUM(J205:J206) -> 42.003544
F207: ='Suspended Ceilings'!L51 -> 37.06 | G207: =F207*'Suspended Ceilings'!N142 -> 1.7070143 | H207: =SUM(F207:G207) -> 38.767014 | I207: =H207*'Suspended Ceilings'!P142 -> 1.9383507 | J207: =SUM(H207:I207) -> 40.705365 | K207: =SUM(J205:J207) -> 82.708909
F212: NOTES:
B213: Ceiling Access Hatches - Plasterboard (Supply & Install) | C213: 287.77 | E213: Plus GST | F213: 530 x 530 Set Bead Ceiling Hatches
B214: Ceiling Access Hatches - Decorative or Perforated (Supply & Install) | C214: 400.909 | E214: Plus GST | F214: 500 x 500 Hard Edge Hatch to Above
B216: Suspended Ceiling & Tiles (Supply & Install) | C216: Tagged out of C-01A and C-01B, Mesh and Grid is bespoke so difficult to provide a m2
B218: Plasterboard Ceiling (Supply & Install) | C218: =K203 -> 77.673653 | E218: Plus GST | F218: 13mm Standard Includes Stopping Level 4 including grid @ 600 crs
B220: Plasterboard Ceiling (Supply & Install) | C220: =K207 -> 82.708909 | E220: Plus GST | F220: 13mm Noiseline Includes Stopping Level 4 including grid @ 600 crs
F227: NOTES:
B228: Ceiling Access Hatches - Plasterboard (Supply & Install) | C228: 287.77 | D228: each | E228: Plus GST | F228: 530 x 530 Set Bead Ceiling Hatches
B229: Ceiling Access Hatches - Decorative or Perforated (Supply & Install) | C229: 400.909 | D229: each | E229: Plus GST | F229: 500 x 500 Hard Edge Hatch to Above
B231: Suspended Ceiling & Tiles (Supply & Install) | C231: 85 | D231: m2 | E231: Plus GST | F231: Standard Tile Grid (Circa Rate, no specific seismic allowances)
B233: Plasterboard Ceiling (Supply & Install) | C233: =K203 -> 77.673653 | D233: m2 | E233: Plus GST | F233: 13mm Standard Includes Stopping Level 4 including grid @ 600 crs
B235: Plasterboard Ceiling (Supply & Install) | C235: =K207 -> 82.708909 | D235: m2 | E235: Plus GST | F235: 13mm Noiseline Includes Stopping Level 4 including grid @ 600 crs
B237: PF-01 Plaster System | C237: 250 | D237: m2 | E237: Plus GST | F237: Circa Rate Plaster System Only (excludes substrate)

Sheet Suspended Ceilings
B1: =Summary!B1 -> Ceilings Unlimited
B2: =Summary!B2 -> Craigs Investment Partners - Fitout
B3: =Summary!B3 -> Tauranga
B6: =Summary!B5 -> 46043
B9: =Summary!B117 -> Suspended Ceilings
H11: 50
A12: Item | B12: Description | C12: Qty | D12: Unit | E12: Constant | F12: Constant X Unit = Total HRS | G12: $ Lab per Unit | H12: Total Labour | I12: Materials per Unit | J12: Total Materials | K12: Total Labour & Materials | L12: Total Labour & Materials Per Unit | M12: Total | N12: % Complete | O12: Claim
B14: Level 4:
B16: (C-01A) | C16: Nil
B18: (C-01B) | C18: Basebuild - By Others | E18: 661m2
B20: (C-02) Concealed Ceiling Grid @ 600 crs | C20: 45 | D20: m2 | E20: 0.47 | F20: =C20*E20 -> 21.15 | G20: =$H$11*E20 -> 23.5 | H20: =F20*$H$11 -> 1057.5 | I20: 30.68 | J20: =C20*I20 -> 1380.6 | K20: =SUM(H20,J20) -> 2438.1 | L20: =K20/C20 -> 54.18 | M20: =C20*L20 -> 2438.1 | N20: 0 | O20: =M20*N20 -> 0
B21: Perimeter to Above | C21: 116 | D21: m
B22: (C-02) 530 x 530 Set Bead Ceiling Hatches to Above | C22: 4 | D22: no | E22: 3 | F22: =C22*E22 -> 12 | G22: =$H$11*E22 -> 150 | H22: =F22*$H$11 -> 600 | I22: 112 | J22: =C22*I22 -> 448 | K22: =SUM(H22,J22) -> 1048 | L22: =K22/C22 -> 262 | M22: =C22*L22 -> 1048 | N22: 0 | O22: =M22*N22 -> 0
B24: (C-04) 50mm Autexquiet Space (AP04) | C24: Nil, By Others | E24: 183m2 | F24: Basebuild?? Colour??
B26: Bulkhead 2900 - 3900 (Detail 9 - ID 502) | C26: 41 | D26: m | E26: =WORKINGS_Ceilngs!G297 -> 1.55 | F26: =C26*E26 -> 63.55 | G26: =$H$11*E26 -> 77.5 | H26: =F26*$H$11 -> 3177.5 | I26: =WORKINGS_Ceilngs!K297 -> 52.731917 | J26: =C26*I26 -> 2162.0086 | K26: =SUM(H26,J26) -> 5339.5086 | L26: =K26/C26 -> 130.23192 | M26: =C26*L26 -> 5339.5086 | N26: 0 | O26: =M26*N26 -> 0
B27: Bulkhead 2900 - 3900 (Detail 4 - ID 502) | C27: 13 | D27: m | E27: =WORKINGS_Ceilngs!G297 -> 1.55 | F27: =C27*E27 -> 20.15 | G27: =$H$11*E27 -> 77.5 | H27: =F27*$H$11 -> 1007.5 | I27: =WORKINGS_Ceilngs!K297 -> 52.731917 | J27: =C27*I27 -> 685.51492 | K27: =SUM(H27,J27) -> 1693.0149 | L27: =K27/C27 -> 130.23192 | M27: =C27*L27 -> 1693.0149 | N27: 0 | O27: =M27*N27 -> 0
B28: Bulkhead 2900 - 3900 (Detail 4 - ID 401) | C28: 4 | D28: m | E28: =WORKINGS_Ceilngs!G317 -> 1.57 | F28: =C28*E28 -> 6.28 | G28: =$H$11*E28 -> 78.5 | H28: =F28*$H$11 -> 314 | I28: =WORKINGS_Ceilngs!K317 -> 133.56292 | J28: =C28*I28 -> 534.25167 | K28: =SUM(H28,J28) -> 848.25167 | L28: =K28/C28 -> 212.06292 | M28: =C28*L28 -> 848.25167 | N28: 0 | O28: =M28*N28 -> 0
B31: Level 5:
B33: (C-01A) | C33: Nil
B35: (C-01B) | C35: Basebuild - By Others | E35: 661m2
B37: (C-04) 50mm Autexquiet Space (AP04) | C37: Nil, By Others | E37: 98m2 | F37: Basebuild?? Colour??
B39: Bulkhead 2900 - 3900 (Detail 9 - ID 502) | C39: 20 | D39: m | E39: =WORKINGS_Ceilngs!G297 -> 1.55 | F39: =C39*E39 -> 31 | G39: =$H$11*E39 -> 77.5 | H39: =F39*$H$11 -> 1550 | I39: =WORKINGS_Ceilngs!K297 -> 52.731917 | J39: =C39*I39 -> 1054.6383 | K39: =SUM(H39,J39) -> 2604.6383 | L39: =K39/C39 -> 130.23192 | M39: =C39*L39 -> 2604.6383 | N39: 0 | O39: =M39*N39 -> 0
B42: Level 6:
B44: (C-01A) | C44: Basebuild - By Others | E44: 39m2
B46: (C-01B) | C46: Basebuild - By Others | E46: 102m2
B48: (C-02) Concealed Grid @ 600 crs | C48: 4 | D48: m2 | E48: 0.68 | F48: =C48*E48 -> 2.72 | G48: =$H$11*E48 -> 34 | H48: =F48*$H$11 -> 136 | I48: 69.28 | J48: =C48*I48 -> 277.12 | K48: =SUM(H48,J48) -> 413.12 | L48: =K48/C48 -> 103.28 | M48: =C48*L48 -> 413.12 | N48: 0 | O48: =M48*N48 -> 0
B49: Perimeter to Above | C49: 19 | D49: m
B51: (C-03) Concealed Grid @ 600 crs | C51: 249 | D51: m2 | E51: 0.33 | F51: =C51*E51 -> 82.17 | G51: =$H$11*E51 -> 16.5 | H51: =F51*$H$11 -> 4108.5 | I51: 20.56 | J51: =C51*I51 -> 5119.44 | K51: =SUM(H51,J51) -> 9227.94 | L51: =K51/C51 -> 37.06 | M51: =C51*L51 -> 9227.94 | N51: 0 | O51: =M51*N51 -> 0
B52: Perimeter to Above | C52: 300 | D52: m
B53: Trim Out Service Penetrations | C53: 47 | D53: no | E53: 1 | F53: =C53*E53 -> 47 | G53: =$H$11*E53 -> 50 | H53: =F53*$H$11 -> 2350 | I53: 20 | J53: =C53*I53 -> 940 | K53: =SUM(H53,J53) -> 3290 | L53: =K53/C53 -> 70 | M53: =C53*L53 -> 3290 | N53: 0 | O53: =M53*N53 -> 0
B54: (C-03) 530 x 530 Set Bead Ceiling Hatches to Above | C54: 30 | D54: no | E54: 3 | F54: =C54*E54 -> 90 | G54: =$H$11*E54 -> 150 | H54: =F54*$H$11 -> 4500 | I54: 112 | J54: =C54*I54 -> 3360 | K54: =SUM(H54,J54) -> 7860 | L54: =K54/C54 -> 262 | M54: =C54*L54 -> 7860 | N54: 0 | O54: =M54*N54 -> 0
B56: Linear Tray Items in C-03 | C56: 34 | D56: m | E56: Workings Below
B57: 12mm MDF Substrate and Packing | C57: 34 | D57: m | E57: 0.5 | F57: =C57*E57 -> 17 | G57: =$H$11*E57 -> 25 | H57: =F57*$H$11 -> 850 | I57: 30 | J57: =C57*I57 -> 1020 | K57: =SUM(H57,J57) -> 1870 | L57: =K57/C57 -> 55 | M57: =C57*L57 -> 1870 | N57: 0 | O57: =M57*N57 -> 0
B58: Trim Services into Above | C58: 34 | D58: m | E58: 0.25 | F58: =C58*E58 -> 8.5 | G58: =$H$11*E58 -> 12.5 | H58: =F58*$H$11 -> 425 | I58: 0 | J58: =C58*I58 -> 0 | K58: =SUM(H58,J58) -> 425 | L58: =K58/C58 -> 12.5 | M58: =C58*L58 -> 425 | N58: 0 | O58: =M58*N58 -> 0
B59: Paint Shadowline/Edge of MDF | C59: 70 | D59: m | E59: 0.1 | F59: =C59*E59 -> 7 | G59: =$H$11*E59 -> 5 | H59: =F59*$H$11 -> 350 | I59: 2 | J59: =C59*I59 -> 140 | K59: =SUM(H59,J59) -> 490 | L59: =K59/C59 -> 7 | M59: =C59*L59 -> 490 | N59: 0 | O59: =M59*N59 -> 0
B60: Tray ex Industrial Sheet Metals | C60: 34 | D60: m | E60: 0 | F60: =C60*E60 -> 0 | G60: =$H$11*E60 -> 0 | H60: =F60*$H$11 -> 0 | I60: 100 | J60: =C60*I60 -> 3400 | K60: =SUM(H60,J60) -> 3400 | L60: =K60/C60 -> 100 | M60: =C60*L60 -> 3400 | N60: 0 | O60: =M60*N60 -> 0
B61: Install Tray | C61: 34 | D61: m | E61: 0.5 | F61: =C61*E61 -> 17 | G61: =$H$11*E61 -> 25 | H61: =F61*$H$11 -> 850 | I61: 2.5 | J61: =C61*I61 -> 85 | K61: =SUM(H61,J61) -> 935 | L61: =K61/C61 -> 27.5 | M61: =C61*L61 -> 935 | N61: 0 | O61: =M61*N61 -> 0
B63: (C-06) Illuminated Membrane and Frame | C63: Nil, Supplied and Installed By Others
B64: Trim Openings to Above | C64: 4 | D64: no | E64: 4.5 | F64: =C64*E64 -> 18 | G64: =$H$11*E64 -> 225 | H64: =F64*$H$11 -> 900 | I64: 50 | J64: =C64*I64 -> 200 | K64: =SUM(H64,J64) -> 1100 | L64: =K64/C64 -> 275 | M64: =C64*L64 -> 1100 | N64: 0 | O64: =M64*N64 -> 0
B65: Bronze Finishing Trim to Above, BR-01 (ID 363) | C65: 4 | D65: no | E65: 5 | F65: =C65*E65 -> 20 | G65: =$H$11*E65 -> 250 | H65: =F65*$H$11 -> 1000 | I65: 572 | J65: =C65*I65 -> 2288 | K65: =SUM(H65,J65) -> 3288 | L65: =K65/C65 -> 822 | M65: =C65*L65 -> 3288 | N65: 0 | O65: =M65*N65 -> 0
B67: (C-08) Rondo Heavy Weight Grid 1200 x 600 | C67: 164 | D67: m2 | E67: 0.25 | F67: =C67*E67 -> 41 | G67: =$H$11*E67 -> 12.5 | H67: =F67*$H$11 -> 2050 | I67: 2 | J67: =C67*I67 -> 328 | K67: =SUM(H67,J67) -> 2378 | L67: =K67/C67 -> 14.5 | M67: =C67*L67 -> 2378 | N67: 0 | O67: =M67*N67 -> 0
B68: Mains | C68: 3 | D68: packs | E68: 0 | F68: =C68*E68 -> 0 | G68: =$H$11*E68 -> 0 | H68: =F68*$H$11 -> 0 | I68: 254 | J68: =C68*I68 -> 762 | K68: =SUM(H68,J68) -> 762 | L68: =K68/C68 -> 254 | M68: =C68*L68 -> 762 | N68: 0 | O68: =M68*N68 -> 0 | P68: $236 + 7.5% freight
B69: Nogs | C69: 5 | D69: packs | E69: 0 | F69: =C69*E69 -> 0 | G69: =$H$11*E69 -> 0 | H69: =F69*$H$11 -> 0 | I69: 290 | J69: =C69*I69 -> 1450 | K69: =SUM(H69,J69) -> 1450 | L69: =K69/C69 -> 290 | M69: =C69*L69 -> 1450 | N69: 0 | O69: =M69*N69 -> 0 | P69: $269 + 7.5% freight
B70: EV Powdercoat to Grid | C70: 1 | D70: item | E70: 1 | F70: =C70*E70 -> 1 | G70: =$H$11*E70 -> 50 | H70: =F70*$H$11 -> 50 | I70: =WORKINGS_Ceilngs!I3 -> 3150 | J70: =C70*I70 -> 3150 | K70: =SUM(H70,J70) -> 3200 | L70: =K70/C70 -> 3200 | M70: =C70*L70 -> 3200 | N70: 0 | O70: =M70*N70 -> 0 | P70: 3 Mains and 5 Nogs
B71: Perimeter 20 x 40 - Mobile Workspace | C71: 60 | D71: m | E71: 0.15 | F71: =C71*E71 -> 9 | G71: =$H$11*E71 -> 7.5 | H71: =F71*$H$11 -> 450 | I71: 12 | J71: =C71*I71 -> 720 | K71: =SUM(H71,J71) -> 1170 | L71: =K71/C71 -> 19.5 | M71: =C71*L71 -> 1170 | N71: 0 | O71: =M71*N71 -> 0
B72: Perimeter 90 x 40 - Board Room External Edge | C72: 35 | D72: m | E72: 0.1 | F72: =C72*E72 -> 3.5 | G72: =$H$11*E72 -> 5 | H72: =F72*$H$11 -> 175 | I72: 17 | J72: =C72*I72 -> 595 | K72: =SUM(H72,J72) -> 770 | L72: =K72/C72 -> 22 | M72: =C72*L72 -> 770 | N72: 0 | O72: =M72*N72 -> 0
B73: Perimeter 20 x 40 - Board Room C-06 Edge | C73: 32 | D73: m | E73: 0.15 | F73: =C73*E73 -> 4.8 | G73: =$H$11*E73 -> 7.5 | H73: =F73*$H$11 -> 240 | I73: 12 | J73: =C73*I73 -> 384 | K73: =SUM(H73,J73) -> 624 | L73: =K73/C73 -> 19.5 | M73: =C73*L73 -> 624 | N73: 0 | O73: =M73*N73 -> 0
B74: Perimeter - Columns | C74: 4 | D74: no | E74: 0.5 | F74: =C74*E74 -> 2 | G74: =$H$11*E74 -> 25 | H74: =F74*$H$11 -> 100 | I74: 100 | J74: =C74*I74 -> 400 | K74: =SUM(H74,J74) -> 500 | L74: =K74/C74 -> 125 | M74: =C74*L74 -> 500 | N74: 0 | O74: =M74*N74 -> 0
B75: AMF Expanded Mesh Rhombic 4 1200 x 600 - Colour PC02 | C75: 164 | D75: m2 | E75: 0.25 | F75: =C75*E75 -> 41 | G75: =$H$11*E75 -> 12.5 | H75: =F75*$H$11 -> 2050 | I75: 158.21 | J75: =C75*I75 -> 25946.44 | K75: =SUM(H75,J75) -> 27996.44 | L75: =K75/C75 -> 170.71 | M75: =C75*L75 -> 27996.44 | N75: 0 | O75: =M75*N75 -> 0
B76: Service Penetrations to Above | C76: 1 | D76: item | E76: 0 | F76: =C76*E76 -> 0 | G76: =$H$11*E76 -> 0 | H76: =F76*$H$11 -> 0 | I76: 2500 | J76: =C76*I76 -> 2500 | K76: =SUM(H76,J76) -> 2500 | L76: =K76/C76 -> 2500 | M76: =C76*L76 -> 2500 | N76: 0 | O76: =M76*N76 -> 0
B77: EV Cut to Curves/Columns | C77: 31 | D77: no | E77: 0.5 | F77: =C77*E77 -> 15.5 | G77: =$H$11*E77 -> 25 | H77: =F77*$H$11 -> 775 | I77: 5 | J77: =C77*I77 -> 155 | K77: =SUM(H77,J77) -> 930 | L77: =K77/C77 -> 30 | M77: =C77*L77 -> 930 | N77: 0 | O77: =M77*N77 -> 0
B78: EV Cut to C-06 | C78: 4 | D78: no | E78: 2 | F78: =C78*E78 -> 8 | G78: =$H$11*E78 -> 100 | H78: =F78*$H$11 -> 400 | I78: 5 | J78: =C78*I78 -> 20 | K78: =SUM(H78,J78) -> 420 | L78: =K78/C78 -> 105 | M78: =C78*L78 -> 420 | N78: 0 | O78: =M78*N78 -> 0
B79: 50mm Autex Quietspace above Mesh | C79: 164 | D79: m2 | E79: 0.15 | F79: =C79*E79 -> 24.6 | G79: =$H$11*E79 -> 7.5 | H79: =F79*$H$11 -> 1230 | I79: 175 | J79: =C79*I79 -> 28700 | K79: =SUM(H79,J79) -> 29930 | L79: =K79/C79 -> 182.5 | M79: =C79*L79 -> 29930 | N79: 0 | O79: =M79*N79 -> 0
B80: MDF Upstand/Surround - 100mm | C80: 26 | D80: m | E80: 0.15 | F80: =C80*E80 -> 3.9 | G80: =$H$11*E80 -> 7.5 | H80: =F80*$H$11 -> 195 | I80: 19.37 | J80: =C80*I80 -> 503.62 | K80: =SUM(H80,J80) -> 698.62 | L80: =K80/C80 -> 26.87 | M80: =C80*L80 -> 698.62 | N80: 0 | O80: =M80*N80 -> 0
B81: (C-08) Ceiling Hatches to Above | C81: Nil, Within Tiles Ceiling
B82: Two Way Back Braces | C82: 12 | D82: no | E82: 1 | F82: =C82*E82 -> 12 | G82: =$H$11*E82 -> 50 | H82: =F82*$H$11 -> 600 | I82: 86.38 | J82: =C82*I82 -> 1036.56 | K82: =SUM(H82,J82) -> 1636.56 | L82: =K82/C82 -> 136.38 | M82: =C82*L82 -> 1636.56 | N82: 0 | O82: =M82*N82 -> 0
B84: (C-09) Concealed Grid @ 600 crs | C84: 36 | D84: m2 | E84: 0.3 | F84: =C84*E84 -> 10.8 | G84: =$H$11*E84 -> 15 | H84: =F84*$H$11 -> 540 | I84: 19.89 | J84: =C84*I84 -> 716.04 | K84: =SUM(H84,J84) -> 1256.04 | L84: =K84/C84 -> 34.89 | M84: =C84*L84 -> 1256.04 | N84: 0 | O84: =M84*N84 -> 0
B85: Perimeter to Above | C85: 27 | D85: m
B86: Trim Out Service Penetrations | C86: 2 | D86: no | E86: 1 | F86: =C86*E86 -> 2 | G86: =$H$11*E86 -> 50 | H86: =F86*$H$11 -> 100 | I86: 20 | J86: =C86*I86 -> 40 | K86: =SUM(H86,J86) -> 140 | L86: =K86/C86 -> 70 | M86: =C86*L86 -> 140 | N86: 0 | O86: =M86*N86 -> 0
B87: (C-09) 530 x 530 Set Bead Ceiling Hatches to Above | C87: 4 | D87: no | E87: 3 | F87: =C87*E87 -> 12 | G87: =$H$11*E87 -> 150 | H87: =F87*$H$11 -> 600 | I87: 112 | J87: =C87*I87 -> 448 | K87: =SUM(H87,J87) -> 1048 | L87: =K87/C87 -> 262 | M87: =C87*L87 -> 1048 | N87: 0 | O87: =M87*N87 -> 0
B89: (C-10) Rondo Grid 1200 x 600 | C89: 33 | D89: m2 | F89: =C89*E89 -> 0 | G89: =$H$11*E89 -> 0 | H89: =F89*$H$11 -> 0 | J89: =C89*I89 -> 0 | K89: =SUM(H89,J89) -> 0 | L89: =K89/C89 -> 0 | M89: =C89*L89 -> 0 | N89: 0 | O89: =M89*N89 -> 0
B90: Mains | C90: 1 | D90: packs | E90: 0 | F90: =C90*E90 -> 0 | G90: =$H$11*E90 -> 0 | H90: =F90*$H$11 -> 0 | I90: 214 | J90: =C90*I90 -> 214 | K90: =SUM(H90,J90) -> 214 | L90: =K90/C90 -> 214 | M90: =C90*L90 -> 214 | N90: 0 | O90: =M90*N90 -> 0 | P90: $199 + 7.5% freight
B91: Nogs | C91: 1 | D91: packs | E91: 0 | F91: =C91*E91 -> 0 | G91: =$H$11*E91 -> 0 | H91: =F91*$H$11 -> 0 | I91: 247 | J91: =C91*I91 -> 247 | K91: =SUM(H91,J91) -> 247 | L91: =K91/C91 -> 247 | M91: =C91*L91 -> 247 | N91: 0 | O91: =M91*N91 -> 0 | P91: $229 + 7.5% freight
B92: EV Powdercoat to Grid | C92: 1 | D92: item | E92: 1 | F92: =C92*E92 -> 1 | G92: =$H$11*E92 -> 50 | H92: =F92*$H$11 -> 50 | I92: =WORKINGS_Ceilngs!I6 -> 790 | J92: =C92*I92 -> 790 | K92: =SUM(H92,J92) -> 840 | L92: =K92/C92 -> 840 | M92: =C92*L92 -> 840 | N92: 0 | O92: =M92*N92 -> 0
B93: Perimeter to Above | C93: 28 | D93: m | E93: 0.15 | F93: =C93*E93 -> 4.2 | G93: =$H$11*E93 -> 7.5 | H93: =F93*$H$11 -> 210 | I93: 12 | J93: =C93*I93 -> 336 | K93: =SUM(H93,J93) -> 546 | L93: =K93/C93 -> 19.5 | M93: =C93*L93 -> 546 | N93: 0 | O93: =M93*N93 -> 0
B94: Perimeter - Columns | C94: 1 | D94: no | E94: 0.5 | F94: =C94*E94 -> 0.5 | G94: =$H$11*E94 -> 25 | H94: =F94*$H$11 -> 25 | I94: 100 | J94: =C94*I94 -> 100 | K94: =SUM(H94,J94) -> 125 | L94: =K94/C94 -> 125 | M94: =C94*L94 -> 125 | N94: 0 | O94: =M94*N94 -> 0
B95: MDF Upstand/Surround - 200mm | C95: 28 | D95: m | E95: 0.15 | F95: =C95*E95 -> 4.2 | G95: =$H$11*E95 -> 7.5 | H95: =F95*$H$11 -> 210 | I95: 21.44 | J95: =C95*I95 -> 600.32 | K95: =SUM(H95,J95) -> 810.32 | L95: =K95/C95 -> 28.94 | M95: =C95*L95 -> 810.32 | N95: 0 | O95: =M95*N95 -> 0
B96: AMF Expanded Mesh Rhombic 4 1200 x 600 - Colour PC02 | C96: 33 | D96: m2 | E96: 0.25 | F96: =C96*E96 -> 8.25 | G96: =$H$11*E96 -> 12.5 | H96: =F96*$H$11 -> 412.5 | I96: 158.21 | J96: =C96*I96 -> 5220.93 | K96: =SUM(H96,J96) -> 5633.43 | L96: =K96/C96 -> 170.71 | M96: =C96*L96 -> 5633.43 | N96: 0 | O96: =M96*N96 -> 0
B97: Service Penetrations to Above | C97: 1 | D97: no | E97: 0 | F97: =C97*E97 -> 0 | G97: =$H$11*E97 -> 0 | H97: =F97*$H$11 -> 0 | I97: 500 | J97: =C97*I97 -> 500 | K97: =SUM(H97,J97) -> 500 | L97: =K97/C97 -> 500 | M97: =C97*L97 -> 500 | N97: 0 | O97: =M97*N97 -> 0
B98: EV Cut to Curves/Columns | C98: 11 | D98: no | E98: 0.5 | F98: =C98*E98 -> 5.5 | G98: =$H$11*E98 -> 25 | H98: =F98*$H$11 -> 275 | I98: 5 | J98: =C98*I98 -> 55 | K98: =SUM(H98,J98) -> 330 | L98: =K98/C98 -> 30 | M98: =C98*L98 -> 330 | N98: 0 | O98: =M98*N98 -> 0
B99: Autex Quietspace 50mm Black - Behind above Mesh | C99: 33 | D99: m2 | E99: 0.15 | F99: =C99*E99 -> 4.95 | G99: =$H$11*E99 -> 7.5 | H99: =F99*$H$11 -> 247.5 | I99: 175 | J99: =C99*I99 -> 5775 | K99: =SUM(H99,J99) -> 6022.5 | L99: =K99/C99 -> 182.5 | M99: =C99*L99 -> 6022.5 | N99: 0 | O99: =M99*N99 -> 0
B100: (C-10) Ceiling Hatches to Above | C100: Nil, Within Tiles Ceiling
B101: Two Way Wire Back Braces | C101: 4 | D101: no | E101: 1.25 | F101: =C101*E101 -> 5 | G101: =$H$11*E101 -> 62.5 | H101: =F101*$H$11 -> 250 | I101: 130 | J101: =C101*I101 -> 520 | K101: =SUM(H101,J101) -> 770 | L101: =K101/C101 -> 192.5 | M101: =C101*L101 -> 770 | N101: 0 | O101: =M101*N101 -> 0
B103: (C-11) Concealed Grid @ 300 crs - WIDE FACE BATTEN | C103: 204 | D103: m2 | E103: 0.35 | F103: =C103*E103 -> 71.4 | G103: =$H$11*E103 -> 17.5 | H103: =F103*$H$11 -> 3570 | I103: 28.63 | J103: =C103*I103 -> 5840.52 | K103: =SUM(H103,J103) -> 9410.52 | L103: =K103/C103 -> 46.13 | M103: =C103*L103 -> 9410.52 | N103: 0 | O103: =M103*N103 -> 0
B104: Perimeter to Above | C104: 155 | D104: m
B105: Trim Out Service Penetrations | C105: 27 | D105: no | E105: 1 | F105: =C105*E105 -> 27 | G105: =$H$11*E105 -> 50 | H105: =F105*$H$11 -> 1350 | I105: 20 | J105: =C105*I105 -> 540 | K105: =SUM(H105,J105) -> 1890 | L105: =K105/C105 -> 70 | M105: =C105*L105 -> 1890 | N105: 0 | O105: =M105*N105 -> 0
B106: (C-11) 500 x 500 Hard Edge Hatch to Above | C106: 23 | D106: no | E106: 3.5 | F106: =C106*E106 -> 80.5 | G106: =$H$11*E106 -> 175 | H106: =F106*$H$11 -> 4025 | I106: 190 | J106: =C106*I106 -> 4370 | K106: =SUM(H106,J106) -> 8395 | L106: =K106/C106 -> 365 | M106: =C106*L106 -> 8395 | N106: 0 | O106: =M106*N106 -> 0
B107: Two Way Back Braces | C107: 12 | D107: no | E107: 1 | F107: =C107*E107 -> 12 | G107: =$H$11*E107 -> 50 | H107: =F107*$H$11 -> 600 | I107: 86.38 | J107: =C107*I107 -> 1036.56 | K107: =SUM(H107,J107) -> 1636.56 | L107: =K107/C107 -> 136.38 | M107: =C107*L107 -> 1636.56 | N107: 0 | O107: =M107*N107 -> 0
B109: EV to Core Koolterm/Gib to pick up Fixing | C109: 1 | D109: item | E109: 40 | F109: =C109*E109 -> 40 | G109: =$H$11*E109 -> 2000 | H109: =F109*$H$11 -> 2000 | I109: 400 | J109: =C109*I109 -> 400 | K109: =SUM(H109,J109) -> 2400 | L109: =K109/C109 -> 2400 | M109: =C109*L109 -> 2400 | N109: 0 | O109: =M109*N109 -> 0
B111: Bulkhead 3000 - 4400 (Detail 4 - ID 401) | C111: 4 | D111: m | E111: =WORKINGS_Ceilngs!G336 -> 1.6366667 | F111: =C111*E111 -> 6.5466667 | G111: =$H$11*E111 -> 81.833333 | H111: =F111*$H$11 -> 327.33333 | I111: =WORKINGS_Ceilngs!K336 -> 92.158333 | J111: =C111*I111 -> 368.63333 | K111: =SUM(H111,J111) -> 695.96667 | L111: =K111/C111 -> 173.99167 | M111: =C111*L111 -> 695.96667 | N111: 0 | O111: =M111*N111 -> 0
B112: Bulkhead 3000 - 4400 (Sides of Ceiling C-10) | C112: 18 | D112: m | E112: =WORKINGS_Ceilngs!G336 -> 1.6366667 | F112: =C112*E112 -> 29.46 | G112: =$H$11*E112 -> 81.833333 | H112: =F112*$H$11 -> 1473 | I112: =WORKINGS_Ceilngs!K336 -> 92.158333 | J112: =C112*I112 -> 1658.85 | K112: =SUM(H112,J112) -> 3131.85 | L112: =K112/C112 -> 173.99167 | M112: =C112*L112 -> 3131.85 | N112: 0 | O112: =M112*N112 -> 0
B114: Perimeter Bulkhead Structure - Level 6 | C114: 106 | D114: m | E114: 1.45 | F114: =C114*E114 -> 153.7 | G114: =$H$11*E114 -> 72.5 | H114: =F114*$H$11 -> 7685 | I114: 62.89 | J114: =C114*I114 -> 6666.34 | K114: =SUM(H114,J114) -> 14351.34 | L114: =K114/C114 -> 135.39 | M114: =C114*L114 -> 14351.34 | N114: 0 | O114: =M114*N114 -> 0
B115: EV Bridging to Purlin Area for Structure | C115: 1 | D115: item | E115: 0 | F115: =C115*E115 -> 0 | G115: =$H$11*E115 -> 0 | H115: =F115*$H$11 -> 0 | I115: 2500 | J115: =C115*I115 -> 2500 | K115: =SUM(H115,J115) -> 2500 | L115: =K115/C115 -> 2500 | M115: =C115*L115 -> 2500 | N115: 0 | O115: =M115*N115 -> 0
B116: Custom Blind Pelmet to Above | C116: 106 | D116: m | E116: 0.3 | F116: =C116*E116 -> 31.8 | G116: =$H$11*E116 -> 15 | H116: =F116*$H$11 -> 1590 | I116: 120 | J116: =C116*I116 -> 12720 | K116: =SUM(H116,J116) -> 14310 | L116: =K116/C116 -> 135 | M116: =C116*L116 -> 14310 | N116: 0 | O116: =M116*N116 -> 0
B118: Structure to Coffer Detail to Central bank of Rooms - Detail 6 ID 502 | C118: 60 | D118: m | E118: 1.6 | F118: =C118*E118 -> 96 | G118: =$H$11*E118 -> 80 | H118: =F118*$H$11 -> 4800 | I118: 70 | J118: =C118*I118 -> 4200 | K118: =SUM(H118,J118) -> 9000 | L118: =K118/C118 -> 150 | M118: =C118*L118 -> 9000 | N118: 0 | O118: =M118*N118 -> 0
B119: MDF Shadow to Above | C119: 60 | D119: m | E119: 0.35 | F119: =C119*E119 -> 21 | G119: =$H$11*E119 -> 17.5 | H119: =F119*$H$11 -> 1050 | I119: 23.84 | J119: =C119*I119 -> 1430.4 | K119: =SUM(H119,J119) -> 2480.4 | L119: =K119/C119 -> 41.34 | M119: =C119*L119 -> 2480.4 | N119: 0 | O119: =M119*N119 -> 0
B120: Bronze Edge | C120: 60 | D120: m | E120: 0.35 | F120: =C120*E120 -> 21 | G120: =$H$11*E120 -> 17.5 | H120: =F120*$H$11 -> 1050 | I120: 155 | J120: =C120*I120 -> 9300 | K120: =SUM(H120,J120) -> 10350 | L120: =K120/C120 -> 172.5 | M120: =C120*L120 -> 10350 | N120: 0 | O120: =M120*N120 -> 0
F123: =SUM(F13:F122) -> 1278.6267 | H123: =SUM(H13:H122) -> 63931.333 | J123: =SUM(J13:J122) -> 156338.79
B124: Total of above | M124: =SUM(M13:M122) -> 220270.12 | O124: =SUM(O13:O122) -> 0
B125: Miscellaneous
B127: P&G - Admin / Supervision | D127: Sum | L127: 0.0205 | M127: =M124*L127 -> 4515.5375 | O127: =(O124/M124)*M127 -> 0
B129: P&G - Site Establishment | D129: Sum | L129: 0.01 | M129: =M124*L129 -> 2202.7012 | O129: =(O124/M124)*M129 -> 0
B131: P&G - Access Equip | D131: Sum | L131: 0.0025 | M131: =M124*L131 -> 550.6753 | O131: =(O124/M124)*M131 -> 0
B133: P&G - Parking | D133: Sum | L133: =M133/M124 -> 0.013060827 | M133: =I146 -> 2876.91
B135: P&G | D135: Sum | O135: =M135*N135 -> 0
B137: Sub total | M137: =SUM(M124:M136) -> 230415.94 | O137: =SUM(O124:O136) -> 0
B139: Margin | L139: 0.05 | M139: =M137*L139 -> 11520.797 | O139: =O137/M137*M139 -> 0
B141: TOTAL OF SUSPENDED CEILINGS | M141: =ROUNDUP(SUM(M137:M140),0) -> 241937 | N141: =O141/M141 -> 0 | O141: =SUM(O137:O140) -> 0 | T141: 218089
N142: =SUM(L126:L136) -> 0.046060827 | P142: =L139 -> 0.05 | T142: 183827
G143: Parking | K143: =SUM(F15:F30) -> 123.13 | L143: LEVEL 4 | M143: =SUM(M15:M30) -> 11366.875 | N143: =M143*$N$142 -> 523.56767 | O143: =SUM(M143:N143) -> 11890.443 | P143: =O143*$P$142 -> 594.52214 | Q143: =SUM(O143:P143) -> 12484.965 | T143: =T141-T142 -> 34262
...

Sheet WORKINGS_Ceilngs
P1: Loadin
B2: 3 Mains and 5 Nogs | C2: Mains | D2: 3 | E2: 20 | F2: =D2*E2 -> 60 | G2: 20 | H2: =F2*G2 -> 1200 | K2: C-08 | L2: 164 | M2: m2 | N2: 223656 | O2: =N2/L2 -> 1363.7561 | P2: 7 | Q2: =O2+P2 -> 1370.7561 | R2: =L2*Q2 -> 224804
C3: Nogs | D3: 5 | E3: 60 | F3: =D3*E3 -> 300 | G3: 6.5 | H3: =F3*G3 -> 1950 | I3: =SUM(H2:H3) -> 3150 | K3: C-10 | L3: 33 | M3: m2 | N3: 45004 | O3: =N3/L3 -> 1363.7576 | P3: 7 | Q3: =O3+P3 -> 1370.7576 | R3: =L3*Q3 -> 45235
B5: 1 Mains and 1 Nogs | C5: Mains | D5: 1 | E5: 20 | F5: =D5*E5 -> 20 | G5: 20 | H5: =F5*G5 -> 400 | N5: =SUM(N2:N4) -> 268660 | R5: =SUM(R2:R4) -> 270039
C6: Nogs | D6: 1 | E6: 60 | F6: =D6*E6 -> 60 | G6: 6.5 | H6: =F6*G6 -> 390 | I6: =SUM(H5:H6) -> 790
G8: Wires | O8: 1.05 | R8: Loadin
B9: Suspended system Rondo | F9: Dis between TCR | G9: Across TCR wire | K9: C-08 | L9: 164 | M9: m2 | N9: 227 | O9: =N9*O8 -> 238.35 | P9: 70.73 | Q9: 31 | R9: 7 | S9: =SUM(P9:R9) -> 108.73 | T9: =O9*S9 -> 25915.796
B10: 28mm furring channel @ | C10: 0.6 | E10: TCR spacing | F10: 1.2 | G10: 1.2 | K10: C-10 | L10: 33 | M10: m2 | N10: 46 | O10: =N10*O8 -> 48.3 | P10: 70.73 | Q10: 31 | R10: 7 | S10: =SUM(P10:R10) -> 108.73 | T10: =O10*S10 -> 5251.659
B11: 40 x 40 | C11: 27
B12: M2 | C12: 36 | E12: Total furring LM | F12: Total Perim LM | G12: M2 of ceiling | L12: =SUM(L9:L11) -> 197 | O12: =SUM(O9:O11) -> 286.65 | T12: =SUM(T9:T11) -> 31167.455 | U12: =T12/O12 -> 108.73 | V12: per tile
B13: Material | E13: =SUM(G13/C10) -> 60 | F13: =C11 -> 27 | G13: =C12 -> 36 | U13: =T12/L12 -> 158.21043 | V13: per m2
C14: $/m | J14: SRP
D15: Area | E15: M/No | F15: Total | G15: Waste | J15: List
B16: 28mm furring channel | C16: =J16 -> 3.01 | D16: Change on spacings | E16: =G13/C10 -> 60 | F16: =SUM(C16*E16) -> 180.6 | I16: 28mm Furring | J16: 3.01
B18: Joiner | C18: =J18 -> 1.2 | D18: =C10*3.6 -> 2.16 | E18: =(G13/D18) -> 16.666667 | F18: =SUM(C18*E18) -> 20 | I18: Joiner | J18: 1.2
B19: Locking clip | C19: =J19 -> 0.49 | D19: =C10*F10 -> 0.72 | E19: =(G13/D19) -> 50 | F19: =SUM(C19*E19) -> 24.5 | I19: Locking Clip | J19: 0.49
B20: TCR .75 BMT | C20: =J20 -> 4.04 | D20: =F10 -> 1.2 | E20: =(G13/D20) -> 30 | F20: =SUM(C20*E20) -> 121.2 | I20: TCR 0.75 | J20: 4.04 | L20: 127 or 128 | N20: 125 | O20: 129
B21: Hanging wire | C21: 100 | E21: =ROUNDUP(G13/200,0) -> 1 | F21: =SUM(C21*E21) -> 100
B22: Fixings (to substrate) | C22: 2 | E22: =(G13/F10/G10) -> 25 | F22: =C22*E22 -> 50
B23: Wall Track/Angle | C23: =J23 -> 5.67 | E23: =C11 -> 27 | F23: =C23*E23 -> 153.09 | I23: Wall Track 141 | J23: 5.67
F24: =SUM(F16:F23) -> 649.39 | I24: 40 x 40 x 1.15 Angle | J24: 4.87
B25: Material cost per m2 | C25: =F24/G13 -> 18.038611
B26: Fixings (screws) | C26: 0.015
B27: Unload | C27: 0.03
C28: =SUM(C25:C27) -> 18.083611
B29: waste 5% | C29: =C28*10% -> 1.8083611
B30: Material cost per m2 | C30: =SUM(C28:C29) -> 19.891972
E32: lab rate
E33: 52
B34: Labour per m as per rates | D34: m/hr
B35: Furring channel | C35: =E33/D35 -> 2.08 | D35: 25 | E35: =C35*E13 -> 124.8
B37: TCR | C37: =E33/D37 -> 5.2 | D37: 10 | E37: =E20*C37 -> 156
B38: Fixings | C38: =E33/D38 -> 4.3333333 | D38: 12 | E38: =SUM(C38*E22) -> 108.33333
B39: 40 x 40 | C39: =E33/D39 -> 5.2 | D39: 10 | E39: =C11*C39 -> 140.4
E40: =SUM(E35:E39) -> 529.53333
B41: Labour cost per m2 | C41: =E40/G13 -> 14.709259 | D41: =C41/E33 -> 0.28287037
C42: =SUM(C30+C41) -> 34.601231 | D42: m2 | E42: Total cost per m2
B43: Total cost of ceiling job is | E43: =C42*G13 -> 1245.6443
B45: Cost per m2
B46: Material | C46: =C30 -> 19.891972 | D46: m2
B47: Labour | C47: =C41 -> 14.709259 | D47: m2 | E47: =C47*G13 -> 529.53333 | F47: =E47/E33 -> 10.183333 | G47: hrs
G50: Wires
B51: Suspended system Rondo | F51: Dis between TCR | G51: Across TCR wire
B52: 28mm furring channel @ | C52: 0.3 | E52: TCR spacing | F52: 1.2 | G52: 1.2
B53: 40 x 40 | C53: 155
B54: M2 | C54: 204 | E54: Total furring LM | F54: Total Perim LM | G54: M2 of ceiling
B55: Material | E55: =SUM(G55/C52) -> 680 | F55: =C53 -> 155 | G55: =C54 -> 204
C56: $/m | J56: SRP
D57: Area | E57: M/No | F57: Total | G57: Waste | J57: List
B58: 28mm furring channel **WIDE FACE** | C58: =J58 -> 4.04 | D58: Change on spacings | E58: =G55/C52 -> 680 | F58: =SUM(C58*E58) -> 2747.2 | I58: 28mm Furring | J58: 4.04 | K58: WIDE FACE
B60: Joiner | C60: =J60 -> 1.2 | D60: =C52*3.6 -> 1.08 | E60: =(G55/D60) -> 188.88889 | F60: =SUM(C60*E60) -> 226.66667 | I60: Joiner | J60: 1.2
B61: Locking clip | C61: =J61 -> 0.49 | D61: =C52*F52 -> 0.36 | E61: =(G55/D61) -> 566.66667 | F61: =SUM(C61*E61) -> 277.66667 | I61: Locking Clip | J61: 0.49
B62: TCR .75 BMT | C62: =J62 -> 4.04 | D62: =F52 -> 1.2 | E62: =(G55/D62) -> 170 | F62: =SUM(C62*E62) -> 686.8 | I62: TCR 0.75 | J62: 4.04 | L62: 127 or 128 | N62: 125 | O62: 129
B63: Hanging wire | C63: 100 | E63: =ROUNDUP(G55/200,0) -> 2 | F63: =SUM(C63*E63) -> 200
B64: Fixings (to substrate) | C64: 2 | E64: =(G55/F52/G52) -> 141.66667 | F64: =C64*E64 -> 283.33333
B65: Wall Track/Angle | C65: =J65 -> 5.67 | E65: =C53 -> 155 | F65: =C65*E65 -> 878.85 | I65: Wall Track 141 | J65: 5.67
F66: =SUM(F58:F65) -> 5300.5167 | I66: 40 x 40 x 1.15 Angle | J66: 4.87
B67: Material cost per m2 | C67: =F66/G55 -> 25.982925
B68: Fixings (screws) | C68: 0.015
B69: Unload | C69: 0.03
C70: =SUM(C67:C69) -> 26.027925
B71: waste 5% | C71: =C70*10% -> 2.6027925
B72: Material cost per m2 | C72: =SUM(C70:C71) -> 28.630717
E74: lab rate
E75: 52
B76: Labour per m as per rates | D76: m/hr
B77: Furring channel | C77: =E75/D77 -> 2.08 | D77: 25 | E77: =C77*E55 -> 1414.4
B79: TCR | C79: =E75/D79 -> 5.2 | D79: 10 | E79: =E62*C79 -> 884
B80: Fixings | C80: =E75/D80 -> 4.3333333 | D80: 12 | E80: =SUM(C80*E64) -> 613.88889
B81: 40 x 40 | C81: =E75/D81 -> 5.2 | D81: 10 | E81: =C53*C81 -> 806
E82: =SUM(E77:E81) -> 3718.2889
B83: Labour cost per m2 | C83: =E82/G55 -> 18.226906 | D83: =C83/E75 -> 0.35051743
C84: =SUM(C72+C83) -> 46.857624 | D84: m2 | E84: Total cost per m2
B85: Total cost of ceiling job is | E85: =C84*G55 -> 9558.9552
B87: Cost per m2
B88: Material | C88: =C72 -> 28.630717 | D88: m2
B89: Labour | C89: =C83 -> 18.226906 | D89: m2 | E89: =C89*G55 -> 3718.2889 | F89: =E89/E75 -> 71.505556 | G89: hrs
B98: Job Name | H98: 0.1 | I98: Waste
B99: total sqm | C99: 164 | D99: m2 | F99: Standard grid | H99: 0.025 | I99: Freight
B100: Cost Plus Margin | F100: Nett cost | H100: =SUM(H98:H99) -> 0.125
B101: admin | F101: Wall angle | H101: =G101*1.13 -> 0
B102: hourly rate | C102: 65 | F102: Mains | G102: 3.68 | H102: =G102*1.13 -> 4.1584
B103: wall trim | D103: m | F103: 1200 Nogs | G103: 4.21 | H103: =G103*1.13 -> 4.7573
B104: tile type | F104: Tiles | H104: =K109 -> 0
B105: tile price | D105: per tile
B106: Module | C106: 1200 x 600
B109: Total Cost | C109: =C99*C128 -> 3890.04
B110: Total Revenue | C110: =C109*(1+C100) -> 3890.04 | D110: Price
B111: Profit | C111: =C110-C109 -> 0
B113: Standard grid
B114: Peakform | E114: Waste 10% on product include in cost
B115: Adminstration | E115: COST | F115: =SUM(C101) -> 0 | G115: HOURS | H115: COST | I115: ='Suspended Ceilings'!H11 -> 50
B116: BPT1932H | C116: =C103 -> 0 | D116: m | E116: =G101 -> 0 | F116: =C116*E116 -> 0
B117: BP734042P | C117: =C99*90% -> 147.6 | D117: m | E117: =G102 -> 3.68 | F117: =C117*E117 -> 543.168 | G117: =C117/25 -> 5.904 | H117: =G117*$I$115 -> 295.2
B118: BP313052P | C118: =C99*180% -> 295.2 | D118: m | E118: =G103 -> 4.21 | F118: =C118*E118 -> 1242.792 | G118: =C118/25 -> 11.808 | H118: =G118*$I$115 -> 590.4
B119: Wire | C119: =ROUND(C99/200, 0) -> 1 | D119: ea | E119: 100 | F119: =C119*E119 -> 100 | H119: =G119*$I$115 -> 0
B120: Fixings | C120: =C99*66% -> 108.24 | D120: ea | E120: 2 | F120: =C120*E120 -> 216.48 | G120: =C120/6 -> 18.04 | H120: =G120*$I$115 -> 902
B121: Grid Only | C121: =F121+H121 -> 3890.04 | F121: =SUM(F115:F120) -> 2102.44 | H121: =SUM(H116:H120) -> 1787.6 | I121: Constant
C122: =C121/C99 -> 23.719756 | D122: M2 | E122: mat | F122: =F121/C99 -> 12.819756 | G122: lab | H122: =H121/C99 -> 10.9 | I122: =H122/I115 -> 0.218
B124: Ceiling Tiles | C124: =C99/0.72 -> 227.77778 | D124: ea | E124: =C105 -> 0 | F124: =C124*E124 -> 0 | G124: =C99/15 -> 10.933333 | H124: =G124*$I$22 -> 0
...

Sheet Partitions
B1: =Summary!B1 -> Ceilings Unlimited
B2: =Summary!B2 -> Craigs Investment Partners - Fitout
B3: =Summary!B3 -> Tauranga
B6: =Summary!B5 -> 46043
B9: =Summary!B119 -> Partitions
H11: 50
A12: Item | B12: Description | C12: Qty | D12: Unit | E12: Constant | F12: Constant X Unit = Total HRS | G12: $ Lab per Unit | H12: Total Labour | I12: Materials per Unit | J12: Total Materials | K12: Total Labour & Materials | L12: Total Labour & Materials Per Unit | M12: Total | N12: % Complete | O12: Claim
B14: Level 4:
B16: (P-10) Potters Aluminium Glazing | C16: Refer Potters Trade
B17: (P-10) Bulkhead Structure | C17: 4 | D17: m | E17: =WORKINGS_Partitions!G41 -> 1.977 | F17: =C17*E17 -> 7.908 | G17: =$H$11*E17 -> 98.85 | H17: =F17*$H$11 -> 395.4 | I17: =WORKINGS_Partitions!K41 -> 87.141738 | J17: =C17*I17 -> 348.56695 | K17: =SUM(H17,J17) -> 743.96695 | L17: =K17/C17 -> 185.99174 | M17: =C17*L17 -> 743.96695 | N17: 0 | O17: =M17*N17 -> 0
B18: 13mm Gib Overlay to Above | C18: 4 | D18: m | E18: 0.15 | F18: =C18*E18 -> 0.6 | G18: =$H$11*E18 -> 7.5 | H18: =F18*$H$11 -> 30 | I18: 3.5 | J18: =C18*I18 -> 14 | K18: =SUM(H18,J18) -> 44 | L18: =K18/C18 -> 11 | M18: =C18*L18 -> 44 | N18: 0 | O18: =M18*N18 -> 0
B20: (P-11) Potters Aluminium Glazing | C20: Refer Potters Trade
B21: (P-11) Bulkhead Structure | C21: 23 | D21: m | E21: =WORKINGS_Partitions!G41 -> 1.977 | F21: =C21*E21 -> 45.471 | G21: =$H$11*E21 -> 98.85 | H21: =F21*$H$11 -> 2273.55 | I21: =WORKINGS_Partitions!K41 -> 87.141738 | J21: =C21*I21 -> 2004.26 | K21: =SUM(H21,J21) -> 4277.81 | L21: =K21/C21 -> 185.99174 | M21: =C21*L21 -> 4277.81 | N21: 0 | O21: =M21*N21 -> 0
B22: MDF Capping Strip - 242mm Wide | C22: Not Required, Refer Brevity Design
B23: 13mm Gib Overlay to Above | C23: 23 | D23: m | E23: 0.15 | F23: =C23*E23 -> 3.45 | G23: =$H$11*E23 -> 7.5 | H23: =F23*$H$11 -> 172.5 | I23: 3.5 | J23: =C23*I23 -> 80.5 | K23: =SUM(H23,J23) -> 253 | L23: =K23/C23 -> 11 | M23: =C23*L23 -> 253 | N23: 0 | O23: =M23*N23 -> 0
B25: (P-13) | C25: Refer Potters Trade/Suspended Ceilings | R25: =SUM(C35,C43,C47,C52,C87,C93,C98,C138,C148) -> 82
B27: (P-20A) Bulkhead Structure | C27: 9 | D27: m | E27: =WORKINGS_Partitions!G76 -> 0.72041667 | F27: =C27*E27 -> 6.48375 | G27: =$H$11*E27 -> 36.020833 | H27: =F27*$H$11 -> 324.1875 | I27: =WORKINGS_Partitions!K76 -> 32.029583 | J27: =C27*I27 -> 288.26625 | K27: =SUM(H27,J27) -> 612.45375 | L27: =K27/C27 -> 68.050417 | M27: =C27*L27 -> 612.45375 | N27: 0 | O27: =M27*N27 -> 0 | R27: 92 x 0.75 Stud | S27: 1.15
B28: (P-20A) 92mm x 0.75 Stud @ 400 crs with 1.15 Head Track and 0.70 Base Track with Nogging Track | C28: 34 | D28: m2 | E28: 0.4 | F28: =C28*E28 -> 13.6 | G28: =$H$11*E28 -> 20 | H28: =F28*$H$11 -> 680 | I28: 22.55 | J28: =C28*I28 -> 766.7 | K28: =SUM(H28,J28) -> 1446.7 | L28: =K28/C28 -> 42.55 | M28: =C28*L28 -> 1446.7 | N28: 0 | O28: =M28*N28 -> 0 | P28: 9 | Q28: 3.9 | R28: =(P28/0.4)*Q28 -> 87.75
B30: (P-21S) 92mm x 0.75 Stud @ 400 crs with 1.15 Head Track and 0.70 Base Track | C30: 19 | D30: m2 | E30: 0.44 | F30: =C30*E30 -> 8.36 | G30: =$H$11*E30 -> 22 | H30: =F30*$H$11 -> 418 | I30: 25.23 | J30: =C30*I30 -> 479.37 | K30: =SUM(H30,J30) -> 897.37 | L30: =K30/C30 -> 47.23 | M30: =C30*L30 -> 897.37 | N30: 0 | O30: =M30*N30 -> 0 | P30: 7 | Q30: 2.95 | R30: =(P30/0.4)*Q30 -> 51.625
B32: (P-21) 92mm x 0.75 Stud @ 400 crs with 1.15 Head Track and 0.70 Base Track | C32: 141 | D32: m2 | E32: 0.43 | F32: =C32*E32 -> 60.63 | G32: =$H$11*E32 -> 21.5 | H32: =F32*$H$11 -> 3031.5 | I32: 24.41 | J32: =C32*I32 -> 3441.81 | K32: =SUM(H32,J32) -> 6473.31 | L32: =K32/C32 -> 45.91 | M32: =C32*L32 -> 6473.31 | N32: 0 | O32: =M32*N32 -> 0 | P32: 48 | Q32: 2.95 | R32: =(P32/0.4)*Q32 -> 354
B34: (P-21A) 92mm x 0.75 Stud @ 400 crs with 1.15 Head Track and 0.70 Base Track | C34: 27 | D34: m2 | E34: 0.43 | F34: =C34*E34 -> 11.61 | G34: =$H$11*E34 -> 21.5 | H34: =F34*$H$11 -> 580.5 | I34: 25.02 | J34: =C34*I34 -> 675.54 | K34: =SUM(H34,J34) -> 1256.04 | L34: =K34/C34 -> 46.52 | M34: =C34*L34 -> 1256.04 | N34: 0 | O34: =M34*N34 -> 0 | P34: 9 | Q34: 2.95 | R34: =(P34/0.4)*Q34 -> 66.375
B35: MDF Capping Strip - 241mm Wide | C35: 9 | D35: m | E35: 0.25 | F35: =C35*E35 -> 2.25 | G35: =$H$11*E35 -> 12.5 | H35: =F35*$H$11 -> 112.5 | I35: 23.84 | J35: =C35*I35 -> 214.56 | K35: =SUM(H35,J35) -> 327.06 | L35: =K35/C35 -> 36.34 | M35: =C35*L35 -> 327.06 | N35: 0 | O35: =M35*N35 -> 0
B36: 13mm Gib Overlay to Above | C36: 9 | D36: m | E36: 0.15 | F36: =C36*E36 -> 1.35 | G36: =$H$11*E36 -> 7.5 | H36: =F36*$H$11 -> 67.5 | I36: 3.5 | J36: =C36*I36 -> 31.5 | K36: =SUM(H36,J36) -> 99 | L36: =K36/C36 -> 11 | M36: =C36*L36 -> 99 | N36: 0 | O36: =M36*N36 -> 0
B38: (P-23) 92mm x 0.75 Stud @ 400 crs with 0.70 Head Track and 0.70 Base Track | C38: 84 | D38: m2 | E38: 0.42 | F38: =C38*E38 -> 35.28 | G38: =$H$11*E38 -> 21 | H38: =F38*$H$11 -> 1764 | I38: 22.62 | J38: =C38*I38 -> 1900.08 | K38: =SUM(H38,J38) -> 3664.08 | L38: =K38/C38 -> 43.62 | M38: =C38*L38 -> 3664.08 | N38: 0 | O38: =M38*N38 -> 0 | P38: 29 | Q38: 2.95 | R38: =(P38/0.4)*Q38 -> 213.875
B40: (P-23S) 92mm x 0.75 Stud @ 400 crs with 0.70 Head Track and 0.70 Base Track | C40: 12 | D40: m2 | E40: 0.45 | F40: =C40*E40 -> 5.4 | G40: =$H$11*E40 -> 22.5 | H40: =F40*$H$11 -> 270 | I40: 24.11 | J40: =C40*I40 -> 289.32 | K40: =SUM(H40,J40) -> 559.32 | L40: =K40/C40 -> 46.61 | M40: =C40*L40 -> 559.32 | N40: 0 | O40: =M40*N40 -> 0 | P40: 4 | Q40: 2.95 | R40: =(P40/0.4)*Q40 -> 29.5
B42: (P-23AS) 92mm x 0.75 Stud @ 400 crs with 1.15 Head Track and 0.70 Base Track | C42: 12 | D42: m2 | E42: 0.45 | F42: =C42*E42 -> 5.4 | G42: =$H$11*E42 -> 22.5 | H42: =F42*$H$11 -> 270 | I42: 24.42 | J42: =C42*I42 -> 293.04 | K42: =SUM(H42,J42) -> 563.04 | L42: =K42/C42 -> 46.92 | M42: =C42*L42 -> 563.04 | N42: 0 | O42: =M42*N42 -> 0 | P42: 4 | Q42: 2.9 | R42: =(P42/0.4)*Q42 -> 29
B43: MDF Capping Strip - 228mm Wide | C43: 4 | D43: m | E43: 0.25 | F43: =C43*E43 -> 1 | G43: =$H$11*E43 -> 12.5 | H43: =F43*$H$11 -> 50 | I43: 23.84 | J43: =C43*I43 -> 95.36 | K43: =SUM(H43,J43) -> 145.36 | L43: =K43/C43 -> 36.34 | M43: =C43*L43 -> 145.36 | N43: 0 | O43: =M43*N43 -> 0
B44: 13mm Gib Overlay to Above | C44: 4 | D44: m | E44: 0.15 | F44: =C44*E44 -> 0.6 | G44: =$H$11*E44 -> 7.5 | H44: =F44*$H$11 -> 30 | I44: 3.5 | J44: =C44*I44 -> 14 | K44: =SUM(H44,J44) -> 44 | L44: =K44/C44 -> 11 | M44: =C44*L44 -> 44 | N44: 0 | O44: =M44*N44 -> 0
B46: (P-23A) 92mm x 0.75 Stud @ 400 crs with 1.15 Head Track and 0.70 Base Track | C46: 74 | D46: m2 | E46: 0.43 | F46: =C46*E46 -> 31.82 | G46: =$H$11*E46 -> 21.5 | H46: =F46*$H$11 -> 1591 | I46: 23 | J46: =C46*I46 -> 1702 | K46: =SUM(H46,J46) -> 3293 | L46: =K46/C46 -> 44.5 | M46: =C46*L46 -> 3293 | N46: 0 | O46: =M46*N46 -> 0 | P46: 25 | Q46: 2.9 | R46: =(P46/0.4)*Q46 -> 181.25
B47: MDF Capping Strip - 228mm Wide | C47: 25 | D47: m | E47: 0.25 | F47: =C47*E47 -> 6.25 | G47: =$H$11*E47 -> 12.5 | H47: =F47*$H$11 -> 312.5 | I47: 23.84 | J47: =C47*I47 -> 596 | K47: =SUM(H47,J47) -> 908.5 | L47: =K47/C47 -> 36.34 | M47: =C47*L47 -> 908.5 | N47: 0 | O47: =M47*N47 -> 0
B48: 13mm Gib Overlay to Above | C48: 25 | D48: m | E48: 0.15 | F48: =C48*E48 -> 3.75 | G48: =$H$11*E48 -> 7.5 | H48: =F48*$H$11 -> 187.5 | I48: 3.5 | J48: =C48*I48 -> 87.5 | K48: =SUM(H48,J48) -> 275 | L48: =K48/C48 -> 11 | M48: =C48*L48 -> 275 | N48: 0 | O48: =M48*N48 -> 0
B50: (P-23B) Bulkhead Structure | C50: 11 | D50: m | E50: =WORKINGS_Partitions!G89 -> 1.005 | F50: =C50*E50 -> 11.055 | G50: =$H$11*E50 -> 50.25 | H50: =F50*$H$11 -> 552.75 | I50: =WORKINGS_Partitions!K89 -> 32.238942 | J50: =C50*I50 -> 354.62836 | K50: =SUM(H50,J50) -> 907.37836 | L50: =K50/C50 -> 82.488942 | M50: =C50*L50 -> 907.37836 | N50: 0 | O50: =M50*N50 -> 0
B51: (P-23B) 92mm x 0.75 Stud @ 400 crs with 1.15 Head Track and 0.70 Base Track | C51: 31 | D51: m2 | E51: 0.44 | F51: =C51*E51 -> 13.64 | G51: =$H$11*E51 -> 22 | H51: =F51*$H$11 -> 682 | I51: 25.25 | J51: =C51*I51 -> 782.75 | K51: =SUM(H51,J51) -> 1464.75 | L51: =K51/C51 -> 47.25 | M51: =C51*L51 -> 1464.75 | N51: 0 | O51: =M51*N51 -> 0 | P51: 11 | Q51: 2.9 | R51: =(P51/0.4)*Q51 -> 79.75
B52: MDF Capping Strip - 228mm Wide | C52: 11 | D52: m | E52: 0.25 | F52: =C52*E52 -> 2.75 | G52: =$H$11*E52 -> 12.5 | H52: =F52*$H$11 -> 137.5 | I52: 23.84 | J52: =C52*I52 -> 262.24 | K52: =SUM(H52,J52) -> 399.74 | L52: =K52/C52 -> 36.34 | M52: =C52*L52 -> 399.74 | N52: 0 | O52: =M52*N52 -> 0
B53: 13mm Gib Overlay to Above | C53: 11 | D53: m | E53: 0.15 | F53: =C53*E53 -> 1.65 | G53: =$H$11*E53 -> 7.5 | H53: =F53*$H$11 -> 82.5 | I53: 3.5 | J53: =C53*I53 -> 38.5 | K53: =SUM(H53,J53) -> 121 | L53: =K53/C53 -> 11 | M53: =C53*L53 -> 121 | N53: 0 | O53: =M53*N53 -> 0
B55: Trackloks - Part Height Walls | C55: 43 | D55: no | E55: 0.75 | F55: =C55*E55 -> 32.25 | G55: =$H$11*E55 -> 37.5 | H55: =F55*$H$11 -> 1612.5 | I55: 85.17 | J55: =C55*I55 -> 3662.31 | K55: =SUM(H55,J55) -> 5274.81 | L55: =K55/C55 -> 122.67 | M55: =C55*L55 -> 5274.81 | N55: 0 | O55: =M55*N55 -> 0
B57: Trackloks - TB-02 | C57: Refer Featurecraft Trade
B59: Bridge to Confloor | C59: =SUM(P28) -> 9 | D59: m | E59: 0.25 | F59: =C59*E59 -> 2.25 | G59: =$H$11*E59 -> 12.5 | H59: =F59*$H$11 -> 112.5 | I59: 15 | J59: =C59*I59 -> 135 | K59: =SUM(H59,J59) -> 247.5 | L59: =K59/C59 -> 27.5 | M59: =C59*L59 -> 247.5 | N59: 0 | O59: =M59*N59 -> 0
B60: EV Stud to Corners/Intersections | C60: 492 | D60: m | E60: 0.09 | F60: =C60*E60 -> 44.28 | G60: =$H$11*E60 -> 4.5 | H60: =F60*$H$11 -> 2214 | I60: 5.61 | J60: =C60*I60 -> 2760.12 | K60: =SUM(H60,J60) -> 4974.12 | L60: =K60/C60 -> 10.11 | M60: =C60*L60 -> 4974.12 | N60: 0 | O60: =M60*N60 -> 0
B61: Plywood Support/Nogging - TV's | C61: 7 | D61: item | E61: 1.5 | F61: =C61*E61 -> 10.5 | G61: =$H$11*E61 -> 75 | H61: =F61*$H$11 -> 525 | I61: 139 | J61: =C61*I61 -> 973 | K61: =SUM(H61,J61) -> 1498 | L61: =K61/C61 -> 214 | M61: =C61*L61 -> 1498 | N61: 0 | O61: =M61*N61 -> 0
B62: Plywood Support/Nogging - Focus Shelf | C62: 6 | D62: item | E62: 1 | F62: =C62*E62 -> 6 | G62: =$H$11*E62 -> 50 | H62: =F62*$H$11 -> 300 | I62: 70 | J62: =C62*I62 -> 420 | K62: =SUM(H62,J62) -> 720 | L62: =K62/C62 -> 120 | M62: =C62*L62 -> 720 | N62: 0 | O62: =M62*N62 -> 0
B63: Horizontal Nogging to pick up Featurecarft TB.01 | C63: 136 | D63: m | E63: 0.1 | F63: =C63*E63 -> 13.6 | G63: =$H$11*E63 -> 5 | H63: =F63*$H$11 -> 680 | I63: 10.1 | J63: =C63*I63 -> 1373.6 | K63: =SUM(H63,J63) -> 2053.6 | L63: =K63/C63 -> 15.1 | M63: =C63*L63 -> 2053.6 | N63: 0 | O63: =M63*N63 -> 0
B65: Battening to Columns to take Curveline | C65: 13 | D65: no | E65: 2.5 | F65: =C65*E65 -> 32.5 | G65: =$H$11*E65 -> 125 | H65: =F65*$H$11 -> 1625 | I65: 175 | J65: =C65*I65 -> 2275 | K65: =SUM(H65,J65) -> 3900 | L65: =K65/C65 -> 300 | M65: =C65*L65 -> 3900 | N65: 0 | O65: =M65*N65 -> 0
B68: Level 5:
B70: (P-10) Potters Aluminium Glazing | C70: Refer Potters Trade
B71: (P-10) Bulkhead Structure | C71: 14 | D71: m | E71: =WORKINGS_Partitions!G41 -> 1.977 | F71: =C71*E71 -> 27.678 | G71: =$H$11*E71 -> 98.85 | H71: =F71*$H$11 -> 1383.9 | I71: =WORKINGS_Partitions!K41 -> 87.141738 | J71: =C71*I71 -> 1219.9843 | K71: =SUM(H71,J71) -> 2603.8843 | L71: =K71/C71 -> 185.99174 | M71: =C71*L71 -> 2603.8843 | N71: 0 | O71: =M71*N71 -> 0
B72: 13mm Gib Overlay to Above | C72: 14 | D72: m | E72: 0.15 | F72: =C72*E72 -> 2.1 | G72: =$H$11*E72 -> 7.5 | H72: =F72*$H$11 -> 105 | I72: 3.5 | J72: =C72*I72 -> 49 | K72: =SUM(H72,J72) -> 154 | L72: =K72/C72 -> 11 | M72: =C72*L72 -> 154 | N72: 0 | O72: =M72*N72 -> 0
B74: (P-11) Potters Aluminium Glazing | C74: Refer Potters Trade
B75: (P-11) Bulkhead Structure | C75: 11 | D75: m | E75: =WORKINGS_Partitions!G41 -> 1.977 | F75: =C75*E75 -> 21.747 | G75: =$H$11*E75 -> 98.85 | H75: =F75*$H$11 -> 1087.35 | I75: =WORKINGS_Partitions!K41 -> 87.141738 | J75: =C75*I75 -> 958.55912 | K75: =SUM(H75,J75) -> 2045.9091 | L75: =K75/C75 -> 185.99174 | M75: =C75*L75 -> 2045.9091 | N75: 0 | O75: =M75*N75 -> 0
B76: MDF Capping Strip - 242mm Wide | C76: Not Required, Refer Brevity Design
B77: 13mm Gib Overlay to Above | C77: 11 | D77: m | E77: 0.15 | F77: =C77*E77 -> 1.65 | G77: =$H$11*E77 -> 7.5 | H77: =F77*$H$11 -> 82.5 | I77: 3.5 | J77: =C77*I77 -> 38.5 | K77: =SUM(H77,J77) -> 121 | L77: =K77/C77 -> 11 | M77: =C77*L77 -> 121 | N77: 0 | O77: =M77*N77 -> 0
B79: (P-20) 92mm x 0.75 Stud @ 400 crs with 1.15 Head Track and 0.70 Base Track with Nogging Track | C79: 114 | D79: m2 | E79: 0.4 | F79: =C79*E79 -> 45.6 | G79: =$H$11*E79 -> 20 | H79: =F79*$H$11 -> 2280 | I79: 22.06 | J79: =C79*I79 -> 2514.84 | K79: =SUM(H79,J79) -> 4794.84 | L79: =K79/C79 -> 42.06 | M79: =C79*L79 -> 4794.84 | N79: 0 | O79: =M79*N79 -> 0 | P79: 29 | Q79: 3.9 | R79: =(P79/0.4)*Q79 -> 282.75
B81: (P-20A) Bulkhead Structure | C81: 18 | D81: m | E81: =WORKINGS_Partitions!G76 -> 0.72041667 | F81: =C81*E81 -> 12.9675 | G81: =$H$11*E81 -> 36.020833 | H81: =F81*$H$11 -> 648.375 | I81: =WORKINGS_Partitions!K76 -> 32.029583 | J81: =C81*I81 -> 576.5325 | K81: =SUM(H81,J81) -> 1224.9075 | L81: =K81/C81 -> 68.050417 | M81: =C81*L81 -> 1224.9075 | N81: 0 | O81: =M81*N81 -> 0
B82: (P-20A) 92mm x 0.75 Stud @ 400 crs with 1.15 Head Track and 0.70 Base Track with Nogging Track | C82: 72 | D82: m2 | E82: 0.4 | F82: =C82*E82 -> 28.8 | G82: =$H$11*E82 -> 20 | H82: =F82*$H$11 -> 1440 | I82: 22.2 | J82: =C82*I82 -> 1598.4 | K82: =SUM(H82,J82) -> 3038.4 | L82: =K82/C82 -> 42.2 | M82: =C82*L82 -> 3038.4 | N82: 0 | O82: =M82*N82 -> 0 | P82: 18 | Q82: 3.9 | R82: =(P82/0.4)*Q82 -> 175.5
B84: (P-21) 92mm x 0.75 Stud @ 400 crs with 1.15 Head Track and 0.70 Base Track | C84: 84 | D84: m2 | E84: 0.43 | F84: =C84*E84 -> 36.12 | G84: =$H$11*E84 -> 21.5 | H84: =F84*$H$11 -> 1806 | I84: 24.68 | J84: =C84*I84 -> 2073.12 | K84: =SUM(H84,J84) -> 3879.12 | L84: =K84/C84 -> 46.18 | M84: =C84*L84 -> 3879.12 | N84: 0 | O84: =M84*N84 -> 0 | P84: 29 | Q84: 2.95 | R84: =(P84/0.4)*Q84 -> 213.875
B86: (P-21A) 92mm x 0.75 Stud @ 400 crs with 1.15 Head Track and 0.70 Base Track | C86: 16 | D86: m2 | E86: 0.45 | F86: =C86*E86 -> 7.2 | G86: =$H$11*E86 -> 22.5 | H86: =F86*$H$11 -> 360 | I86: 25.99 | J86: =C86*I86 -> 415.84 | K86: =SUM(H86,J86) -> 775.84 | L86: =K86/C86 -> 48.49 | M86: =C86*L86 -> 775.84 | N86: 0 | O86: =M86*N86 -> 0 | P86: 5 | Q86: 2.9 | R86: =(P86/0.4)*Q86 -> 36.25
B87: MDF Capping Strip - 241mm Wide | C87: 5 | D87: m | E87: 0.25 | F87: =C87*E87 -> 1.25 | G87: =$H$11*E87 -> 12.5 | H87: =F87*$H$11 -> 62.5 | I87: 23.84 | J87: =C87*I87 -> 119.2 | K87: =SUM(H87,J87) -> 181.7 | L87: =K87/C87 -> 36.34 | M87: =C87*L87 -> 181.7 | N87: 0 | O87: =M87*N87 -> 0
B88: 13mm Gib Overlay to Above | C88: 5 | D88: m | E88: 0.15 | F88: =C88*E88 -> 0.75 | G88: =$H$11*E88 -> 7.5 | H88: =F88*$H$11 -> 37.5 | I88: 3.5 | J88: =C88*I88 -> 17.5 | K88: =SUM(H88,J88) -> 55 | L88: =K88/C88 -> 11 | M88: =C88*L88 -> 55 | N88: 0 | O88: =M88*N88 -> 0
B90: (P-23) 92mm x 0.75 Stud @ 400 crs with 0.70 Head Track and 0.70 Base Track | C90: 15 | D90: m2 | E90: 0.44 | F90: =C90*E90 -> 6.6 | G90: =$H$11*E90 -> 22 | H90: =F90*$H$11 -> 330 | I90: 23.6 | J90: =C90*I90 -> 354 | K90: =SUM(H90,J90) -> 684 | L90: =K90/C90 -> 45.6 | M90: =C90*L90 -> 684 | N90: 0 | O90: =M90*N90 -> 0 | P90: 5 | Q90: 2.95 | R90: =(P90/0.4)*Q90 -> 36.875
B92: (P-23A) 92mm x 0.75 Stud @ 400 crs with 1.15 Head Track and 0.70 Base Track | C92: 52 | D92: m2 | E92: 0.45 | F92: =C92*E92 -> 23.4 | G92: =$H$11*E92 -> 22.5 | H92: =F92*$H$11 -> 1170 | I92: 25.01 | J92: =C92*I92 -> 1300.52 | K92: =SUM(H92,J92) -> 2470.52 | L92: =K92/C92 -> 47.51 | M92: =C92*L92 -> 2470.52 | N92: 0 | O92: =M92*N92 -> 0 | P92: 18 | Q92: 2.9 | R92: =(P92/0.4)*Q92 -> 130.5
B93: MDF Capping Strip - 228mm Wide | C93: 18 | D93: m | E93: 0.25 | F93: =C93*E93 -> 4.5 | G93: =$H$11*E93 -> 12.5 | H93: =F93*$H$11 -> 225 | I93: 23.84 | J93: =C93*I93 -> 429.12 | K93: =SUM(H93,J93) -> 654.12 | L93: =K93/C93 -> 36.34 | M93: =C93*L93 -> 654.12 | N93: 0 | O93: =M93*N93 -> 0
B94: 13mm Gib Overlay to Above | C94: 18 | D94: m | E94: 0.15 | F94: =C94*E94 -> 2.7 | G94: =$H$11*E94 -> 7.5 | H94: =F94*$H$11 -> 135 | I94: 3.5 | J94: =C94*I94 -> 63 | K94: =SUM(H94,J94) -> 198 | L94: =K94/C94 -> 11 | M94: =C94*L94 -> 198 | N94: 0 | O94: =M94*N94 -> 0
B96: (P-23B) Bulkhead Structure | C96: 5 | D96: m | E96: =WORKINGS_Partitions!G89 -> 1.005 | F96: =C96*E96 -> 5.025 | G96: =$H$11*E96 -> 50.25 | H96: =F96*$H$11 -> 251.25 | I96: =WORKINGS_Partitions!K89 -> 32.238942 | J96: =C96*I96 -> 161.19471 | K96: =SUM(H96,J96) -> 412.44471 | L96: =K96/C96 -> 82.488942 | M96: =C96*L96 -> 412.44471 | N96: 0 | O96: =M96*N96 -> 0
B97: (P-23B) 92mm x 0.75 Stud @ 400 crs with 1.15 Head Track and 0.70 Base Track | C97: 14 | D97: m2 | E97: 0.43 | F97: =C97*E97 -> 6.02 | G97: =$H$11*E97 -> 21.5 | H97: =F97*$H$11 -> 301 | I97: 25.01 | J97: =C97*I97 -> 350.14 | K97: =SUM(H97,J97) -> 651.14 | L97: =K97/C97 -> 46.51 | M97: =C97*L97 -> 651.14 | N97: 0 | O97: =M97*N97 -> 0 | P97: 5 | Q97: 2.9 | R97: =(P97/0.4)*Q97 -> 36.25
B98: MDF Capping Strip - 228mm Wide | C98: 5 | D98: m | E98: 0.25 | F98: =C98*E98 -> 1.25 | G98: =$H$11*E98 -> 12.5 | H98: =F98*$H$11 -> 62.5 | I98: 23.84 | J98: =C98*I98 -> 119.2 | K98: =SUM(H98,J98) -> 181.7 | L98: =K98/C98 -> 36.34 | M98: =C98*L98 -> 181.7 | N98: 0 | O98: =M98*N98 -> 0
B99: 13mm Gib Overlay to Above | C99: 5 | D99: m | E99: 0.15 | F99: =C99*E99 -> 0.75 | G99: =$H$11*E99 -> 7.5 | H99: =F99*$H$11 -> 37.5 | I99: 3.5 | J99: =C99*I99 -> 17.5 | K99: =SUM(H99,J99) -> 55 | L99: =K99/C99 -> 11 | M99: =C99*L99 -> 55 | N99: 0 | O99: =M99*N99 -> 0
B101: Trackloks - Part Height Walls | C101: 18 | D101: no | E101: 0.75 | F101: =C101*E101 -> 13.5 | G101: =$H$11*E101 -> 37.5 | H101: =F101*$H$11 -> 675 | I101: 85.17 | J101: =C101*I101 -> 1533.06 | K101: =SUM(H101,J101) -> 2208.06 | L101: =K101/C101 -> 122.67 | M101: =C101*L101 -> 2208.06 | N101: 0 | O101: =M101*N101 -> 0
R102: =SUM(R28:R101) -> 2005.125
B103: Trackloks - TB-02 | C103: Refer Featurecraft Trade
B105: Bridge to Confloor | C105: =SUM(P79,P82) -> 47 | D105: m | E105: 0.25 | F105: =C105*E105 -> 11.75 | G105: =$H$11*E105 -> 12.5 | H105: =F105*$H$11 -> 587.5 | I105: 15 | J105: =C105*I105 -> 705 | K105: =SUM(H105,J105) -> 1292.5 | L105: =K105/C105 -> 27.5 | M105: =C105*L105 -> 1292.5 | N105: 0 | O105: =M105*N105 -> 0
B106: EV Stud to Corners/Intersections | C106: 285 | D106: m | E106: 0.09 | F106: =C106*E106 -> 25.65 | G106: =$H$11*E106 -> 4.5 | H106: =F106*$H$11 -> 1282.5 | I106: 5.61 | J106: =C106*I106 -> 1598.85 | K106: =SUM(H106,J106) -> 2881.35 | L106: =K106/C106 -> 10.11 | M106: =C106*L106 -> 2881.35 | N106: 0 | O106: =M106*N106 -> 0
B107: Plywood Support/Nogging - TV's | C107: 6 | D107: item | E107: 1.5 | F107: =C107*E107 -> 9 | G107: =$H$11*E107 -> 75 | H107: =F107*$H$11 -> 450 | I107: 139 | J107: =C107*I107 -> 834 | K107: =SUM(H107,J107) -> 1284 | L107: =K107/C107 -> 214 | M107: =C107*L107 -> 1284 | N107: 0 | O107: =M107*N107 -> 0
B108: Plywood Support/Nogging - Focus Shelf | C108: 3 | D108: item | E108: 1 | F108: =C108*E108 -> 3 | G108: =$H$11*E108 -> 50 | H108: =F108*$H$11 -> 150 | I108: 70 | J108: =C108*I108 -> 210 | K108: =SUM(H108,J108) -> 360 | L108: =K108/C108 -> 120 | M108: =C108*L108 -> 360 | N108: 0 | O108: =M108*N108 -> 0
B109: Horizontal Nogging to pick up Featurecarft TB.01 | C109: 92 | D109: m | E109: 0.1 | F109: =C109*E109 -> 9.2 | G109: =$H$11*E109 -> 5 | H109: =F109*$H$11 -> 460 | I109: 10.1 | J109: =C109*I109 -> 929.2 | K109: =SUM(H109,J109) -> 1389.2 | L109: =K109/C109 -> 15.1 | M109: =C109*L109 -> 1389.2 | N109: 0 | O109: =M109*N109 -> 0
B111: Battening to Columns to take Curveline | C111: 19 | D111: no | E111: 2.5 | F111: =C111*E111 -> 47.5 | G111: =$H$11*E111 -> 125 | H111: =F111*$H$11 -> 2375 | I111: 175 | J111: =C111*I111 -> 3325 | K111: =SUM(H111,J111) -> 5700 | L111: =K111/C111 -> 300 | M111: =C111*L111 -> 5700 | N111: 0 | O111: =M111*N111 -> 0
B114: Level 6:
B116: (P-10) Potters Aluminium Glazing | C116: Refer Potters Trade
B117: (P-10) Bulkhead Structure | C117: 48 | D117: m | E117: =WORKINGS_Partitions!G41 -> 1.977 | F117: =C117*E117 -> 94.896 | G117: =$H$11*E117 -> 98.85 | H117: =F117*$H$11 -> 4744.8 | I117: =WORKINGS_Partitions!K41 -> 87.141738 | J117: =C117*I117 -> 4182.8034 | K117: =SUM(H117,J117) -> 8927.6034 | L117: =K117/C117 -> 185.99174 | M117: =C117*L117 -> 8927.6034 | N117: 0 | O117: =M117*N117 -> 0
B118: 13mm Gib Overlay to Above | C118: 48 | D118: m | E118: 0.15 | F118: =C118*E118 -> 7.2 | G118: =$H$11*E118 -> 7.5 | H118: =F118*$H$11 -> 360 | I118: 3.5 | J118: =C118*I118 -> 168 | K118: =SUM(H118,J118) -> 528 | L118: =K118/C118 -> 11 | M118: =C118*L118 -> 528 | N118: 0 | O118: =M118*N118 -> 0
B120: (P-10) Bulkhead Structure - Adjust for ID 502, Detail 6 Coffer Detail | C120: 14 | D120: m
B122: (P-12) Bulkhead Structure | C122: 10 | D122: m | E122: =WORKINGS_Partitions!G62 -> 1.27 | F122: =C122*E122 -> 12.7 | G122: =$H$11*E122 -> 63.5 | H122: =F122*$H$11 -> 635 | I122: =WORKINGS_Partitions!K62 -> 68.029056 | J122: =C122*I122 -> 680.29056 | K122: =SUM(H122,J122) -> 1315.2906 | L122: =K122/C122 -> 131.52906 | M122: =C122*L122 -> 1315.2906 | N122: 0 | O122: =M122*N122 -> 0
B124: (P-13) | C124: Refer Potters Trade/Suspended Ceilings
B126: (P-20) 92mm x 0.75 Stud @ 400 crs with 1.15 Head Track and 0.70 Base Track with Nogging Track | C126: 239 | D126: m2 | E126: 0.4 | F126: =C126*E126 -> 95.6 | G126: =$H$11*E126 -> 20 | H126: =F126*$H$11 -> 4780 | I126: 21.02 | J126: =C126*I126 -> 5023.78 | K126: =SUM(H126,J126) -> 9803.78 | L126: =K126/C126 -> 41.02 | M126: =C126*L126 -> 9803.78 | N126: 0 | O126: =M126*N126 -> 0 | P126: 64 | Q126: 4.4 | R126: =(P126/0.4)*Q126 -> 704
B128: (P-20A) Bulkhead Structure | C128: 50 | D128: m | E128: =WORKINGS_Partitions!G76 -> 0.72041667 | F128: =C128*E128 -> 36.020833 | G128: =$H$11*E128 -> 36.020833 | H128: =F128*$H$11 -> 1801.0417 | I128: =WORKINGS_Partitions!K76 -> 32.029583 | J128: =C128*I128 -> 1601.4792 | K128: =SUM(H128,J128) -> 3402.5208 | L128: =K128/C128 -> 68.050417 | M128: =C128*L128 -> 3402.5208 | N128: 0 | O128: =M128*N128 -> 0 | P128: 40 | Q128: 4.4 | R128: =(P128/0.4)*Q128 -> 440
B129: (P-20A) 92mm x 0.75 Stud @ 400 crs with 1.15 Head Track and 0.70 Base Track with Nogging Track | C129: 221 | D129: m2 | E129: 0.4 | F129: =C129*E129 -> 88.4 | G129: =$H$11*E129 -> 20 | H129: =F129*$H$11 -> 4420 | I129: 21.08 | J129: =C129*I129 -> 4658.68 | K129: =SUM(H129,J129) -> 9078.68 | L129: =K129/C129 -> 41.08 | M129: =C129*L129 -> 9078.68 | N129: 0 | O129: =M129*N129 -> 0
B131: (P-20A) Bulkhead Structure - Adjust for ID 502, Detail 6 Coffer Detail | C131: 30 | D131: m
B133: (P-23) 92mm x 0.75 Stud @ 400 crs with 0.70 Head Track and 0.70 Base Track | C133: 58 | D133: m2 | E133: 0.45 | F133: =C133*E133 -> 26.1 | G133: =$H$11*E133 -> 22.5 | H133: =F133*$H$11 -> 1305 | I133: 22.78 | J133: =C133*I133 -> 1321.24 | K133: =SUM(H133,J133) -> 2626.24 | L133: =K133/C133 -> 45.28 | M133: =C133*L133 -> 2626.24 | N133: 0 | O133: =M133*N133 -> 0 | P133: 19 | Q133: 3 | R133: =(P133/0.4)*Q133 -> 142.5
B135: (P-23) Bulkhead Structure - Adjust for ID 502, Detail 6 Coffer Detail | C135: 7 | D135: m
B137: (P-23A) 92mm x 0.75 Stud @ 400 crs with 1.15 Head Track and 0.70 Base Track | C137: 10 | D137: m2 | E137: 0.45 | F137: =C137*E137 -> 4.5 | G137: =$H$11*E137 -> 22.5 | H137: =F137*$H$11 -> 225 | I137: 26.51 | J137: =C137*I137 -> 265.1 | K137: =SUM(H137,J137) -> 490.1 | L137: =K137/C137 -> 49.01 | M137: =C137*L137 -> 490.1 | N137: 0 | O137: =M137*N137 -> 0 | P137: 3 | Q137: 3 | R137: =(P137/0.4)*Q137 -> 22.5
B138: MDF Capping Strip - 228mm Wide | C138: 3 | D138: m | E138: 0.25 | F138: =C138*E138 -> 0.75 | G138: =$H$11*E138 -> 12.5 | H138: =F138*$H$11 -> 37.5 | I138: 23.84 | J138: =C138*I138 -> 71.52 | K138: =SUM(H138,J138) -> 109.02 | L138: =K138/C138 -> 36.34 | M138: =C138*L138 -> 109.02 | N138: 0 | O138: =M138*N138 -> 0
B139: 13mm Gib Overlay to Above | C139: 3 | D139: m | E139: 0.15 | F139: =C139*E139 -> 0.45 | G139: =$H$11*E139 -> 7.5 | H139: =F139*$H$11 -> 22.5 | I139: 3.5 | J139: =C139*I139 -> 10.5 | K139: =SUM(H139,J139) -> 33 | L139: =K139/C139 -> 11 | M139: =C139*L139 -> 33 | N139: 0 | O139: =M139*N139 -> 0
B141: (P-23A) Bulkhead Structure - Adjust for ID 502, Detail 6 Coffer Detail | C141: 3 | D141: m
B143: (P-23S) 92mm x 0.75 Stud @ 400 crs with 0.70 Head Track and 0.70 Base Track | C143: 13 | D143: m2 | E143: 0.4 | F143: =C143*E143 -> 5.2 | G143: =$H$11*E143 -> 20 | H143: =F143*$H$11 -> 260 | I143: 22.39 | J143: =C143*I143 -> 291.07 | K143: =SUM(H143,J143) -> 551.07 | L143: =K143/C143 -> 42.39 | M143: =C143*L143 -> 551.07 | N143: 0 | O143: =M143*N143 -> 0 | P143: 4 | Q143: 3 | R143: =(P143/0.4)*Q143 -> 30
B145: (P-23S) Bulkhead Structure - Adjust for ID 502, Detail 6 Coffer Detail | C145: 4 | D145: m
B147: (P-23AS) 92mm x 0.75 Stud @ 400 crs with 1.15 Head Track and 0.70 Base Track | C147: 7 | D147: m2 | E147: 0.45 | F147: =C147*E147 -> 3.15 | G147: =$H$11*E147 -> 22.5 | H147: =F147*$H$11 -> 157.5 | I147: 27.63 | J147: =C147*I147 -> 193.41 | K147: =SUM(H147,J147) -> 350.91 | L147: =K147/C147 -> 50.13 | M147: =C147*L147 -> 350.91 | N147: 0 | O147: =M147*N147 -> 0 | P147: 2 | Q147: 3 | R147: =(P147/0.4)*Q147 -> 15
B148: MDF Capping Strip - 228mm Wide | C148: 2 | D148: m | E148: 0.25 | F148: =C148*E148 -> 0.5 | G148: =$H$11*E148 -> 12.5 | H148: =F148*$H$11 -> 25 | I148: 23.84 | J148: =C148*I148 -> 47.68 | K148: =SUM(H148,J148) -> 72.68 | L148: =K148/C148 -> 36.34 | M148: =C148*L148 -> 72.68 | N148: 0 | O148: =M148*N148 -> 0
B149: 13mm Gib Overlay to Above | C149: 2 | D149: m | E149: 0.15 | F149: =C149*E149 -> 0.3 | G149: =$H$11*E149 -> 7.5 | H149: =F149*$H$11 -> 15 | I149: 3.5 | J149: =C149*I149 -> 7 | K149: =SUM(H149,J149) -> 22 | L149: =K149/C149 -> 11 | M149: =C149*L149 -> 22 | N149: 0 | O149: =M149*N149 -> 0
B151: (P-23AS) Bulkhead Structure - Adjust for ID 502, Detail 6 Coffer Detail | C151: 2 | D151: m
B153: (P-24) TWIN WALL - 64mm x 0.75 Stud @ 400 crs with 0.70 Head Track and 0.70 Base Track | C153: 31 | D153: m2 | E153: 0.7 | F153: =C153*E153 -> 21.7 | G153: =$H$11*E153 -> 35 | H153: =F153*$H$11 -> 1085 | I153: 38.16 | J153: =C153*I153 -> 1182.96 | K153: =SUM(H153,J153) -> 2267.96 | L153: =K153/C153 -> 73.16 | M153: =C153*L153 -> 2267.96 | N153: 0 | O153: =M153*N153 -> 0
B155: Trackloks - Part Height Walls | C155: 6 | D155: no | E155: 1 | F155: =C155*E155 -> 6 | G155: =$H$11*E155 -> 50 | H155: =F155*$H$11 -> 300 | I155: 90.71 | J155: =C155*I155 -> 544.26 | K155: =SUM(H155,J155) -> 844.26 | L155: =K155/C155 -> 140.71 | M155: =C155*L155 -> 844.26 | N155: 0 | O155: =M155*N155 -> 0
...

Sheet Partitions SPEC Rates
B1: =Summary!B1 -> Ceilings Unlimited
B2: =Summary!B2 -> Craigs Investment Partners - Fitout
B3: =Summary!B3 -> Tauranga
B6: =Summary!B5 -> 46043
B9: =Summary!B119 -> Partitions
H11: 50
A12: Item | B12: Description | C12: Qty | D12: Unit | E12: Constant | F12: Constant X Unit = Total HRS | G12: $ Lab per Unit | H12: Total Labour | I12: Materials per Unit | J12: Total Materials | K12: Total Labour & Materials | L12: Total Labour & Materials Per Unit | M12: Total | N12: % Complete | O12: Claim
B14: Level 4:
B16: (P-10) Potters Aluminium Glazing | C16: Refer Potters Trade
B17: (P-10) Bulkhead Structure | C17: 4 | D17: m | E17: ='WORKINGS_Partitions SPEC Rates'!G41 -> 1.977 | F17: =C17*E17 -> 7.908 | G17: =$H$11*E17 -> 98.85 | H17: =F17*$H$11 -> 395.4 | I17: ='WORKINGS_Partitions SPEC Rates'!K41 -> 68.917518 | J17: =C17*I17 -> 275.67007 | K17: =SUM(H17,J17) -> 671.07007 | L17: =K17/C17 -> 167.76752 | M17: =C17*L17 -> 671.07007 | N17: 0 | O17: =M17*N17 -> 0
B18: 13mm Gib Overlay to Above | C18: 4 | D18: m | E18: 0.15 | F18: =C18*E18 -> 0.6 | G18: =$H$11*E18 -> 7.5 | H18: =F18*$H$11 -> 30 | I18: 3.5 | J18: =C18*I18 -> 14 | K18: =SUM(H18,J18) -> 44 | L18: =K18/C18 -> 11 | M18: =C18*L18 -> 44 | N18: 0 | O18: =M18*N18 -> 0
B20: (P-11) Potters Aluminium Glazing | C20: Refer Potters Trade
B21: (P-11) Bulkhead Structure | C21: 23 | D21: m | E21: ='WORKINGS_Partitions SPEC Rates'!G41 -> 1.977 | F21: =C21*E21 -> 45.471 | G21: =$H$11*E21 -> 98.85 | H21: =F21*$H$11 -> 2273.55 | I21: ='WORKINGS_Partitions SPEC Rates'!K41 -> 68.917518 | J21: =C21*I21 -> 1585.1029 | K21: =SUM(H21,J21) -> 3858.6529 | L21: =K21/C21 -> 167.76752 | M21: =C21*L21 -> 3858.6529 | N21: 0 | O21: =M21*N21 -> 0
B22: MDF Capping Strip - 242mm Wide | C22: Not Required, Refer Brevity Design
B23: 13mm Gib Overlay to Above | C23: 23 | D23: m | E23: 0.15 | F23: =C23*E23 -> 3.45 | G23: =$H$11*E23 -> 7.5 | H23: =F23*$H$11 -> 172.5 | I23: 3.5 | J23: =C23*I23 -> 80.5 | K23: =SUM(H23,J23) -> 253 | L23: =K23/C23 -> 11 | M23: =C23*L23 -> 253 | N23: 0 | O23: =M23*N23 -> 0
B25: (P-13) | C25: Refer Potters Trade/Suspended Ceilings | R25: =SUM(C36,C44,C48,C53,C88,C94,C99,C137,C143) -> 82
B27: (P-20A) Bulkhead Structure | C27: 9 | D27: m | E27: ='WORKINGS_Partitions SPEC Rates'!G76 -> 0.72041667 | F27: =C27*E27 -> 6.48375 | G27: =$H$11*E27 -> 36.020833 | H27: =F27*$H$11 -> 324.1875 | I27: ='WORKINGS_Partitions SPEC Rates'!K76 -> 23.380602 | J27: =C27*I27 -> 210.42542 | K27: =SUM(H27,J27) -> 534.61292 | L27: =K27/C27 -> 59.401435 | M27: =C27*L27 -> 534.61292 | N27: 0 | O27: =M27*N27 -> 0 | R27: 92 x 0.75 Stud | S27: 1.15
B28: (P-20A) 92mm x 0.75 Stud @ 400 crs with 1.15 Head Track and 0.70 Base Track with Nogging Track | C28: 34 | D28: m2 | E28: 0.4 | F28: =C28*E28 -> 13.6 | G28: =$H$11*E28 -> 20 | H28: =F28*$H$11 -> 680 | I28: 17.74 | J28: =C28*I28 -> 603.16 | K28: =SUM(H28,J28) -> 1283.16 | L28: =K28/C28 -> 37.74 | M28: =C28*L28 -> 1283.16 | N28: 0 | O28: =M28*N28 -> 0 | P28: 9 | Q28: 3.9 | R28: =(P28/0.4)*Q28 -> 87.75
B31: (P-21S) 92mm x 0.75 Stud @ 400 crs with 1.15 Head Track and 0.70 Base Track | C31: 19 | D31: m2 | E31: 0.44 | F31: =C31*E31 -> 8.36 | G31: =$H$11*E31 -> 22 | H31: =F31*$H$11 -> 418 | I31: 19.7 | J31: =C31*I31 -> 374.3 | K31: =SUM(H31,J31) -> 792.3 | L31: =K31/C31 -> 41.7 | M31: =C31*L31 -> 792.3 | N31: 0 | O31: =M31*N31 -> 0 | P31: 7 | Q31: 2.95 | R31: =(P31/0.4)*Q31 -> 51.625
B33: (P-21) 92mm x 0.75 Stud @ 400 crs with 1.15 Head Track and 0.70 Base Track | C33: 141 | D33: m2 | E33: 0.43 | F33: =C33*E33 -> 60.63 | G33: =$H$11*E33 -> 21.5 | H33: =F33*$H$11 -> 3031.5 | I33: 19 | J33: =C33*I33 -> 2679 | K33: =SUM(H33,J33) -> 5710.5 | L33: =K33/C33 -> 40.5 | M33: =C33*L33 -> 5710.5 | N33: 0 | O33: =M33*N33 -> 0 | P33: 48 | Q33: 2.95 | R33: =(P33/0.4)*Q33 -> 354
B35: (P-21A) 92mm x 0.75 Stud @ 400 crs with 1.15 Head Track and 0.70 Base Track | C35: 27 | D35: m2 | E35: 0.43 | F35: =C35*E35 -> 11.61 | G35: =$H$11*E35 -> 21.5 | H35: =F35*$H$11 -> 580.5 | I35: 19.52 | J35: =C35*I35 -> 527.04 | K35: =SUM(H35,J35) -> 1107.54 | L35: =K35/C35 -> 41.02 | M35: =C35*L35 -> 1107.54 | N35: 0 | O35: =M35*N35 -> 0 | P35: 9 | Q35: 2.95 | R35: =(P35/0.4)*Q35 -> 66.375
B36: MDF Capping Strip - 241mm Wide | C36: 9 | D36: m | E36: 0.25 | F36: =C36*E36 -> 2.25 | G36: =$H$11*E36 -> 12.5 | H36: =F36*$H$11 -> 112.5 | I36: 23.84 | J36: =C36*I36 -> 214.56 | K36: =SUM(H36,J36) -> 327.06 | L36: =K36/C36 -> 36.34 | M36: =C36*L36 -> 327.06 | N36: 0 | O36: =M36*N36 -> 0
B37: 13mm Gib Overlay to Above | C37: 9 | D37: m | E37: 0.15 | F37: =C37*E37 -> 1.35 | G37: =$H$11*E37 -> 7.5 | H37: =F37*$H$11 -> 67.5 | I37: 3.5 | J37: =C37*I37 -> 31.5 | K37: =SUM(H37,J37) -> 99 | L37: =K37/C37 -> 11 | M37: =C37*L37 -> 99 | N37: 0 | O37: =M37*N37 -> 0
B39: (P-23) 92mm x 0.75 Stud @ 400 crs with 0.70 Head Track and 0.70 Base Track | C39: 84 | D39: m2 | E39: 0.42 | F39: =C39*E39 -> 35.28 | G39: =$H$11*E39 -> 21 | H39: =F39*$H$11 -> 1764 | I39: 19.08 | J39: =C39*I39 -> 1602.72 | K39: =SUM(H39,J39) -> 3366.72 | L39: =K39/C39 -> 40.08 | M39: =C39*L39 -> 3366.72 | N39: 0 | O39: =M39*N39 -> 0 | P39: 29 | Q39: 2.95 | R39: =(P39/0.4)*Q39 -> 213.875
B41: (P-23S) 92mm x 0.75 Stud @ 400 crs with 0.70 Head Track and 0.70 Base Track | C41: 12 | D41: m2 | E41: 0.45 | F41: =C41*E41 -> 5.4 | G41: =$H$11*E41 -> 22.5 | H41: =F41*$H$11 -> 270 | I41: 19.89 | J41: =C41*I41 -> 238.68 | K41: =SUM(H41,J41) -> 508.68 | L41: =K41/C41 -> 42.39 | M41: =C41*L41 -> 508.68 | N41: 0 | O41: =M41*N41 -> 0 | P41: 4 | Q41: 2.95 | R41: =(P41/0.4)*Q41 -> 29.5
B43: (P-23AS) 92mm x 0.75 Stud @ 400 crs with 1.15 Head Track and 0.70 Base Track | C43: 12 | D43: m2 | E43: 0.45 | F43: =C43*E43 -> 5.4 | G43: =$H$11*E43 -> 22.5 | H43: =F43*$H$11 -> 270 | I43: 20.59 | J43: =C43*I43 -> 247.08 | K43: =SUM(H43,J43) -> 517.08 | L43: =K43/C43 -> 43.09 | M43: =C43*L43 -> 517.08 | N43: 0 | O43: =M43*N43 -> 0 | P43: 4 | Q43: 2.9 | R43: =(P43/0.4)*Q43 -> 29
B44: MDF Capping Strip - 228mm Wide | C44: 4 | D44: m | E44: 0.25 | F44: =C44*E44 -> 1 | G44: =$H$11*E44 -> 12.5 | H44: =F44*$H$11 -> 50 | I44: 23.84 | J44: =C44*I44 -> 95.36 | K44: =SUM(H44,J44) -> 145.36 | L44: =K44/C44 -> 36.34 | M44: =C44*L44 -> 145.36 | N44: 0 | O44: =M44*N44 -> 0
B45: 13mm Gib Overlay to Above | C45: 4 | D45: m | E45: 0.15 | F45: =C45*E45 -> 0.6 | G45: =$H$11*E45 -> 7.5 | H45: =F45*$H$11 -> 30 | I45: 3.5 | J45: =C45*I45 -> 14 | K45: =SUM(H45,J45) -> 44 | L45: =K45/C45 -> 11 | M45: =C45*L45 -> 44 | N45: 0 | O45: =M45*N45 -> 0
B47: (P-23A) 92mm x 0.75 Stud @ 400 crs with 1.15 Head Track and 0.70 Base Track | C47: 74 | D47: m2 | E47: 0.43 | F47: =C47*E47 -> 31.82 | G47: =$H$11*E47 -> 21.5 | H47: =F47*$H$11 -> 1591 | I47: 19.38 | J47: =C47*I47 -> 1434.12 | K47: =SUM(H47,J47) -> 3025.12 | L47: =K47/C47 -> 40.88 | M47: =C47*L47 -> 3025.12 | N47: 0 | O47: =M47*N47 -> 0 | P47: 25 | Q47: 2.9 | R47: =(P47/0.4)*Q47 -> 181.25
B48: MDF Capping Strip - 228mm Wide | C48: 25 | D48: m | E48: 0.25 | F48: =C48*E48 -> 6.25 | G48: =$H$11*E48 -> 12.5 | H48: =F48*$H$11 -> 312.5 | I48: 23.84 | J48: =C48*I48 -> 596 | K48: =SUM(H48,J48) -> 908.5 | L48: =K48/C48 -> 36.34 | M48: =C48*L48 -> 908.5 | N48: 0 | O48: =M48*N48 -> 0
B49: 13mm Gib Overlay to Above | C49: 25 | D49: m | E49: 0.15 | F49: =C49*E49 -> 3.75 | G49: =$H$11*E49 -> 7.5 | H49: =F49*$H$11 -> 187.5 | I49: 3.5 | J49: =C49*I49 -> 87.5 | K49: =SUM(H49,J49) -> 275 | L49: =K49/C49 -> 11 | M49: =C49*L49 -> 275 | N49: 0 | O49: =M49*N49 -> 0
B51: (P-23B) Bulkhead Structure | C51: 11 | D51: m | E51: =WORKINGS_Partitions!G89 -> 1.005 | F51: =C51*E51 -> 11.055 | G51: =$H$11*E51 -> 50.25 | H51: =F51*$H$11 -> 552.75 | I51: ='WORKINGS_Partitions SPEC Rates'!K89 -> 26.385192 | J51: =C51*I51 -> 290.23711 | K51: =SUM(H51,J51) -> 842.98711 | L51: =K51/C51 -> 76.635192 | M51: =C51*L51 -> 842.98711 | N51: 0 | O51: =M51*N51 -> 0
B52: (P-23B) 92mm x 0.75 Stud @ 400 crs with 1.15 Head Track and 0.70 Base Track | C52: 31 | D52: m2 | E52: 0.44 | F52: =C52*E52 -> 13.64 | G52: =$H$11*E52 -> 22 | H52: =F52*$H$11 -> 682 | I52: 19.67 | J52: =C52*I52 -> 609.77 | K52: =SUM(H52,J52) -> 1291.77 | L52: =K52/C52 -> 41.67 | M52: =C52*L52 -> 1291.77 | N52: 0 | O52: =M52*N52 -> 0 | P52: 11 | Q52: 2.9 | R52: =(P52/0.4)*Q52 -> 79.75
B53: MDF Capping Strip - 228mm Wide | C53: 11 | D53: m | E53: 0.25 | F53: =C53*E53 -> 2.75 | G53: =$H$11*E53 -> 12.5 | H53: =F53*$H$11 -> 137.5 | I53: 23.84 | J53: =C53*I53 -> 262.24 | K53: =SUM(H53,J53) -> 399.74 | L53: =K53/C53 -> 36.34 | M53: =C53*L53 -> 399.74 | N53: 0 | O53: =M53*N53 -> 0
B54: 13mm Gib Overlay to Above | C54: 11 | D54: m | E54: 0.15 | F54: =C54*E54 -> 1.65 | G54: =$H$11*E54 -> 7.5 | H54: =F54*$H$11 -> 82.5 | I54: 3.5 | J54: =C54*I54 -> 38.5 | K54: =SUM(H54,J54) -> 121 | L54: =K54/C54 -> 11 | M54: =C54*L54 -> 121 | N54: 0 | O54: =M54*N54 -> 0
B56: Trackloks - Part Height Walls | C56: 43 | D56: no | E56: 0.75 | F56: =C56*E56 -> 32.25 | G56: =$H$11*E56 -> 37.5 | H56: =F56*$H$11 -> 1612.5 | I56: 82.5 | J56: =C56*I56 -> 3547.5 | K56: =SUM(H56,J56) -> 5160 | L56: =K56/C56 -> 120 | M56: =C56*L56 -> 5160 | N56: 0 | O56: =M56*N56 -> 0
B58: Trackloks - TB-02 | C58: Refer Featurecraft Trade
B60: Bridge to Confloor | C60: =SUM(P28) -> 9 | D60: m | E60: 0.25 | F60: =C60*E60 -> 2.25 | G60: =$H$11*E60 -> 12.5 | H60: =F60*$H$11 -> 112.5 | I60: 15 | J60: =C60*I60 -> 135 | K60: =SUM(H60,J60) -> 247.5 | L60: =K60/C60 -> 27.5 | M60: =C60*L60 -> 247.5 | N60: 0 | O60: =M60*N60 -> 0
B61: EV Stud to Corners/Intersections | C61: 492 | D61: m | E61: 0.09 | F61: =C61*E61 -> 44.28 | G61: =$H$11*E61 -> 4.5 | H61: =F61*$H$11 -> 2214 | I61: 5.61 | J61: =C61*I61 -> 2760.12 | K61: =SUM(H61,J61) -> 4974.12 | L61: =K61/C61 -> 10.11 | M61: =C61*L61 -> 4974.12 | N61: 0 | O61: =M61*N61 -> 0
B62: Plywood Support/Nogging - TV's | C62: 7 | D62: item | E62: 1.5 | F62: =C62*E62 -> 10.5 | G62: =$H$11*E62 -> 75 | H62: =F62*$H$11 -> 525 | I62: 139 | J62: =C62*I62 -> 973 | K62: =SUM(H62,J62) -> 1498 | L62: =K62/C62 -> 214 | M62: =C62*L62 -> 1498 | N62: 0 | O62: =M62*N62 -> 0
B63: Plywood Support/Nogging - Focus Shelf | C63: 6 | D63: item | E63: 1 | F63: =C63*E63 -> 6 | G63: =$H$11*E63 -> 50 | H63: =F63*$H$11 -> 300 | I63: 70 | J63: =C63*I63 -> 420 | K63: =SUM(H63,J63) -> 720 | L63: =K63/C63 -> 120 | M63: =C63*L63 -> 720 | N63: 0 | O63: =M63*N63 -> 0
B64: Horizontal Nogging to pick up Featurecarft TB.01 | C64: 136 | D64: m | E64: 0.1 | F64: =C64*E64 -> 13.6 | G64: =$H$11*E64 -> 5 | H64: =F64*$H$11 -> 680 | I64: 10.1 | J64: =C64*I64 -> 1373.6 | K64: =SUM(H64,J64) -> 2053.6 | L64: =K64/C64 -> 15.1 | M64: =C64*L64 -> 2053.6 | N64: 0 | O64: =M64*N64 -> 0
B66: Battening to Columns to take Curveline | C66: 13 | D66: no | E66: 2.5 | F66: =C66*E66 -> 32.5 | G66: =$H$11*E66 -> 125 | H66: =F66*$H$11 -> 1625 | I66: 175 | J66: =C66*I66 -> 2275 | K66: =SUM(H66,J66) -> 3900 | L66: =K66/C66 -> 300 | M66: =C66*L66 -> 3900 | N66: 0 | O66: =M66*N66 -> 0
B69: Level 5:
B71: (P-10) Potters Aluminium Glazing | C71: Refer Potters Trade
B72: (P-10) Bulkhead Structure | C72: 14 | D72: m | E72: ='WORKINGS_Partitions SPEC Rates'!G41 -> 1.977 | F72: =C72*E72 -> 27.678 | G72: =$H$11*E72 -> 98.85 | H72: =F72*$H$11 -> 1383.9 | I72: ='WORKINGS_Partitions SPEC Rates'!K41 -> 68.917518 | J72: =C72*I72 -> 964.84526 | K72: =SUM(H72,J72) -> 2348.7453 | L72: =K72/C72 -> 167.76752 | M72: =C72*L72 -> 2348.7453 | N72: 0 | O72: =M72*N72 -> 0
B73: 13mm Gib Overlay to Above | C73: 14 | D73: m | E73: 0.15 | F73: =C73*E73 -> 2.1 | G73: =$H$11*E73 -> 7.5 | H73: =F73*$H$11 -> 105 | I73: 3.5 | J73: =C73*I73 -> 49 | K73: =SUM(H73,J73) -> 154 | L73: =K73/C73 -> 11 | M73: =C73*L73 -> 154 | N73: 0 | O73: =M73*N73 -> 0
B75: (P-11) Potters Aluminium Glazing | C75: Refer Potters Trade
B76: (P-11) Bulkhead Structure | C76: 11 | D76: m | E76: ='WORKINGS_Partitions SPEC Rates'!G41 -> 1.977 | F76: =C76*E76 -> 21.747 | G76: =$H$11*E76 -> 98.85 | H76: =F76*$H$11 -> 1087.35 | I76: ='WORKINGS_Partitions SPEC Rates'!K41 -> 68.917518 | J76: =C76*I76 -> 758.0927 | K76: =SUM(H76,J76) -> 1845.4427 | L76: =K76/C76 -> 167.76752 | M76: =C76*L76 -> 1845.4427 | N76: 0 | O76: =M76*N76 -> 0
B77: MDF Capping Strip - 242mm Wide | C77: Not Required, Refer Brevity Design
B78: 13mm Gib Overlay to Above | C78: 11 | D78: m | E78: 0.15 | F78: =C78*E78 -> 1.65 | G78: =$H$11*E78 -> 7.5 | H78: =F78*$H$11 -> 82.5 | I78: 3.5 | J78: =C78*I78 -> 38.5 | K78: =SUM(H78,J78) -> 121 | L78: =K78/C78 -> 11 | M78: =C78*L78 -> 121 | N78: 0 | O78: =M78*N78 -> 0
B80: (P-20) 92mm x 0.75 Stud @ 400 crs with 1.15 Head Track and 0.70 Base Track with Nogging Track | C80: 114 | D80: m2 | E80: 0.4 | F80: =C80*E80 -> 45.6 | G80: =$H$11*E80 -> 20 | H80: =F80*$H$11 -> 2280 | I80: 17.33 | J80: =C80*I80 -> 1975.62 | K80: =SUM(H80,J80) -> 4255.62 | L80: =K80/C80 -> 37.33 | M80: =C80*L80 -> 4255.62 | N80: 0 | O80: =M80*N80 -> 0 | P80: 29 | Q80: 3.9 | R80: =(P80/0.4)*Q80 -> 282.75
B82: (P-20A) Bulkhead Structure | C82: 18 | D82: m | E82: ='WORKINGS_Partitions SPEC Rates'!G76 -> 0.72041667 | F82: =C82*E82 -> 12.9675 | G82: =$H$11*E82 -> 36.020833 | H82: =F82*$H$11 -> 648.375 | I82: ='WORKINGS_Partitions SPEC Rates'!K76 -> 23.380602 | J82: =C82*I82 -> 420.85084 | K82: =SUM(H82,J82) -> 1069.2258 | L82: =K82/C82 -> 59.401435 | M82: =C82*L82 -> 1069.2258 | N82: 0 | O82: =M82*N82 -> 0
B83: (P-20A) 92mm x 0.75 Stud @ 400 crs with 1.15 Head Track and 0.70 Base Track with Nogging Track | C83: 72 | D83: m2 | E83: 0.4 | F83: =C83*E83 -> 28.8 | G83: =$H$11*E83 -> 20 | H83: =F83*$H$11 -> 1440 | I83: 17.44 | J83: =C83*I83 -> 1255.68 | K83: =SUM(H83,J83) -> 2695.68 | L83: =K83/C83 -> 37.44 | M83: =C83*L83 -> 2695.68 | N83: 0 | O83: =M83*N83 -> 0 | P83: 18 | Q83: 3.9 | R83: =(P83/0.4)*Q83 -> 175.5
B85: (P-21) 92mm x 0.75 Stud @ 400 crs with 1.15 Head Track and 0.70 Base Track | C85: 84 | D85: m2 | E85: 0.43 | F85: =C85*E85 -> 36.12 | G85: =$H$11*E85 -> 21.5 | H85: =F85*$H$11 -> 1806 | I85: 24.68 | J85: =C85*I85 -> 2073.12 | K85: =SUM(H85,J85) -> 3879.12 | L85: =K85/C85 -> 46.18 | M85: =C85*L85 -> 3879.12 | N85: 0 | O85: =M85*N85 -> 0 | P85: 29 | Q85: 2.95 | R85: =(P85/0.4)*Q85 -> 213.875
B87: (P-21A) 92mm x 0.75 Stud @ 400 crs with 1.15 Head Track and 0.70 Base Track | C87: 16 | D87: m2 | E87: 0.45 | F87: =C87*E87 -> 7.2 | G87: =$H$11*E87 -> 22.5 | H87: =F87*$H$11 -> 360 | I87: 25.99 | J87: =C87*I87 -> 415.84 | K87: =SUM(H87,J87) -> 775.84 | L87: =K87/C87 -> 48.49 | M87: =C87*L87 -> 775.84 | N87: 0 | O87: =M87*N87 -> 0 | P87: 5 | Q87: 2.9 | R87: =(P87/0.4)*Q87 -> 36.25
B88: MDF Capping Strip - 241mm Wide | C88: 5 | D88: m | E88: 0.25 | F88: =C88*E88 -> 1.25 | G88: =$H$11*E88 -> 12.5 | H88: =F88*$H$11 -> 62.5 | I88: 23.84 | J88: =C88*I88 -> 119.2 | K88: =SUM(H88,J88) -> 181.7 | L88: =K88/C88 -> 36.34 | M88: =C88*L88 -> 181.7 | N88: 0 | O88: =M88*N88 -> 0
B89: 13mm Gib Overlay to Above | C89: 5 | D89: m | E89: 0.15 | F89: =C89*E89 -> 0.75 | G89: =$H$11*E89 -> 7.5 | H89: =F89*$H$11 -> 37.5 | I89: 3.5 | J89: =C89*I89 -> 17.5 | K89: =SUM(H89,J89) -> 55 | L89: =K89/C89 -> 11 | M89: =C89*L89 -> 55 | N89: 0 | O89: =M89*N89 -> 0
B91: (P-23) 92mm x 0.75 Stud @ 400 crs with 0.70 Head Track and 0.70 Base Track | C91: 15 | D91: m2 | E91: 0.44 | F91: =C91*E91 -> 6.6 | G91: =$H$11*E91 -> 22 | H91: =F91*$H$11 -> 330 | I91: 19.86 | J91: =C91*I91 -> 297.9 | K91: =SUM(H91,J91) -> 627.9 | L91: =K91/C91 -> 41.86 | M91: =C91*L91 -> 627.9 | N91: 0 | O91: =M91*N91 -> 0 | P91: 5 | Q91: 2.95 | R91: =(P91/0.4)*Q91 -> 36.875
B93: (P-23A) 92mm x 0.75 Stud @ 400 crs with 1.15 Head Track and 0.70 Base Track | C93: 52 | D93: m2 | E93: 0.45 | F93: =C93*E93 -> 23.4 | G93: =$H$11*E93 -> 22.5 | H93: =F93*$H$11 -> 1170 | I93: 19.47 | J93: =C93*I93 -> 1012.44 | K93: =SUM(H93,J93) -> 2182.44 | L93: =K93/C93 -> 41.97 | M93: =C93*L93 -> 2182.44 | N93: 0 | O93: =M93*N93 -> 0 | P93: 18 | Q93: 2.9 | R93: =(P93/0.4)*Q93 -> 130.5
B94: MDF Capping Strip - 228mm Wide | C94: 18 | D94: m | E94: 0.25 | F94: =C94*E94 -> 4.5 | G94: =$H$11*E94 -> 12.5 | H94: =F94*$H$11 -> 225 | I94: 23.84 | J94: =C94*I94 -> 429.12 | K94: =SUM(H94,J94) -> 654.12 | L94: =K94/C94 -> 36.34 | M94: =C94*L94 -> 654.12 | N94: 0 | O94: =M94*N94 -> 0
B95: 13mm Gib Overlay to Above | C95: 18 | D95: m | E95: 0.15 | F95: =C95*E95 -> 2.7 | G95: =$H$11*E95 -> 7.5 | H95: =F95*$H$11 -> 135 | I95: 3.5 | J95: =C95*I95 -> 63 | K95: =SUM(H95,J95) -> 198 | L95: =K95/C95 -> 11 | M95: =C95*L95 -> 198 | N95: 0 | O95: =M95*N95 -> 0
B97: (P-23B) Bulkhead Structure | C97: 5 | D97: m | E97: ='WORKINGS_Partitions SPEC Rates'!G89 -> 1.005 | F97: =C97*E97 -> 5.025 | G97: =$H$11*E97 -> 50.25 | H97: =F97*$H$11 -> 251.25 | I97: ='WORKINGS_Partitions SPEC Rates'!K89 -> 26.385192 | J97: =C97*I97 -> 131.92596 | K97: =SUM(H97,J97) -> 383.17596 | L97: =K97/C97 -> 76.635192 | M97: =C97*L97 -> 383.17596 | N97: 0 | O97: =M97*N97 -> 0
B98: (P-23B) 92mm x 0.75 Stud @ 400 crs with 1.15 Head Track and 0.70 Base Track | C98: 14 | D98: m2 | E98: 0.43 | F98: =C98*E98 -> 6.02 | G98: =$H$11*E98 -> 21.5 | H98: =F98*$H$11 -> 301 | I98: 20.3 | J98: =C98*I98 -> 284.2 | K98: =SUM(H98,J98) -> 585.2 | L98: =K98/C98 -> 41.8 | M98: =C98*L98 -> 585.2 | N98: 0 | O98: =M98*N98 -> 0 | P98: 5 | Q98: 2.9 | R98: =(P98/0.4)*Q98 -> 36.25
B99: MDF Capping Strip - 228mm Wide | C99: 5 | D99: m | E99: 0.25 | F99: =C99*E99 -> 1.25 | G99: =$H$11*E99 -> 12.5 | H99: =F99*$H$11 -> 62.5 | I99: 23.84 | J99: =C99*I99 -> 119.2 | K99: =SUM(H99,J99) -> 181.7 | L99: =K99/C99 -> 36.34 | M99: =C99*L99 -> 181.7 | N99: 0 | O99: =M99*N99 -> 0
B100: 13mm Gib Overlay to Above | C100: 5 | D100: m | E100: 0.15 | F100: =C100*E100 -> 0.75 | G100: =$H$11*E100 -> 7.5 | H100: =F100*$H$11 -> 37.5 | I100: 3.5 | J100: =C100*I100 -> 17.5 | K100: =SUM(H100,J100) -> 55 | L100: =K100/C100 -> 11 | M100: =C100*L100 -> 55 | N100: 0 | O100: =M100*N100 -> 0
B102: Trackloks - Part Height Walls | C102: 18 | D102: no | E102: 0.75 | F102: =C102*E102 -> 13.5 | G102: =$H$11*E102 -> 37.5 | H102: =F102*$H$11 -> 675 | I102: 82.5 | J102: =C102*I102 -> 1485 | K102: =SUM(H102,J102) -> 2160 | L102: =K102/C102 -> 120 | M102: =C102*L102 -> 2160 | N102: 0 | O102: =M102*N102 -> 0
R103: =SUM(R28:R102) -> 2005.125
B104: Trackloks - TB-02 | C104: Refer Featurecraft Trade
B106: Bridge to Confloor | C106: =SUM(P80,P83) -> 47 | D106: m | E106: 0.25 | F106: =C106*E106 -> 11.75 | G106: =$H$11*E106 -> 12.5 | H106: =F106*$H$11 -> 587.5 | I106: 15 | J106: =C106*I106 -> 705 | K106: =SUM(H106,J106) -> 1292.5 | L106: =K106/C106 -> 27.5 | M106: =C106*L106 -> 1292.5 | N106: 0 | O106: =M106*N106 -> 0
B107: EV Stud to Corners/Intersections | C107: 285 | D107: m | E107: 0.09 | F107: =C107*E107 -> 25.65 | G107: =$H$11*E107 -> 4.5 | H107: =F107*$H$11 -> 1282.5 | I107: 5.61 | J107: =C107*I107 -> 1598.85 | K107: =SUM(H107,J107) -> 2881.35 | L107: =K107/C107 -> 10.11 | M107: =C107*L107 -> 2881.35 | N107: 0 | O107: =M107*N107 -> 0
B108: Plywood Support/Nogging - TV's | C108: 6 | D108: item | E108: 1.5 | F108: =C108*E108 -> 9 | G108: =$H$11*E108 -> 75 | H108: =F108*$H$11 -> 450 | I108: 139 | J108: =C108*I108 -> 834 | K108: =SUM(H108,J108) -> 1284 | L108: =K108/C108 -> 214 | M108: =C108*L108 -> 1284 | N108: 0 | O108: =M108*N108 -> 0
B109: Plywood Support/Nogging - Focus Shelf | C109: 3 | D109: item | E109: 1 | F109: =C109*E109 -> 3 | G109: =$H$11*E109 -> 50 | H109: =F109*$H$11 -> 150 | I109: 70 | J109: =C109*I109 -> 210 | K109: =SUM(H109,J109) -> 360 | L109: =K109/C109 -> 120 | M109: =C109*L109 -> 360 | N109: 0 | O109: =M109*N109 -> 0
B110: Horizontal Nogging to pick up Featurecarft TB.01 | C110: 92 | D110: m | E110: 0.1 | F110: =C110*E110 -> 9.2 | G110: =$H$11*E110 -> 5 | H110: =F110*$H$11 -> 460 | I110: 10.1 | J110: =C110*I110 -> 929.2 | K110: =SUM(H110,J110) -> 1389.2 | L110: =K110/C110 -> 15.1 | M110: =C110*L110 -> 1389.2 | N110: 0 | O110: =M110*N110 -> 0
B112: Battening to Columns to take Curveline | C112: 19 | D112: no | E112: 2.5 | F112: =C112*E112 -> 47.5 | G112: =$H$11*E112 -> 125 | H112: =F112*$H$11 -> 2375 | I112: 175 | J112: =C112*I112 -> 3325 | K112: =SUM(H112,J112) -> 5700 | L112: =K112/C112 -> 300 | M112: =C112*L112 -> 5700 | N112: 0 | O112: =M112*N112 -> 0
B115: Level 6:
B117: (P-10) Potters Aluminium Glazing | C117: Refer Potters Trade
B118: (P-10) Bulkhead Structure | C118: 48 | D118: m | E118: 2.14 | F118: =C118*E118 -> 102.72 | G118: =$H$11*E118 -> 107 | H118: =F118*$H$11 -> 5136 | I118: 75.39 | J118: =C118*I118 -> 3618.72 | K118: =SUM(H118,J118) -> 8754.72 | L118: =K118/C118 -> 182.39 | M118: =C118*L118 -> 8754.72 | N118: 0 | O118: =M118*N118 -> 0
B119: 13mm Gib Overlay to Above | C119: 48 | D119: m | E119: 0.15 | F119: =C119*E119 -> 7.2 | G119: =$H$11*E119 -> 7.5 | H119: =F119*$H$11 -> 360 | I119: 3.5 | J119: =C119*I119 -> 168 | K119: =SUM(H119,J119) -> 528 | L119: =K119/C119 -> 11 | M119: =C119*L119 -> 528 | N119: 0 | O119: =M119*N119 -> 0
B121: (P-10) Bulkhead Structure - Adjust for ID 502, Detail 6 Coffer Detail | C121: -14 | D121: m | E121: 0.62 | F121: =C121*E121 -> -8.68 | G121: =$H$11*E121 -> 31 | H121: =F121*$H$11 -> -434 | I121: 17.43 | J121: =C121*I121 -> -244.02 | K121: =SUM(H121,J121) -> -678.02 | L121: =K121/C121 -> 48.43 | M121: =C121*L121 -> -678.02 | N121: 0 | O121: =M121*N121 -> 0
B123: (P-12) Bulkhead Structure | C123: 10 | D123: m | E123: 1.35 | F123: =C123*E123 -> 13.5 | G123: =$H$11*E123 -> 67.5 | H123: =F123*$H$11 -> 675 | I123: 55.48 | J123: =C123*I123 -> 554.8 | K123: =SUM(H123,J123) -> 1229.8 | L123: =K123/C123 -> 122.98 | M123: =C123*L123 -> 1229.8 | N123: 0 | O123: =M123*N123 -> 0
B125: (P-13) | C125: Refer Potters Trade/Suspended Ceilings
B127: (P-20) 92mm x 0.75 Stud @ 400 crs with 1.15 Head Track and 0.70 Base Track with Nogging Track | C127: 239 | D127: m2 | E127: 0.4 | F127: =C127*E127 -> 95.6 | G127: =$H$11*E127 -> 20 | H127: =F127*$H$11 -> 4780 | I127: 16.56 | J127: =C127*I127 -> 3957.84 | K127: =SUM(H127,J127) -> 8737.84 | L127: =K127/C127 -> 36.56 | M127: =C127*L127 -> 8737.84 | N127: 0 | O127: =M127*N127 -> 0 | P127: 64 | Q127: 4.4 | R127: =(P127/0.4)*Q127 -> 704
B129: (P-20A) Bulkhead Structure | C129: 50 | D129: m | E129: 0.82 | F129: =C129*E129 -> 41 | G129: =$H$11*E129 -> 41 | H129: =F129*$H$11 -> 2050 | I129: 27 | J129: =C129*I129 -> 1350 | K129: =SUM(H129,J129) -> 3400 | L129: =K129/C129 -> 68 | M129: =C129*L129 -> 3400 | N129: 0 | O129: =M129*N129 -> 0 | P129: 40 | Q129: 4.4 | R129: =(P129/0.4)*Q129 -> 440
B130: (P-20A) 92mm x 0.75 Stud @ 400 crs with 1.15 Head Track and 0.70 Base Track with Nogging Track | C130: 221 | D130: m2 | E130: 0.4 | F130: =C130*E130 -> 88.4 | G130: =$H$11*E130 -> 20 | H130: =F130*$H$11 -> 4420 | I130: 16.58 | J130: =C130*I130 -> 3664.18 | K130: =SUM(H130,J130) -> 8084.18 | L130: =K130/C130 -> 36.58 | M130: =C130*L130 -> 8084.18 | N130: 0 | O130: =M130*N130 -> 0 | P130: 50 | Q130: 4.4 | R130: =(P130/0.4)*Q130 -> 550
B132: (P-20A) Bulkhead Structure - Adjust for ID 502, Detail 6 Coffer Detail | C132: -30 | D132: m | E132: 0.82 | F132: =C132*E132 -> -24.6 | G132: =$H$11*E132 -> 41 | H132: =F132*$H$11 -> -1230 | I132: 27 | J132: =C132*I132 -> -810 | K132: =SUM(H132,J132) -> -2040 | L132: =K132/C132 -> 68 | M132: =C132*L132 -> -2040 | N132: 0 | O132: =M132*N132 -> 0
B134: (P-23) 92mm x 0.75 Stud @ 400 crs with 0.70 Head Track and 0.70 Base Track | C134: 59 | D134: m2 | E134: 0.45 | F134: =C134*E134 -> 26.55 | G134: =$H$11*E134 -> 22.5 | H134: =F134*$H$11 -> 1327.5 | I134: 18.76 | J134: =C134*I134 -> 1106.84 | K134: =SUM(H134,J134) -> 2434.34 | L134: =K134/C134 -> 41.26 | M134: =C134*L134 -> 2434.34 | N134: 0 | O134: =M134*N134 -> 0 | P134: 19 | Q134: 3.1 | R134: =(P134/0.4)*Q134 -> 147.25
B136: (P-23A) 92mm x 0.75 Stud @ 400 crs with 1.15 Head Track and 0.70 Base Track | C136: 11 | D136: m2 | E136: 0.45 | F136: =C136*E136 -> 4.95 | G136: =$H$11*E136 -> 22.5 | H136: =F136*$H$11 -> 247.5 | I136: 20.8 | J136: =C136*I136 -> 228.8 | K136: =SUM(H136,J136) -> 476.3 | L136: =K136/C136 -> 43.3 | M136: =C136*L136 -> 476.3 | N136: 0 | O136: =M136*N136 -> 0 | P136: 3 | Q136: 3.1 | R136: =(P136/0.4)*Q136 -> 23.25
B137: MDF Capping Strip - 228mm Wide | C137: 3 | D137: m | E137: 0.25 | F137: =C137*E137 -> 0.75 | G137: =$H$11*E137 -> 12.5 | H137: =F137*$H$11 -> 37.5 | I137: 23.84 | J137: =C137*I137 -> 71.52 | K137: =SUM(H137,J137) -> 109.02 | L137: =K137/C137 -> 36.34 | M137: =C137*L137 -> 109.02 | N137: 0 | O137: =M137*N137 -> 0
B138: 13mm Gib Overlay to Above | C138: 3 | D138: m | E138: 0.15 | F138: =C138*E138 -> 0.45 | G138: =$H$11*E138 -> 7.5 | H138: =F138*$H$11 -> 22.5 | I138: 3.5 | J138: =C138*I138 -> 10.5 | K138: =SUM(H138,J138) -> 33 | L138: =K138/C138 -> 11 | M138: =C138*L138 -> 33 | N138: 0 | O138: =M138*N138 -> 0
B140: (P-23S) 92mm x 0.75 Stud @ 400 crs with 0.70 Head Track and 0.70 Base Track | C140: 14 | D140: m2 | E140: 0.4 | F140: =C140*E140 -> 5.6 | G140: =$H$11*E140 -> 20 | H140: =F140*$H$11 -> 280 | I140: 19.89 | J140: =C140*I140 -> 278.46 | K140: =SUM(H140,J140) -> 558.46 | L140: =K140/C140 -> 39.89 | M140: =C140*L140 -> 558.46 | N140: 0 | O140: =M140*N140 -> 0 | P140: 4 | Q140: 3.1 | R140: =(P140/0.4)*Q140 -> 31
B142: (P-23AS) 92mm x 0.75 Stud @ 400 crs with 1.15 Head Track and 0.70 Base Track | C142: 8 | D142: m2 | E142: 0.45 | F142: =C142*E142 -> 3.6 | G142: =$H$11*E142 -> 22.5 | H142: =F142*$H$11 -> 180 | I142: 21.75 | J142: =C142*I142 -> 174 | K142: =SUM(H142,J142) -> 354 | L142: =K142/C142 -> 44.25 | M142: =C142*L142 -> 354 | N142: 0 | O142: =M142*N142 -> 0 | P142: 2 | Q142: 3.1 | R142: =(P142/0.4)*Q142 -> 15.5
B143: MDF Capping Strip - 228mm Wide | C143: 2 | D143: m | E143: 0.25 | F143: =C143*E143 -> 0.5 | G143: =$H$11*E143 -> 12.5 | H143: =F143*$H$11 -> 25 | I143: 23.84 | J143: =C143*I143 -> 47.68 | K143: =SUM(H143,J143) -> 72.68 | L143: =K143/C143 -> 36.34 | M143: =C143*L143 -> 72.68 | N143: 0 | O143: =M143*N143 -> 0
B144: 13mm Gib Overlay to Above | C144: 2 | D144: m | E144: 0.15 | F144: =C144*E144 -> 0.3 | G144: =$H$11*E144 -> 7.5 | H144: =F144*$H$11 -> 15 | I144: 3.5 | J144: =C144*I144 -> 7 | K144: =SUM(H144,J144) -> 22 | L144: =K144/C144 -> 11 | M144: =C144*L144 -> 22 | N144: 0 | O144: =M144*N144 -> 0
B146: (P-23AS) MDF Capping Strip -228mm Wide - Adjust for ID 502, Detail 6 Coffer Detail | C146: -2 | D146: m | E146: 0.25 | F146: =C146*E146 -> -0.5 | G146: =$H$11*E146 -> 12.5 | H146: =F146*$H$11 -> -25 | I146: 23.84 | J146: =C146*I146 -> -47.68 | K146: =SUM(H146,J146) -> -72.68 | L146: =K146/C146 -> 36.34 | M146: =C146*L146 -> -72.68 | N146: 0 | O146: =M146*N146 -> 0
B147: (P-23AS) 13mm Gib Overlay to Above - Adjust for ID 502, Detail 6 Coffer Detail | C147: -2 | D147: m | E147: 0.15 | F147: =C147*E147 -> -0.3 | G147: =$H$11*E147 -> 7.5 | H147: =F147*$H$11 -> -15 | I147: 3.5 | J147: =C147*I147 -> -7 | K147: =SUM(H147,J147) -> -22 | L147: =K147/C147 -> 11 | M147: =C147*L147 -> -22 | N147: 0 | O147: =M147*N147 -> 0
B149: (P-24) TWIN WALL - 64mm x 0.75 Stud @ 400 crs with 0.70 Head Track and 0.70 Base Track | C149: 31 | D149: m2 | E149: 0.7 | F149: =C149*E149 -> 21.7 | G149: =$H$11*E149 -> 35 | H149: =F149*$H$11 -> 1085 | I149: 32.6 | J149: =C149*I149 -> 1010.6 | K149: =SUM(H149,J149) -> 2095.6 | L149: =K149/C149 -> 67.6 | M149: =C149*L149 -> 2095.6 | N149: 0 | O149: =M149*N149 -> 0
B151: Trackloks - Part Height Walls | C151: 6 | D151: no | E151: 1 | F151: =C151*E151 -> 6 | G151: =$H$11*E151 -> 50 | H151: =F151*$H$11 -> 300 | I151: 87.07 | J151: =C151*I151 -> 522.42 | K151: =SUM(H151,J151) -> 822.42 | L151: =K151/C151 -> 137.07 | M151: =C151*L151 -> 822.42 | N151: 0 | O151: =M151*N151 -> 0
B153: EV Stud to Corners/Intersections | C153: 448 | D153: m | E153: 0.09 | F153: =C153*E153 -> 40.32 | G153: =$H$11*E153 -> 4.5 | H153: =F153*$H$11 -> 2016 | I153: 5.61 | J153: =C153*I153 -> 2513.28 | K153: =SUM(H153,J153) -> 4529.28 | L153: =K153/C153 -> 10.11 | M153: =C153*L153 -> 4529.28 | N153: 0 | O153: =M153*N153 -> 0
B154: Plywood Support/Nogging - TV's | C154: 10 | D154: item | E154: 1.5 | F154: =C154*E154 -> 15 | G154: =$H$11*E154 -> 75 | H154: =F154*$H$11 -> 750 | I154: 139 | J154: =C154*I154 -> 1390 | K154: =SUM(H154,J154) -> 2140 | L154: =K154/C154 -> 214 | M154: =C154*L154 -> 2140 | N154: 0 | O154: =M154*N154 -> 0
...

Sheet WORKINGS_Partitions SPEC Rates
R2: Rondo | T2: SRP
R3: List | S3: Job Special | T3: List | U3: Job Special
O4: 92mm x 1.15 Head Track | T4: 10.17
C5: Plywood Nogging | D5: 12mm Plywood | E5: 1 | F5: Sheet | G5: 75 | H5: =E5*G5 -> 75 | O5: 92mm x 1.15 DHT | P5: 375 l/m | T5: 11.4 | U5: 6.45
D6: Nogging Brackets | E6: 14 | F6: No | G6: 4.34 | H6: =E6*G6 -> 60.76 | O6: 92mm x 0.75 DHT | T6: 6.13 | U6: 4.31
D7: Fixings | E7: 1 | F7: item | G7: 2.5 | H7: =E7*G7 -> 2.5 | O7: 92mm x 0.75 Stud | P7: 4500 l/m | T7: 5.23 | U7: 3.71
H8: =SUM(H5:H7) -> 138.26 | O8: 92mm x 0.70 Base Track | P8: 375 l/m | T8: 5.23 | U8: 3.71
O9: 92mm Nogging Track | T9: 8.48
O10: 64mm x 0.75 DHT | T10: 5.67 | U10: 3.71
O11: 64mm Nogging Track | T11: 6.5 | U11: 4.29
O12: 64mm x 0.55 Head Track | T12: 2.89
O13: 64mm x 0.70 Stud | T13: 4.71 | U13: 3.21
O14: BC90 Brackets | T14: 4.85 | U14: 4.85
O15: BC45 Brackets | T15: 4.85 | U15: 4.85
O16: 90 x 45 SG8 | Q16: 3.8
O17: Hilti Hus 4-H 70mm | Q17: 1.7
C20: P10 or P11 - Bulkhead Structure Make Up | D20: 1 | E20: LENGTH | F20: 1 | G20: HEIGHT | H20: =Partitions!H11 -> 50
P21: Rate | Q21: Wastage | S21: Loadin
Q22: 1.05
C23: 92 x 1.15 Head Track | D23: =D20 -> 1 | E23: m | F23: 0.15 | G23: =D23*F23 -> 0.15 | H23: =$H$20*F23 -> 7.5 | I23: =G23*$H$20 -> 7.5 | J23: =T23 -> 7.0225 | K23: =D23*J23 -> 7.0225 | L23: =SUM(I23,K23) -> 14.5225 | M23: =L23/D23 -> 14.5225 | N23: =D23*M23 -> 14.5225 | P23: =U5 -> 6.45 | Q23: =P23*$Q$22 -> 6.7725 | R23: =Q23 -> 6.7725 | S23: 0.25 | T23: =SUM(R23:S23) -> 7.0225
C24: Hilti Hus 4-H 70mm Fixing to above | D24: =D23/0.6 -> 1.6666667 | E24: no | F24: 0.1 | G24: =D24*F24 -> 0.16666667 | H24: =$H$20*F24 -> 5 | I24: =G24*$H$20 -> 8.3333333 | J24: =Q17 -> 1.7 | K24: =D24*J24 -> 2.8333333 | L24: =SUM(I24,K24) -> 11.166667 | M24: =L24/D24 -> 6.7 | N24: =D24*M24 -> 11.166667 | Q24: =P24*$Q$22 -> 0 | R24: =Q24 -> 0 | T24: =SUM(R24:S24) -> 0
C25: 92 x 0.75 Dropper Stud | D25: =(D20/0.6)*F20 -> 1.6666667 | E25: m | F25: 0.1 | G25: =D25*F25 -> 0.16666667 | H25: =$H$20*F25 -> 5 | I25: =G25*$H$20 -> 8.3333333 | J25: =T25 -> 4.1455 | K25: =D25*J25 -> 6.9091667 | L25: =SUM(I25,K25) -> 15.2425 | M25: =L25/D25 -> 9.1455 | N25: =D25*M25 -> 15.2425 | P25: =U7 -> 3.71 | Q25: =P25*$Q$22 -> 3.8955 | R25: =Q25 -> 3.8955 | S25: 0.25 | T25: =SUM(R25:S25) -> 4.1455
C27: 64mm x 0.55 Head Track | D27: =D20 -> 1 | E27: m | F27: 0.15 | G27: =D27*F27 -> 0.15 | H27: =$H$20*F27 -> 7.5 | I27: =G27*$H$20 -> 7.5 | J27: =T27 -> 3.2845 | K27: =D27*J27 -> 3.2845 | L27: =SUM(I27,K27) -> 10.7845 | M27: =L27/D27 -> 10.7845 | N27: =D27*M27 -> 10.7845 | P27: =T12 -> 2.89 | Q27: =P27*$Q$22 -> 3.0345 | R27: =Q27 -> 3.0345 | S27: 0.25 | T27: =SUM(R27:S27) -> 3.2845
C28: Hilti Hus 4-H 70mm Fixing to above | D28: =D27/0.6 -> 1.6666667 | E28: no | F28: 0.1 | G28: =D28*F28 -> 0.16666667 | H28: =$H$20*F28 -> 5 | I28: =G28*$H$20 -> 8.3333333 | J28: =Q17 -> 1.7 | K28: =D28*J28 -> 2.8333333 | L28: =SUM(I28,K28) -> 11.166667 | M28: =L28/D28 -> 6.7 | N28: =D28*M28 -> 11.166667 | Q28: =P28*$Q$22 -> 0 | R28: =Q28 -> 0 | T28: =SUM(R28:S28) -> 0
C29: 64 x 0.70 Dropper Stud | D29: =(D20/0.6)*F20 -> 1.6666667 | E29: m | F29: 0.1 | G29: =D29*F29 -> 0.16666667 | H29: =$H$20*F29 -> 5 | I29: =G29*$H$20 -> 8.3333333 | J29: =T29 -> 3.6205 | K29: =D29*J29 -> 6.0341667 | L29: =SUM(I29,K29) -> 14.3675 | M29: =L29/D29 -> 8.6205 | N29: =D29*M29 -> 14.3675 | P29: =U13 -> 3.21 | Q29: =P29*$Q$22 -> 3.3705 | R29: =Q29 -> 3.3705 | S29: 0.25 | T29: =SUM(R29:S29) -> 3.6205
C31: 92 x 0.75 Bridge Stud | D31: =(D20/0.6)*0.242 -> 0.40333333 | E31: m | F31: 0.1 | G31: =D31*F31 -> 0.040333333 | H31: =$H$20*F31 -> 5 | I31: =G31*$H$20 -> 2.0166667 | J31: =T31 -> 4.1455 | K31: =D31*J31 -> 1.6720183 | L31: =SUM(I31,K31) -> 3.688685 | M31: =L31/D31 -> 9.1455 | N31: =D31*M31 -> 3.688685 | P31: =U7 -> 3.71 | Q31: =P31*$Q$22 -> 3.8955 | R31: =Q31 -> 3.8955 | S31: 0.25 | T31: =SUM(R31:S31) -> 4.1455
C32: BC90 Brackets | D32: =(D20/0.6)*2 -> 3.3333333 | E32: no | F32: 0.15 | G32: =D32*F32 -> 0.5 | H32: =$H$20*F32 -> 7.5 | I32: =G32*$H$20 -> 25 | J32: =T32 -> 5.0925 | K32: =D32*J32 -> 16.975 | L32: =SUM(I32,K32) -> 41.975 | M32: =L32/D32 -> 12.5925 | N32: =D32*M32 -> 41.975 | P32: =T14 -> 4.85 | Q32: =P32*$Q$22 -> 5.0925 | R32: =Q32 -> 5.0925 | T32: =SUM(R32:S32) -> 5.0925
C34: 92 x 0.70 Boxed Stud Lintel | D34: =D20 -> 1 | E34: m | F34: 0.2 | G34: =D34*F34 -> 0.2 | H34: =$H$20*F34 -> 10 | I34: =G34*$H$20 -> 10 | J34: =T34*2 -> 8.791 | K34: =D34*J34 -> 8.791 | L34: =SUM(I34,K34) -> 18.791 | M34: =L34/D34 -> 18.791 | N34: =D34*M34 -> 18.791 | O34: Double Rate | P34: =U7 -> 3.71 | Q34: =P34*$Q$22 -> 3.8955 | R34: =Q34 -> 3.8955 | S34: 0.5 | T34: =SUM(R34:S34) -> 4.3955
C35: 92 x 1.15 DHT | D35: =D20 -> 1 | E35: m | F35: 0.1 | G35: =D35*F35 -> 0.1 | H35: =$H$20*F35 -> 5 | I35: =G35*$H$20 -> 5 | J35: =T35 -> 7.0225 | K35: =D35*J35 -> 7.0225 | L35: =SUM(I35,K35) -> 12.0225 | M35: =L35/D35 -> 12.0225 | N35: =D35*M35 -> 12.0225 | P35: =U5 -> 6.45 | Q35: =P35*$Q$22 -> 6.7725 | R35: =Q35 -> 6.7725 | S35: 0.25 | T35: =SUM(R35:S35) -> 7.0225
C37: 90 x 45 SG8 Timber Support | D37: =D20 -> 1 | E37: m | F37: 0.17 | G37: =D37*F37 -> 0.17 | H37: =$H$20*F37 -> 8.5 | I37: =G37*$H$20 -> 8.5 | J37: =T37 -> 4.24 | K37: =D37*J37 -> 4.24 | L37: =SUM(I37,K37) -> 12.74 | M37: =L37/D37 -> 12.74 | N37: =D37*M37 -> 12.74 | P37: =Q16 -> 3.8 | Q37: =P37*$Q$22 -> 3.99 | R37: =Q37 -> 3.99 | S37: 0.25 | T37: =SUM(R37:S37) -> 4.24
C39: Teks | D39: =(D20/0.6)*30 -> 50 | E39: no | F39: 0 | G39: =D39*F39 -> 0 | H39: =$H$20*F39 -> 0 | I39: =G39*$H$20 -> 0 | J39: 0.026 | K39: =D39*J39 -> 1.3 | L39: =SUM(I39,K39) -> 1.3 | M39: =L39/D39 -> 0.026 | N39: =D39*M39 -> 1.3 | Q39: =P39*$Q$22 -> 0 | R39: =Q39 -> 0 | T39: =SUM(R39:S39) -> 0
G41: =SUM(G23:G40) -> 1.977 | I41: =SUM(I23:I40) -> 98.85 | K41: =SUM(K23:K40) -> 68.917518 | N41: =SUM(N23:N40) -> 167.76752
C43: P12 - Bulkhead Structure Make Up | D43: 1 | E43: LENGTH | F43: 1 | G43: HEIGHT | H43: =Partitions!H11 -> 50
P44: Rate | Q44: Wastage | S44: Loadin
Q45: 1.05
C46: 92 x 1.15 Head Track | D46: =D43 -> 1 | E46: m | F46: 0.15 | G46: =D46*F46 -> 0.15 | H46: =$H$43*F46 -> 7.5 | I46: =G46*$H$20 -> 7.5 | J46: =T46 -> 7.0225 | K46: =D46*J46 -> 7.0225 | L46: =SUM(I46,K46) -> 14.5225 | M46: =L46/D46 -> 14.5225 | N46: =D46*M46 -> 14.5225 | P46: =U5 -> 6.45 | Q46: =P46*$Q$22 -> 6.7725 | R46: =Q46 -> 6.7725 | S46: 0.25 | T46: =SUM(R46:S46) -> 7.0225
C47: Hilti Hus 4-H 70mm Fixing to above | D47: =D43/0.6 -> 1.6666667 | E47: no | F47: 0.1 | G47: =D47*F47 -> 0.16666667 | H47: =$H$43*F47 -> 5 | I47: =G47*$H$20 -> 8.3333333 | J47: =Q17 -> 1.7 | K47: =D47*J47 -> 2.8333333 | L47: =SUM(I47,K47) -> 11.166667 | M47: =L47/D47 -> 6.7 | N47: =D47*M47 -> 11.166667 | Q47: =P47*$Q$22 -> 0 | R47: =Q47 -> 0 | T47: =SUM(R47:S47) -> 0
C48: 92 x 0.75 Dropper Stud | D48: =(D43/0.6)*F43 -> 1.6666667 | E48: m | F48: 0.1 | G48: =D48*F48 -> 0.16666667 | H48: =$H$43*F48 -> 5 | I48: =G48*$H$20 -> 8.3333333 | J48: =T48 -> 4.1455 | K48: =D48*J48 -> 6.9091667 | L48: =SUM(I48,K48) -> 15.2425 | M48: =L48/D48 -> 9.1455 | N48: =D48*M48 -> 15.2425 | P48: =U7 -> 3.71 | Q48: =P48*$Q$22 -> 3.8955 | R48: =Q48 -> 3.8955 | S48: 0.25 | T48: =SUM(R48:S48) -> 4.1455
C50: BC90 Brackets | D50: =D43/0.6 -> 1.6666667 | E50: no | F50: 0.07 | G50: =D50*F50 -> 0.11666667 | H50: =$H$43*F50 -> 3.5 | I50: =G50*$H$20 -> 5.8333333 | J50: =T50 -> 5.0925 | K50: =D50*J50 -> 8.4875 | L50: =SUM(I50,K50) -> 14.320833 | M50: =L50/D50 -> 8.5925 | N50: =D50*M50 -> 14.320833 | P50: =T14 -> 4.85 | Q50: =P50*$Q$22 -> 5.0925 | R50: =Q50 -> 5.0925 | T50: =SUM(R50:S50) -> 5.0925
C52: BC45 Brackets | D52: =(D43/1.8)*2 -> 1.1111111 | E52: no | F52: 0.07 | G52: =D52*F52 -> 0.077777778 | H52: =$H$43*F52 -> 3.5 | I52: =G52*$H$20 -> 3.8888889 | J52: =T52 -> 5.0925 | K52: =D52*J52 -> 5.6583333 | L52: =SUM(I52,K52) -> 9.5472222 | M52: =L52/D52 -> 8.5925 | N52: =D52*M52 -> 9.5472222 | P52: =T15 -> 4.85 | Q52: =P52*$Q$22 -> 5.0925 | R52: =Q52 -> 5.0925 | T52: =SUM(R52:S52) -> 5.0925
C53: 92 x 0.75 Stud Brace | D53: =(D43/1.8)*2.2 -> 1.2222222 | E53: m | F53: 0.1 | G53: =D53*F53 -> 0.12222222 | H53: =$H$43*F53 -> 5 | I53: =G53*$H$20 -> 6.1111111 | J53: =T53 -> 4.1455 | K53: =D53*J53 -> 5.0667222 | L53: =SUM(I53,K53) -> 11.177833 | M53: =L53/D53 -> 9.1455 | N53: =D53*M53 -> 11.177833 | P53: =U7 -> 3.71 | Q53: =P53*$Q$22 -> 3.8955 | R53: =Q53 -> 3.8955 | S53: 0.25 | T53: =SUM(R53:S53) -> 4.1455
C55: 92 x 0.70 Boxed Stud Lintel | D55: =D43 -> 1 | E55: m | F55: 0.2 | G55: =D55*F55 -> 0.2 | H55: =$H$43*F55 -> 10 | I55: =G55*$H$20 -> 10 | J55: =T55 -> 4.3955 | K55: =D55*J55 -> 4.3955 | L55: =SUM(I55,K55) -> 14.3955 | M55: =L55/D55 -> 14.3955 | N55: =D55*M55 -> 14.3955 | O55: Double Rate | P55: =U7 -> 3.71 | Q55: =P55*$Q$22 -> 3.8955 | R55: =Q55 -> 3.8955 | S55: 0.5 | T55: =SUM(R55:S55) -> 4.3955
C56: 92 x 1.15 DHT | D56: =D43 -> 1 | E56: m | F56: 0.1 | G56: =D56*F56 -> 0.1 | H56: =$H$43*F56 -> 5 | I56: =G56*$H$20 -> 5 | J56: =T56 -> 7.0225 | K56: =D56*J56 -> 7.0225 | L56: =SUM(I56,K56) -> 12.0225 | M56: =L56/D56 -> 12.0225 | N56: =D56*M56 -> 12.0225 | P56: =U5 -> 6.45 | Q56: =P56*$Q$22 -> 6.7725 | R56: =Q56 -> 6.7725 | S56: 0.25 | T56: =SUM(R56:S56) -> 7.0225
C58: 90 x 45 SG8 Timber Support | D58: =D43 -> 1 | E58: m | F58: 0.17 | G58: =D58*F58 -> 0.17 | H58: =$H$43*F58 -> 8.5 | I58: =G58*$H$20 -> 8.5 | J58: =T58 -> 4.24 | K58: =D58*J58 -> 4.24 | L58: =SUM(I58,K58) -> 12.74 | M58: =L58/D58 -> 12.74 | N58: =D58*M58 -> 12.74 | P58: =Q16 -> 3.8 | Q58: =P58*$Q$22 -> 3.99 | R58: =Q58 -> 3.99 | S58: 0.25 | T58: =SUM(R58:S58) -> 4.24
C60: Teks | D60: =(D43/0.6)*25 -> 41.666667 | E60: no | F60: 0 | G60: =D60*F60 -> 0 | H60: =$H$43*F60 -> 0 | I60: =G60*$H$20 -> 0 | J60: 0.026 | K60: =D60*J60 -> 1.0833333 | L60: =SUM(I60,K60) -> 1.0833333 | M60: =L60/D60 -> 0.026 | N60: =D60*M60 -> 1.0833333 | Q60: =P60*$Q$22 -> 0 | R60: =Q60 -> 0 | T60: =SUM(R60:S60) -> 0
G62: =SUM(G44:G61) -> 1.27 | I62: =SUM(I44:I61) -> 63.5 | K62: =SUM(K44:K61) -> 52.718889 | N62: =SUM(N44:N61) -> 116.21889
C64: P20A - Bulkhead Structure Make Up | D64: 1 | E64: LENGTH | F64: 1 | G64: HEIGHT | H64: =Partitions!H11 -> 50
P65: Rate | Q65: Wastage | S65: Loadin
Q66: 1.05
C67: 64mm x 0.75 Head Track | D67: =D64 -> 1 | E67: m | F67: 0.15 | G67: =D67*F67 -> 0.15 | H67: =$H$64*F67 -> 7.5 | I67: =G67*$H$20 -> 7.5 | J67: =T67 -> 4.1455 | K67: =D67*J67 -> 4.1455 | L67: =SUM(I67,K67) -> 11.6455 | M67: =L67/D67 -> 11.6455 | N67: =D67*M67 -> 11.6455 | P67: =U10 -> 3.71 | Q67: =P67*$Q$22 -> 3.8955 | R67: =Q67 -> 3.8955 | S67: 0.25 | T67: =SUM(R67:S67) -> 4.1455
C68: Hilti Hus 4-H 70mm Fixing to above | D68: =D64/0.6 -> 1.6666667 | E68: no | F68: 0.1 | G68: =D68*F68 -> 0.16666667 | H68: =$H$64*F68 -> 5 | I68: =G68*$H$20 -> 8.3333333 | J68: =Q17 -> 1.7 | K68: =D68*J68 -> 2.8333333 | L68: =SUM(I68,K68) -> 11.166667 | M68: =L68/D68 -> 6.7 | N68: =D68*M68 -> 11.166667 | R68: =Q68 -> 0 | T68: =SUM(R68:S68) -> 0
C69: 64 x 0.70 Dropper Stud | D69: =(D64/0.4)*F64 -> 2.5 | E69: m | F69: 0.1 | G69: =D69*F69 -> 0.25 | H69: =$H$64*F69 -> 5 | I69: =G69*$H$20 -> 12.5 | J69: =T69 -> 3.6205 | K69: =D69*J69 -> 9.05125 | L69: =SUM(I69,K69) -> 21.55125 | M69: =L69/D69 -> 8.6205 | N69: =D69*M69 -> 21.55125 | P69: =U13 -> 3.21 | Q69: =P69*$Q$22 -> 3.3705 | R69: =Q69 -> 3.3705 | S69: 0.25 | T69: =SUM(R69:S69) -> 3.6205
C70: 64mm Nogging Track @ 400 crs | D70: =D64 -> 1 | E70: m | F70: 0.1 | G70: =D70*F70 -> 0.1 | H70: =$H$64*F70 -> 5 | I70: =G70*$H$20 -> 5 | J70: =T70 -> 4.7545 | K70: =D70*J70 -> 4.7545 | L70: =SUM(I70,K70) -> 9.7545 | M70: =L70/D70 -> 9.7545 | N70: =D70*M70 -> 9.7545 | P70: =U11 -> 4.29 | Q70: =P70*$Q$22 -> 4.5045 | R70: =Q70 -> 4.5045 | S70: 0.25 | T70: =SUM(R70:S70) -> 4.7545
C72: 64 x 0.70 Bridge Stud | D72: =(D64/0.4) *0.215 -> 0.5375 | E72: m | F72: 0.1 | G72: =D72*F72 -> 0.05375 | H72: =$H$64*F72 -> 5 | I72: =G72*$H$20 -> 2.6875 | J72: =T72 -> 3.6205 | K72: =D72*J72 -> 1.9460188 | L72: =SUM(I72,K72) -> 4.6335188 | M72: =L72/D72 -> 8.6205 | N72: =D72*M72 -> 4.6335188 | P72: =U13 -> 3.21 | Q72: =P72*$Q$22 -> 3.3705 | R72: =Q72 -> 3.3705 | S72: 0.25 | T72: =SUM(R72:S72) -> 3.6205
C74: Teks | D74: =(D64/0.4)*10 -> 25 | E74: no | F74: 0 | G74: =D74*F74 -> 0 | H74: =$H$64*F74 -> 0 | I74: =G74*$H$20 -> 0 | J74: 0.026 | K74: =D74*J74 -> 0.65 | L74: =SUM(I74,K74) -> 0.65 | M74: =L74/D74 -> 0.026 | N74: =D74*M74 -> 0.65 | R74: =Q74 -> 0 | T74: =SUM(R74:S74) -> 0
G76: =SUM(G67:G75) -> 0.72041667 | I76: =SUM(I67:I75) -> 36.020833 | K76: =SUM(K67:K75) -> 23.380602 | N76: =SUM(N67:N75) -> 59.401435
C78: P23B - Bulkhead Structure Make Up | D78: 1 | E78: LENGTH | F78: 1 | G78: HEIGHT | H78: =Partitions!H11 -> 50
P79: Rate | Q79: Wastage | S79: Loadin
Q80: 1.05
C81: 64mm x 0.55 Head Track | D81: =D78*2 -> 2 | E81: m | F81: 0.15 | G81: =D81*F81 -> 0.3 | H81: =$H$78*F81 -> 7.5 | I81: =G81*$H$20 -> 15 | J81: =T81 -> 3.2845 | K81: =D81*J81 -> 6.569 | L81: =SUM(I81,K81) -> 21.569 | M81: =L81/D81 -> 10.7845 | N81: =D81*M81 -> 21.569 | P81: =T12 -> 2.89 | Q81: =P81*$Q$80 -> 3.0345 | R81: =Q81 -> 3.0345 | S81: 0.25 | T81: =SUM(R81:S81) -> 3.2845
C82: Hilti Hus 4-H 70mm Fixing to above | D82: =(D78/0.6)*2 -> 3.3333333 | E82: no | F82: 0.1 | G82: =D82*F82 -> 0.33333333 | H82: =$H$78*F82 -> 5 | I82: =G82*$H$20 -> 16.666667 | J82: =Q17 -> 1.7 | K82: =D82*J82 -> 5.6666667 | L82: =SUM(I82,K82) -> 22.333333 | M82: =L82/D82 -> 6.7 | N82: =D82*M82 -> 22.333333 | Q82: =P82*$Q$80 -> 0 | R82: =Q82 -> 0 | T82: =SUM(R82:S82) -> 0
C83: 64 x 0.70 Dropper Stud | D83: =2*(D78/0.6)*F78 -> 3.3333333 | E83: m | F83: 0.1 | G83: =D83*F83 -> 0.33333333 | H83: =$H$78*F83 -> 5 | I83: =G83*$H$20 -> 16.666667 | J83: =T83 -> 3.6205 | K83: =D83*J83 -> 12.068333 | L83: =SUM(I83,K83) -> 28.735 | M83: =L83/D83 -> 8.6205 | N83: =D83*M83 -> 28.735 | P83: =U13 -> 3.21 | Q83: =P83*$Q$80 -> 3.3705 | R83: =Q83 -> 3.3705 | S83: 0.25 | T83: =SUM(R83:S83) -> 3.6205
C85: 64 x 0.70 Bridge Stud | D85: =(D78/0.6)*0.23 -> 0.38333333 | E85: m | F85: 0.1 | G85: =D85*F85 -> 0.038333333 | H85: =$H$78*F85 -> 5 | I85: =G85*$H$20 -> 1.9166667 | J85: =T85 -> 3.6205 | K85: =D85*J85 -> 1.3878583 | L85: =SUM(I85,K85) -> 3.304525 | M85: =L85/D85 -> 8.6205 | N85: =D85*M85 -> 3.304525 | P85: =U13 -> 3.21 | Q85: =P85*$Q$80 -> 3.3705 | R85: =Q85 -> 3.3705 | S85: 0.25 | T85: =SUM(R85:S85) -> 3.6205
C87: Teks | D87: =(D78/0.6)*16 -> 26.666667 | E87: no | F87: 0 | G87: =D87*F87 -> 0 | H87: =$H$78*F87 -> 0 | I87: =G87*$H$20 -> 0 | J87: 0.026 | K87: =D87*J87 -> 0.69333333 | L87: =SUM(I87,K87) -> 0.69333333 | M87: =L87/D87 -> 0.026 | N87: =D87*M87 -> 0.69333333 | Q87: =P87*$Q$80 -> 0 | R87: =Q87 -> 0 | T87: =SUM(R87:S87) -> 0
G89: =SUM(G81:G88) -> 1.005 | I89: =SUM(I81:I88) -> 50.25 | K89: =SUM(K81:K88) -> 26.385192 | N89: =SUM(N81:N88) -> 76.635192
D99: 92mm steel studs @ | E99: 0.4 | F99: Stud spacing | G99: With DH
D101: Material | F101: Length of wall | G101: Height of wall | H101: Total stud LM | I101: Total track LM | J101: M2 of wall
E102: $/m | F102: 2 | G102: 3 | H102: =SUM(F111*G102) -> 18 | I102: =F102*2 -> 4 | J102: =F102*G102 -> 6
C103: Stud | D103: 92 0.75 bmt | E103: 4.31
D104: Nog | E104: =H105/H102 -> 0.54777778 | F104: 4.93 | G104: m | H104: =SUM(F104*F102) -> 9.86
F105: Number of nogs | G105: 1 | H105: =G105*H104 -> 9.86
D107: Unload | E107: 0.09
D108: Fixings
D109: say 4 each stud
D110: L of wl ÷ spacings = ttl studs | F110: =SUM(F102/E99) -> 5
D111: add 1 for end of wall | F111: =F110+1 -> 6 | G111: total studs in wall
D112: Studs x 4 screws per stud = ttl screws | F112: =SUM(F111*4) -> 24 | G112: total screws | H112: 0.015
D113: Screws @ $15.00/1000 = .015 | E113: =SUM(F112*H112)/H102 -> 0.02 | F113: Cost of fixings per LM
E115: =SUM(E103:E114) -> 4.9677778
D116: waste 5% | E116: =E115*5% -> 0.24838889
E117: =SUM(E115:E116) -> 5.2161667
C118: Stud | D118: Labour per m as per rates | F118: Lab rate
D119: m/hr | F119: =Partitions!H11 -> 50
D120: 12 | E120: =F119/D120 -> 4.1666667
E123: =SUM(E117:E120) -> 9.3828333 | I123: Labour cost per m | L123: per m2
D124: Plant | I124: =E126-I126 -> 4.7303083 | K124: =H102*I124 -> 85.14555 | L124: =K124/J102 -> 14.190925
D125: 0.05 | E125: =E123*5% -> 0.46914167 | I125: Material cost per m
E126: =SUM(E123:E125) -> 9.851975 | F126: per m | I126: =SUM(E103+E104+E113)*1.05 -> 5.1216667 | K126: =H102*I126 -> 92.19 | L126: =K126/J102 -> 15.365
D127: Total cost of stud job is | F127: =E126*H102 -> 177.33555
F128: To get the medium of the two
C129: Track | D129: 92 | E129: =G130 -> 5.23 | F129: Top 1.15 | G129: Bot 0.70 | I129: Avge
D130: DPC | E130: 0.31 | F130: 6.45 | G130: =T8 -> 5.23 | H130: =SUM(F130:G130) -> 11.68 | I130: =H130/2 -> 5.84
D131: Unload | E131: 0.09
D133: Fixings for track
D134: Spaced @ 0.6 1.7 @ 2.50 each | F134: =F102/E99 -> 5
D135: add extra for ends | F135: =F134+2 -> 7 | G135: total fixings | H135: 1.7
E136: =SUM(F135*H135)/I102 -> 2.975 | F136: Cost of fixings per LM
E138: =SUM(E129:E136) -> 8.605
D139: waste 5% | E139: =E138*5% -> 0.43025
E140: =SUM(E138:E139) -> 9.03525
...

Sheet WORKINGS_Partitions
R2: Rondo | T2: SRP
R3: List | S3: Job Special | T3: List | U3: Job Special
O4: 92mm x 1.15 Head Track | T4: 10.17
C5: Plywood Nogging | D5: 12mm Plywood | E5: 1 | F5: Sheet | G5: 75 | H5: =E5*G5 -> 75 | O5: 92mm x 1.15 DHT | P5: 375 l/m | T5: 11.4
D6: Nogging Brackets | E6: 14 | F6: No | G6: 4.34 | H6: =E6*G6 -> 60.76 | O6: 92mm x 0.75 DHT | T6: 6.13
D7: Fixings | E7: 1 | F7: item | G7: 2.5 | H7: =E7*G7 -> 2.5 | O7: 92mm x 0.75 Stud | P7: 4500 l/m | T7: 5.23
H8: =SUM(H5:H7) -> 138.26 | O8: 92mm x 0.70 Base Track | P8: 375 l/m | T8: 5.23
O9: 92mm Nogging Track | T9: 8.48
O10: 64mm x 0.75 DHT | T10: 5.67
O11: 64mm Nogging Track | T11: 6.5
O12: 64mm x 0.55 Head Track | T12: 2.89
O13: 64mm x 0.70 Stud | T13: 4.71
O14: BC90 Brackets | T14: 4.85
O15: BC45 Brackets | T15: 4.85
O16: 90 x 45 SG8 | Q16: 3.8
O17: Hilti Hus 4-H 70mm | Q17: 1.7
C20: P10 or P11 - Bulkhead Structure Make Up | D20: 1 | E20: LENGTH | F20: 1 | G20: HEIGHT | H20: =Partitions!H11 -> 50
P21: Rate | Q21: Wastage | S21: Loadin
Q22: 1.05
C23: 92 x 1.15 Head Track | D23: =D20 -> 1 | E23: m | F23: 0.15 | G23: =D23*F23 -> 0.15 | H23: =$H$20*F23 -> 7.5 | I23: =G23*$H$20 -> 7.5 | J23: =T23 -> 10.9285 | K23: =D23*J23 -> 10.9285 | L23: =SUM(I23,K23) -> 18.4285 | M23: =L23/D23 -> 18.4285 | N23: =D23*M23 -> 18.4285 | P23: =T4 -> 10.17 | Q23: =P23*$Q$22 -> 10.6785 | R23: =Q23 -> 10.6785 | S23: 0.25 | T23: =SUM(R23:S23) -> 10.9285
C24: Hilti Hus 4-H 70mm Fixing to above | D24: =D23/0.6 -> 1.6666667 | E24: no | F24: 0.1 | G24: =D24*F24 -> 0.16666667 | H24: =$H$20*F24 -> 5 | I24: =G24*$H$20 -> 8.3333333 | J24: =Q17 -> 1.7 | K24: =D24*J24 -> 2.8333333 | L24: =SUM(I24,K24) -> 11.166667 | M24: =L24/D24 -> 6.7 | N24: =D24*M24 -> 11.166667 | Q24: =P24*$Q$22 -> 0 | R24: =Q24 -> 0 | T24: =SUM(R24:S24) -> 0
C25: 92 x 0.75 Dropper Stud | D25: =(D20/0.6)*F20 -> 1.6666667 | E25: m | F25: 0.1 | G25: =D25*F25 -> 0.16666667 | H25: =$H$20*F25 -> 5 | I25: =G25*$H$20 -> 8.3333333 | J25: =T25 -> 5.7415 | K25: =D25*J25 -> 9.5691667 | L25: =SUM(I25,K25) -> 17.9025 | M25: =L25/D25 -> 10.7415 | N25: =D25*M25 -> 17.9025 | P25: =T7 -> 5.23 | Q25: =P25*$Q$22 -> 5.4915 | R25: =Q25 -> 5.4915 | S25: 0.25 | T25: =SUM(R25:S25) -> 5.7415
C27: 64mm x 0.55 Head Track | D27: =D20 -> 1 | E27: m | F27: 0.15 | G27: =D27*F27 -> 0.15 | H27: =$H$20*F27 -> 7.5 | I27: =G27*$H$20 -> 7.5 | J27: =T27 -> 3.2845 | K27: =D27*J27 -> 3.2845 | L27: =SUM(I27,K27) -> 10.7845 | M27: =L27/D27 -> 10.7845 | N27: =D27*M27 -> 10.7845 | P27: =T12 -> 2.89 | Q27: =P27*$Q$22 -> 3.0345 | R27: =Q27 -> 3.0345 | S27: 0.25 | T27: =SUM(R27:S27) -> 3.2845
C28: Hilti Hus 4-H 70mm Fixing to above | D28: =D27/0.6 -> 1.6666667 | E28: no | F28: 0.1 | G28: =D28*F28 -> 0.16666667 | H28: =$H$20*F28 -> 5 | I28: =G28*$H$20 -> 8.3333333 | J28: =Q17 -> 1.7 | K28: =D28*J28 -> 2.8333333 | L28: =SUM(I28,K28) -> 11.166667 | M28: =L28/D28 -> 6.7 | N28: =D28*M28 -> 11.166667 | Q28: =P28*$Q$22 -> 0 | R28: =Q28 -> 0 | T28: =SUM(R28:S28) -> 0
C29: 64 x 0.70 Dropper Stud | D29: =(D20/0.6)*F20 -> 1.6666667 | E29: m | F29: 0.1 | G29: =D29*F29 -> 0.16666667 | H29: =$H$20*F29 -> 5 | I29: =G29*$H$20 -> 8.3333333 | J29: =T29 -> 5.1955 | K29: =D29*J29 -> 8.6591667 | L29: =SUM(I29,K29) -> 16.9925 | M29: =L29/D29 -> 10.1955 | N29: =D29*M29 -> 16.9925 | P29: =T13 -> 4.71 | Q29: =P29*$Q$22 -> 4.9455 | R29: =Q29 -> 4.9455 | S29: 0.25 | T29: =SUM(R29:S29) -> 5.1955
C31: 92 x 0.75 Bridge Stud | D31: =(D20/0.6)*0.242 -> 0.40333333 | E31: m | F31: 0.1 | G31: =D31*F31 -> 0.040333333 | H31: =$H$20*F31 -> 5 | I31: =G31*$H$20 -> 2.0166667 | J31: =T31 -> 5.7415 | K31: =D31*J31 -> 2.3157383 | L31: =SUM(I31,K31) -> 4.332405 | M31: =L31/D31 -> 10.7415 | N31: =D31*M31 -> 4.332405 | P31: =T7 -> 5.23 | Q31: =P31*$Q$22 -> 5.4915 | R31: =Q31 -> 5.4915 | S31: 0.25 | T31: =SUM(R31:S31) -> 5.7415
C32: BC90 Brackets | D32: =(D20/0.6)*2 -> 3.3333333 | E32: no | F32: 0.15 | G32: =D32*F32 -> 0.5 | H32: =$H$20*F32 -> 7.5 | I32: =G32*$H$20 -> 25 | J32: =T32 -> 5.0925 | K32: =D32*J32 -> 16.975 | L32: =SUM(I32,K32) -> 41.975 | M32: =L32/D32 -> 12.5925 | N32: =D32*M32 -> 41.975 | P32: =T14 -> 4.85 | Q32: =P32*$Q$22 -> 5.0925 | R32: =Q32 -> 5.0925 | T32: =SUM(R32:S32) -> 5.0925
C34: 92 x 0.70 Boxed Stud Lintel | D34: =D20 -> 1 | E34: m | F34: 0.2 | G34: =D34*F34 -> 0.2 | H34: =$H$20*F34 -> 10 | I34: =G34*$H$20 -> 10 | J34: =T34*2 -> 11.983 | K34: =D34*J34 -> 11.983 | L34: =SUM(I34,K34) -> 21.983 | M34: =L34/D34 -> 21.983 | N34: =D34*M34 -> 21.983 | O34: Double Rate | P34: =T7 -> 5.23 | Q34: =P34*$Q$22 -> 5.4915 | R34: =Q34 -> 5.4915 | S34: 0.5 | T34: =SUM(R34:S34) -> 5.9915
C35: 92 x 1.15 DHT | D35: =D20 -> 1 | E35: m | F35: 0.1 | G35: =D35*F35 -> 0.1 | H35: =$H$20*F35 -> 5 | I35: =G35*$H$20 -> 5 | J35: =T35 -> 12.22 | K35: =D35*J35 -> 12.22 | L35: =SUM(I35,K35) -> 17.22 | M35: =L35/D35 -> 17.22 | N35: =D35*M35 -> 17.22 | P35: =T5 -> 11.4 | Q35: =P35*$Q$22 -> 11.97 | R35: =Q35 -> 11.97 | S35: 0.25 | T35: =SUM(R35:S35) -> 12.22
C37: 90 x 45 SG8 Timber Support | D37: =D20 -> 1 | E37: m | F37: 0.17 | G37: =D37*F37 -> 0.17 | H37: =$H$20*F37 -> 8.5 | I37: =G37*$H$20 -> 8.5 | J37: =T37 -> 4.24 | K37: =D37*J37 -> 4.24 | L37: =SUM(I37,K37) -> 12.74 | M37: =L37/D37 -> 12.74 | N37: =D37*M37 -> 12.74 | P37: =Q16 -> 3.8 | Q37: =P37*$Q$22 -> 3.99 | R37: =Q37 -> 3.99 | S37: 0.25 | T37: =SUM(R37:S37) -> 4.24
C39: Teks | D39: =(D20/0.6)*30 -> 50 | E39: no | F39: 0 | G39: =D39*F39 -> 0 | H39: =$H$20*F39 -> 0 | I39: =G39*$H$20 -> 0 | J39: 0.026 | K39: =D39*J39 -> 1.3 | L39: =SUM(I39,K39) -> 1.3 | M39: =L39/D39 -> 0.026 | N39: =D39*M39 -> 1.3 | Q39: =P39*$Q$22 -> 0 | R39: =Q39 -> 0 | T39: =SUM(R39:S39) -> 0
G41: =SUM(G23:G40) -> 1.977 | I41: =SUM(I23:I40) -> 98.85 | K41: =SUM(K23:K40) -> 87.141738 | N41: =SUM(N23:N40) -> 185.99174
C43: P12 - Bulkhead Structure Make Up | D43: 1 | E43: LENGTH | F43: 1 | G43: HEIGHT | H43: =Partitions!H11 -> 50
P44: Rate | Q44: Wastage | S44: Loadin
Q45: 1.05
C46: 92 x 1.15 Head Track | D46: =D43 -> 1 | E46: m | F46: 0.15 | G46: =D46*F46 -> 0.15 | H46: =$H$43*F46 -> 7.5 | I46: =G46*$H$20 -> 7.5 | J46: =T46 -> 10.9285 | K46: =D46*J46 -> 10.9285 | L46: =SUM(I46,K46) -> 18.4285 | M46: =L46/D46 -> 18.4285 | N46: =D46*M46 -> 18.4285 | P46: =T4 -> 10.17 | Q46: =P46*$Q$22 -> 10.6785 | R46: =Q46 -> 10.6785 | S46: 0.25 | T46: =SUM(R46:S46) -> 10.9285
C47: Hilti Hus 4-H 70mm Fixing to above | D47: =D43/0.6 -> 1.6666667 | E47: no | F47: 0.1 | G47: =D47*F47 -> 0.16666667 | H47: =$H$43*F47 -> 5 | I47: =G47*$H$20 -> 8.3333333 | J47: =Q17 -> 1.7 | K47: =D47*J47 -> 2.8333333 | L47: =SUM(I47,K47) -> 11.166667 | M47: =L47/D47 -> 6.7 | N47: =D47*M47 -> 11.166667 | Q47: =P47*$Q$22 -> 0 | R47: =Q47 -> 0 | T47: =SUM(R47:S47) -> 0
C48: 92 x 0.75 Dropper Stud | D48: =(D43/0.6)*F43 -> 1.6666667 | E48: m | F48: 0.1 | G48: =D48*F48 -> 0.16666667 | H48: =$H$43*F48 -> 5 | I48: =G48*$H$20 -> 8.3333333 | J48: =T48 -> 5.7415 | K48: =D48*J48 -> 9.5691667 | L48: =SUM(I48,K48) -> 17.9025 | M48: =L48/D48 -> 10.7415 | N48: =D48*M48 -> 17.9025 | P48: =T7 -> 5.23 | Q48: =P48*$Q$22 -> 5.4915 | R48: =Q48 -> 5.4915 | S48: 0.25 | T48: =SUM(R48:S48) -> 5.7415
C50: BC90 Brackets | D50: =D43/0.6 -> 1.6666667 | E50: no | F50: 0.07 | G50: =D50*F50 -> 0.11666667 | H50: =$H$43*F50 -> 3.5 | I50: =G50*$H$20 -> 5.8333333 | J50: =T50 -> 5.0925 | K50: =D50*J50 -> 8.4875 | L50: =SUM(I50,K50) -> 14.320833 | M50: =L50/D50 -> 8.5925 | N50: =D50*M50 -> 14.320833 | P50: =T14 -> 4.85 | Q50: =P50*$Q$22 -> 5.0925 | R50: =Q50 -> 5.0925 | T50: =SUM(R50:S50) -> 5.0925
C52: BC45 Brackets | D52: =(D43/1.8)*2 -> 1.1111111 | E52: no | F52: 0.07 | G52: =D52*F52 -> 0.077777778 | H52: =$H$43*F52 -> 3.5 | I52: =G52*$H$20 -> 3.8888889 | J52: =T52 -> 5.0925 | K52: =D52*J52 -> 5.6583333 | L52: =SUM(I52,K52) -> 9.5472222 | M52: =L52/D52 -> 8.5925 | N52: =D52*M52 -> 9.5472222 | P52: =T15 -> 4.85 | Q52: =P52*$Q$22 -> 5.0925 | R52: =Q52 -> 5.0925 | T52: =SUM(R52:S52) -> 5.0925
C53: 92 x 0.75 Stud Brace | D53: =(D43/1.8)*2.2 -> 1.2222222 | E53: m | F53: 0.1 | G53: =D53*F53 -> 0.12222222 | H53: =$H$43*F53 -> 5 | I53: =G53*$H$20 -> 6.1111111 | J53: =T53 -> 5.7415 | K53: =D53*J53 -> 7.0173889 | L53: =SUM(I53,K53) -> 13.1285 | M53: =L53/D53 -> 10.7415 | N53: =D53*M53 -> 13.1285 | P53: =T7 -> 5.23 | Q53: =P53*$Q$22 -> 5.4915 | R53: =Q53 -> 5.4915 | S53: 0.25 | T53: =SUM(R53:S53) -> 5.7415
C55: 92 x 0.70 Boxed Stud Lintel | D55: =D43 -> 1 | E55: m | F55: 0.2 | G55: =D55*F55 -> 0.2 | H55: =$H$43*F55 -> 10 | I55: =G55*$H$20 -> 10 | J55: =T55 -> 5.9915 | K55: =D55*J55 -> 5.9915 | L55: =SUM(I55,K55) -> 15.9915 | M55: =L55/D55 -> 15.9915 | N55: =D55*M55 -> 15.9915 | O55: Double Rate | P55: =T7 -> 5.23 | Q55: =P55*$Q$22 -> 5.4915 | R55: =Q55 -> 5.4915 | S55: 0.5 | T55: =SUM(R55:S55) -> 5.9915
C56: 92 x 1.15 DHT | D56: =D43 -> 1 | E56: m | F56: 0.1 | G56: =D56*F56 -> 0.1 | H56: =$H$43*F56 -> 5 | I56: =G56*$H$20 -> 5 | J56: =T56 -> 12.22 | K56: =D56*J56 -> 12.22 | L56: =SUM(I56,K56) -> 17.22 | M56: =L56/D56 -> 17.22 | N56: =D56*M56 -> 17.22 | P56: =T5 -> 11.4 | Q56: =P56*$Q$22 -> 11.97 | R56: =Q56 -> 11.97 | S56: 0.25 | T56: =SUM(R56:S56) -> 12.22
C58: 90 x 45 SG8 Timber Support | D58: =D43 -> 1 | E58: m | F58: 0.17 | G58: =D58*F58 -> 0.17 | H58: =$H$43*F58 -> 8.5 | I58: =G58*$H$20 -> 8.5 | J58: =T58 -> 4.24 | K58: =D58*J58 -> 4.24 | L58: =SUM(I58,K58) -> 12.74 | M58: =L58/D58 -> 12.74 | N58: =D58*M58 -> 12.74 | P58: =Q16 -> 3.8 | Q58: =P58*$Q$22 -> 3.99 | R58: =Q58 -> 3.99 | S58: 0.25 | T58: =SUM(R58:S58) -> 4.24
C60: Teks | D60: =(D43/0.6)*25 -> 41.666667 | E60: no | F60: 0 | G60: =D60*F60 -> 0 | H60: =$H$43*F60 -> 0 | I60: =G60*$H$20 -> 0 | J60: 0.026 | K60: =D60*J60 -> 1.0833333 | L60: =SUM(I60,K60) -> 1.0833333 | M60: =L60/D60 -> 0.026 | N60: =D60*M60 -> 1.0833333 | Q60: =P60*$Q$22 -> 0 | R60: =Q60 -> 0 | T60: =SUM(R60:S60) -> 0
G62: =SUM(G44:G61) -> 1.27 | I62: =SUM(I44:I61) -> 63.5 | K62: =SUM(K44:K61) -> 68.029056 | N62: =SUM(N44:N61) -> 131.52906
C64: P20A - Bulkhead Structure Make Up | D64: 1 | E64: LENGTH | F64: 1 | G64: HEIGHT | H64: =Partitions!H11 -> 50
P65: Rate | Q65: Wastage | S65: Loadin
Q66: 1.05
C67: 64mm x 0.75 Head Track | D67: =D64 -> 1 | E67: m | F67: 0.15 | G67: =D67*F67 -> 0.15 | H67: =$H$64*F67 -> 7.5 | I67: =G67*$H$20 -> 7.5 | J67: =T67 -> 6.2035 | K67: =D67*J67 -> 6.2035 | L67: =SUM(I67,K67) -> 13.7035 | M67: =L67/D67 -> 13.7035 | N67: =D67*M67 -> 13.7035 | P67: =T10 -> 5.67 | Q67: =P67*$Q$22 -> 5.9535 | R67: =Q67 -> 5.9535 | S67: 0.25 | T67: =SUM(R67:S67) -> 6.2035
C68: Hilti Hus 4-H 70mm Fixing to above | D68: =D64/0.6 -> 1.6666667 | E68: no | F68: 0.1 | G68: =D68*F68 -> 0.16666667 | H68: =$H$64*F68 -> 5 | I68: =G68*$H$20 -> 8.3333333 | J68: =Q17 -> 1.7 | K68: =D68*J68 -> 2.8333333 | L68: =SUM(I68,K68) -> 11.166667 | M68: =L68/D68 -> 6.7 | N68: =D68*M68 -> 11.166667 | R68: =Q68 -> 0 | T68: =SUM(R68:S68) -> 0
C69: 64 x 0.70 Dropper Stud | D69: =(D64/0.4)*F64 -> 2.5 | E69: m | F69: 0.1 | G69: =D69*F69 -> 0.25 | H69: =$H$64*F69 -> 5 | I69: =G69*$H$20 -> 12.5 | J69: =T69 -> 5.1955 | K69: =D69*J69 -> 12.98875 | L69: =SUM(I69,K69) -> 25.48875 | M69: =L69/D69 -> 10.1955 | N69: =D69*M69 -> 25.48875 | P69: =T13 -> 4.71 | Q69: =P69*$Q$22 -> 4.9455 | R69: =Q69 -> 4.9455 | S69: 0.25 | T69: =SUM(R69:S69) -> 5.1955
C70: 64mm Nogging Track @ 400 crs | D70: =D64 -> 1 | E70: m | F70: 0.1 | G70: =D70*F70 -> 0.1 | H70: =$H$64*F70 -> 5 | I70: =G70*$H$20 -> 5 | J70: =T70 -> 7.075 | K70: =D70*J70 -> 7.075 | L70: =SUM(I70,K70) -> 12.075 | M70: =L70/D70 -> 12.075 | N70: =D70*M70 -> 12.075 | P70: =T11 -> 6.5 | Q70: =P70*$Q$22 -> 6.825 | R70: =Q70 -> 6.825 | S70: 0.25 | T70: =SUM(R70:S70) -> 7.075
C72: 64 x 0.70 Bridge Stud | D72: =(D64/0.4) *0.215 -> 0.5375 | E72: m | F72: 0.1 | G72: =D72*F72 -> 0.05375 | H72: =$H$64*F72 -> 5 | I72: =G72*$H$20 -> 2.6875 | J72: =T72 -> 4.24 | K72: =D72*J72 -> 2.279 | L72: =SUM(I72,K72) -> 4.9665 | M72: =L72/D72 -> 9.24 | N72: =D72*M72 -> 4.9665 | P72: =Q16 -> 3.8 | Q72: =P72*$Q$22 -> 3.99 | R72: =Q72 -> 3.99 | S72: 0.25 | T72: =SUM(R72:S72) -> 4.24
C74: Teks | D74: =(D64/0.4)*10 -> 25 | E74: no | F74: 0 | G74: =D74*F74 -> 0 | H74: =$H$64*F74 -> 0 | I74: =G74*$H$20 -> 0 | J74: 0.026 | K74: =D74*J74 -> 0.65 | L74: =SUM(I74,K74) -> 0.65 | M74: =L74/D74 -> 0.026 | N74: =D74*M74 -> 0.65 | R74: =Q74 -> 0 | T74: =SUM(R74:S74) -> 0
G76: =SUM(G67:G75) -> 0.72041667 | I76: =SUM(I67:I75) -> 36.020833 | K76: =SUM(K67:K75) -> 32.029583 | N76: =SUM(N67:N75) -> 68.050417
C78: P23B - Bulkhead Structure Make Up | D78: 1 | E78: LENGTH | F78: 1 | G78: HEIGHT | H78: =Partitions!H11 -> 50
P79: Rate | Q79: Wastage | S79: Loadin
Q80: 1.05
C81: 64mm x 0.55 Head Track | D81: =D78*2 -> 2 | E81: m | F81: 0.15 | G81: =D81*F81 -> 0.3 | H81: =$H$78*F81 -> 7.5 | I81: =G81*$H$20 -> 15 | J81: =T81 -> 3.2845 | K81: =D81*J81 -> 6.569 | L81: =SUM(I81,K81) -> 21.569 | M81: =L81/D81 -> 10.7845 | N81: =D81*M81 -> 21.569 | P81: =T12 -> 2.89 | Q81: =P81*$Q$80 -> 3.0345 | R81: =Q81 -> 3.0345 | S81: 0.25 | T81: =SUM(R81:S81) -> 3.2845
C82: Hilti Hus 4-H 70mm Fixing to above | D82: =(D78/0.6)*2 -> 3.3333333 | E82: no | F82: 0.1 | G82: =D82*F82 -> 0.33333333 | H82: =$H$78*F82 -> 5 | I82: =G82*$H$20 -> 16.666667 | J82: =Q17 -> 1.7 | K82: =D82*J82 -> 5.6666667 | L82: =SUM(I82,K82) -> 22.333333 | M82: =L82/D82 -> 6.7 | N82: =D82*M82 -> 22.333333 | Q82: =P82*$Q$80 -> 0 | R82: =Q82 -> 0 | T82: =SUM(R82:S82) -> 0
C83: 64 x 0.70 Dropper Stud | D83: =2*(D78/0.6)*F78 -> 3.3333333 | E83: m | F83: 0.1 | G83: =D83*F83 -> 0.33333333 | H83: =$H$78*F83 -> 5 | I83: =G83*$H$20 -> 16.666667 | J83: =T83 -> 5.1955 | K83: =D83*J83 -> 17.318333 | L83: =SUM(I83,K83) -> 33.985 | M83: =L83/D83 -> 10.1955 | N83: =D83*M83 -> 33.985 | P83: =T13 -> 4.71 | Q83: =P83*$Q$80 -> 4.9455 | R83: =Q83 -> 4.9455 | S83: 0.25 | T83: =SUM(R83:S83) -> 5.1955
C85: 64 x 0.70 Bridge Stud | D85: =(D78/0.6)*0.23 -> 0.38333333 | E85: m | F85: 0.1 | G85: =D85*F85 -> 0.038333333 | H85: =$H$78*F85 -> 5 | I85: =G85*$H$20 -> 1.9166667 | J85: =T85 -> 5.1955 | K85: =D85*J85 -> 1.9916083 | L85: =SUM(I85,K85) -> 3.908275 | M85: =L85/D85 -> 10.1955 | N85: =D85*M85 -> 3.908275 | P85: =T13 -> 4.71 | Q85: =P85*$Q$80 -> 4.9455 | R85: =Q85 -> 4.9455 | S85: 0.25 | T85: =SUM(R85:S85) -> 5.1955
C87: Teks | D87: =(D78/0.6)*16 -> 26.666667 | E87: no | F87: 0 | G87: =D87*F87 -> 0 | H87: =$H$78*F87 -> 0 | I87: =G87*$H$20 -> 0 | J87: 0.026 | K87: =D87*J87 -> 0.69333333 | L87: =SUM(I87,K87) -> 0.69333333 | M87: =L87/D87 -> 0.026 | N87: =D87*M87 -> 0.69333333 | Q87: =P87*$Q$80 -> 0 | R87: =Q87 -> 0 | T87: =SUM(R87:S87) -> 0
G89: =SUM(G81:G88) -> 1.005 | I89: =SUM(I81:I88) -> 50.25 | K89: =SUM(K81:K88) -> 32.238942 | N89: =SUM(N81:N88) -> 82.488942
D99: 92mm steel studs @ | E99: 0.4 | F99: Stud spacing | G99: With DH
D101: Material | F101: Length of wall | G101: Height of wall | H101: Total stud LM | I101: Total track LM | J101: M2 of wall
E102: $/m | F102: 11 | G102: 2.9 | H102: =SUM(F111*G102) -> 82.65 | I102: =F102*2 -> 22 | J102: =F102*G102 -> 31.9
C103: Stud | D103: 92 0.75 bmt | E103: =T7 -> 5.23
D104: Nog | E104: =H105/H102 -> 1.1286146 | F104: =T9 -> 8.48 | G104: m | H104: =SUM(F104*F102) -> 93.28
F105: Number of nogs | G105: 1 | H105: =G105*H104 -> 93.28
D107: Unload | E107: 0.09
D108: Fixings
D109: say 4 each stud
D110: L of wl ÷ spacings = ttl studs | F110: =SUM(F102/E99) -> 27.5
D111: add 1 for end of wall | F111: =F110+1 -> 28.5 | G111: total studs in wall
D112: Studs x 4 screws per stud = ttl screws | F112: =SUM(F111*4) -> 114 | G112: total screws | H112: 0.015
D113: Screws @ $15.00/1000 = .015 | E113: =SUM(F112*H112)/H102 -> 0.020689655 | F113: Cost of fixings per LM
E115: =SUM(E103:E114) -> 6.4693043
D116: waste 5% | E116: =E115*5% -> 0.32346521
E117: =SUM(E115:E116) -> 6.7927695
C118: Stud | D118: Labour per m as per rates | F118: Lab rate
D119: m/hr | F119: =Partitions!H11 -> 50
D120: 12 | E120: =F119/D120 -> 4.1666667
E123: =SUM(E117:E120) -> 10.959436 | I123: Labour cost per m | L123: per m2
D124: Plant | I124: =E126-I126 -> 4.8091385 | K124: =H102*I124 -> 397.4753 | L124: =K124/J102 -> 12.460041
D125: 0.05 | E125: =E123*5% -> 0.54797181 | I125: Material cost per m
E126: =SUM(E123:E125) -> 11.507408 | F126: per m | I126: =SUM(E103+E104+E113)*1.05 -> 6.6982695 | K126: =H102*I126 -> 553.61198 | L126: =K126/J102 -> 17.354607
D127: Total cost of stud job is | F127: =E126*H102 -> 951.08727
F128: To get the medium of the two
C129: Track | D129: 92 | E129: =I130 -> 8.315 | F129: Top 1.15 | G129: Bot 0.70 | I129: Avge
D130: DPC | E130: 0.31 | F130: =T5 -> 11.4 | G130: =T8 -> 5.23 | H130: =SUM(F130:G130) -> 16.63 | I130: =H130/2 -> 8.315
D131: Unload | E131: 0.09
D133: Fixings for track
D134: Spaced @ 0.6 1.7 @ 2.50 each | F134: =F102/E99 -> 27.5
D135: add extra for ends | F135: =F134+2 -> 29.5 | G135: total fixings | H135: 1.7
E136: =SUM(F135*H135)/I102 -> 2.2795455 | F136: Cost of fixings per LM
E138: =SUM(E129:E136) -> 10.994545
D139: waste 5% | E139: =E138*5% -> 0.54972727
E140: =SUM(E138:E139) -> 11.544273
...

Sheet Insulation
B1: =Summary!B1 -> Ceilings Unlimited
B2: =Summary!B2 -> Craigs Investment Partners - Fitout
B3: =Summary!B3 -> Tauranga
B6: =Summary!B5 -> 46043
B9: =Summary!B121 -> Insulation
H11: 45
A12: Item | B12: Description | C12: Qty | D12: Unit | E12: Constant | F12: Constant X Unit = Total HRS | G12: $ Lab per Unit | H12: Total Labour | I12: Materials per Unit | J12: Total Materials | K12: Total Labour & Materials | L12: Total Labour & Materials Per Unit | M12: Total | N12: % Complete | O12: Claim
B14: Ceiling Insulation:
B16: Level 4:
B18: (C-01B) | C18: Nil, By Others Basebuid
B19: (C-02) R1.8 Autex Sound Solution on top | C19: 45 | D19: m2 | E19: 0.15 | F19: =C19*E19 -> 6.75 | G19: =$H$11*E19 -> 6.75 | H19: =F19*$H$11 -> 303.75 | I19: =$X$26 -> 8.8710241 | J19: =C19*I19 -> 399.19608 | K19: =SUM(H19,J19) -> 702.94608 | L19: =K19/C19 -> 15.621024 | M19: =C19*L19 -> 702.94608 | N19: 0 | O19: =M19*N19 -> 0
B20: (C-04) 50mm Autex Quietpsace | C20: Nil, By Others
V22: Freight
B23: Level 5: | V23: 1.05
B25: (C-01B) | C25: Nil, By Others Basebuid | Q25: =SUM(C45,C49,C51,C54,C57,C60,C65,C69,C71,C73,C76,C82,C84,C86,C88,C90,C92,C92) -> 1149 | R25: Walls | S25: 47 | T25: 210.37 | U25: Bales | V25: =T25*$V$23 -> 220.8885 | W25: =S25*V25 -> 10381.76 | X25: =W25/Q25 -> 9.0354739
B26: (C-04) 50mm Autex Quietpsace | C26: Nil, By Others | Q26: =SUM(C25,C34) -> 249 | R26: Ceiling | S26: 10 | T26: 210.37 | U26: Bales | V26: =T26*$V$23 -> 220.8885 | W26: =S26*V26 -> 2208.885 | X26: =W26/Q26 -> 8.8710241
Q27: 121 | R27: Baffle | T27: 78.67 | U27: Roll | V27: =T27*$V$23 -> 82.6035 | W27: =Q27*V27 -> 9995.0235 | X27: =W27/Q29 -> 75.719875
B29: Level 6: | Q29: =SUM(C47,C52,C55,C58,C67,C74,C77) -> 132
B31: (C-01A) | C31: Nil, By Others Basebuid
B32: (C-01B) | C32: Nil, By Others Basebuid
B33: (C-02) R1.8 Autex Sound Solutuion on top | C33: 4 | D33: m2 | E33: 0.15 | F33: =C33*E33 -> 0.6 | G33: =$H$11*E33 -> 6.75 | H33: =F33*$H$11 -> 27 | I33: =$X$26 -> 8.8710241 | J33: =C33*I33 -> 35.484096 | K33: =SUM(H33,J33) -> 62.484096 | L33: =K33/C33 -> 15.621024 | M33: =C33*L33 -> 62.484096 | N33: 0 | O33: =M33*N33 -> 0
B34: (C-03) R1.8 Autex Sound Solutuion on top | C34: 249 | D34: m2 | E34: 0.15 | F34: =C34*E34 -> 37.35 | G34: =$H$11*E34 -> 6.75 | H34: =F34*$H$11 -> 1680.75 | I34: =$X$26 -> 8.8710241 | J34: =C34*I34 -> 2208.885 | K34: =SUM(H34,J34) -> 3889.635 | L34: =K34/C34 -> 15.621024 | M34: =C34*L34 -> 3889.635 | N34: 0 | O34: =M34*N34 -> 0
B35: (C-08) 50mm Autex Quietspace Black Above Mesh | C35: Refer Suspended Ceiling Trade
B36: (C-09) R1.8 Autex Sound Solutuion on top | C36: 36 | D36: m2 | E36: 0.15 | F36: =C36*E36 -> 5.4 | G36: =$H$11*E36 -> 6.75 | H36: =F36*$H$11 -> 243 | I36: =$X$26 -> 8.8710241 | J36: =C36*I36 -> 319.35687 | K36: =SUM(H36,J36) -> 562.35687 | L36: =K36/C36 -> 15.621024 | M36: =C36*L36 -> 562.35687 | N36: 0 | O36: =M36*N36 -> 0
B37: (C-10) 50mm Autex Quietspace Black Above Mesh | C37: Refer Suspended Ceiling Trade
B38: C-11) AAB 35-50 | C38: 204 | D38: m2 | E38: 0.15 | F38: =C38*E38 -> 30.6 | G38: =$H$11*E38 -> 6.75 | H38: =F38*$H$11 -> 1377 | I38: 14.75 | J38: =C38*I38 -> 3009 | K38: =SUM(H38,J38) -> 4386 | L38: =K38/C38 -> 21.5 | M38: =C38*L38 -> 4386 | N38: 0 | O38: =M38*N38 -> 0
B41: Wall and Baffle Stack Insulation:
B43: Level 4:
B45: (P-10) Autex R1.8 Sound Solution | C45: 4 | D45: m2 | E45: 0.12 | F45: =C45*E45 -> 0.48 | G45: =$H$11*E45 -> 5.4 | H45: =F45*$H$11 -> 21.6 | I45: =$X$25 -> 9.0354739 | J45: =C45*I45 -> 36.141896 | K45: =SUM(H45,J45) -> 57.741896 | L45: =K45/C45 -> 14.435474 | M45: =C45*L45 -> 57.741896 | N45: 0 | O45: =M45*N45 -> 0
B47: (P-11) Autex Baffle Block | C47: 23 | D47: m | E47: 0.7 | F47: =C47*E47 -> 16.1 | G47: =$H$11*E47 -> 31.5 | H47: =F47*$H$11 -> 724.5 | I47: =$X$27 -> 75.719875 | J47: =C47*I47 -> 1741.5571 | K47: =SUM(H47,J47) -> 2466.0571 | L47: =K47/C47 -> 107.21987 | M47: =C47*L47 -> 2466.0571 | N47: 0 | O47: =M47*N47 -> 0 | P47: 21
B49: (P-20A) Autex R1.8 Sound Solution | C49: 34 | D49: m2 | E49: 0.12 | F49: =C49*E49 -> 4.08 | G49: =$H$11*E49 -> 5.4 | H49: =F49*$H$11 -> 183.6 | I49: =$X$25 -> 9.0354739 | J49: =C49*I49 -> 307.20611 | K49: =SUM(H49,J49) -> 490.80611 | L49: =K49/C49 -> 14.435474 | M49: =C49*L49 -> 490.80611 | N49: 0 | O49: =M49*N49 -> 0
B51: (P-21S) Autex R1.8 Sound Solution | C51: 19 | D51: m2 | E51: 0.12 | F51: =C51*E51 -> 2.28 | G51: =$H$11*E51 -> 5.4 | H51: =F51*$H$11 -> 102.6 | J51: =C51*I51 -> 0 | K51: =SUM(H51,J51) -> 102.6 | L51: =K51/C51 -> 5.4 | M51: =C51*L51 -> 102.6 | N51: 0 | O51: =M51*N51 -> 0
B52: Autex Baffle Block to Above | C52: 7 | D52: m | E52: 0.7 | F52: =C52*E52 -> 4.9 | G52: =$H$11*E52 -> 31.5 | H52: =F52*$H$11 -> 220.5 | I52: =$X$27 -> 75.719875 | J52: =C52*I52 -> 530.03913 | K52: =SUM(H52,J52) -> 750.53913 | L52: =K52/C52 -> 107.21988 | M52: =C52*L52 -> 750.53913 | N52: 0 | O52: =M52*N52 -> 0 | P52: 6.5
B54: (P-21) Autex R1.8 Sound Solution | C54: 141 | D54: m2 | E54: 0.12 | F54: =C54*E54 -> 16.92 | G54: =$H$11*E54 -> 5.4 | H54: =F54*$H$11 -> 761.4 | J54: =C54*I54 -> 0 | K54: =SUM(H54,J54) -> 761.4 | L54: =K54/C54 -> 5.4 | M54: =C54*L54 -> 761.4 | N54: 0 | O54: =M54*N54 -> 0
B55: Autex Baffle Block to Above | C55: 48 | D55: m | E55: 0.7 | F55: =C55*E55 -> 33.6 | G55: =$H$11*E55 -> 31.5 | H55: =F55*$H$11 -> 1512 | I55: =$X$27 -> 75.719875 | J55: =C55*I55 -> 3634.554 | K55: =SUM(H55,J55) -> 5146.554 | L55: =K55/C55 -> 107.21988 | M55: =C55*L55 -> 5146.554 | N55: 0 | O55: =M55*N55 -> 0 | P55: 43.5
B57: (P-21A) Autex R1.8 Sound Solution | C57: 27 | D57: m2 | E57: 0.12 | F57: =C57*E57 -> 3.24 | G57: =$H$11*E57 -> 5.4 | H57: =F57*$H$11 -> 145.8 | J57: =C57*I57 -> 0 | K57: =SUM(H57,J57) -> 145.8 | L57: =K57/C57 -> 5.4 | M57: =C57*L57 -> 145.8 | N57: 0 | O57: =M57*N57 -> 0
B58: Autex Baffle Block to Above | C58: 9 | D58: m | E58: 0.7 | F58: =C58*E58 -> 6.3 | G58: =$H$11*E58 -> 31.5 | H58: =F58*$H$11 -> 283.5 | I58: =$X$27 -> 75.719875 | J58: =C58*I58 -> 681.47888 | K58: =SUM(H58,J58) -> 964.97888 | L58: =K58/C58 -> 107.21988 | M58: =C58*L58 -> 964.97888 | N58: 0 | O58: =M58*N58 -> 0 | P58: 8.5
B60: (P-23AS) Autex R1.8 Sound Solution | C60: 12 | D60: m2 | E60: 0.12 | F60: =C60*E60 -> 1.44 | G60: =$H$11*E60 -> 5.4 | H60: =F60*$H$11 -> 64.8 | I60: =$X$25 -> 9.0354739 | J60: =C60*I60 -> 108.42569 | K60: =SUM(H60,J60) -> 173.22569 | L60: =K60/C60 -> 14.435474 | M60: =C60*L60 -> 173.22569 | N60: 0 | O60: =M60*N60 -> 0
B63: Level 5:
B65: (P-10) Autex R1.8 Sound Solution | C65: 14 | D65: m2 | E65: 0.12 | F65: =C65*E65 -> 1.68 | G65: =$H$11*E65 -> 5.4 | H65: =F65*$H$11 -> 75.6 | I65: =$X$25 -> 9.0354739 | J65: =C65*I65 -> 126.49663 | K65: =SUM(H65,J65) -> 202.09663 | L65: =K65/C65 -> 14.435474 | M65: =C65*L65 -> 202.09663 | N65: 0 | O65: =M65*N65 -> 0
B67: (P-11) Autex Baffle Block | C67: 11 | D67: m | E67: 0.7 | F67: =C67*E67 -> 7.7 | G67: =$H$11*E67 -> 31.5 | H67: =F67*$H$11 -> 346.5 | I67: =$X$27 -> 75.719875 | J67: =C67*I67 -> 832.91863 | K67: =SUM(H67,J67) -> 1179.4186 | L67: =K67/C67 -> 107.21988 | M67: =C67*L67 -> 1179.4186 | N67: 0 | O67: =M67*N67 -> 0 | P67: 10
B69: (P-20) Autex R1.8 Sound Solution | C69: 114 | D69: m2 | E69: 0.12 | F69: =C69*E69 -> 13.68 | G69: =$H$11*E69 -> 5.4 | H69: =F69*$H$11 -> 615.6 | I69: =$X$25 -> 9.0354739 | J69: =C69*I69 -> 1030.044 | K69: =SUM(H69,J69) -> 1645.644 | L69: =K69/C69 -> 14.435474 | M69: =C69*L69 -> 1645.644 | N69: 0 | O69: =M69*N69 -> 0
B71: (P-20A) Autex R1.8 Sound Solution | C71: 72 | D71: m2 | E71: 0.12 | F71: =C71*E71 -> 8.64 | G71: =$H$11*E71 -> 5.4 | H71: =F71*$H$11 -> 388.8 | I71: =$X$25 -> 9.0354739 | J71: =C71*I71 -> 650.55412 | K71: =SUM(H71,J71) -> 1039.3541 | L71: =K71/C71 -> 14.435474 | M71: =C71*L71 -> 1039.3541 | N71: 0 | O71: =M71*N71 -> 0
B73: (P-21) Autex R1.8 Sound Solution | C73: 84 | D73: m2 | E73: 0.12 | F73: =C73*E73 -> 10.08 | G73: =$H$11*E73 -> 5.4 | H73: =F73*$H$11 -> 453.6 | J73: =C73*I73 -> 0 | K73: =SUM(H73,J73) -> 453.6 | L73: =K73/C73 -> 5.4 | M73: =C73*L73 -> 453.6 | N73: 0 | O73: =M73*N73 -> 0
B74: Autex Baffle Block to Above | C74: 29 | D74: m | E74: 0.7 | F74: =C74*E74 -> 20.3 | G74: =$H$11*E74 -> 31.5 | H74: =F74*$H$11 -> 913.5 | I74: =$X$27 -> 75.719875 | J74: =C74*I74 -> 2195.8764 | K74: =SUM(H74,J74) -> 3109.3764 | L74: =K74/C74 -> 107.21987 | M74: =C74*L74 -> 3109.3764 | N74: 0 | O74: =M74*N74 -> 0 | P74: 26.5
B76: (P-21A) Autex R1.8 Sound Solution | C76: 16 | D76: m2 | E76: 0.12 | F76: =C76*E76 -> 1.92 | G76: =$H$11*E76 -> 5.4 | H76: =F76*$H$11 -> 86.4 | J76: =C76*I76 -> 0 | K76: =SUM(H76,J76) -> 86.4 | L76: =K76/C76 -> 5.4 | M76: =C76*L76 -> 86.4 | N76: 0 | O76: =M76*N76 -> 0
B77: Autex Baffle Block to Above | C77: 5 | D77: m | E77: 0.7 | F77: =C77*E77 -> 3.5 | G77: =$H$11*E77 -> 31.5 | H77: =F77*$H$11 -> 157.5 | I77: =$X$27 -> 75.719875 | J77: =C77*I77 -> 378.59938 | K77: =SUM(H77,J77) -> 536.09938 | L77: =K77/C77 -> 107.21988 | M77: =C77*L77 -> 536.09938 | N77: 0 | O77: =M77*N77 -> 0 | P77: 4.5
B80: Level 6:
B82: (P-10) Autex R1.8 Sound Solution | C82: 68 | D82: m2 | E82: 0.12 | F82: =C82*E82 -> 8.16 | G82: =$H$11*E82 -> 5.4 | H82: =F82*$H$11 -> 367.2 | I82: =$X$25 -> 9.0354739 | J82: =C82*I82 -> 614.41222 | K82: =SUM(H82,J82) -> 981.61222 | L82: =K82/C82 -> 14.435474 | M82: =C82*L82 -> 981.61222 | N82: 0 | O82: =M82*N82 -> 0
B84: (P-12) Autex R1.8 Sound Solution | C84: 15 | D84: m2 | E84: 0.12 | F84: =C84*E84 -> 1.8 | G84: =$H$11*E84 -> 5.4 | H84: =F84*$H$11 -> 81 | I84: =$X$25 -> 9.0354739 | J84: =C84*I84 -> 135.53211 | K84: =SUM(H84,J84) -> 216.53211 | L84: =K84/C84 -> 14.435474 | M84: =C84*L84 -> 216.53211 | N84: 0 | O84: =M84*N84 -> 0
B86: (P-20) Autex R1.8 Sound Solution | C86: 239 | D86: m2 | E86: 0.12 | F86: =C86*E86 -> 28.68 | G86: =$H$11*E86 -> 5.4 | H86: =F86*$H$11 -> 1290.6 | I86: =$X$25 -> 9.0354739 | J86: =C86*I86 -> 2159.4783 | K86: =SUM(H86,J86) -> 3450.0783 | L86: =K86/C86 -> 14.435474 | M86: =C86*L86 -> 3450.0783 | N86: 0 | O86: =M86*N86 -> 0
B88: (P-20A) Autex R1.8 Sound Solution | C88: 221 | D88: m2 | E88: 0.12 | F88: =C88*E88 -> 26.52 | G88: =$H$11*E88 -> 5.4 | H88: =F88*$H$11 -> 1193.4 | I88: =$X$25 -> 9.0354739 | J88: =C88*I88 -> 1996.8397 | K88: =SUM(H88,J88) -> 3190.2397 | L88: =K88/C88 -> 14.435474 | M88: =C88*L88 -> 3190.2397 | N88: 0 | O88: =M88*N88 -> 0
B90: (P-23AS) Autex R1.8 Sound Solution | C90: 7 | D90: m2 | E90: 0.12 | F90: =C90*E90 -> 0.84 | G90: =$H$11*E90 -> 5.4 | H90: =F90*$H$11 -> 37.8 | I90: =$X$25 -> 9.0354739 | J90: =C90*I90 -> 63.248317 | K90: =SUM(H90,J90) -> 101.04832 | L90: =K90/C90 -> 14.435474 | M90: =C90*L90 -> 101.04832 | N90: 0 | O90: =M90*N90 -> 0
B92: (P-24) TWIN WALL - Autex R1.8 Sound Solution | C92: 31 | D92: m2 | E92: 0.24 | F92: =C92*E92 -> 7.44 | G92: =$H$11*E92 -> 10.8 | H92: =F92*$H$11 -> 334.8 | I92: =$X$25*2 -> 18.070948 | J92: =C92*I92 -> 560.19938 | K92: =SUM(H92,J92) -> 894.99938 | L92: =K92/C92 -> 28.870948 | M92: =C92*L92 -> 894.99938 | N92: 0 | O92: =M92*N92 -> 0 | P92: DOUBLE RATE
F95: =SUM(F13:F94) -> 310.98 | H95: =SUM(H13:H94) -> 13994.1 | J95: =SUM(J13:J94) -> 23755.524
B96: Total of above | M96: =SUM(M13:M94) -> 37749.624 | O96: =SUM(O13:O94) -> 0
B97: Miscellaneous
B99: P&G - Admin / Supervision | D99: Sum | L99: 0.0205 | M99: =M96*L99 -> 773.86729 | O99: =(O96/M96)*M99 -> 0
B101: P&G - Site Establishment | D101: Sum | L101: 0.01 | M101: =M96*L101 -> 377.49624 | O101: =(O96/M96)*M101 -> 0
B103: P&G - Access Equip | D103: Sum | L103: 0.0025 | M103: =M96*L103 -> 94.37406 | O103: =(O96/M96)*M103 -> 0
B105: P&G - Parking | D105: Sum | L105: =M105/M96 -> 0.018535416 | M105: =I118 -> 699.705
B107: P&G Travel | D107: Sum | O107: =M107*N107 -> 0
B109: Sub total | M109: =SUM(M96:M108) -> 39695.067 | O109: =SUM(O96:O108) -> 0
B111: Margin | L111: 0.05 | M111: =M109*L111 -> 1984.7533 | O111: =O109/M109*M111 -> 0
B113: TOTAL OF INSULATION | M113: =ROUNDUP(SUM(M109:M112),0) -> 41680 | N113: =O113/M113 -> 0 | O113: =SUM(O109:O112) -> 0
N114: =SUM(L98:L108) -> 0.051535416 | P114: =L111 -> 0.05
G115: Parking | K115: =SUM(F16:F22,F43:F60) -> 96.09 | L115: LEVEL 4 | M115: =SUM(M16:M22,M43:M60) -> 11762.649 | N115: =M115*$N$114 -> 606.19301 | O115: =SUM(M115:N115) -> 12368.842 | P115: =O115*$P$114 -> 618.4421 | Q115: =SUM(O115:P115) -> 12987.284
H116: Man
G117: =F95/8 -> 38.8725 | H117: 1 | K117: =SUM(F23:F27,F64:F78) -> 67.5 | L117: LEVEL 5 | M117: =SUM(M23:M27,M64:M78) -> 8251.9892 | N117: =M117*$N$114 -> 425.2697 | O117: =SUM(M117:N117) -> 8677.2589 | P117: =O117*$P$114 -> 433.86294 | Q117: =SUM(O117:P117) -> 9111.1218
G118: =G117/H117 -> 38.8725 | H118: 18 | I118: =G118*H118 -> 699.705
K119: =SUM(F29:F38,F81:F92) -> 147.39 | L119: LEVEL 6 | M119: =SUM(M29:M38,M81:M92) -> 17734.986 | N119: =M119*$N$114 -> 913.97989 | O119: =SUM(M119:N119) -> 18648.966 | P119: =O119*$P$114 -> 932.44829 | Q119: =SUM(O119:P119) -> 19581.414
K121: =SUM(K115:K120) -> 310.98 | M121: =SUM(M115:M120) -> 37749.624 | Q121: =SUM(Q115:Q120) -> 41679.82
B122: Rate build for travel by car | I122: Rate build for travel by car
B123: Travel there and back based on 4 | I123: Travel there and back based on 1
B124: hrs travel per person | C124: Rate /Km | D124: Total | E124: Number of people | I124: hrs travel per person | J124: Rate /Km | K124: Total | L124: Number of people
B125: 1 | C125: 55 | D125: =B125*C125 -> 55 | E125: =D125*F125 -> 110 | F125: 2 | I125: 4 | J125: 55 | K125: =I125*J125 -> 220 | L125: =K125*M125 -> 440 | M125: 2
B126: km | E126: There and back | I126: km | L126: There and back
B127: 0.7 | E127: =B127*C127 -> 0 | I127: 0.7 | J127: 310 | L127: =I127*J127 -> 217
B128: Amount of trips needed | E128: =SUM(E125:E127) -> 110 | I128: Amount of trips needed | L128: =SUM(L125:L127) -> 657
B129: 2 | E129: =B129*E128 -> 220 | I129: 1 | L129: =I129*L128 -> 657
B130: Accom/per day | C130: days | E130: Times amount of people | I130: Accom/per day | J130: days | L130: Times amount of people
D131: =B131*C131 -> 0 | E131: =D131*F125 -> 0 | I131: 125 | J131: 4 | K131: =I131*J131 -> 500 | L131: =K131*M125 -> 1000
E132: =SUM(E129:E131) -> 220 | L132: =SUM(L129:L131) -> 1657
D136: Parking | E136: =F95/8.5 -> 36.585882 | F136: =E136*17.5 -> 640.25294 | G136: $17.50 per day

Sheet Gib Linings
B1: =Summary!B1 -> Ceilings Unlimited
B2: =Summary!B2 -> Craigs Investment Partners - Fitout
B3: =Summary!B3 -> Tauranga
B6: =Summary!B5 -> 46043
B9: =Summary!B123 -> Gib Wall and Ceiling Linings
H11: 50
A12: Item | B12: Description | C12: Qty | D12: Unit | E12: Constant | F12: Constant X Unit = Total HRS | G12: $ Lab per Unit | H12: Total Labour | I12: Materials per Unit | J12: Total Materials | K12: Total Labour & Materials | L12: Total Labour & Materials Per Unit | M12: Total | N12: % Complete | O12: Claim
B14: Ceiling/Bulkhead Linings:
B16: Level 4:
B17: (C-02) 13mm Gib Standard | C17: 45 | D17: m2 | E17: 0.2 | F17: =C17*E17 -> 9 | G17: =$H$11*E17 -> 10 | H17: =F17*$H$11 -> 450 | I17: 14 | J17: =C17*I17 -> 630 | K17: =SUM(H17,J17) -> 1080 | L17: =K17/C17 -> 24 | M17: =C17*L17 -> 1080 | N17: 0 | O17: =M17*N17 -> 0
B18: Bulkhead to C-02/C-04 13mm Gib Standard | C18: 45 | D18: m2 | E18: 0.35 | F18: =C18*E18 -> 15.75 | G18: =$H$11*E18 -> 17.5 | H18: =F18*$H$11 -> 787.5 | I18: 14 | J18: =C18*I18 -> 630 | K18: =SUM(H18,J18) -> 1417.5 | L18: =K18/C18 -> 31.5 | M18: =C18*L18 -> 1417.5 | N18: 0 | O18: =M18*N18 -> 0
B19: Trim to Floor Above | C19: 41 | D19: m | E19: 0.1 | F19: =C19*E19 -> 4.1 | G19: =$H$11*E19 -> 5 | H19: =F19*$H$11 -> 205 | I19: 0 | J19: =C19*I19 -> 0 | K19: =SUM(H19,J19) -> 205 | L19: =K19/C19 -> 5 | M19: =C19*L19 -> 205 | N19: 0 | O19: =M19*N19 -> 0
B20: Sealant to Floor | C20: 41 | D20: m | E20: 0.1 | F20: =C20*E20 -> 4.1 | G20: =$H$11*E20 -> 5 | H20: =F20*$H$11 -> 205 | I20: 4 | J20: =C20*I20 -> 164 | K20: =SUM(H20,J20) -> 369 | L20: =K20/C20 -> 9 | M20: =C20*L20 -> 369 | N20: 0 | O20: =M20*N20 -> 0
B22: Bulkhead to C-01/C-04 13mm Gib Standard | C22: 14 | D22: m2 | E22: 0.35 | F22: =C22*E22 -> 4.9 | G22: =$H$11*E22 -> 17.5 | H22: =F22*$H$11 -> 245 | I22: 14 | J22: =C22*I22 -> 196 | K22: =SUM(H22,J22) -> 441 | L22: =K22/C22 -> 31.5 | M22: =C22*L22 -> 441 | N22: 0 | O22: =M22*N22 -> 0
B23: Trim to Floor Above | C23: 13 | D23: m | E23: 0.1 | F23: =C23*E23 -> 1.3 | G23: =$H$11*E23 -> 5 | H23: =F23*$H$11 -> 65 | I23: 0 | J23: =C23*I23 -> 0 | K23: =SUM(H23,J23) -> 65 | L23: =K23/C23 -> 5 | M23: =C23*L23 -> 65 | N23: 0 | O23: =M23*N23 -> 0
B24: EV to Bottom Edge Return | C24: 13 | D24: m | E24: 0.1 | F24: =C24*E24 -> 1.3 | G24: =$H$11*E24 -> 5 | H24: =F24*$H$11 -> 65 | I24: 0 | J24: =C24*I24 -> 0 | K24: =SUM(H24,J24) -> 65 | L24: =K24/C24 -> 5 | M24: =C24*L24 -> 65 | N24: 0 | O24: =M24*N24 -> 0
B25: Sealant to Floor | C25: 13 | D25: m | E25: 0.1 | F25: =C25*E25 -> 1.3 | G25: =$H$11*E25 -> 5 | H25: =F25*$H$11 -> 65 | I25: 4 | J25: =C25*I25 -> 52 | K25: =SUM(H25,J25) -> 117 | L25: =K25/C25 -> 9 | M25: =C25*L25 -> 117 | N25: 0 | O25: =M25*N25 -> 0
B27: Bulkhead to C-01/C-02 13mm Gib Standard | C27: 4 | D27: m2 | E27: 0.35 | F27: =C27*E27 -> 1.4 | G27: =$H$11*E27 -> 17.5 | H27: =F27*$H$11 -> 70 | I27: 14 | J27: =C27*I27 -> 56 | K27: =SUM(H27,J27) -> 126 | L27: =K27/C27 -> 31.5 | M27: =C27*L27 -> 126 | N27: 0 | O27: =M27*N27 -> 0
B28: Trim to Floor Above | C28: 4 | D28: m | E28: 0.1 | F28: =C28*E28 -> 0.4 | G28: =$H$11*E28 -> 5 | H28: =F28*$H$11 -> 20 | I28: 0 | J28: =C28*I28 -> 0 | K28: =SUM(H28,J28) -> 20 | L28: =K28/C28 -> 5 | M28: =C28*L28 -> 20 | N28: 0 | O28: =M28*N28 -> 0
B29: EV to Bottom Edge Return | C29: 4 | D29: m | E29: 0.1 | F29: =C29*E29 -> 0.4 | G29: =$H$11*E29 -> 5 | H29: =F29*$H$11 -> 20 | I29: 0 | J29: =C29*I29 -> 0 | K29: =SUM(H29,J29) -> 20 | L29: =K29/C29 -> 5 | M29: =C29*L29 -> 20 | N29: 0 | O29: =M29*N29 -> 0
B30: Sealant to Floor | C30: 4 | D30: m | E30: 0.1 | F30: =C30*E30 -> 0.4 | G30: =$H$11*E30 -> 5 | H30: =F30*$H$11 -> 20 | I30: 4 | J30: =C30*I30 -> 16 | K30: =SUM(H30,J30) -> 36 | L30: =K30/C30 -> 9 | M30: =C30*L30 -> 36 | N30: 0 | O30: =M30*N30 -> 0 | R30: =SUM(F17:F30) -> 44.35
B33: Level 5:
B34: Bulkhead to C-01/C-04 13mm Gib Standard | C34: 15 | D34: m2 | E34: 0.35 | F34: =C34*E34 -> 5.25 | G34: =$H$11*E34 -> 17.5 | H34: =F34*$H$11 -> 262.5 | I34: 14 | J34: =C34*I34 -> 210 | K34: =SUM(H34,J34) -> 472.5 | L34: =K34/C34 -> 31.5 | M34: =C34*L34 -> 472.5 | N34: 0 | O34: =M34*N34 -> 0
B35: Trim to Floor Above | C35: 14 | D35: m | E35: 0.1 | F35: =C35*E35 -> 1.4 | G35: =$H$11*E35 -> 5 | H35: =F35*$H$11 -> 70 | I35: 0 | J35: =C35*I35 -> 0 | K35: =SUM(H35,J35) -> 70 | L35: =K35/C35 -> 5 | M35: =C35*L35 -> 70 | N35: 0 | O35: =M35*N35 -> 0
B36: EV to Bottom Edge Return | C36: 14 | D36: m | E36: 0.1 | F36: =C36*E36 -> 1.4 | G36: =$H$11*E36 -> 5 | H36: =F36*$H$11 -> 70 | I36: 0 | J36: =C36*I36 -> 0 | K36: =SUM(H36,J36) -> 70 | L36: =K36/C36 -> 5 | M36: =C36*L36 -> 70 | N36: 0 | O36: =M36*N36 -> 0
B37: Sealant to Floor | C37: 14 | D37: m | E37: 0.05 | F37: =C37*E37 -> 0.7 | G37: =$H$11*E37 -> 2.5 | H37: =F37*$H$11 -> 35 | I37: 4 | J37: =C37*I37 -> 56 | K37: =SUM(H37,J37) -> 91 | L37: =K37/C37 -> 6.5 | M37: =C37*L37 -> 91 | N37: 0 | O37: =M37*N37 -> 0
B40: Level 6:
B41: (C-02) 13mm Gib Standard | C41: 4 | D41: m2 | E41: 0.2 | F41: =C41*E41 -> 0.8 | G41: =$H$11*E41 -> 10 | H41: =F41*$H$11 -> 40 | I41: 14 | J41: =C41*I41 -> 56 | K41: =SUM(H41,J41) -> 96 | L41: =K41/C41 -> 24 | M41: =C41*L41 -> 96 | N41: 0 | O41: =M41*N41 -> 0
B43: (C-03) 13mm Gib Noiseline | C43: 249 | D43: m2 | E43: 0.2 | F43: =C43*E43 -> 49.8 | G43: =$H$11*E43 -> 10 | H43: =F43*$H$11 -> 2490 | I43: 18.57 | J43: =C43*I43 -> 4623.93 | K43: =SUM(H43,J43) -> 7113.93 | L43: =K43/C43 -> 28.57 | M43: =C43*L43 -> 7113.93 | N43: 0 | O43: =M43*N43 -> 0
B44: Caulking to Above | C44: 300 | D44: m | E44: 0.05 | F44: =C44*E44 -> 15 | G44: =$H$11*E44 -> 2.5 | H44: =F44*$H$11 -> 750 | I44: 2.5 | J44: =C44*I44 -> 750 | K44: =SUM(H44,J44) -> 1500 | L44: =K44/C44 -> 5 | M44: =C44*L44 -> 1500 | N44: 0 | O44: =M44*N44 -> 0
B46: (C-09) 13mm Gib Aqualine | C46: 36 | D46: m2 | E46: 0.22 | F46: =C46*E46 -> 7.92 | G46: =$H$11*E46 -> 11 | H46: =F46*$H$11 -> 396 | I46: 24.97 | J46: =C46*I46 -> 898.92 | K46: =SUM(H46,J46) -> 1294.92 | L46: =K46/C46 -> 35.97 | M46: =C46*L46 -> 1294.92 | N46: 0 | O46: =M46*N46 -> 0
B48: Bulkhead to C-03/C-11 13mm Gib Standard | C48: 4 | D48: m2 | E48: 0.34 | F48: =C48*E48 -> 1.36 | G48: =$H$11*E48 -> 17 | H48: =F48*$H$11 -> 68 | I48: 14 | J48: =C48*I48 -> 56 | K48: =SUM(H48,J48) -> 124 | L48: =K48/C48 -> 31 | M48: =C48*L48 -> 124 | N48: 0 | O48: =M48*N48 -> 0
B49: Trim to Floor Above | C49: 4 | D49: m | E49: 0.1 | F49: =C49*E49 -> 0.4 | G49: =$H$11*E49 -> 5 | H49: =F49*$H$11 -> 20 | I49: 0 | J49: =C49*I49 -> 0 | K49: =SUM(H49,J49) -> 20 | L49: =K49/C49 -> 5 | M49: =C49*L49 -> 20 | N49: 0 | O49: =M49*N49 -> 0
B50: EV to Bottom Edge Return | C50: 4 | D50: m | E50: 0.1 | F50: =C50*E50 -> 0.4 | G50: =$H$11*E50 -> 5 | H50: =F50*$H$11 -> 20 | I50: 0 | J50: =C50*I50 -> 0 | K50: =SUM(H50,J50) -> 20 | L50: =K50/C50 -> 5 | M50: =C50*L50 -> 20 | N50: 0 | O50: =M50*N50 -> 0
B51: Sealant to Floor | C51: 4 | D51: m | E51: 0.05 | F51: =C51*E51 -> 0.2 | G51: =$H$11*E51 -> 2.5 | H51: =F51*$H$11 -> 10 | I51: 2.5 | J51: =C51*I51 -> 10 | K51: =SUM(H51,J51) -> 20 | L51: =K51/C51 -> 5 | M51: =C51*L51 -> 20 | N51: 0 | O51: =M51*N51 -> 0 | P51: =SUM(C46,C43,C41) -> 289
B54: Wall Linings:
B56: Level 4: | P56: =SUM(C58,C59,C67,C68,C74,C75,C78,C79,C82,C83,C86,C88,C90,C92,C94) -> 878
P57: =SUM(C70,C95) -> 31
B58: (P-10) 2/13mm Gib Noiseline | C58: 4 | D58: m2 | E58: 0.42 | F58: =C58*E58 -> 1.68 | G58: =$H$11*E58 -> 21 | H58: =F58*$H$11 -> 84 | I58: 37.14 | J58: =C58*I58 -> 148.56 | K58: =SUM(H58,J58) -> 232.56 | L58: =K58/C58 -> 58.14 | M58: =C58*L58 -> 232.56 | N58: 0 | O58: =M58*N58 -> 0
B59: (P-10) 13mm Gib Noiseline | C59: 4 | D59: m2 | E59: 0.21 | F59: =C59*E59 -> 0.84 | G59: =$H$11*E59 -> 10.5 | H59: =F59*$H$11 -> 42 | I59: 18.57 | J59: =C59*I59 -> 74.28 | K59: =SUM(H59,J59) -> 116.28 | L59: =K59/C59 -> 29.07 | M59: =C59*L59 -> 116.28 | N59: 0 | O59: =M59*N59 -> 0
B60: Soundseal | C60: 8 | D60: m | E60: 0.05 | F60: =C60*E60 -> 0.4 | G60: =$H$11*E60 -> 2.5 | H60: =F60*$H$11 -> 20 | I60: 2.5 | J60: =C60*I60 -> 20 | K60: =SUM(H60,J60) -> 40 | L60: =K60/C60 -> 5 | M60: =C60*L60 -> 40 | N60: 0 | O60: =M60*N60 -> 0
B61: Trim to Floor Above | C61: 12 | D61: m | E61: 0.1 | F61: =C61*E61 -> 1.2 | G61: =$H$11*E61 -> 5 | H61: =F61*$H$11 -> 60 | I61: 0 | J61: =C61*I61 -> 0 | K61: =SUM(H61,J61) -> 60 | L61: =K61/C61 -> 5 | M61: =C61*L61 -> 60 | N61: 0 | O61: =M61*N61 -> 0
B63: (P-11) 13mm Gib Overlay | C63: Refer Partitions
B65: (P-13) | C65: Refer Suspended Ceilings/Potters
B67: (P-20A) 2/13mm Gib Noiseline | C67: 34 | D67: m2 | E67: 0.42 | F67: =C67*E67 -> 14.28 | G67: =$H$11*E67 -> 21 | H67: =F67*$H$11 -> 714 | I67: 37.14 | J67: =C67*I67 -> 1262.76 | K67: =SUM(H67,J67) -> 1976.76 | L67: =K67/C67 -> 58.14 | M67: =C67*L67 -> 1976.76 | N67: 0 | O67: =M67*N67 -> 0
B68: (P-20A) 13mm Gib Noiseline | C68: 34 | D68: m2 | E68: 0.21 | F68: =C68*E68 -> 7.14 | G68: =$H$11*E68 -> 10.5 | H68: =F68*$H$11 -> 357 | I68: 18.57 | J68: =C68*I68 -> 631.38 | K68: =SUM(H68,J68) -> 988.38 | L68: =K68/C68 -> 29.07 | M68: =C68*L68 -> 988.38 | N68: 0 | O68: =M68*N68 -> 0
B69: Soundseal | C69: 36 | D69: m | E69: 0.05 | F69: =C69*E69 -> 1.8 | G69: =$H$11*E69 -> 2.5 | H69: =F69*$H$11 -> 90 | I69: 2.5 | J69: =C69*I69 -> 90 | K69: =SUM(H69,J69) -> 180 | L69: =K69/C69 -> 5 | M69: =C69*L69 -> 180 | N69: 0 | O69: =M69*N69 -> 0
B70: (P-20A) 13mm Noiseline Bulkhead/Upstand | C70: 20 | D70: m2 | E70: 0.21 | F70: =C70*E70 -> 4.2 | G70: =$H$11*E70 -> 10.5 | H70: =F70*$H$11 -> 210 | I70: 18.57 | J70: =C70*I70 -> 371.4 | K70: =SUM(H70,J70) -> 581.4 | L70: =K70/C70 -> 29.07 | M70: =C70*L70 -> 581.4 | N70: 0 | O70: =M70*N70 -> 0
B71: EV less then 300 bottom edge | C71: 18 | D71: m | E71: 0.1 | F71: =C71*E71 -> 1.8 | G71: =$H$11*E71 -> 5 | H71: =F71*$H$11 -> 90 | I71: 0 | J71: =C71*I71 -> 0 | K71: =SUM(H71,J71) -> 90 | L71: =K71/C71 -> 5 | M71: =C71*L71 -> 90 | N71: 0 | O71: =M71*N71 -> 0
B72: Trim to Floor Above | C72: 27 | D72: m | E72: 0.1 | F72: =C72*E72 -> 2.7 | G72: =$H$11*E72 -> 5 | H72: =F72*$H$11 -> 135 | I72: 0 | J72: =C72*I72 -> 0 | K72: =SUM(H72,J72) -> 135 | L72: =K72/C72 -> 5 | M72: =C72*L72 -> 135 | N72: 0 | O72: =M72*N72 -> 0
B74: (P-21S) 2/13mm Gib Noiseline | C74: 19 | D74: m2 | E74: 0.42 | F74: =C74*E74 -> 7.98 | G74: =$H$11*E74 -> 21 | H74: =F74*$H$11 -> 399 | I74: 37.14 | J74: =C74*I74 -> 705.66 | K74: =SUM(H74,J74) -> 1104.66 | L74: =K74/C74 -> 58.14 | M74: =C74*L74 -> 1104.66 | N74: 0 | O74: =M74*N74 -> 0
B75: (P-21S) 13mm Gib Noiseline | C75: 19 | D75: m2 | E75: 0.21 | F75: =C75*E75 -> 3.99 | G75: =$H$11*E75 -> 10.5 | H75: =F75*$H$11 -> 199.5 | I75: 18.57 | J75: =C75*I75 -> 352.83 | K75: =SUM(H75,J75) -> 552.33 | L75: =K75/C75 -> 29.07 | M75: =C75*L75 -> 552.33 | N75: 0 | O75: =M75*N75 -> 0
B76: Soundseal | C76: 14 | D76: m | E76: 0.05 | F76: =C76*E76 -> 0.7 | G76: =$H$11*E76 -> 2.5 | H76: =F76*$H$11 -> 35 | I76: 2.5 | J76: =C76*I76 -> 35 | K76: =SUM(H76,J76) -> 70 | L76: =K76/C76 -> 5 | M76: =C76*L76 -> 70 | N76: 0 | O76: =M76*N76 -> 0
B78: (P-21) 2/13mm Gib Noiseline | C78: 141 | D78: m2 | E78: 0.42 | F78: =C78*E78 -> 59.22 | G78: =$H$11*E78 -> 21 | H78: =F78*$H$11 -> 2961 | I78: 37.14 | J78: =C78*I78 -> 5236.74 | K78: =SUM(H78,J78) -> 8197.74 | L78: =K78/C78 -> 58.14 | M78: =C78*L78 -> 8197.74 | N78: 0 | O78: =M78*N78 -> 0
B79: (P-21) 13mm Gib Noiseline | C79: 141 | D79: m2 | E79: 0.21 | F79: =C79*E79 -> 29.61 | G79: =$H$11*E79 -> 10.5 | H79: =F79*$H$11 -> 1480.5 | I79: 18.57 | J79: =C79*I79 -> 2618.37 | K79: =SUM(H79,J79) -> 4098.87 | L79: =K79/C79 -> 29.07 | M79: =C79*L79 -> 4098.87 | N79: 0 | O79: =M79*N79 -> 0
B80: Soundseal | C80: 96 | D80: m | E80: 0.05 | F80: =C80*E80 -> 4.8 | G80: =$H$11*E80 -> 2.5 | H80: =F80*$H$11 -> 240 | I80: 2.5 | J80: =C80*I80 -> 240 | K80: =SUM(H80,J80) -> 480 | L80: =K80/C80 -> 5 | M80: =C80*L80 -> 480 | N80: 0 | O80: =M80*N80 -> 0
... B103: 2/6.5mm Layer of Curveline Gib to Coumns (PF-01) | C103: 1 | D103: no | E103: 4 | F103: =C103*E103 -> 4 | G103: =$H$11*E103 -> 200 | H103: =F103*$H$11 -> 200 | I103: 430 | J103: =C103*I103 -> 430 | K103: =SUM(H103,J103) -> 630 | L103: =K103/C103 -> 630 | M103: =C103*L103 -> 630 | N103: 0 | O103: =M103*N103 -> 0
B105: Level 5: | P105: =SUM(C107,C108,C114,C115,C118,C119,C125,C126,C129,C130,C133,C135,C137) -> 762
P106: =SUM(C121,C138) -> 25
B107: (P-10) 2/13mm Gib Noiseline | C107: 14 | D107: m2 | E107: 0.42 | F107: =C107*E107 -> 5.88 | G107: =$H$11*E107 -> 21 | H107: =F107*$H$11 -> 294 | I107: 37.14 | J107: =C107*I107 -> 519.96 | K107: =SUM(H107,J107) -> 813.96 | L107: =K107/C107 -> 58.14 | M107: =C107*L107 -> 813.96 | N107: 0 | O107: =M107*N107 -> 0
B108: (P-10) 13mm Gib Noiseline | C108: 14 | D108: m2 | E108: 0.21 | F108: =C108*E108 -> 2.94 | G108: =$H$11*E108 -> 10.5 | H108: =F108*$H$11 -> 147 | I108: 18.57 | J108: =C108*I108 -> 259.98 | K108: =SUM(H108,J108) -> 406.98 | L108: =K108/C108 -> 29.07 | M108: =C108*L108 -> 406.98 | N108: 0 | O108: =M108*N108 -> 0
B109: Soundseal | C109: 28 | D109: m | E109: 0.05 | F109: =C109*E109 -> 1.4 | G109: =$H$11*E109 -> 2.5 | H109: =F109*$H$11 -> 70 | I109: 2.5 | J109: =C109*I109 -> 70 | K109: =SUM(H109,J109) -> 140 | L109: =K109/C109 -> 5 | M109: =C109*L109 -> 140 | N109: 0 | O109: =M109*N109 -> 0
B110: Trim to Floor Above | C110: 42 | D110: m | E110: 0.1 | F110: =C110*E110 -> 4.2 | G110: =$H$11*E110 -> 5 | H110: =F110*$H$11 -> 210 | I110: 0 | J110: =C110*I110 -> 0 | K110: =SUM(H110,J110) -> 210 | L110: =K110/C110 -> 5 | M110: =C110*L110 -> 210 | N110: 0 | O110: =M110*N110 -> 0
B112: (P-11) 13mm Gib Overlay | C112: Refer Partitions
B114: (P-20) 2/13mm Gib Noiseline | C114: 114 | D114: m2 | E114: 0.42 | F114: =C114*E114 -> 47.88 | G114: =$H$11*E114 -> 21 | H114: =F114*$H$11 -> 2394 | I114: 37.14 | J114: =C114*I114 -> 4233.96 | K114: =SUM(H114,J114) -> 6627.96 | L114: =K114/C114 -> 58.14 | M114: =C114*L114 -> 6627.96 | N114: 0 | O114: =M114*N114 -> 0
B115: (P-20) 13mm Gib Noiseline | C115: 114 | D115: m2 | E115: 0.21 | F115: =C115*E115 -> 23.94 | G115: =$H$11*E115 -> 10.5 | H115: =F115*$H$11 -> 1197 | I115: 18.57 | J115: =C115*I115 -> 2116.98 | K115: =SUM(H115,J115) -> 3313.98 | L115: =K115/C115 -> 29.07 | M115: =C115*L115 -> 3313.98 | N115: 0 | O115: =M115*N115 -> 0
B116: Soundseal | C116: 116 | D116: m | E116: 0.05 | F116: =C116*E116 -> 5.8 | G116: =$H$11*E116 -> 2.5 | H116: =F116*$H$11 -> 290 | I116: 2.5 | J116: =C116*I116 -> 290 | K116: =SUM(H116,J116) -> 580 | L116: =K116/C116 -> 5 | M116: =C116*L116 -> 580 | N116: 0 | O116: =M116*N116 -> 0
B118: (P-20A) 2/13mm Gib Noiseline | C118: 72 | D118: m2 | E118: 0.42 | F118: =C118*E118 -> 30.24 | G118: =$H$11*E118 -> 21 | H118: =F118*$H$11 -> 1512 | I118: 37.14 | J118: =C118*I118 -> 2674.08 | K118: =SUM(H118,J118) -> 4186.08 | L118: =K118/C118 -> 58.14 | M118: =C118*L118 -> 4186.08 | N118: 0 | O118: =M118*N118 -> 0
B119: (P-20A) 13mm Gib Noiseline | C119: 72 | D119: m2 | E119: 0.21 | F119: =C119*E119 -> 15.12 | G119: =$H$11*E119 -> 10.5 | H119: =F119*$H$11 -> 756 | I119: 18.57 | J119: =C119*I119 -> 1337.04 | K119: =SUM(H119,J119) -> 2093.04 | L119: =K119/C119 -> 29.07 | M119: =C119*L119 -> 2093.04 | N119: 0 | O119: =M119*N119 -> 0
B120: Soundseal | C120: 72 | D120: m | E120: 0.05 | F120: =C120*E120 -> 3.6 | G120: =$H$11*E120 -> 2.5 | H120: =F120*$H$11 -> 180 | I120: 2.5 | J120: =C120*I120 -> 180 | K120: =SUM(H120,J120) -> 360 | L120: =K120/C120 -> 5 | M120: =C120*L120 -> 360 | N120: 0 | O120: =M120*N120 -> 0
B121: (P-20A) 13mm Noiseline Bulkhead/Upstand | C121: 20 | D121: m2 | E121: 0.21 | F121: =C121*E121 -> 4.2 | G121: =$H$11*E121 -> 10.5 | H121: =F121*$H$11 -> 210 | I121: 18.57 | J121: =C121*I121 -> 371.4 | K121: =SUM(H121,J121) -> 581.4 | L121: =K121/C121 -> 29.07 | M121: =C121*L121 -> 581.4 | N121: 0 | O121: =M121*N121 -> 0
B122: EV less then 300 bottom edge | C122: 18 | D122: m | E122: 0.1 | F122: =C122*E122 -> 1.8 | G122: =$H$11*E122 -> 5 | H122: =F122*$H$11 -> 90 | I122: 2.5 | J122: =C122*I122 -> 45 | K122: =SUM(H122,J122) -> 135 | L122: =K122/C122 -> 7.5 | M122: =C122*L122 -> 135 | N122: 0 | O122: =M122*N122 -> 0
B123: Trim to Floor Above | C123: 87 | D123: m | E123: 0.1 | F123: =C123*E123 -> 8.7 | G123: =$H$11*E123 -> 5 | H123: =F123*$H$11 -> 435 | I123: 0 | J123: =C123*I123 -> 0 | K123: =SUM(H123,J123) -> 435 | L123: =K123/C123 -> 5 | M123: =C123*L123 -> 435 | N123: 0 | O123: =M123*N123 -> 0
B125: (P-21) 2/13mm Gib Noiseline | C125: 84 | D125: m2 | E125: 0.42 | F125: =C125*E125 -> 35.28 | G125: =$H$11*E125 -> 21 | H125: =F125*$H$11 -> 1764 | I125: 37.14 | J125: =C125*I125 -> 3119.76 | K125: =SUM(H125,J125) -> 4883.76 | L125: =K125/C125 -> 58.14 | M125: =C125*L125 -> 4883.76 | N125: 0 | O125: =M125*N125 -> 0
B126: (P-21) 13mm Gib Noiseline | C126: 84 | D126: m2 | E126: 0.21 | F126: =C126*E126 -> 17.64 | G126: =$H$11*E126 -> 10.5 | H126: =F126*$H$11 -> 882 | I126: 18.57 | J126: =C126*I126 -> 1559.88 | K126: =SUM(H126,J126) -> 2441.88 | L126: =K126/C126 -> 29.07 | M126: =C126*L126 -> 2441.88 | N126: 0 | O126: =M126*N126 -> 0
B127: Soundseal | C127: 58 | D127: m | E127: 0.05 | F127: =C127*E127 -> 2.9 | G127: =$H$11*E127 -> 2.5 | H127: =F127*$H$11 -> 145 | I127: 2.5 | J127: =C127*I127 -> 145 | K127: =SUM(H127,J127) -> 290 | L127: =K127/C127 -> 5 | M127: =C127*L127 -> 290 | N127: 0 | O127: =M127*N127 -> 0
... B144: 1/6.5mm Layer of Curveline Gib to Columns | C144: 12 | D144: no | E144: 2.25 | F144: =C144*E144 -> 27 | G144: =$H$11*E144 -> 112.5 | H144: =F144*$H$11 -> 1350 | I144: 215 | J144: =C144*I144 -> 2580 | K144: =SUM(H144,J144) -> 3930 | L144: =K144/C144 -> 327.5 | M144: =C144*L144 -> 3930 | N144: 0 | O144: =M144*N144 -> 0
B147: Level 6: | P147: =SUM(C149,C150,C154,C155,C161,C162,C166,C167,C175,C177,C179,C181,C183) -> 1324
P148: =SUM(C169) -> 76
B149: (P-10) 2/13mm Gib Noiseline | C149: 68 | D149: m2 | E149: 0.42 | F149: =C149*E149 -> 28.56 | G149: =$H$11*E149 -> 21 | H149: =F149*$H$11 -> 1428 | I149: 37.14 | J149: =C149*I149 -> 2525.52 | K149: =SUM(H149,J149) -> 3953.52 | L149: =K149/C149 -> 58.14 | M149: =C149*L149 -> 3953.52 | N149: 0 | O149: =M149*N149 -> 0
B150: (P-10) 13mm Gib Noiseline | C150: 68 | D150: m2 | E150: 0.21 | F150: =C150*E150 -> 14.28 | G150: =$H$11*E150 -> 10.5 | H150: =F150*$H$11 -> 714 | I150: 18.57 | J150: =C150*I150 -> 1262.76 | K150: =SUM(H150,J150) -> 1976.76 | L150: =K150/C150 -> 29.07 | M150: =C150*L150 -> 1976.76 | N150: 0 | O150: =M150*N150 -> 0
B151: Soundseal | C151: 96 | D151: m | E151: 0.05 | F151: =C151*E151 -> 4.8 | G151: =$H$11*E151 -> 2.5 | H151: =F151*$H$11 -> 240 | I151: 2.5 | J151: =C151*I151 -> 240 | K151: =SUM(H151,J151) -> 480 | L151: =K151/C151 -> 5 | M151: =C151*L151 -> 480 | N151: 0 | O151: =M151*N151 -> 0
B152: Trim to Floor Above | C152: 144 | D152: m | E152: 0.1 | F152: =C152*E152 -> 14.4 | G152: =$H$11*E152 -> 5 | H152: =F152*$H$11 -> 720 | I152: 0 | J152: =C152*I152 -> 0 | K152: =SUM(H152,J152) -> 720 | L152: =K152/C152 -> 5 | M152: =C152*L152 -> 720 | N152: 0 | O152: =M152*N152 -> 0
B154: (P-12) 2/13mm Gib Noiseline | C154: 15 | D154: m2 | E154: 0.42 | F154: =C154*E154 -> 6.3 | G154: =$H$11*E154 -> 21 | H154: =F154*$H$11 -> 315 | I154: 37.14 | J154: =C154*I154 -> 557.1 | K154: =SUM(H154,J154) -> 872.1 | L154: =K154/C154 -> 58.14 | M154: =C154*L154 -> 872.1 | N154: 0 | O154: =M154*N154 -> 0
B155: (P-12) 13mm Gib Noiseline | C155: 15 | D155: m2 | E155: 0.21 | F155: =C155*E155 -> 3.15 | G155: =$H$11*E155 -> 10.5 | H155: =F155*$H$11 -> 157.5 | I155: 18.57 | J155: =C155*I155 -> 278.55 | K155: =SUM(H155,J155) -> 436.05 | L155: =K155/C155 -> 29.07 | M155: =C155*L155 -> 436.05 | N155: 0 | O155: =M155*N155 -> 0
B156: Soundseal | C156: 20 | D156: m | E156: 0.05 | F156: =C156*E156 -> 1 | G156: =$H$11*E156 -> 2.5 | H156: =F156*$H$11 -> 50 | I156: 2.5 | J156: =C156*I156 -> 50 | K156: =SUM(H156,J156) -> 100 | L156: =K156/C156 -> 5 | M156: =C156*L156 -> 100 | N156: 0 | O156: =M156*N156 -> 0
B157: Trim to Floor Above | C157: 40 | D157: m | E157: 0.1 | F157: =C157*E157 -> 4 | G157: =$H$11*E157 -> 5 | H157: =F157*$H$11 -> 200 | I157: 0 | J157: =C157*I157 -> 0 | K157: =SUM(H157,J157) -> 200 | L157: =K157/C157 -> 5 | M157: =C157*L157 -> 200 | N157: 0 | O157: =M157*N157 -> 0
B159: (P-13) | C159: Refer Suspended Ceilings/Potters
B161: (P-20) 2/13mm Gib Noiseline | C161: 239 | D161: m2 | E161: 0.42 | F161: =C161*E161 -> 100.38 | G161: =$H$11*E161 -> 21 | H161: =F161*$H$11 -> 5019 | I161: 37.14 | J161: =C161*I161 -> 8876.46 | K161: =SUM(H161,J161) -> 13895.46 | L161: =K161/C161 -> 58.14 | M161: =C161*L161 -> 13895.46 | N161: 0 | O161: =M161*N161 -> 0
B162: (P-20) 13mm Gib Noiseline | C162: 239 | D162: m2 | E162: 0.21 | F162: =C162*E162 -> 50.19 | G162: =$H$11*E162 -> 10.5 | H162: =F162*$H$11 -> 2509.5 | I162: 18.57 | J162: =C162*I162 -> 4438.23 | K162: =SUM(H162,J162) -> 6947.73 | L162: =K162/C162 -> 29.07 | M162: =C162*L162 -> 6947.73 | N162: 0 | O162: =M162*N162 -> 0
B163: Soundseal | C163: 216 | D163: m | E163: 0.05 | F163: =C163*E163 -> 10.8 | G163: =$H$11*E163 -> 2.5 | H163: =F163*$H$11 -> 540 | I163: 2.5 | J163: =C163*I163 -> 540 | K163: =SUM(H163,J163) -> 1080 | L163: =K163/C163 -> 5 | M163: =C163*L163 -> 1080 | N163: 0 | O163: =M163*N163 -> 0
B164: Trim to Floor Above | C164: 162 | D164: m | E164: 0.1 | F164: =C164*E164 -> 16.2 | G164: =$H$11*E164 -> 5 | H164: =F164*$H$11 -> 810 | I164: 0 | J164: =C164*I164 -> 0 | K164: =SUM(H164,J164) -> 810 | L164: =K164/C164 -> 5 | M164: =C164*L164 -> 810 | N164: 0 | O164: =M164*N164 -> 0
B166: (P-20A) 2/13mm Gib Noiseline | C166: 221 | D166: m2 | E166: 0.42 | F166: =C166*E166 -> 92.82 | G166: =$H$11*E166 -> 21 | H166: =F166*$H$11 -> 4641 | I166: 37.14 | J166: =C166*I166 -> 8207.94 | K166: =SUM(H166,J166) -> 12848.94 | L166: =K166/C166 -> 58.14 | M166: =C166*L166 -> 12848.94 | N166: 0 | O166: =M166*N166 -> 0
B167: (P-20A) 13mm Gib Noiseline | C167: 221 | D167: m2 | E167: 0.21 | F167: =C167*E167 -> 46.41 | G167: =$H$11*E167 -> 10.5 | H167: =F167*$H$11 -> 2320.5 | I167: 18.57 | J167: =C167*I167 -> 4103.97 | K167: =SUM(H167,J167) -> 6424.47 | L167: =K167/C167 -> 29.07 | M167: =C167*L167 -> 6424.47 | N167: 0 | O167: =M167*N167 -> 0
B168: Soundseal | C168: 200 | D168: m | E168: 0.05 | F168: =C168*E168 -> 10 | G168: =$H$11*E168 -> 2.5 | H168: =F168*$H$11 -> 500 | I168: 2.5 | J168: =C168*I168 -> 500 | K168: =SUM(H168,J168) -> 1000 | L168: =K168/C168 -> 5 | M168: =C168*L168 -> 1000 | N168: 0 | O168: =M168*N168 -> 0
B169: (P-20A) 13mm Noiseline Bulkhead/Upstand | C169: 76 | D169: m2 | E169: 0.21 | F169: =C169*E169 -> 15.96 | G169: =$H$11*E169 -> 10.5 | H169: =F169*$H$11 -> 798 | I169: 18.57 | J169: =C169*I169 -> 1411.32 | K169: =SUM(H169,J169) -> 2209.32 | L169: =K169/C169 -> 29.07 | M169: =C169*L169 -> 2209.32 | N169: 0 | O169: =M169*N169 -> 0
B170: EV less then 300 bottom edge | C170: 50 | D170: m | E170: 0.1 | F170: =C170*E170 -> 5 | G170: =$H$11*E170 -> 5 | H170: =F170*$H$11 -> 250 | I170: 0 | J170: =C170*I170 -> 0 | K170: =SUM(H170,J170) -> 250 | L170: =K170/C170 -> 5 | M170: =C170*L170 -> 250 | N170: 0 | O170: =M170*N170 -> 0
B171: Trim to Floor Above | C171: 50 | D171: m | E171: 0.1 | F171: =C171*E171 -> 5 | G171: =$H$11*E171 -> 5 | H171: =F171*$H$11 -> 250 | I171: 0 | J171: =C171*I171 -> 0 | K171: =SUM(H171,J171) -> 250 | L171: =K171/C171 -> 5 | M171: =C171*L171 -> 250 | N171: 0 | O171: =M171*N171 -> 0
B173: Adjust for ID 502, Detail 6 Coffer Detail | C173: -30 | D173: m | E173: 0.1 | F173: =C173*E173 -> -3 | G173: =$H$11*E173 -> 5 | H173: =F173*$H$11 -> -150 | I173: 0 | J173: =C173*I173 -> 0 | K173: =SUM(H173,J173) -> -150 | L173: =K173/C173 -> 5 | M173: =C173*L173 -> -150 | N173: 0 | O173: =M173*N173 -> 0
B175: (P-23) 13mm Gib Standard | C175: 116 | D175: m2 | E175: 0.18 | F175: =C175*E175 -> 20.88 | G175: =$H$11*E175 -> 9 | H175: =F175*$H$11 -> 1044 | I175: 14 | J175: =C175*I175 -> 1624 | K175: =SUM(H175,J175) -> 2668 | L175: =K175/C175 -> 23 | M175: =C175*L175 -> 2668 | N175: 0 | O175: =M175*N175 -> 0
...

Sheet Stopping
B1: =Summary!B1 -> Ceilings Unlimited
B2: =Summary!B2 -> Craigs Investment Partners - Fitout
B3: =Summary!B3 -> Tauranga
B6: =Summary!B5 -> 46043
B9: Stopping
H11: 42
A12: Item | B12: Description | C12: Qty | D12: Unit | E12: Constant | F12: Constant X Unit = Total HRS | G12: $ Lab per Unit | H12: Total Labour | I12: Materials per Unit | J12: Total Materials | K12: Total Labour & Materials | L12: Total Labour & Materials Per Unit | M12: Total | N12: % Complete | O12: Claim | T12: External | U12: Cap | V12: P-01 | W12: External | X12: Cap | Y12: P-01 | Z12: External | AA12: Cap | AB12: P-01
T13: Level 4 | W13: Level 5 | Z13: Level 6
B14: Ceiling Stopping: | T14: =SUM(T15:T31) -> 93 | U14: =SUM(U15:U31) -> 84 | V14: =SUM(V15:V31) -> 82 | W14: =SUM(W15:W31) -> 71 | X14: =SUM(X15:X31) -> 53 | Y14: =SUM(Y15:Y31) -> 34 | Z14: =SUM(Z15:Z31) -> 192 | AA14: =SUM(AA15:AA31) -> 152 | AB14: =SUM(AB15:AB31) -> 13
R15: P-10 | T15: 8 | U15: 8 | V15: 0 | W15: 28 | X15: 28 | Y15: 0 | Z15: 96 | AA15: 96 | AB15: 0
B16: Level 4: | R16: P-11 | T16: 0 | U16: 0 | V16: 23 | W16: 0 | X16: 0 | Y16: 11 | Z16: 0 | AA16: 0 | AB16: 0
B17: Level 4 Stopping to Gib Board | C17: 45 | D17: m2 | E17: 0.2 | F17: =C17*E17 -> 9 | G17: =$H$11*E17 -> 8.4 | H17: =F17*$H$11 -> 378 | I17: 0.95 | J17: =C17*I17 -> 42.75 | K17: =SUM(H17,J17) -> 420.75 | L17: =K17/C17 -> 9.35 | M17: =C17*L17 -> 420.75 | N17: 0 | O17: =M17*N17 -> 0 | R17: P-12 | T17: 0 | U17: 0 | V17: 0 | W17: 0 | X17: 0 | Y17: 0 | Z17: 20 | AA17: 30 | AB17: 0
B18: Level 4 to Bulkhead | C18: 63 | D18: m2 | E18: 0.25 | F18: =C18*E18 -> 15.75 | G18: =$H$11*E18 -> 10.5 | H18: =F18*$H$11 -> 661.5 | I18: 0.95 | J18: =C18*I18 -> 59.85 | K18: =SUM(H18,J18) -> 721.35 | L18: =K18/C18 -> 11.45 | M18: =C18*L18 -> 721.35 | N18: 0 | O18: =M18*N18 -> 0 | R18: P-13 | T18: 7 | U18: 7 | V18: 7 | W18: 0 | X18: 0 | Y18: 0 | Z18: 4 | AA18: 4 | AB18: 4
B19: External Corner - Bulkhead | C19: 93 | D19: m | E19: 0.15 | F19: =C19*E19 -> 13.95 | G19: =$H$11*E19 -> 6.3 | H19: =F19*$H$11 -> 585.9 | I19: 2.5 | J19: =C19*I19 -> 232.5 | K19: =SUM(H19,J19) -> 818.4 | L19: =K19/C19 -> 8.8 | M19: =C19*L19 -> 818.4 | N19: 0 | O19: =M19*N19 -> 0 | R19: P-20 | T19: 0 | U19: 0 | V19: 0 | W19: 0 | X19: 0 | Y19: 0 | Z19: 0 | AA19: 0 | AB19: 0
B20: P13/P26 | C20: 84 | D20: m | E20: 0.18 | F20: =C20*E20 -> 15.12 | G20: =$H$11*E20 -> 7.56 | H20: =F20*$H$11 -> 635.04 | I20: 2.5 | J20: =C20*I20 -> 210 | K20: =SUM(H20,J20) -> 845.04 | L20: =K20/C20 -> 10.06 | M20: =C20*L20 -> 845.04 | N20: 0 | O20: =M20*N20 -> 0 | R20: P-20a | T20: 9 | U20: 0 | V20: 0 | W20: 18 | X20: 0 | Y20: 0 | Z20: 50 | AA20: 0 | AB20: 0
B21: P01 Trim - Plasterboard Strip | C21: 82 | D21: m | E21: 0.15 | F21: =C21*E21 -> 12.3 | G21: =$H$11*E21 -> 6.3 | H21: =F21*$H$11 -> 516.6 | I21: 3 | J21: =C21*I21 -> 246 | K21: =SUM(H21,J21) -> 762.6 | L21: =K21/C21 -> 9.3 | M21: =C21*L21 -> 762.6 | N21: 0 | O21: =M21*N21 -> 0 | R21: P-21 | T21: 0 | U21: 0 | V21: 0 | W21: 0 | X21: 0 | Y21: 0 | Z21: 0 | AA21: 0 | AB21: 0
B22: Square Stopping | C22: 28 | D22: m | E22: 0.15 | F22: =C22*E22 -> 4.2 | G22: =$H$11*E22 -> 6.3 | H22: =F22*$H$11 -> 176.4 | I22: 1.4 | J22: =C22*I22 -> 39.2 | K22: =SUM(H22,J22) -> 215.6 | L22: =K22/C22 -> 7.7 | M22: =C22*L22 -> 215.6 | N22: 0 | O22: =M22*N22 -> 0 | R22: P-21s | T22: 0 | U22: 0 | V22: 0 | W22: 0 | X22: 0 | Y22: 0 | Z22: 0 | AA22: 0 | AB22: 0
R23: P-21a | T23: 0 | U23: 0 | V23: 10 | W23: 0 | X23: 0 | Y23: 5 | Z23: 0 | AA23: 0 | AB23: 0
B24: Level 5: | R24: P-23 | T24: 0 | U24: 0 | V24: 0 | W24: 0 | X24: 0 | Y24: 0 | Z24: 0 | AA24: 0 | AB24: 0
B25: Level 4 to Bulkhead | C25: 15 | D25: m2 | E25: 0.25 | F25: =C25*E25 -> 3.75 | G25: =$H$11*E25 -> 10.5 | H25: =F25*$H$11 -> 157.5 | I25: 0.95 | J25: =C25*I25 -> 14.25 | K25: =SUM(H25,J25) -> 171.75 | L25: =K25/C25 -> 11.45 | M25: =C25*L25 -> 171.75 | N25: 0 | O25: =M25*N25 -> 0 | R25: P-23s | T25: 0 | U25: 0 | V25: 0 | W25: 0 | X25: 0 | Y25: 0 | Z25: 0 | AA25: 0 | AB25: 0
B26: External Corner - Bulkhead | C26: 71 | D26: m | E26: 0.15 | F26: =C26*E26 -> 10.65 | G26: =$H$11*E26 -> 6.3 | H26: =F26*$H$11 -> 447.3 | I26: 2.5 | J26: =C26*I26 -> 177.5 | K26: =SUM(H26,J26) -> 624.8 | L26: =K26/C26 -> 8.8 | M26: =C26*L26 -> 624.8 | N26: 0 | O26: =M26*N26 -> 0 | R26: P-23a | T26: 0 | U26: 0 | V26: 25 | W26: 0 | X26: 0 | Y26: 18 | Z26: 0 | AA26: 0 | AB26: 3
B27: P13/P26 | C27: 53 | D27: m | E27: 0.18 | F27: =C27*E27 -> 9.54 | G27: =$H$11*E27 -> 7.56 | H27: =F27*$H$11 -> 400.68 | I27: 2.5 | J27: =C27*I27 -> 132.5 | K27: =SUM(H27,J27) -> 533.18 | L27: =K27/C27 -> 10.06 | M27: =C27*L27 -> 533.18 | N27: 0 | O27: =M27*N27 -> 0 | R27: P-23as | T27: 0 | U27: 0 | V27: 4 | W27: 0 | X27: 0 | Y27: 0 | Z27: 0 | AA27: 0 | AB27: 2
B28: P01 Trim - Plasterboard Strip | C28: 34 | D28: m | E28: 0.15 | F28: =C28*E28 -> 5.1 | G28: =$H$11*E28 -> 6.3 | H28: =F28*$H$11 -> 214.2 | I28: 3 | J28: =C28*I28 -> 102 | K28: =SUM(H28,J28) -> 316.2 | L28: =K28/C28 -> 9.3 | M28: =C28*L28 -> 316.2 | N28: 0 | O28: =M28*N28 -> 0 | R28: P-23b | T28: 11 | U28: 11 | V28: 0 | W28: 5 | X28: 5 | Y28: 0 | Z28: 0 | AA28: 0 | AB28: 0
R29: P-24 | T29: 0 | U29: 0 | V29: 0 | W29: 0 | X29: 0 | Y29: 0 | Z29: 0 | AA29: 0 | AB29: 0
T30: 58 | U30: 58 | V30: 13 | W30: 20 | X30: 20 | Y30: 0 | Z30: 22 | AA30: 22 | AB30: 4
B31: Level 6:
B32: Level 4 Stopping to Gib Board | C32: 285 | D32: m2 | E32: 0.2 | F32: =C32*E32 -> 57 | G32: =$H$11*E32 -> 8.4 | H32: =F32*$H$11 -> 2394 | I32: 0.95 | J32: =C32*I32 -> 270.75 | K32: =SUM(H32,J32) -> 2664.75 | L32: =K32/C32 -> 9.35 | M32: =C32*L32 -> 2664.75 | N32: 0 | O32: =M32*N32 -> 0
B33: Level 4 to Bulkhead | C33: 4 | D33: m2 | E33: 0.25 | F33: =C33*E33 -> 1 | G33: =$H$11*E33 -> 10.5 | H33: =F33*$H$11 -> 42 | I33: 0.95 | J33: =C33*I33 -> 3.8 | K33: =SUM(H33,J33) -> 45.8 | L33: =K33/C33 -> 11.45 | M33: =C33*L33 -> 45.8 | N33: 0 | O33: =M33*N33 -> 0
B34: External Corner - Bulkhead | C34: 192 | D34: m | E34: 0.15 | F34: =C34*E34 -> 28.8 | G34: =$H$11*E34 -> 6.3 | H34: =F34*$H$11 -> 1209.6 | I34: 2.5 | J34: =C34*I34 -> 480 | K34: =SUM(H34,J34) -> 1689.6 | L34: =K34/C34 -> 8.8 | M34: =C34*L34 -> 1689.6 | N34: 0 | O34: =M34*N34 -> 0
B35: P13/P26 | C35: 152 | D35: m | E35: 0.18 | F35: =C35*E35 -> 27.36 | G35: =$H$11*E35 -> 7.56 | H35: =F35*$H$11 -> 1149.12 | I35: 2.5 | J35: =C35*I35 -> 380 | K35: =SUM(H35,J35) -> 1529.12 | L35: =K35/C35 -> 10.06 | M35: =C35*L35 -> 1529.12 | N35: 0 | O35: =M35*N35 -> 0
B36: P01 Trim - Linear Tray Edge | C36: 70 | D36: m | E36: 0.15 | F36: =C36*E36 -> 10.5 | G36: =$H$11*E36 -> 6.3 | H36: =F36*$H$11 -> 441 | I36: 3 | J36: =C36*I36 -> 210 | K36: =SUM(H36,J36) -> 651 | L36: =K36/C36 -> 9.3 | M36: =C36*L36 -> 651 | N36: 0 | O36: =M36*N36 -> 0
B37: P01 Trim - Plasterboard Strip | C37: 13 | D37: m | E37: 0.15 | F37: =C37*E37 -> 1.95 | G37: =$H$11*E37 -> 6.3 | H37: =F37*$H$11 -> 81.9 | I37: 3 | J37: =C37*I37 -> 39 | K37: =SUM(H37,J37) -> 120.9 | L37: =K37/C37 -> 9.3 | M37: =C37*L37 -> 120.9 | N37: 0 | O37: =M37*N37 -> 0
B38: Stop Edge of C-10 Ceiling to Perforated C-11 | C38: 9 | D38: m | E38: 0.15 | F38: =C38*E38 -> 1.35 | G38: =$H$11*E38 -> 6.3 | H38: =F38*$H$11 -> 56.7 | I38: 1.4 | J38: =C38*I38 -> 12.6 | K38: =SUM(H38,J38) -> 69.3 | L38: =K38/C38 -> 7.7 | M38: =C38*L38 -> 69.3 | N38: 0 | O38: =M38*N38 -> 0
B39: Square Stopping | C39: 327 | D39: m | E39: 0.15 | F39: =C39*E39 -> 49.05 | G39: =$H$11*E39 -> 6.3 | H39: =F39*$H$11 -> 2060.1 | I39: 1.4 | J39: =C39*I39 -> 457.8 | K39: =SUM(H39,J39) -> 2517.9 | L39: =K39/C39 -> 7.7 | M39: =C39*L39 -> 2517.9 | N39: 0 | O39: =M39*N39 -> 0
B40: Control Joints | C40: 17 | D40: m | E40: 0.4 | F40: =C40*E40 -> 6.8 | G40: =$H$11*E40 -> 16.8 | H40: =F40*$H$11 -> 285.6 | I40: 15 | J40: =C40*I40 -> 255 | K40: =SUM(H40,J40) -> 540.6 | L40: =K40/C40 -> 31.8 | M40: =C40*L40 -> 540.6 | N40: 0 | O40: =M40*N40 -> 0
B43: Wall Stopping:
B45: Level 4:
B46: Level 4 Stopping - Walls | C46: ='Gib Linings'!P56 -> 878 | D46: m2 | E46: 0.2 | F46: =C46*E46 -> 175.6 | G46: =$H$11*E46 -> 8.4 | H46: =F46*$H$11 -> 7375.2 | I46: 0.95 | J46: =C46*I46 -> 834.1 | K46: =SUM(H46,J46) -> 8209.3 | L46: =K46/C46 -> 9.35 | M46: =C46*L46 -> 8209.3 | N46: 0 | O46: =M46*N46 -> 0
B47: Level 4 Stopping - Upstand | C47: ='Gib Linings'!P57 -> 31 | D47: m2 | E47: 0.25 | F47: =C47*E47 -> 7.75 | G47: =$H$11*E47 -> 10.5 | H47: =F47*$H$11 -> 325.5 | I47: 0.95 | J47: =C47*I47 -> 29.45 | K47: =SUM(H47,J47) -> 354.95 | L47: =K47/C47 -> 11.45 | M47: =C47*L47 -> 354.95 | N47: 0 | O47: =M47*N47 -> 0
B48: External Corners | C48: 101 | D48: m | E48: 0.15 | F48: =C48*E48 -> 15.15 | G48: =$H$11*E48 -> 6.3 | H48: =F48*$H$11 -> 636.3 | I48: 2.5 | J48: =C48*I48 -> 252.5 | K48: =SUM(H48,J48) -> 888.8 | L48: =K48/C48 -> 8.8 | M48: =C48*L48 -> 888.8 | N48: 0 | O48: =M48*N48 -> 0
B49: External Corners - Abutting Ali Edge | C49: 165 | D49: m | E49: 0.15 | F49: =C49*E49 -> 24.75 | G49: =$H$11*E49 -> 6.3 | H49: =F49*$H$11 -> 1039.5 | I49: 2.5 | J49: =C49*I49 -> 412.5 | K49: =SUM(H49,J49) -> 1452 | L49: =K49/C49 -> 8.8 | M49: =C49*L49 -> 1452 | N49: 0 | O49: =M49*N49 -> 0
B51: Stop Curveline Columns | C51: 13 | D51: no | E51: 0 | F51: =C51*E51 -> 0 | G51: =$H$11*E51 -> 0 | H51: =F51*$H$11 -> 0 | I51: 165 | J51: =C51*I51 -> 2145 | K51: =SUM(H51,J51) -> 2145 | L51: =K51/C51 -> 165 | M51: =C51*L51 -> 2145 | N51: 0 | O51: =M51*N51 -> 0
B54: Level 5:
B55: Level 4 Stopping - Walls | C55: ='Gib Linings'!P105 -> 762 | D55: m2 | E55: 0.2 | F55: =C55*E55 -> 152.4 | G55: =$H$11*E55 -> 8.4 | H55: =F55*$H$11 -> 6400.8 | I55: 0.95 | J55: =C55*I55 -> 723.9 | K55: =SUM(H55,J55) -> 7124.7 | L55: =K55/C55 -> 9.35 | M55: =C55*L55 -> 7124.7 | N55: 0 | O55: =M55*N55 -> 0
B56: Level 4 Stopping - Upstand | C56: ='Gib Linings'!P106 -> 25 | D56: m2 | E56: 0.25 | F56: =C56*E56 -> 6.25 | G56: =$H$11*E56 -> 10.5 | H56: =F56*$H$11 -> 262.5 | I56: 0.95 | J56: =C56*I56 -> 23.75 | K56: =SUM(H56,J56) -> 286.25 | L56: =K56/C56 -> 11.45 | M56: =C56*L56 -> 286.25 | N56: 0 | O56: =M56*N56 -> 0
B57: External Corners | C57: 99 | D57: m | E57: 0.15 | F57: =C57*E57 -> 14.85 | G57: =$H$11*E57 -> 6.3 | H57: =F57*$H$11 -> 623.7 | I57: 2.5 | J57: =C57*I57 -> 247.5 | K57: =SUM(H57,J57) -> 871.2 | L57: =K57/C57 -> 8.8 | M57: =C57*L57 -> 871.2 | N57: 0 | O57: =M57*N57 -> 0
B58: External Corners - Abutting Ali Edge | C58: 130 | D58: m | E58: 0.15 | F58: =C58*E58 -> 19.5 | G58: =$H$11*E58 -> 6.3 | H58: =F58*$H$11 -> 819 | I58: 2.5 | J58: =C58*I58 -> 325 | K58: =SUM(H58,J58) -> 1144 | L58: =K58/C58 -> 8.8 | M58: =C58*L58 -> 1144 | N58: 0 | O58: =M58*N58 -> 0
B60: Stop Curveline Columns | C60: 19 | D60: no | E60: 0 | F60: =C60*E60 -> 0 | G60: =$H$11*E60 -> 0 | H60: =F60*$H$11 -> 0 | I60: 165 | J60: =C60*I60 -> 3135 | K60: =SUM(H60,J60) -> 3135 | L60: =K60/C60 -> 165 | M60: =C60*L60 -> 3135 | N60: 0 | O60: =M60*N60 -> 0
B63: Level 6:
B64: Level 4 Stopping - Walls | C64: ='Gib Linings'!P147 -> 1324 | D64: m2 | E64: 0.2 | F64: =C64*E64 -> 264.8 | G64: =$H$11*E64 -> 8.4 | H64: =F64*$H$11 -> 11121.6 | I64: 0.95 | J64: =C64*I64 -> 1257.8 | K64: =SUM(H64,J64) -> 12379.4 | L64: =K64/C64 -> 9.35 | M64: =C64*L64 -> 12379.4 | N64: 0 | O64: =M64*N64 -> 0
B65: Level 4 Stopping - Upstand | C65: ='Gib Linings'!P148 -> 76 | D65: m2 | E65: 0.25 | F65: =C65*E65 -> 19 | G65: =$H$11*E65 -> 10.5 | H65: =F65*$H$11 -> 798 | I65: 0.95 | J65: =C65*I65 -> 72.2 | K65: =SUM(H65,J65) -> 870.2 | L65: =K65/C65 -> 11.45 | M65: =C65*L65 -> 870.2 | N65: 0 | O65: =M65*N65 -> 0
B66: External Corners | C66: 45 | D66: m | E66: 0.15 | F66: =C66*E66 -> 6.75 | G66: =$H$11*E66 -> 6.3 | H66: =F66*$H$11 -> 283.5 | I66: 2.5 | J66: =C66*I66 -> 112.5 | K66: =SUM(H66,J66) -> 396 | L66: =K66/C66 -> 8.8 | M66: =C66*L66 -> 396 | N66: 0 | O66: =M66*N66 -> 0
B67: External Corners - Abutting Ali Edge | C67: 245 | D67: m | E67: 0.15 | F67: =C67*E67 -> 36.75 | G67: =$H$11*E67 -> 6.3 | H67: =F67*$H$11 -> 1543.5 | I67: 2.5 | J67: =C67*I67 -> 612.5 | K67: =SUM(H67,J67) -> 2156 | L67: =K67/C67 -> 8.8 | M67: =C67*L67 -> 2156 | N67: 0 | O67: =M67*N67 -> 0
B69: Stop Curveline Columns | C69: 15 | D69: no | E69: 0 | F69: =C69*E69 -> 0 | G69: =$H$11*E69 -> 0 | H69: =F69*$H$11 -> 0 | I69: 165 | J69: =C69*I69 -> 2475 | K69: =SUM(H69,J69) -> 2475 | L69: =K69/C69 -> 165 | M69: =C69*L69 -> 2475 | N69: 0 | O69: =M69*N69 -> 0
F72: =SUM(F13:F71) -> 1026.72 | H72: =SUM(H13:H71) -> 43122.24 | J72: =SUM(J13:J71) -> 16024.2
B73: Total of above | M73: =SUM(M13:M71) -> 59146.44 | O73: =SUM(O13:O71) -> 0
B74: Miscellaneous
B76: P&G - Admin / Supervision | D76: Sum | L76: 0.0205 | M76: =M73*L76 -> 1212.502 | O76: =(O73/M73)*M76 -> 0
B78: P&G - Site Establishment | D78: Sum | L78: 0.01 | M78: =M73*L78 -> 591.4644 | O78: =(O73/M73)*M78 -> 0
B80: P&G - Access Equip | D80: Sum | L80: 0.0025 | M80: =M73*L80 -> 147.8661 | O80: =(O73/M73)*M80 -> 0
B82: P&G - Parking | D82: Sum | L82: =M82/M73 -> 0.039057634 | M82: =I95 -> 2310.12
B84: P&G Travel | D84: Sum | O84: =M84*N84 -> 0
B86: Sub total | M86: =SUM(M73:M85) -> 63408.393 | O86: =SUM(O73:O85) -> 0
B88: Margin | L88: 0.05 | M88: =M86*L88 -> 3170.4196 | O88: =O86/M86*M88 -> 0
B90: TOTAL OF STOPPING | M90: =ROUNDUP(SUM(M86:M89),0) -> 66579 | N90: =O90/M90 -> 0 | O90: =SUM(O86:O89) -> 0
N91: =SUM(L75:L85) -> 0.072057634 | P91: =L88 -> 0.05
G92: Parking | K92: =SUM(F16:F22,F46:F52) -> 293.57 | L92: LEVEL 4 | M92: =SUM(M16:M22,M46:M52) -> 16833.79 | N92: =M92*$N$91 -> 1213.0031 | O92: =SUM(M92:N92) -> 18046.793 | P92: =O92*$P$91 -> 902.33965 | Q92: =SUM(O92:P92) -> 18949.133
H93: Man
G94: =F72/8 -> 128.34 | H94: 1 | K94: =SUM(F24:F29,F55:F58) -> 222.04 | L94: LEVEL 5 | M94: =SUM(M24:M29,M55:M60) -> 14207.08 | N94: =M94*$N$91 -> 1023.7286 | O94: =SUM(M94:N94) -> 15230.809 | P94: =O94*$P$91 -> 761.54043 | Q94: =SUM(O94:P94) -> 15992.349
G95: =G94/H94 -> 128.34 | H95: 18 | I95: =G95*H95 -> 2310.12
K96: =SUM(F31:F40,F64:F69) -> 511.11 | L96: LEVEL 6 | M96: =SUM(M31:M40,M64:M69) -> 28105.57 | N96: =M96*$N$91 -> 2025.2209 | O96: =SUM(M96:N96) -> 30130.791 | P96: =O96*$P$91 -> 1506.5395 | Q96: =SUM(O96:P96) -> 31637.33
K98: =SUM(K92:K97) -> 1026.72 | M98: =SUM(M92:M97) -> 59146.44 | Q98: =SUM(Q92:Q97) -> 66578.812
B99: Rate build for travel by car | I99: Rate build for travel by car
B100: Travel there and back based on 4 | I100: Travel there and back based on 1
B101: hrs travel per person | C101: Rate /Km | D101: Total | E101: Number of people | I101: hrs travel per person | J101: Rate /Km | K101: Total | L101: Number of people
B102: 1 | C102: 55 | D102: =B102*C102 -> 55 | E102: =D102*F102 -> 110 | F102: 2 | I102: 4 | J102: 55 | K102: =I102*J102 -> 220 | L102: =K102*M102 -> 440 | M102: 2
B103: km | E103: There and back | I103: km | L103: There and back
B104: 0.7 | E104: =B104*C104 -> 0 | I104: 0.7 | J104: 310 | L104: =I104*J104 -> 217
B105: Amount of trips needed | E105: =SUM(E102:E104) -> 110 | I105: Amount of trips needed | L105: =SUM(L102:L104) -> 657
B106: 2 | E106: =B106*E105 -> 220 | I106: 1 | L106: =I106*L105 -> 657
B107: Accom/per day | C107: days | E107: Times amount of people | I107: Accom/per day | J107: days | L107: Times amount of people
D108: =B108*C108 -> 0 | E108: =D108*F102 -> 0 | I108: 125 | J108: 4 | K108: =I108*J108 -> 500 | L108: =K108*M102 -> 1000
E109: =SUM(E106:E108) -> 220 | L109: =SUM(L106:L108) -> 1657
D113: Parking | E113: =F72/8.5 -> 120.79059 | F113: =E113*17.5 -> 2113.8353 | G113: $17.50 per day

Sheet Potters Rigitone Matrix
B1: =Summary!B1 -> Ceilings Unlimited
B2: =Summary!B2 -> Craigs Investment Partners - Fitout
B3: =Summary!B3 -> Tauranga
B6: =Summary!B5 -> 46043
B9: =Summary!B127 -> Potters Rigitone Matrix Ceiling Lining
H11: 50
A12: Item | B12: Description | C12: Qty | D12: Unit | E12: Constant | F12: Constant X Unit = Total HRS | G12: $ Lab per Unit | H12: Total Labour | I12: Materials per Unit | J12: Total Materials | K12: Total Labour & Materials | L12: Total Labour & Materials Per Unit | M12: Total | N12: % Complete | O12: Claim
B14: Ceiling:
B16: Level 4: | C16: Nil
B19: Level 5: | C19: Nil
B22: Level 6:
B24: (C-11) Potters Rigitone Matrix 12mm | C24: 204 | D24: m2 | E24: 1.25 | F24: =C24*E24 -> 255 | G24: =$H$11*E24 -> 62.5 | H24: =F24*$H$11 -> 12750 | I24: 85.95 | J24: =C24*I24 -> 17533.8 | K24: =SUM(H24,J24) -> 30283.8 | L24: =K24/C24 -> 148.45 | M24: =C24*L24 -> 30283.8 | N24: 0 | O24: =M24*N24 -> 0
B25: EV for Service Pentrations | C25: 204 | D25: m2 | E25: 0.25 | F25: =C25*E25 -> 51 | G25: =$H$11*E25 -> 12.5 | H25: =F25*$H$11 -> 2550 | I25: 0 | J25: =C25*I25 -> 0 | K25: =SUM(H25,J25) -> 2550 | L25: =K25/C25 -> 12.5 | M25: =C25*L25 -> 2550 | N25: 0 | O25: =M25*N25 -> 0
B26: Caulking to Sheet Joints | C26: 204 | D26: m2 | E26: 0.25 | F26: =C26*E26 -> 51 | G26: =$H$11*E26 -> 12.5 | H26: =F26*$H$11 -> 2550 | I26: 3.35 | J26: =C26*I26 -> 683.4 | K26: =SUM(H26,J26) -> 3233.4 | L26: =K26/C26 -> 15.85 | M26: =C26*L26 -> 3233.4 | N26: 0 | O26: =M26*N26 -> 0 | P26: 261 l/m
B27: Misc - Caulking attachements, guns, spacers, primer etc | C27: 1 | D27: item | E27: 0 | F27: =C27*E27 -> 0 | G27: =$H$11*E27 -> 0 | H27: =F27*$H$11 -> 0 | I27: 500 | J27: =C27*I27 -> 500 | K27: =SUM(H27,J27) -> 500 | L27: =K27/C27 -> 500 | M27: =C27*L27 -> 500 | N27: 0 | O27: =M27*N27 -> 0
B28: Stopping of Screw Holes | C28: 204 | D28: m2 | E28: 0.25 | F28: =C28*E28 -> 51 | G28: =$H$11*E28 -> 12.5 | H28: =F28*$H$11 -> 2550 | I28: 3 | J28: =C28*I28 -> 612 | K28: =SUM(H28,J28) -> 3162 | L28: =K28/C28 -> 15.5 | M28: =C28*L28 -> 3162 | N28: 0 | O28: =M28*N28 -> 0
B29: Powdercoated Perimeter Angle to Cap Off Perforation to Perimeter | C29: 155 | D29: m | E29: 0.15 | F29: =C29*E29 -> 23.25 | G29: =$H$11*E29 -> 7.5 | H29: =F29*$H$11 -> 1162.5 | I29: 20 | J29: =C29*I29 -> 3100 | K29: =SUM(H29,J29) -> 4262.5 | L29: =K29/C29 -> 27.5 | M29: =C29*L29 -> 4262.5 | N29: 0 | O29: =M29*N29 -> 0
B32: Walls/Columns:
B34: Level 4: | C34: Nil
B37: Level 5: | C37: Nil
B40: Level 6: | C40: Nil
F43: =SUM(F13:F42) -> 431.25 | H43: =SUM(H13:H42) -> 21562.5 | J43: =SUM(J13:J42) -> 22429.2
B44: Total of above | M44: =SUM(M13:M42) -> 43991.7 | O44: =SUM(O13:O42) -> 0
B45: Miscellaneous
B47: P&G - Admin / Supervision | D47: Sum | L47: 0.0205 | M47: =M44*L47 -> 901.82985 | O47: =(O44/M44)*M47 -> 0
B49: P&G - Site Establishment | D49: Sum | L49: 0.01 | M49: =M44*L49 -> 439.917 | O49: =(O44/M44)*M49 -> 0
B51: P&G - Access Equip | D51: Sum | L51: 0.0025 | M51: =M44*L51 -> 109.97925 | O51: =(O44/M44)*M51 -> 0
B53: P&G - Parking | D53: Sum | L53: =M53/M44 -> 0.022056718 | M53: =I66 -> 970.3125
B55: P&G Travel | D55: Sum | O55: =M55*N55 -> 0
B57: Sub total | M57: =SUM(M44:M56) -> 46413.739 | O57: =SUM(O44:O56) -> 0
B59: Margin | L59: 0.05 | M59: =M57*L59 -> 2320.6869 | O59: =O57/M57*M59 -> 0
B61: TOTAL OF POTTERS RIGITONE MATRIX | M61: =ROUNDUP(SUM(M57:M60),0) -> 48735 | N61: =O61/M61 -> 0 | O61: =SUM(O57:O60) -> 0
N62: =SUM(L46:L56) -> 0.055056718 | P62: =L59 -> 0.05
G63: Parking | L63: LEVEL 4 | O63: =SUM(M63:N63) -> 0 | Q63: =SUM(O63:P63) -> 0
H64: Man
G65: =F43/8 -> 53.90625 | H65: 1 | L65: LEVEL 5 | O65: =SUM(M65:N65) -> 0 | Q65: =SUM(O65:P65) -> 0
G66: =G65/H65 -> 53.90625 | H66: 18 | I66: =G66*H66 -> 970.3125
K67: =F43 -> 431.25 | L67: LEVEL 6 | O67: =SUM(M67:N67) -> 0 | Q67: =SUM(O67:P67) -> 0
M69: =SUM(M63:M68) -> 0 | Q69: =SUM(Q63:Q68) -> 0
B70: Rate build for travel by car | I70: Rate build for travel by car
B71: Travel there and back based on 4 | I71: Travel there and back based on 1
B72: hrs travel per person | C72: Rate /Km | D72: Total | E72: Number of people | I72: hrs travel per person | J72: Rate /Km | K72: Total | L72: Number of people
B73: 1 | C73: 55 | D73: =B73*C73 -> 55 | E73: =D73*F73 -> 110 | F73: 2 | I73: 4 | J73: 55 | K73: =I73*J73 -> 220 | L73: =K73*M73 -> 440 | M73: 2
B74: km | E74: There and back | I74: km | L74: There and back
B75: 0.7 | E75: =B75*C75 -> 0 | I75: 0.7 | J75: 310 | L75: =I75*J75 -> 217
B76: Amount of trips needed | E76: =SUM(E73:E75) -> 110 | I76: Amount of trips needed | L76: =SUM(L73:L75) -> 657
B77: 2 | E77: =B77*E76 -> 220 | I77: 1 | L77: =I77*L76 -> 657
B78: Accom/per day | C78: days | E78: Times amount of people | I78: Accom/per day | J78: days | L78: Times amount of people
D79: =B79*C79 -> 0 | E79: =D79*F73 -> 0 | I79: 125 | J79: 4 | K79: =I79*J79 -> 500 | L79: =K79*M73 -> 1000
E80: =SUM(E77:E79) -> 220 | L80: =SUM(L77:L79) -> 1657
D84: Parking | E84: =F43/8.5 -> 50.735294 | F84: =E84*17.5 -> 887.86765 | G84: $17.50 per day

Sheet Ambitec
B1: =Summary!B1 -> Ceilings Unlimited
B2: =Summary!B2 -> Craigs Investment Partners - Fitout
B3: =Summary!B3 -> Tauranga
B6: =Summary!B5 -> 46043
B9: =Summary!B129 -> Ambitec (PF-01 and PF-02 to Wall and Bulkheads Only)
H11: 50
A12: Item | B12: Description | C12: Qty | D12: Unit | E12: Constant | F12: Constant X Unit = Total HRS | G12: $ Lab per Unit | H12: Total Labour | I12: Materials per Unit | J12: Total Materials | K12: Total Labour & Materials | L12: Total Labour & Materials Per Unit | M12: Total | N12: % Complete | O12: Claim
S13: PF-01 | T13: PF-02
B14: Ceiling:
S15: =SUM(S16:S65) -> 72960 | T15: =SUM(T16:T65) -> 29460 | V15: =SUM(S15:T15) -> 102420
B16: Level 4: | C16: Nil
B19: Level 5: | C19: Nil
B22: Level 6: | C22: Nil
B25: Bulkheads:
B27: Level 4:
B28: PF-01 | C28: 45 | D28: m2 | E28: 0 | F28: =C28*E28 -> 0 | G28: =$H$11*E28 -> 0 | H28: =F28*$H$11 -> 0 | I28: 233 | J28: =C28*I28 -> 10485 | K28: =SUM(H28,J28) -> 10485 | L28: =K28/C28 -> 233 | M28: =C28*L28 -> 10485 | N28: 0 | O28: =M28*N28 -> 0 | Q28: 190 | S28: =C28*Q28 -> 8550
B30: Level 5:
B31: PF-01 | C31: 59 | D31: m2 | E31: 0 | F31: =C31*E31 -> 0 | G31: =$H$11*E31 -> 0 | H31: =F31*$H$11 -> 0 | I31: 233 | J31: =C31*I31 -> 13747 | K31: =SUM(H31,J31) -> 13747 | L31: =K31/C31 -> 233 | M31: =C31*L31 -> 13747 | N31: 0 | O31: =M31*N31 -> 0 | Q31: 190 | S31: =C31*Q31 -> 11210
B33: Level 6:
B34: PF-01 | C34: Nil
B37: Walls/Columns:
B39: Level 4:
B40: PF-01, Walls to 2.9m | C40: 98 | D40: m2 | E40: 0 | F40: =C40*E40 -> 0 | G40: =$H$11*E40 -> 0 | H40: =F40*$H$11 -> 0 | I40: 233 | J40: =C40*I40 -> 22834 | K40: =SUM(H40,J40) -> 22834 | L40: =K40/C40 -> 233 | M40: =C40*L40 -> 22834 | N40: 0 | O40: =M40*N40 -> 0 | Q40: 190 | S40: =C40*Q40 -> 18620
B41: PF-01, Columns (1x) | C41: 10 | D41: m2 | E41: 0 | F41: =C41*E41 -> 0 | G41: =$H$11*E41 -> 0 | H41: =F41*$H$11 -> 0 | I41: 233 | J41: =C41*I41 -> 2330 | K41: =SUM(H41,J41) -> 2330 | L41: =K41/C41 -> 233 | M41: =C41*L41 -> 2330 | N41: 0 | O41: =M41*N41 -> 0 | Q41: 190 | S41: =C41*Q41 -> 1900
B43: PF-02 | C43: Nil
B46: Level 5:
B47: PF-01, Walls to 2.9m | C47: 58 | D47: m2 | E47: 0 | F47: =C47*E47 -> 0 | G47: =$H$11*E47 -> 0 | H47: =F47*$H$11 -> 0 | I47: 233 | J47: =C47*I47 -> 13514 | K47: =SUM(H47,J47) -> 13514 | L47: =K47/C47 -> 233 | M47: =C47*L47 -> 13514 | N47: 0 | O47: =M47*N47 -> 0 | Q47: 190 | S47: =C47*Q47 -> 11020
B49: PF-02 | C49: Nil
B52: Level 6:
B53: PF-01, Walls to 3.0m - 3.1m | C53: 34 | D53: m2 | E53: 0 | F53: =C53*E53 -> 0 | G53: =$H$11*E53 -> 0 | H53: =F53*$H$11 -> 0 | I53: 233 | J53: =C53*I53 -> 7922 | K53: =SUM(H53,J53) -> 7922 | L53: =K53/C53 -> 233 | M53: =C53*L53 -> 7922 | N53: 0 | O53: =M53*N53 -> 0 | Q53: 190 | S53: =C53*Q53 -> 6460
B54: PF-01, Columns (11x) | C54: 80 | D54: m2 | E54: 0 | F54: =C54*E54 -> 0 | G54: =$H$11*E54 -> 0 | H54: =F54*$H$11 -> 0 | I54: 233 | J54: =C54*I54 -> 18640 | K54: =SUM(H54,J54) -> 18640 | L54: =K54/C54 -> 233 | M54: =C54*L54 -> 18640 | N54: 0 | O54: =M54*N54 -> 0 | Q54: 190 | S54: =C54*Q54 -> 15200
B55: Bronze Finishing Coffer Trim and Skirting to Above, BR-01 (ID 501) | C55: 2 | D55: no | E55: 3 | F55: =C55*E55 -> 6 | G55: =$H$11*E55 -> 150 | H55: =F55*$H$11 -> 300 | I55: 462 | J55: =C55*I55 -> 924 | K55: =SUM(H55,J55) -> 1224 | L55: =K55/C55 -> 612 | M55: =C55*L55 -> 1224 | N55: 0 | O55: =M55*N55 -> 0
B57: PF-02 | C57: 92 | D57: m2 | E57: 1 | F57: =C57*E57 -> 92 | G57: =$H$11*E57 -> 50 | H57: =F57*$H$11 -> 4600 | I57: =D63 -> 339.53804 | J57: =C57*I57 -> 31237.5 | K57: =SUM(H57,J57) -> 35837.5 | L57: =K57/C57 -> 389.53804 | M57: =C57*L57 -> 35837.5 | N57: 0 | O57: =M57*N57 -> 0
B58: 74 Sheets @ $330 | C58: 24420 | P58: 74 | Q58: 330 | T58: =P58*Q58 -> 24420
B59: 15 Sheets @ $360 Curved | C59: 5400 | P59: 14 | Q59: 360 | T59: =P59*Q59 -> 5040
B60: 89 Sheets @ $5 freight | C60: 445
B61: 89 Sheets @ $2.50 Glue | C61: 222.5
B62: Loadin 10 mins per sheet 15.0 hr @ $50 | C62: 750
C63: =SUM(C58:C62) -> 31237.5 | D63: =C63/C57 -> 339.53804 | E63: m2
F65: =SUM(F13:F63) -> 98 | H65: =SUM(H13:H63) -> 4900 | J65: =SUM(J13:J63) -> 121633.5
B66: Total of above | M66: =SUM(M13:M63) -> 126533.5 | O66: =SUM(O13:O63) -> 0
B67: Miscellaneous | Q67: =M55 -> 1224 | R67: =Q67*N84 -> 42.524969 | S67: =SUM(Q67:R67) -> 1266.525 | T67: =S67*P84 -> 44.328374 | U67: =SUM(S67:T67) -> 1310.8533
Q68: =M57 -> 35837.5 | R68: =M57*N84 -> 1245.0887 | S68: =SUM(Q68:R68) -> 37082.589 | T68: =S68*L81 -> 1297.8906 | U68: =SUM(S68:T68) -> 38380.479
B69: P&G - Admin / Supervision | D69: Sum | L69: 0.0205 | M69: =M66*L69 -> 2593.9368 | O69: =(O66/M66)*M69 -> 0
B71: P&G - Site Establishment | D71: Sum | L71: 0.01 | M71: =M66*L71 -> 1265.335 | O71: =(O66/M66)*M71 -> 0
B73: P&G - Access Equip | D73: Sum | L73: 0.0025 | M73: =M66*L73 -> 316.33375 | O73: =(O66/M66)*M73 -> 0
B75: P&G - Parking | D75: Sum | L75: =M75/M66 -> 0.0017426215 | M75: =I88 -> 220.5
B77: P&G Travel | D77: Sum | O77: =M77*N77 -> 0
S78: 135362
B79: Sub total | M79: =SUM(M66:M78) -> 130929.61 | O79: =SUM(O66:O78) -> 0 | R79: PF-01 | S79: 96804
R80: PF-02 | S80: =S78-S79 -> 38558
B81: Margin | L81: 0.035 | M81: =M79*L81 -> 4582.5362 | O81: =O79/M79*M81 -> 0 | T81: =SUM(S79:S80) -> 135362
B83: TOTAL OF MISC WALL AND CEILING | M83: =ROUNDUP(SUM(M79:M82),0) -> 135513 | N83: =O83/M83 -> 0 | O83: =SUM(O79:O82) -> 0
N84: =SUM(L68:L78) -> 0.034742622 | P84: =L81 -> 0.035
G85: Parking | K85: =SUM(F28,F40:F43) -> 0 | L85: LEVEL 4 | M85: =SUM(M28,M40:M43) -> 35649 | N85: =M85*$N$84 -> 1238.5397 | O85: =SUM(M85:N85) -> 36887.54 | P85: =O85*$P$84 -> 1291.0639 | S85: =SUM(O85:P85) -> 38178.604
H86: Man
G87: =F65/8 -> 12.25 | H87: 1 | K87: =SUM(F31,F47:F49) -> 0 | L87: LEVEL 5 | M87: =SUM(M31,M47:M49) -> 27261 | N87: =M87*$N$84 -> 947.11861 | O87: =SUM(M87:N87) -> 28208.119 | P87: =O87*$P$84 -> 987.28415 | S87: =SUM(O87:P87) -> 29195.403
G88: =G87/H87 -> 12.25 | H88: 18 | I88: =G88*H88 -> 220.5
K89: =SUM(F33:F34,F53:F57) -> 98 | L89: LEVEL 6 | M89: =SUM(M33:M34,M53:M57) -> 63623.5 | N89: =M89*$N$84 -> 2210.4472 | O89: =SUM(M89:N89) -> 65833.947 | P89: =O89*$P$84 -> 2304.1882 | S89: =SUM(O89:P89) -> 68138.135
K91: =SUM(K85:K90) -> 98 | M91: =SUM(M85:M90) -> 126533.5 | S91: =SUM(S85:S90) -> 135512.14
B92: Rate build for travel by car | I92: Rate build for travel by car
B93: Travel there and back based on 4 | I93: Travel there and back based on 1
B94: hrs travel per person | C94: Rate /Km | D94: Total | E94: Number of people | I94: hrs travel per person | J94: Rate /Km | K94: Total | L94: Number of people
B95: 1 | C95: 55 | D95: =B95*C95 -> 55 | E95: =D95*F95 -> 110 | F95: 2 | I95: 4 | J95: 55 | K95: =I95*J95 -> 220 | L95: =K95*M95 -> 440 | M95: 2
B96: km | E96: There and back | I96: km | L96: There and back
B97: 0.7 | E97: =B97*C97 -> 0 | I97: 0.7 | J97: 310 | L97: =I97*J97 -> 217
B98: Amount of trips needed | E98: =SUM(E95:E97) -> 110 | I98: Amount of trips needed | L98: =SUM(L95:L97) -> 657
B99: 2 | E99: =B99*E98 -> 220 | I99: 1 | L99: =I99*L98 -> 657
B100: Accom/per day | C100: days | E100: Times amount of people | I100: Accom/per day | J100: days | L100: Times amount of people
D101: =B101*C101 -> 0 | E101: =D101*F95 -> 0 | I101: 125 | J101: 4 | K101: =I101*J101 -> 500 | L101: =K101*M95 -> 1000
E102: =SUM(E99:E101) -> 220 | L102: =SUM(L99:L101) -> 1657
D106: Parking | E106: =F65/8.5 -> 11.529412 | F106: =E106*17.5 -> 201.76471 | G106: $17.50 per day

Sheet Featurecraft
B1: =Summary!B1 -> Ceilings Unlimited
B2: =Summary!B2 -> Craigs Investment Partners - Fitout
B3: =Summary!B3 -> Tauranga | S3: L4 | T3: L5 | U3: L6
R4: TB.01 | S4: 95 | T4: 66 | U4: 93 | V4: m2 | W4: =SUM(S4:U4) -> 254 | X4: =SUM(J18,J38,J60) -> 431376
S5: 34 | T5: 23 | U5: 30 | V5: l/m
B6: =Summary!B5 -> 46043 | R6: TB.02 | S6: 35 | T6: 28 | V6: m2 | W6: =SUM(S6:U6) -> 63 | X6: =SUM(J25,J46) -> 74008
B9: =Summary!B131 -> Featurecraft (TB-01 and TB-02) | R9: TB.02 L/m | S9: 12 | T9: 10
R10: @ | S10: 2.9 | T10: 2.9 | X10: =SUM(J29,J31,J50) -> 39100
H11: 50
